Workbook

Sheet Current Decisions
A1: ` | B1: Date | C1: Revenue | D1: Work Authorization | E1: Glassdoor | F1: Relationship with A&M | G1: =SUM(C1 + D1 + E1 + F1) -> #VALUE! | H1: Weeks Pending | I1: Decision | J1: Requested Wednesday Booths | K1: Final Wednesday Booths | L1: Requested Thursday Booths | M1: Final Thursday Booths | N1: Primary Major
A2: A&S Engineers, Inc. | C2: 0 | D2: 0 | E2: 0 | F2: 5 | G2: =IF(AND(C2>=0,D2>=0,E2>=0,F2>=0),SUM(C2:F2),"needs update") -> 5 | J2: 1 | L2: 1
A3: ABB Inc. | C3: 17.6 | D3: 15 | E3: 7.5 | F3: 10 | G3: =IF(AND(C3>=0,D3>=0,E3>=0,F3>=0),SUM(C3:F3),"needs update") -> 50.1 | J3: 2 | L3: 0
A4: ABS (American Bureau of Shipping) | C4: 0 | D4: 0 | E4: 3.8 | F4: 15 | G4: =IF(AND(C4>=0,D4>=0,E4>=0,F4>=0),SUM(C4:F4),"needs update") -> 18.8 | J4: 1 | L4: 1
A5: Accuracy | C5: 14.3 | D5: 15 | E5: 8.2 | F5: 0 | G5: =IF(AND(C5>=0,D5>=0,E5>=0,F5>=0),SUM(C5:F5),"needs update") -> 37.5 | J5: 1 | L5: 0
A6: Ace Thermal Systems | C6: 0 | D6: 0 | E6: 0 | F6: 0 | G6: =IF(AND(C6>=0,D6>=0,E6>=0,F6>=0),SUM(C6:F6),"needs update") -> 0 | J6: 1 | L6: 1
A7: Affiliated Engineers Inc | C7: 0 | D7: 15 | E7: 9.7 | F7: 0 | G7: =IF(AND(C7>=0,D7>=0,E7>=0,F7>=0),SUM(C7:F7),"needs update") -> 24.7 | J7: 1 | L7: 0
A8: Air Liquide | C8: 15.9 | D8: 0 | E8: 6 | F8: 20 | G8: =IF(AND(C8>=0,D8>=0,E8>=0,F8>=0),SUM(C8:F8),"needs update") -> 41.9 | J8: 1 | L8: 0
A9: Albemarle Corporation | C9: 12.3 | D9: 0 | E9: 1.5 | F9: 5 | G9: =IF(AND(C9>=0,D9>=0,E9>=0,F9>=0),SUM(C9:F9),"needs update") -> 18.8 | J9: 1 | L9: 0
A10: Albers Aerospace | C10: 0 | D10: 0 | E10: 0 | F10: 5 | G10: =IF(AND(C10>=0,D10>=0,E10>=0,F10>=0),SUM(C10:F10),"needs update") -> 5 | J10: 1 | L10: 1
A11: Alcon | C11: 15 | D11: 15 | E11: 5.3 | F11: 5 | G11: =IF(AND(C11>=0,D11>=0,E11>=0,F11>=0),SUM(C11:F11),"needs update") -> 40.3 | J11: 1 | L11: 0
A12: alliantgroup | C12: 0 | D12: 15 | E12: 3.8 | F12: 5 | G12: =IF(AND(C12>=0,D12>=0,E12>=0,F12>=0),SUM(C12:F12),"needs update") -> 23.8 | J12: 1 | L12: 1
A13: AME | C13: 13.3 | D13: 15 | E13: 0 | F13: 0 | G13: =IF(AND(C13>=0,D13>=0,E13>=0,F13>=0),SUM(C13:F13),"needs update") -> 28.3 | J13: 1 | L13: 1
... A535: Rehrig Pacific Company | C535: -1 | D535: 15 | E535: 0 | F535: 0 | G535: =IF(AND(C535>=0,D535>=0,E535>=0,F535>=0),SUM(C535:F535),"needs update") -> needs update | J535: 1 | L535: 0

Sheet Analytics
A1: Majors | B1: Requested Wednesday Booths | C1: Final Wednesday Booths | D1: Requested Thursday Booths | E1: Final Thursday Booths | F1: How full is this major? (%) | G1: Need more of this major? (<20%) | H1: Need less of this major? (>80%) | I1: Registrations % | J1: Allocated Booths | K1: Acceptance Rate

Sheet Manual Analytics
A1: Majors | B1: Requested Wednesday Booths | C1: Final Wednesday Booths | D1: Requested Thursday Booths | E1: Final Thursday Booths | F1: Allocated Total Booths | G1: Total Booths Confirmed | H1: Bump to Thursdays | I1: How full is this major? (%) | J1: Need more of this major? (<20%) | K1: Need less of this major? (>80%) | L1: Registrations % | M1: Allocated Booths | N1: Acceptance Rate | O1: Acceptance Rate
A2: AERO | B2: =sum(AERO!C2:C885) -> 22 | C2: =sum(AERO!D2:D885) -> 21 | D2: =sum(AERO!E2:E885) -> 12 | E2: =sum(AERO!F2:F885) -> 11 | F2: 54 | G2: =C2+E2 -> 32 | H2: =SUM(IF(AND(AERO!C2:C100 > 0, AERO!D2:D100 = 0, AERO!F2:F100 > 0), 1, 0)) -> 0 | I2: =G2/F2 -> 0.59259259 | J2: =IF((I2<0.2),"YES","") | K2: =IF((I2>0.8),"YES","")
A3: AREN | B3: =SUM(AREN!C2:C885) -> 8 | C3: =SUM(AREN!D2:D885) -> 5 | D3: =SUM(AREN!E2:E885) -> 3 | E3: =SUM(AREN!F2:F885) -> 3 | F3: 12 | G3: =C3+E3 -> 8 | H3: =SUM(IF(AND(AERO!C3:C101 > 0, AERO!D3:D101 = 0, AERO!F3:F101 > 0), 1, 0)) -> 0 | I3: =G3/F3 -> 0.66666667 | J3: =IF((I3<0.2),"YES","") | K3: =IF((I3>0.8),"YES","")
A4: BAEN | B4: =sum(BAEN!C2:C885) -> 0 | C4: =sum(BAEN!D2:D885) -> 0 | D4: =sum(BAEN!E2:E885) -> 0 | E4: =sum(BAEN!F2:F885) -> 0 | F4: 18 | G4: =C4+E4 -> 0 | H4: =SUM(IF(AND(AERO!C4:C102 > 0, AERO!D4:D102 = 0, AERO!F4:F102 > 0), 1, 0)) -> 0 | I4: =G4/F4 -> 0
A5: BMEN | B5: =SUM(BMEN!C2:C885) -> 2 | C5: =SUM(BMEN!D2:D885) -> 1 | D5: =SUM(BMEN!E2:E885) -> 4 | E5: =SUM(BMEN!F2:F885) -> 3 | F5: 40 | G5: =C5+E5 -> 4 | H5: =SUM(IF(AND(AERO!C5:C103 > 0, AERO!D5:D103 = 0, AERO!F5:F103 > 0), 1, 0)) -> 0 | I5: =G5/F5 -> 0.1
A6: CHEN | B6: =SUM(CHEN!C2:C885) -> 67 | C6: =SUM(CHEN!D2:D885) -> 62 | D6: =SUM(CHEN!E2:E885) -> 40 | E6: =SUM(CHEN!F2:F885) -> 41 | F6: 52 | G6: =C6+E6 -> 103 | H6: =SUM(IF(AND(AERO!C6:C104 > 0, AERO!D6:D104 = 0, AERO!F6:F104 > 0), 1, 0)) -> 0 | I6: =G6/F6 -> 1.9807692
A7: CECN/CEEN | B7: =SUM(CECNCEEN!C2:C885) -> 20 | C7: =SUM(CECNCEEN!D2:D885) -> 16 | D7: =SUM(CECNCEEN!E2:E885) -> 5 | E7: =SUM(CECNCEEN!F2:F885) -> 5 | F7: 38 | G7: =C7+E7 -> 21 | H7: =SUM(IF(AND(AERO!C7:C105 > 0, AERO!D7:D105 = 0, AERO!F7:F105 > 0), 1, 0)) -> 0 | I7: =G7/F7 -> 0.55263158
A8: CPSC | B8: =SUM(CPSC!C2:C885) -> 23 | C8: =SUM(CPSC!D2:D885) -> 20 | D8: =SUM(CPSC!E2:E885) -> 10 | E8: =SUM(CPSC!F2:F885) -> 10 | F8: 100 | G8: =C8+E8 -> 30 | H8: =SUM(IF(AND(AERO!C8:C106 > 0, AERO!D8:D106 = 0, AERO!F8:F106 > 0), 1, 0)) -> 0 | I8: =G8/F8 -> 0.3
A9: CVEN | B9: =SUM(CVEN!C2:C885) -> 116 | C9: =SUM(CVEN!D2:D885) -> 92 | D9: =SUM(CVEN!E2:E885) -> 92 | E9: =SUM(CVEN!F2:F885) -> 100 | F9: 64 | G9: =C9+E9 -> 192 | H9: =SUM(IF(AND(AERO!C9:C107 > 0, AERO!D9:D107 = 0, AERO!F9:F107 > 0), 1, 0)) -> 0 | I9: =G9/F9 -> 3
A10: ELEN | B10: =SUM(ELEN!C2:C885) -> 72 | C10: =SUM(ELEN!D2:D885) -> 63 | D10: =SUM(ELEN!E2:E885) -> 54 | E10: =SUM(ELEN!F2:F885) -> 46 | F10: 92 | G10: =C10+E10 -> 109 | H10: =SUM(IF(AND(AERO!C10:C108 > 0, AERO!D10:D108 = 0, AERO!F10:F108 > 0), 1, 0)) -> 0 | I10: =G10/F10 -> 1.1847826
A11: ESET | B11: =SUM(ESET!C2:C885) -> 1 | C11: =SUM(ESET!D2:D885) -> 1 | D11: =SUM(ESET!E2:E885) -> 1 | E11: =SUM(ESET!F2:F885) -> 1 | F11: 26 | G11: =C11+E11 -> 2 | H11: =SUM(IF(AND(AERO!C11:C109 > 0, AERO!D11:D109 = 0, AERO!F11:F109 > 0), 1, 0)) -> 0 | I11: =G11/F11 -> 0.076923077
A12: EVEN | B12: =SUM(EVEN!C2:C885) -> 1 | C12: =SUM(EVEN!D2:D885) -> 1 | D12: =SUM(EVEN!E2:E885) -> 0 | E12: =SUM(EVEN!F2:F885) -> 0 | F12: 12 | G12: =C12+E12 -> 1 | H12: =SUM(IF(AND(AERO!C12:C110 > 0, AERO!D12:D110 = 0, AERO!F12:F110 > 0), 1, 0)) -> 0 | I12: =G12/F12 -> 0.083333333
A13: IDIS | B13: =SUM(IDIS!C2:C885) -> 3 | C13: =SUM(IDIS!D2:D885) -> 3 | D13: =SUM(IDIS!E2:E885) -> 2 | E13: =SUM(IDIS!F2:F885) -> 2 | F13: 56 | G13: =C13+E13 -> 5 | H13: =SUM(IF(AND(AERO!C13:C111 > 0, AERO!D13:D111 = 0, AERO!F13:F111 > 0), 1, 0)) -> 0 | I13: =G13/F13 -> 0.089285714
A14: ISEN | B14: =SUM(ISEN!C2:C885) -> 9 | C14: =SUM(ISEN!D2:D885) -> 5 | D14: =SUM(ISEN!E2:E885) -> 7 | E14: =SUM(ISEN!F2:F885) -> 3 | F14: 78 | G14: =C14+E14 -> 8 | H14: =SUM(IF(AND(AERO!C14:C112 > 0, AERO!D14:D112 = 0, AERO!F14:F112 > 0), 1, 0)) -> 0 | I14: =G14/F14 -> 0.1025641
A15: MEEN | B15: =SUM(MEEN!C2:C885) -> 125 | C15: =SUM(MEEN!D2:D885) -> 108 | D15: =SUM(MEEN!E2:E885) -> 109 | E15: =SUM(MEEN!F2:F885) -> 102 | F15: 114 | G15: =C15+E15 -> 210 | H15: =SUM(IF(AND(AERO!C15:C113 > 0, AERO!D15:D113 = 0, AERO!F15:F113 > 0), 1, 0)) -> 0 | I15: =G15/F15 -> 1.8421053
A16: MMET | B16: =SUM(MMET!C2:C885) -> 6 | C16: =SUM(MMET!D2:D885) -> 6 | D16: =SUM(MMET!E2:E885) -> 10 | E16: =SUM(MMET!F2:F885) -> 6 | F16: 26 | G16: =C16+E16 -> 12 | H16: =SUM(IF(AND(AERO!C16:C114 > 0, AERO!D16:D114 = 0, AERO!F16:F114 > 0), 1, 0)) -> 0 | I16: =G16/F16 -> 0.46153846
A17: MSEN | B17: =sum(MSEN!C2:C885) -> 7 | C17: =sum(MSEN!D2:D885) -> 3 | D17: =sum(MSEN!E2:E885) -> 1 | E17: =sum(MSEN!F2:F885) -> 1 | F17: 24 | G17: =C17+E17 -> 4 | H17: =SUM(IF(AND(AERO!C17:C115 > 0, AERO!D17:D115 = 0, AERO!F17:F115 > 0), 1, 0)) -> 0 | I17: =G17/F17 -> 0.16666667
A18: MXET | B18: =SUM(MXET!C2:C885) -> 2 | C18: =SUM(MXET!D2:D885) -> 2 | D18: =SUM(MXET!E2:E885) -> 2 | E18: =SUM(MXET!F2:F885) -> 2 | F18: 26 | G18: =C18+E18 -> 4 | H18: =SUM(IF(AND(AERO!C18:C116 > 0, AERO!D18:D116 = 0, AERO!F18:F116 > 0), 1, 0)) -> 0 | I18: =G18/F18 -> 0.15384615
A19: NUEN | B19: =SUM(NUEN!C2:C885) -> 7 | C19: =SUM(NUEN!D2:D885) -> 7 | D19: =SUM(NUEN!E2:E885) -> 5 | E19: =SUM(NUEN!F2:F885) -> 5 | F19: 24 | G19: =C19+E19 -> 12 | H19: =SUM(IF(AND(AERO!C19:C117 > 0, AERO!D19:D117 = 0, AERO!F19:F117 > 0), 1, 0)) -> 0 | I19: =G19/F19 -> 0.5
A20: OCEN | B20: =SUM(OCEN!C2:C885) -> 5 | C20: =SUM(OCEN!D2:D885) -> 4 | D20: =SUM(OCEN!E2:E885) -> 3 | E20: =SUM(OCEN!F2:F885) -> 2 | F20: 14 | G20: =C20+E20 -> 6 | H20: =SUM(IF(AND(AERO!C20:C118 > 0, AERO!D20:D118 = 0, AERO!F20:F118 > 0), 1, 0)) -> 0 | I20: =G20/F20 -> 0.42857143
A21: PETE | B21: =SUM(PETE!C2:C885) -> 18 | C21: =SUM(PETE!D2:D885) -> 17 | D21: =SUM(PETE!E2:E885) -> 12 | E21: =SUM(PETE!F2:F885) -> 13 | F21: 26 | G21: =C21+E21 -> 30 | H21: =SUM(IF(AND(AERO!C21:C119 > 0, AERO!D21:D119 = 0, AERO!F21:F119 > 0), 1, 0)) -> 0 | I21: =G21/F21 -> 1.1538462
A22: DATA | B22: =SUM(DATA!C2:C885) -> 2 | C22: =SUM(DATA!D2:D885) -> 2 | D22: =SUM(DATA!E2:E885) -> 2 | E22: =SUM(DATA!F2:F885) -> 2 | F22: 4 | G22: =C22+E22 -> 4 | H22: =SUM(IF(AND(AERO!C22:C120 > 0, AERO!D22:D120 = 0, AERO!F22:F120 > 0), 1, 0)) -> 0 | I22: =G22/F22 -> 1
B23: =SUM(B2:B22) -> 516 | C23: =SUM(C2:C22) -> 439 | D23: =SUM(D2:D22) -> 374 | E23: =SUM(E2:E22) -> 358
C24: =C23/450 -> 0.97555556 | E24: =E23/450 -> 0.79555556

Sheet Companies on Wednesday Waitlist
A1: Company Name | B1: Points Values | C1: Status | E1: Package | F1: Status/Outcome | G1: Notes | I1: Legend
A2: Powell Industries | C2: switch to wednesday? | D2: Yes
A3: Lubrizol | C3: Unable to attend Thursday | D3: Yes
A4: Enercon | C4: said no to BTT, been BTT'ed for 2 fairs | D4: Yes
A5: Samson | C5: Unable to attend Thursday | D5: Yes

Sheet AERO
A1: AERO 54 | B1: Score | C1: Requested Wednesday Booths | D1: Final Wednesday Booths | E1: Requested Thursday Booths | F1: Final Thursday Booths | G1: Decision
A2: Lockheed Martin | B2: =IFERROR(VLOOKUP(A2, 'Current Decisions'!A:G, 7, FALSE), "") -> 58.2 | C2: 2 | D2: 2 | E2: 0 | F2: 0 | G2: C
A3: American Airlines | B3: =IFERROR(VLOOKUP(A3, 'Current Decisions'!A:G, 7, FALSE), "") -> 52 | C3: 2 | D3: 2 | E3: 0 | F3: 0 | G3: C
A4: Delta Airlines | B4: =IFERROR(VLOOKUP(A4, 'Current Decisions'!A:G, 7, FALSE), "") -> 41.9 | C4: 2 | D4: 2 | E4: 0 | F4: 0 | G4: C
A5: RTX | B5: =IFERROR(VLOOKUP(A5, 'Current Decisions'!A:G, 7, FALSE), "") -> 39.3 | C5: 2 | D5: =C5 -> 2 | E5: 0 | F5: =E5 -> 0 | G5: C
A6: Odyssey Space Research | B6: =IFERROR(VLOOKUP(A6, 'Current Decisions'!A:G, 7, FALSE), "") -> 39 | C6: 1 | D6: =C6 -> 1 | E6: 1 | F6: =E6 -> 1 | G6: C
A7: Bayer U.S. | B7: =IFERROR(VLOOKUP(A7, 'Current Decisions'!A:G, 7, FALSE), "") -> 26.7 | C7: 1 | D7: 1 | E7: 0 | F7: 0 | G7: C
A8: Science Applications International Corporation (SAIC) | B8: =IFERROR(VLOOKUP(A8, 'Current Decisions'!A:G, 7, FALSE), "") -> 26.1 | C8: 1 | D8: =C8 -> 1 | E8: 1 | F8: =E8 -> 1 | G8: C
A9: Genesys Aerosystems | B9: =IFERROR(VLOOKUP(A9, 'Current Decisions'!A:G, 7, FALSE), "") -> 25.6 | C9: 1 | D9: 1 | E9: 0 | F9: 0 | G9: C
A10: Aegis Aerospace | B10: =IFERROR(VLOOKUP(A10, 'Current Decisions'!A:G, 7, FALSE), "") -> 24 | C10: 1 | D10: 1 | E10: 0 | F10: 0 | G10: C
A11: The Acutronic Company | B11: =IFERROR(VLOOKUP(A11, 'Current Decisions'!A:G, 7, FALSE), "") -> 22.5 | C11: 1 | D11: =C11 -> 1 | E11: 1 | F11: =E11 -> 1 | G11: C
A12: L3Harris Technologies (Gold Partner) | B12: =IFERROR(VLOOKUP(A12, 'Current Decisions'!A:G, 7, FALSE), "") -> 20.6 | C12: 3 | D12: =C12 -> 3 | E12: 3 | F12: =E12 -> 3 | G12: C
A13: SEC Test Employer | B13: =IFERROR(VLOOKUP(A13, 'Current Decisions'!A:G, 7, FALSE), "") -> 16.2 | C13: 1 | D13: 0 | E13: 1 | F13: 0 | G13: r
A14: Firefly Aerospace | B14: =IFERROR(VLOOKUP(A14, 'Current Decisions'!A:G, 7, FALSE), "") -> 12.5 | C14: 1 | D14: =C14 -> 1 | E14: 1 | F14: =E14 -> 1 | G14: C
A15: Elbit Systems of America | B15: =IFERROR(VLOOKUP(A15, 'Current Decisions'!A:G, 7, FALSE), "") -> 8.8 | C15: 2 | D15: =C15 -> 2 | E15: 0 | F15: =E15 -> 0 | G15: C
A16: Albers Aerospace | B16: =IFERROR(VLOOKUP(A16, 'Current Decisions'!A:G, 7, FALSE), "") -> 5 | C16: 1 | D16: =C16 -> 1 | E16: 1 | F16: =E16 -> 1 | G16: C
A17: Gulfstream Aerospace | B17: =IFERROR(VLOOKUP(A17, 'Current Decisions'!A:G, 7, FALSE), "") -> 45.3 | C17: 0 | D17: 0 | E17: 1 | F17: 1 | G17: C
A18: Palski & Associates, Inc. | B18: =IFERROR(VLOOKUP(A18, 'Current Decisions'!A:G, 7, FALSE), "") -> 10.5 | C18: 0 | D18: 0 | E18: 1 | F18: 1 | G18: C
A19: Amentum | B19: =IFERROR(VLOOKUP(A19, 'Current Decisions'!A:G, 7, FALSE), "") -> 24.6 | C19: 0 | D19: 0 | E19: 1 | F19: 1 | G19: C

Sheet AREN
A1: AREN 42 | B1: Score | C1: Requested Wednesday Booths | D1: Final Wednesday Booths | E1: Requested Thursday Booths | F1: Final Thursday Booths | G1: Decision
A2: Intelligent Engineering Services | B2: =IFERROR(VLOOKUP(A2, 'Current Decisions'!A:G, 7, FALSE), "") -> 23.8 | C2: 1 | D2: =C2 -> 1 | E2: 1 | F2: =E2 -> 1 | G2: C
A3: Keystone Concrete | B3: =IFERROR(VLOOKUP(A3, 'Current Decisions'!A:G, 7, FALSE), "") -> 22.5 | C3: 1 | D3: =C3 -> 1 | E3: 1 | F3: =E3 -> 1 | G3: C
A4: QTS Data Centers | B4: =IFERROR(VLOOKUP(A4, 'Current Decisions'!A:G, 7, FALSE), "") -> 14.7 | C4: 1 | D4: =C4 -> 1 | E4: 1 | F4: =E4 -> 1 | G4: C
A5: Telios Corporation | B5: =IFERROR(VLOOKUP(A5, 'Current Decisions'!A:G, 7, FALSE), "") -> 24 | C5: 1 | D5: =C5 -> 1 | E5: 0 | F5: =E5 -> 0 | G5: C
A6: Wylie Engineering | B6: =IFERROR(VLOOKUP(A6, 'Current Decisions'!A:G, 7, FALSE), "") -> 26 | C6: 1 | D6: =C6 -> 1 | E6: 0 | F6: =E6 -> 0 | G6: C
A7: Fransen Pittman General Contractors | B7: =IFERROR(VLOOKUP(A7, 'Current Decisions'!A:G, 7, FALSE), "") -> 8.2 | C7: 1 | E7: 0 | G7: r
A8: Smith Seckman Reid, inc. (SSR) | B8: =IFERROR(VLOOKUP(A8, 'Current Decisions'!A:G, 7, FALSE), "") -> 10.5 | C8: 1 | E8: 0 | G8: r
A9: Talley Riggins Construction Group | B9: =IFERROR(VLOOKUP(A9, 'Current Decisions'!A:G, 7, FALSE), "") -> 23.4 | C9: 1 | E9: 0 | G9: r

Sheet BAEN
A1: BAEN 18 | B1: Score | C1: Requested Wednesday Booths | D1: Final Wednesday Booths | E1: Requested Thursday Booths | F1: Final Thursday Booths | G1: Decision

Sheet BMEN
A1: BMEN 40 | B1: Score | C1: Requested Wednesday Booths | D1: Final Wednesday Booths | E1: Requested Thursday Booths | F1: Final Thursday Booths | G1: Decision
A2: School of Engineering Medicine | B2: =IFERROR(VLOOKUP(A2, 'Current Decisions'!A:G, 7, FALSE), "") -> 1.5 | C2: 0 | D2: 0 | E2: 1 | F2: 1 | G2: C
A3: Texas A&M Military Medicine | B3: =IFERROR(VLOOKUP(A3, 'Current Decisions'!A:G, 7, FALSE), "") -> 15 | C3: 1 | E3: 1 | G3: r
A4: Texas A&M University School of Public Health | B4: =IFERROR(VLOOKUP(A4, 'Current Decisions'!A:G, 7, FALSE), "") -> 30.5 | C4: 0 | D4: 0 | E4: 1 | F4: 1 | G4: C
A5: Eli Lilly and Company | B5: =IFERROR(VLOOKUP(A5, 'Current Decisions'!A:G, 7, FALSE), "") -> 44.7 | C5: 1 | D5: 1 | E5: 1 | F5: 1 | G5: C

Sheet CHEN
B1: Score | C1: Requested Wednesday Booths | D1: Final Wednesday Booths | E1: Requested Thursday Booths | F1: Final Thursday Booths | G1: Decision
A2: Valero | B2: =IFERROR(VLOOKUP(A2, 'Current Decisions'!A:G, 7, FALSE), "") -> 64 | C2: 2 | D2: =C2 -> 2 | E2: 2 | F2: =E2 -> 2 | G2: C
A3: Dow inc. | B3: =IFERROR(VLOOKUP(A3, 'Current Decisions'!A:G, 7, FALSE), "") -> 60 | C3: 1 | D3: =C3 -> 1 | E3: 0 | F3: =E3 -> 0 | G3: C | H3: WS not calculated in invoice
A4: ExxonMobil (Silver Partner) | B4: =IFERROR(VLOOKUP(A4, 'Current Decisions'!A:G, 7, FALSE), "") -> 59.5 | C4: 3 | D4: =C4 -> 3 | E4: 3 | F4: =E4 -> 3 | G4: C
A5: ConocoPhillips (Gold Partner) | B5: =IFERROR(VLOOKUP(A5, 'Current Decisions'!A:G, 7, FALSE), "") -> 51.6 | C5: 2 | E5: 0 | G5: r
A6: Johnson & Johnson | B6: =IFERROR(VLOOKUP(A6, 'Current Decisions'!A:G, 7, FALSE), "") -> 47.6 | C6: 1 | D6: =C6 -> 1 | E6: 1 | F6: =E6 -> 1 | G6: C
A7: Marathon Petroleum Corporation | B7: =IFERROR(VLOOKUP(A7, 'Current Decisions'!A:G, 7, FALSE), "") -> 46.7 | C7: 2 | D7: =C7 -> 2 | E7: 2 | F7: =E7 -> 2 | G7: C
A8: Indorama Ventures | B8: =IFERROR(VLOOKUP(A8, 'Current Decisions'!A:G, 7, FALSE), "") -> 45.3 | C8: 1 | D8: =C8 -> 1 | E8: 0 | F8: =E8 -> 0 | G8: C
A9: Hess Corporation | B9: =IFERROR(VLOOKUP(A9, 'Current Decisions'!A:G, 7, FALSE), "") -> 44.8 | C9: 1 | D9: 0 | E9: 1 | F9: 0 | G9: r
A10: Phillips 66 (Silver Partner) | B10: =IFERROR(VLOOKUP(A10, 'Current Decisions'!A:G, 7, FALSE), "") -> 43.8 | C10: 2 | D10: 2 | E10: 0 | F10: 0 | G10: C
A11: Covestro LLC | B11: =IFERROR(VLOOKUP(A11, 'Current Decisions'!A:G, 7, FALSE), "") -> 42.7 | C11: 1 | D11: 1 | E11: 0 | F11: 0 | G11: C
A12: Fluor Corporation | B12: =IFERROR(VLOOKUP(A12, 'Current Decisions'!A:G, 7, FALSE), "") -> 42.1 | C12: 1 | D12: =C12 -> 1 | E12: 1 | F12: =E12 -> 1 | G12: C
A13: Evonik | B13: =IFERROR(VLOOKUP(A13, 'Current Decisions'!A:G, 7, FALSE), "") -> 42 | C13: 2 | D13: 2 | E13: 2 | F13: 2 | G13: C
A14: Air Liquide | B14: =IFERROR(VLOOKUP(A14, 'Current Decisions'!A:G, 7, FALSE), "") -> 41.9 | C14: 1 | D14: =C14 -> 1 | E14: 0 | F14: =E14 -> 0 | G14: C
A15: Eastman Chemical | B15: =IFERROR(VLOOKUP(A15, 'Current Decisions'!A:G, 7, FALSE), "") -> 39.9 | C15: 2 | D15: =C15 -> 2 | E15: 2 | F15: =E15 -> 2 | G15: C
A16: Venture Global LNG | B16: =IFERROR(VLOOKUP(A16, 'Current Decisions'!A:G, 7, FALSE), "") -> 38.4 | C16: 1 | D16: 2 | E16: 1 | F16: 2 | G16: C
A17: LyondellBasell | B17: =IFERROR(VLOOKUP(A17, 'Current Decisions'!A:G, 7, FALSE), "") -> 38.3 | C17: 2 | D17: =C17 -> 2 | E17: 2 | F17: =E17 -> 2 | G17: C
A18: Kaneka North America | B18: =IFERROR(VLOOKUP(A18, 'Current Decisions'!A:G, 7, FALSE), "") -> 36.7 | C18: 1 | D18: 1 | E18: 1 | F18: 1 | G18: C
A19: Enterprise Products Company | B19: =IFERROR(VLOOKUP(A19, 'Current Decisions'!A:G, 7, FALSE), "") -> 35.8 | C19: 2 | D19: 2 | E19: 0 | F19: 0 | G19: C
A20: Olin | B20: =IFERROR(VLOOKUP(A20, 'Current Decisions'!A:G, 7, FALSE), "") -> 34.6 | C20: 3 | D20: =C20 -> 3 | E20: 0 | F20: =E20 -> 0 | G20: C
A21: Trinity Consultants | B21: =IFERROR(VLOOKUP(A21, 'Current Decisions'!A:G, 7, FALSE), "") -> 31.5 | C21: 1 | D21: =C21 -> 1 | E21: 0 | F21: =E21 -> 0 | G21: C
A22: Audubon Companies | B22: =IFERROR(VLOOKUP(A22, 'Current Decisions'!A:G, 7, FALSE), "") -> 31.2 | C22: 1 | D22: =C22 -> 1 | E22: 0 | F22: =E22 -> 0 | G22: C
A23: Nouryon | B23: =IFERROR(VLOOKUP(A23, 'Current Decisions'!A:G, 7, FALSE), "") -> 31.2 | C23: 1 | D23: 1 | E23: 0 | F23: 0 | G23: C
A24: Energy Transfer | B24: =IFERROR(VLOOKUP(A24, 'Current Decisions'!A:G, 7, FALSE), "") -> 30.7 | C24: 2 | D24: 2 | E24: 0 | F24: 0 | G24: C
A25: AbbVie | B25: =IFERROR(VLOOKUP(A25, 'Current Decisions'!A:G, 7, FALSE), "") -> 30.1 | C25: 1 | D25: 1 | E25: 0 | F25: 0 | G25: C
A26: Bryan Research & Engineering | B26: =IFERROR(VLOOKUP(A26, 'Current Decisions'!A:G, 7, FALSE), "") -> 30 | C26: 1 | D26: =C26 -> 1 | E26: 0 | F26: =E26 -> 0 | G26: C
A27: Westlake Corporation | B27: =IFERROR(VLOOKUP(A27, 'Current Decisions'!A:G, 7, FALSE), "") -> 26.8 | C27: 2 | D27: =C27 -> 2 | E27: 0 | F27: =E27 -> 0 | G27: C
A28: Owens Corning | B28: =IFERROR(VLOOKUP(A28, 'Current Decisions'!A:G, 7, FALSE), "") -> 26.1 | C28: 1 | D28: =C28 -> 1 | E28: 0 | F28: =E28 -> 0 | G28: C
A29: INEOS Olefins & Polymers USA | B29: =IFERROR(VLOOKUP(A29, 'Current Decisions'!A:G, 7, FALSE), "") -> 25.3 | C29: 2 | D29: =C29 -> 2 | E29: 2 | F29: =E29 -> 2 | G29: C
A30: Ecolab | B30: =IFERROR(VLOOKUP(A30, 'Current Decisions'!A:G, 7, FALSE), "") -> 25.3 | C30: 2 | D30: 2 | E30: 0 | F30: 0 | G30: C
A31: SI Group | B31: =IFERROR(VLOOKUP(A31, 'Current Decisions'!A:G, 7, FALSE), "") -> 23.8 | C31: 1 | D31: =C31 -> 1 | E31: 0 | F31: =E31 -> 0 | G31: C
A32: Entegris, Inc. | B32: =IFERROR(VLOOKUP(A32, 'Current Decisions'!A:G, 7, FALSE), "") -> 20 | C32: 1 | D32: 1 | E32: 1 | F32: 1 | G32: C
A33: Syensqo | B33: =IFERROR(VLOOKUP(A33, 'Current Decisions'!A:G, 7, FALSE), "") -> 19.9 | C33: 0 | D33: 0 | E33: 1 | F33: 1 | G33: C
A34: CLS Industrial Purification | B34: =IFERROR(VLOOKUP(A34, 'Current Decisions'!A:G, 7, FALSE), "") -> 19.5 | C34: 1 | D34: 1 | E34: 1 | F34: 1 | G34: C
A35: Albemarle Corporation | B35: =IFERROR(VLOOKUP(A35, 'Current Decisions'!A:G, 7, FALSE), "") -> 18.8 | C35: 1 | D35: =C35 -> 1 | E35: 0 | F35: =E35 -> 0 | G35: C
A36: CITGO Refining & Chemical | B36: =IFERROR(VLOOKUP(A36, 'Current Decisions'!A:G, 7, FALSE), "") -> 18 | C36: 4 | D36: =C36 -> 4 | E36: 4 | F36: =E36 -> 4 | G36: C
A37: FUJIFILM Biotechnologies | B37: =IFERROR(VLOOKUP(A37, 'Current Decisions'!A:G, 7, FALSE), "") -> 17.2 | C37: 1 | D37: 1 | E37: 1 | F37: 1 | G37: C
A38: Ingenia Polymers Inc | B38: =IFERROR(VLOOKUP(A38, 'Current Decisions'!A:G, 7, FALSE), "") -> 17.2 | C38: 0 | D38: 0 | E38: 1 | F38: 1 | G38: C
A39: *Weaver | B39: =IFERROR(VLOOKUP(A39, 'Current Decisions'!A:G, 7, FALSE), "") -> 15.3 | C39: 1 | E39: 0 | G39: BTT - emailed
A40: Motiva Enterprises (Silver Partner) | B40: =IFERROR(VLOOKUP(A40, 'Current Decisions'!A:G, 7, FALSE), "") -> 15 | C40: 2 | D40: =C40 -> 2 | E40: 2 | F40: =E40 -> 2 | G40: C
A41: Lubrizol Corporation | B41: =IFERROR(VLOOKUP(A41, 'Current Decisions'!A:G, 7, FALSE), "") -> 8 | C41: 1 | D41: 1 | E41: 0 | F41: 0 | G41: C
A42: Harvest Midstream Company | B42: =IFERROR(VLOOKUP(A42, 'Current Decisions'!A:G, 7, FALSE), "") -> 7.2 | C42: 1 | D42: 1 | E42: 1 | F42: 1 | G42: C
A43: Chevron Phillips Chemical Company - The Woodlands, TX | B43: =IFERROR(VLOOKUP(A43, 'Current Decisions'!A:G, 7, FALSE), "") -> 6.7 | C43: 2 | D43: =C43 -> 2 | E43: 2 | F43: =E43 -> 2 | G43: C
A44: Altamira-US, LLC | B44: =IFERROR(VLOOKUP(A44, 'Current Decisions'!A:G, 7, FALSE), "") -> 6.7 | C44: 0 | D44: 0 | E44: 1 | F44: 1 | G44: C
A45: Ketjen Corporation | B45: =IFERROR(VLOOKUP(A45, 'Current Decisions'!A:G, 7, FALSE), "") -> 6.5 | C45: 1 | D45: 1 | E45: 0 | F45: 0 | G45: C
A46: Signal Peak Silica, LLC | B46: =IFERROR(VLOOKUP(A46, 'Current Decisions'!A:G, 7, FALSE), "") -> 0 | C46: 0 | D46: 0 | E46: 1 | F46: 1 | G46: C
A47: Huntsman | B47: =IFERROR(VLOOKUP(A47, 'Current Decisions'!A:G, 7, FALSE), "") -> 39.5 | C47: 2 | D47: 2 | E47: 0 | F47: 0 | G47: C | H47: emailed about discounted thursday
A48: C. Tumey Law Group PLLC | B48: =IFERROR(VLOOKUP(A48, 'Current Decisions'!A:G, 7, FALSE), "") -> 0 | C48: 0 | D48: 0 | E48: 1 | F48: 1 | G48: C - BTT
A49: Celanese | B49: =IFERROR(VLOOKUP(A49, 'Current Decisions'!A:G, 7, FALSE), "") -> 25.3 | C49: 1 | D49: 1 | E49: 0 | F49: 0 | G49: C
A50: MEGlobal Americas Inc. | B50: =IFERROR(VLOOKUP(A50, 'Current Decisions'!A:G, 7, FALSE), "") -> 19.94 | C50: 1 | D50: 0 | E50: 0 | F50: 1 | G50: C - BTT
A51: Chemours Company | B51: =IFERROR(VLOOKUP(A51, 'Current Decisions'!A:G, 7, FALSE), "") -> 21.5 | C51: 0 | D51: 0 | E51: 1 | F51: 1 | G51: C
A52: BASF Corporation | B52: =IFERROR(VLOOKUP(A52, 'Current Decisions'!A:G, 7, FALSE), "") -> 54.7 | C52: 1 | D52: 0 | E52: 1 | F52: 1 | G52: C - BTT
A53: Contech | B53: =IFERROR(VLOOKUP(A53, 'Current Decisions'!A:G, 7, FALSE), "") -> 38.1 | C53: 0 | D53: 0 | E53: 1 | F53: 1 | G53: C

Sheet CPSC
A1: CPSC 100 | B1: Score | C1: Requested Wednesday Booths | D1: Final Wednesday Booths | E1: Requested Thursday Booths | F1: Final Thursday Booths | G1: Decision
A2: Toyota | B2: =IFERROR(VLOOKUP(A2, 'Current Decisions'!A:G, 7, FALSE), "") -> 47.5 | C2: 1 | D2: =C2 -> 1 | E2: 0 | F2: =E2 -> 0 | G2: C
A3: Capco | B3: =IFERROR(VLOOKUP(A3, 'Current Decisions'!A:G, 7, FALSE), "") -> 45.3 | C3: 1 | D3: =C3 -> 1 | E3: 0 | F3: =E3 -> 0 | G3: C
A4: Arm, Inc. | B4: =IFERROR(VLOOKUP(A4, 'Current Decisions'!A:G, 7, FALSE), "") -> 42 | C4: 1 | D4: =C4 -> 1 | E4: 0 | F4: =E4 -> 0 | G4: C
A5: Alcon | B5: =IFERROR(VLOOKUP(A5, 'Current Decisions'!A:G, 7, FALSE), "") -> 40.3 | C5: 1 | D5: =C5 -> 1 | E5: 0 | F5: =E5 -> 0 | G5: C
A6: NCR Atleos | B6: =IFERROR(VLOOKUP(A6, 'Current Decisions'!A:G, 7, FALSE), "") -> 36.7 | C6: 0 | D6: 0 | E6: 1 | F6: 1 | G6: C
A7: Paycom | B7: =IFERROR(VLOOKUP(A7, 'Current Decisions'!A:G, 7, FALSE), "") -> 32.7 | C7: 1 | D7: =C7 -> 1 | E7: 1 | F7: =E7 -> 1 | G7: C
A8: CAPSHER Technology | B8: =IFERROR(VLOOKUP(A8, 'Current Decisions'!A:G, 7, FALSE), "") -> 29.7 | C8: 1 | D8: =C8 -> 1 | E8: 1 | F8: =E8 -> 1 | G8: C
A9: Credera | B9: =IFERROR(VLOOKUP(A9, 'Current Decisions'!A:G, 7, FALSE), "") -> 28 | C9: 2 | D9: 2 | E9: 0 | F9: 0 | G9: C
A10: Epic | B10: =IFERROR(VLOOKUP(A10, 'Current Decisions'!A:G, 7, FALSE), "") -> 22.2 | C10: 1 | D10: 1 | E10: 1 | F10: 1 | G10: C
A11: Labatt Food Service | B11: =IFERROR(VLOOKUP(A11, 'Current Decisions'!A:G, 7, FALSE), "") -> 21.5 | C11: 1 | D11: =C11 -> 1 | E11: 0 | F11: =E11 -> 0 | G11: C
A12: Texas A&M Institute of Data Science | B12: =IFERROR(VLOOKUP(A12, 'Current Decisions'!A:G, 7, FALSE), "") -> 20 | C12: 1 | D12: 0 | E12: 1 | F12: 1 | G12: C
A13: Valent Partners | B13: =IFERROR(VLOOKUP(A13, 'Current Decisions'!A:G, 7, FALSE), "") -> 17 | C13: 1 | D13: =C13 -> 1 | E13: 0 | F13: =E13 -> 0 | G13: C
A14: LoneStar NDE Innovations | B14: =IFERROR(VLOOKUP(A14, 'Current Decisions'!A:G, 7, FALSE), "") -> 15 | C14: 1 | D14: 1 | E14: 1 | F14: 1 | G14: C
A15: CACI-NASA Johnson Space Center | B15: =IFERROR(VLOOKUP(A15, 'Current Decisions'!A:G, 7, FALSE), "") -> 14.1 | C15: 1 | D15: =C15 -> 1 | E15: 1 | F15: =E15 -> 1 | G15: C
A16: State Farm | B16: =IFERROR(VLOOKUP(A16, 'Current Decisions'!A:G, 7, FALSE), "") -> 9.5 | C16: 1 | D16: =C16 -> 1 | E16: 0 | F16: =E16 -> 0 | G16: C
A17: Capital One | B17: =IFERROR(VLOOKUP(A17, 'Current Decisions'!A:G, 7, FALSE), "") -> 52.7 | C17: 2 | D17: 2 | E17: 0 | F17: 0 | G17: C | H17: emailed about discounted thursday
A18: Pariveda | B18: =IFERROR(VLOOKUP(A18, 'Current Decisions'!A:G, 7, FALSE), "") -> 15.5 | C18: 0 | D18: 0 | E18: 1 | F18: 1 | G18: C | H18: BTT
A19: G-Research | B19: =IFERROR(VLOOKUP(A19, 'Current Decisions'!A:G, 7, FALSE), "") -> 2.1 | C19: 1 | D19: 1 | E19: 0 | F19: 0 | G19: C
A20: Vectra AI | B20: =IFERROR(VLOOKUP(A20, 'Current Decisions'!A:G, 7, FALSE), "") -> 25.58 | C20: 1 | D20: 1 | E20: 0 | F20: 0 | G20: C
A21: Bitkernel Technology Inc | B21: =IFERROR(VLOOKUP(A21, 'Current Decisions'!A:G, 7, FALSE), "") -> 24.7 | C21: 1 | D21: 0 | E21: 1 | F21: 1 | G21: C | H21: BTT
A22: 1Finity, a Fujitsu Company | B22: =IFERROR(VLOOKUP(A22, 'Current Decisions'!A:G, 7, FALSE), "") -> 7.5 | C22: 1 | D22: 1 | E22: 0 | F22: 0 | G22: C
A23: Johns Hopkins Whiting School of Engineering | B23: =IFERROR(VLOOKUP(A23, 'Current Decisions'!A:G, 7, FALSE), "") -> 15 | C23: 1 | E23: 1 | F23: 1 | G23: BTT - emailed
A24: Epsilon | B24: =IFERROR(VLOOKUP(A24, 'Current Decisions'!A:G, 7, FALSE), "") -> 31.3 | C24: 1 | D24: 1 | E24: 0 | F24: 0 | G24: C

Sheet CVEN
A1: CVEN 64 | B1: Score | C1: Requested Wednesday Booths | D1: Final Wednesday Booths | E1: Requested Thursday Booths | F1: Final Thursday Booths | G1: Decision
A2: BGE, Inc | B2: =IFERROR(VLOOKUP(A2, 'Current Decisions'!A:G, 7, FALSE), "") -> 51.1 | C2: 2 | D2: =C2 -> 2 | E2: 2 | F2: =E2 -> 2 | G2: C
A3: Weaver Consultants Group | B3: =IFERROR(VLOOKUP(A3, 'Current Decisions'!A:G, 7, FALSE), "") -> 43.7 | C3: 1 | D3: =C3 -> 1 | E3: 0 | F3: =E3 -> 0 | G3: C
A4: AtkinsRéalis | B4: =IFERROR(VLOOKUP(A4, 'Current Decisions'!A:G, 7, FALSE), "") -> 43 | C4: 1 | D4: =C4 -> 1 | E4: 0 | F4: =E4 -> 0 | G4: C
A5: Massman Construction Co. | B5: =IFERROR(VLOOKUP(A5, 'Current Decisions'!A:G, 7, FALSE), "") -> 43 | C5: 1 | D5: 1 | E5: 0 | F5: 0 | G5: C
A6: Worley | B6: =IFERROR(VLOOKUP(A6, 'Current Decisions'!A:G, 7, FALSE), "") -> 41.8 | C6: 1 | D6: 1 | E6: 0 | F6: 0 | G6: C
A7: WSP USA | B7: =IFERROR(VLOOKUP(A7, 'Current Decisions'!A:G, 7, FALSE), "") -> 40.7 | C7: 1 | D7: =C7 -> 1 | E7: 1 | F7: =E7 -> 1 | G7: C
A8: Ferrovial | B8: =IFERROR(VLOOKUP(A8, 'Current Decisions'!A:G, 7, FALSE), "") -> 40.5 | C8: 2 | D8: =C8 -> 2 | E8: 2 | F8: =E8 -> 2 | G8: C
A9: Ferrovial | B9: =IFERROR(VLOOKUP(A9, 'Current Decisions'!A:G, 7, FALSE), "") -> 40.5 | C9: 2 | E9: 0 | G9: r
A10: Freese and Nichols | B10: =IFERROR(VLOOKUP(A10, 'Current Decisions'!A:G, 7, FALSE), "") -> 40.5 | C10: 2 | D10: =C10 -> 2 | E10: 2 | F10: =E10 -> 2 | G10: C
A11: Quanta Infrastructure Solutions Group LLC | B11: =IFERROR(VLOOKUP(A11, 'Current Decisions'!A:G, 7, FALSE), "") -> 38.5 | C11: 1 | D11: 1 | E11: 1 | F11: 1 | G11: C
A12: Pape-Dawson | B12: =IFERROR(VLOOKUP(A12, 'Current Decisions'!A:G, 7, FALSE), "") -> 38.2 | C12: 4 | D12: =C12 -> 4 | E12: 4 | F12: =E12 -> 4 | G12: C
A13: Accuracy | B13: =IFERROR(VLOOKUP(A13, 'Current Decisions'!A:G, 7, FALSE), "") -> 37.5 | C13: 1 | D13: =C13 -> 1 | E13: 0 | F13: =E13 -> 0 | G13: C
A14: TRC Companies Inc | B14: =IFERROR(VLOOKUP(A14, 'Current Decisions'!A:G, 7, FALSE), "") -> 36.4 | C14: 1 | D14: 1 | E14: 0 | F14: 0 | G14: C
A15: IEA Inc | B15: =IFERROR(VLOOKUP(A15, 'Current Decisions'!A:G, 7, FALSE), "") -> 35.9 | C15: 1 | D15: =C15 -> 1 | E15: 0 | F15: =E15 -> 0 | G15: C
A16: Civil & Environmental Consultants, Inc. | B16: =IFERROR(VLOOKUP(A16, 'Current Decisions'!A:G, 7, FALSE), "") -> 35.9 | C16: 0 | D16: 0 | E16: 1 | F16: 1 | G16: C
A17: HR Green | B17: =IFERROR(VLOOKUP(A17, 'Current Decisions'!A:G, 7, FALSE), "") -> 30.5 | C17: 1 | D17: =C17 -> 1 | E17: 0 | F17: =E17 -> 0 | G17: C
A18: Plummer Associates, Inc. | B18: =IFERROR(VLOOKUP(A18, 'Current Decisions'!A:G, 7, FALSE), "") -> 30.5 | C18: 1 | D18: =C18 -> 1 | E18: 0 | F18: =E18 -> 0 | G18: C
A19: Woolpert | B19: =IFERROR(VLOOKUP(A19, 'Current Decisions'!A:G, 7, FALSE), "") -> 30.5 | C19: 1 | D19: =C19 -> 1 | E19: 0 | F19: =E19 -> 0 | G19: C
A20: Benesch | B20: =IFERROR(VLOOKUP(A20, 'Current Decisions'!A:G, 7, FALSE), "") -> 29.7 | C20: 1 | D20: =C20 -> 1 | E20: 0 | F20: =E20 -> 0 | G20: C
A21: Halff Associates, Inc. | B21: =IFERROR(VLOOKUP(A21, 'Current Decisions'!A:G, 7, FALSE), "") -> 29.7 | C21: 2 | D21: =C21 -> 2 | E21: 2 | F21: =E21 -> 2 | G21: C
A22: McCarthy Building Companies, Inc. | B22: =IFERROR(VLOOKUP(A22, 'Current Decisions'!A:G, 7, FALSE), "") -> 29.7 | C22: 1 | D22: =C22 -> 1 | E22: 1 | F22: =E22 -> 1 | G22: C
A23: Dunaway | B23: =IFERROR(VLOOKUP(A23, 'Current Decisions'!A:G, 7, FALSE), "") -> 29 | C23: 1 | D23: 0 | E23: 0 | F23: =E23 -> 0 | G23: r
A24: DCS | B24: =IFERROR(VLOOKUP(A24, 'Current Decisions'!A:G, 7, FALSE), "") -> 29 | C24: 1 | D24: 1 | E24: 0 | F24: 0 | G24: C
A25: Great Lakes Dredge & Dock Company | B25: =IFERROR(VLOOKUP(A25, 'Current Decisions'!A:G, 7, FALSE), "") -> 28.9 | C25: 0 | D25: 1 | E25: 1 | F25: =E25 -> 1 | G25: C
A26: AME | B26: =IFERROR(VLOOKUP(A26, 'Current Decisions'!A:G, 7, FALSE), "") -> 28.3 | C26: 1 | D26: =C26 -> 1 | E26: 1 | F26: =E26 -> 1 | G26: C
A27: Burns & McDonnell | B27: =IFERROR(VLOOKUP(A27, 'Current Decisions'!A:G, 7, FALSE), "") -> 28.2 | C27: 2 | D27: =C27 -> 2 | E27: 2 | F27: =E27 -> 2 | G27: C
A28: Federal Aviation Administration (FAA) | B28: =IFERROR(VLOOKUP(A28, 'Current Decisions'!A:G, 7, FALSE), "") -> 28.2 | C28: 2 | D28: =C28 -> 2 | E28: 2 | F28: =E28 -> 2 | G28: C
A29: LJB Inc. | B29: =IFERROR(VLOOKUP(A29, 'Current Decisions'!A:G, 7, FALSE), "") -> 28.2 | C29: 1 | D29: =C29 -> 1 | E29: 0 | F29: =E29 -> 0 | G29: C
A30: Lockwood, Andrews, and Newnam, Inc. | B30: =IFERROR(VLOOKUP(A30, 'Current Decisions'!A:G, 7, FALSE), "") -> 28.2 | C30: 1 | D30: =C30 -> 1 | E30: 1 | F30: =E30 -> 1 | G30: C
A31: Schnabel | B31: =IFERROR(VLOOKUP(A31, 'Current Decisions'!A:G, 7, FALSE), "") -> 28.2 | C31: 1 | D31: =C31 -> 1 | E31: 0 | F31: =E31 -> 0 | G31: C
A32: Bush School Online | B32: =IFERROR(VLOOKUP(A32, 'Current Decisions'!A:G, 7, FALSE), "") -> 27.5 | C32: 0 | D32: 0 | E32: 1 | F32: 1 | G32: C
A33: Mott MacDonald | B33: =IFERROR(VLOOKUP(A33, 'Current Decisions'!A:G, 7, FALSE), "") -> 27.5 | C33: 1 | D33: =C33 -> 1 | E33: 0 | F33: =E33 -> 0 | G33: C
A34: Felsburg Holt & Ullevig | B34: =IFERROR(VLOOKUP(A34, 'Current Decisions'!A:G, 7, FALSE), "") -> 27 | C34: 1 | D34: 0 | E34: 0 | F34: =E34 -> 0 | G34: r
A35: BOE Consulting Services LLC | B35: =IFERROR(VLOOKUP(A35, 'Current Decisions'!A:G, 7, FALSE), "") -> 26.7 | C35: 1 | D35: =C35 -> 1 | E35: 0 | F35: =E35 -> 0 | G35: C
A36: Colliers Engineering & Design | B36: =IFERROR(VLOOKUP(A36, 'Current Decisions'!A:G, 7, FALSE), "") -> 26.7 | C36: 1 | D36: =C36 -> 1 | E36: 0 | F36: =E36 -> 0 | G36: C
A37: Manhard Consulting | B37: =IFERROR(VLOOKUP(A37, 'Current Decisions'!A:G, 7, FALSE), "") -> 26.7 | C37: 1 | D37: =C37 -> 1 | E37: 1 | F37: =E37 -> 1 | G37: C
A38: EHRA | B38: =IFERROR(VLOOKUP(A38, 'Current Decisions'!A:G, 7, FALSE), "") -> 26.7 | C38: 0 | D38: 0 | E38: 1 | F38: 1 | G38: C - BTT
A39: Quiddity Engineering | B39: =IFERROR(VLOOKUP(A39, 'Current Decisions'!A:G, 7, FALSE), "") -> 26 | C39: 1 | D39: =C39 -> 1 | E39: 1 | F39: =E39 -> 1 | G39: C
A40: Wade Trim | B40: =IFERROR(VLOOKUP(A40, 'Current Decisions'!A:G, 7, FALSE), "") -> 26 | C40: 1 | D40: =C40 -> 1 | E40: 0 | F40: =E40 -> 0 | G40: C
A41: Locke Solutions | B41: =IFERROR(VLOOKUP(A41, 'Current Decisions'!A:G, 7, FALSE), "") -> 25.5 | D41: 0 | F41: =E41 | G41: R
A42: Lynn Engineering | B42: =IFERROR(VLOOKUP(A42, 'Current Decisions'!A:G, 7, FALSE), "") -> 25.3 | C42: 0 | D42: =C42 -> 0 | E42: 1 | F42: =E42 -> 1 | G42: C
A43: TRC Companies | B43: =IFERROR(VLOOKUP(A43, 'Current Decisions'!A:G, 7, FALSE), "") -> 25.3 | D43: 0 | F43: 0 | G43: R | H43: confirmed their other registration
A44: Engineering Consulting Services (ECS) | B44: =IFERROR(VLOOKUP(A44, 'Current Decisions'!A:G, 7, FALSE), "") -> 24.5 | C44: 1 | D44: =C44 -> 1 | E44: 0 | F44: =E44 -> 0 | G44: C
A45: Graham Associates, Inc. | B45: =IFERROR(VLOOKUP(A45, 'Current Decisions'!A:G, 7, FALSE), "") -> 24.5 | C45: 1 | D45: =C45 -> 1 | E45: 0 | F45: =E45 -> 0 | G45: C
A46: Mahoney Engineering | B46: =IFERROR(VLOOKUP(A46, 'Current Decisions'!A:G, 7, FALSE), "") -> 24.5 | C46: 1 | D46: =C46 -> 1 | E46: 0 | F46: =E46 -> 0 | G46: C
A47: FlatironDragados | B47: =IFERROR(VLOOKUP(A47, 'Current Decisions'!A:G, 7, FALSE), "") -> 24 | C47: 1 | D47: =C47 -> 1 | E47: 0 | F47: =E47 -> 0 | G47: C
A48: Illinois Department of Transportation ( IDOT) | B48: =IFERROR(VLOOKUP(A48, 'Current Decisions'!A:G, 7, FALSE), "") -> 24 | C48: 1 | D48: =C48 -> 1 | E48: 0 | F48: =E48 -> 0 | G48: C
A49: LJA Engineering | B49: =IFERROR(VLOOKUP(A49, 'Current Decisions'!A:G, 7, FALSE), "") -> 24 | C49: 0 | D49: =C49 -> 0 | E49: 2 | F49: =E49 -> 2 | G49: C
A50: Westwood Professional Services | B50: =IFERROR(VLOOKUP(A50, 'Current Decisions'!A:G, 7, FALSE), "") -> 23.8 | C50: 2 | D50: =C50 -> 2 | E50: 2 | F50: =E50 -> 2 | G50: C
A51: UES | B51: =IFERROR(VLOOKUP(A51, 'Current Decisions'!A:G, 7, FALSE), "") -> 23.4 | C51: 0 | D51: 0 | E51: 1 | F51: 1 | G51: C
A52: Black & Veatch | B52: =IFERROR(VLOOKUP(A52, 'Current Decisions'!A:G, 7, FALSE), "") -> 23 | C52: 1 | D52: =C52 -> 1 | E52: 0 | F52: =E52 -> 0 | G52: C
A53: Granite Construction | B53: =IFERROR(VLOOKUP(A53, 'Current Decisions'!A:G, 7, FALSE), "") -> 22.7 | C53: 1 | D53: =C53 -> 1 | E53: 1 | F53: =E53 -> 1 | G53: C
A54: Cobb, Fendley & Associates, Inc. | B54: =IFERROR(VLOOKUP(A54, 'Current Decisions'!A:G, 7, FALSE), "") -> 22.5 | C54: 1 | D54: =C54 -> 1 | E54: 1 | F54: =E54 -> 1 | G54: C
A55: PCL Solar Constructor USA, Inc. | B55: =IFERROR(VLOOKUP(A55, 'Current Decisions'!A:G, 7, FALSE), "") -> 22.5 | C55: 1 | D55: 1 | E55: 0 | F55: 0 | G55: C
A56: HASKELL | B56: =IFERROR(VLOOKUP(A56, 'Current Decisions'!A:G, 7, FALSE), "") -> 22.5 | C56: 1 | D56: 1 | E56: 1 | F56: 1 | G56: C
A57: Manson Construction Co. | B57: =IFERROR(VLOOKUP(A57, 'Current Decisions'!A:G, 7, FALSE), "") -> 22.2 | C57: 1 | D57: 1 | E57: 1 | F57: 1 | G57: C
A58: Terracon Consulting | B58: =IFERROR(VLOOKUP(A58, 'Current Decisions'!A:G, 7, FALSE), "") -> 21.7 | C58: 1 | D58: =C58 -> 1 | E58: 0 | F58: =E58 -> 0 | G58: C
A59: Kiewit | B59: =IFERROR(VLOOKUP(A59, 'Current Decisions'!A:G, 7, FALSE), "") -> 21 | C59: 2 | D59: =C59 -> 2 | E59: 2 | F59: =E59 -> 2 | G59: C
A60: Kimley-Horn & Associates Inc | B60: =IFERROR(VLOOKUP(A60, 'Current Decisions'!A:G, 7, FALSE), "") -> 21 | C60: 2 | D60: =C60 -> 2 | E60: 2 | F60: =E60 -> 2 | G60: C
A61: Indus Road & Bridge | B61: =IFERROR(VLOOKUP(A61, 'Current Decisions'!A:G, 7, FALSE), "") -> 20.8 | C61: 0 | D61: 0 | E61: 1 | F61: 1 | G61: C
A62: Jones Engineering Solutions | B62: =IFERROR(VLOOKUP(A62, 'Current Decisions'!A:G, 7, FALSE), "") -> 20.3 | D62: 0 | F62: =E62 | G62: r
A63: Dally + Associates, Inc. | B63: =IFERROR(VLOOKUP(A63, 'Current Decisions'!A:G, 7, FALSE), "") -> 20 | C63: 1 | D63: =C63 -> 1 | E63: 0 | F63: =E63 -> 0 | G63: C
A64: ENTACT, LLC | B64: =IFERROR(VLOOKUP(A64, 'Current Decisions'!A:G, 7, FALSE), "") -> 20 | C64: 1 | D64: =C64 -> 1 | E64: 1 | F64: =E64 -> 1 | G64: C
A65: IDS Engineering Group | B65: =IFERROR(VLOOKUP(A65, 'Current Decisions'!A:G, 7, FALSE), "") -> 20 | C65: 4 | D65: =C65 -> 4 | E65: 4 | F65: =E65 -> 4 | G65: C
A66: KFM Engineering & Design | B66: =IFERROR(VLOOKUP(A66, 'Current Decisions'!A:G, 7, FALSE), "") -> 20 | C66: 1 | D66: =C66 -> 1 | E66: 0 | F66: =E66 -> 0 | G66: C
A67: Oscar Orduno, Inc | B67: =IFERROR(VLOOKUP(A67, 'Current Decisions'!A:G, 7, FALSE), "") -> 20 | C67: 1 | D67: =C67 -> 1 | E67: 1 | F67: =E67 -> 1 | G67: C
A68: San Jacinto River Authority | B68: =IFERROR(VLOOKUP(A68, 'Current Decisions'!A:G, 7, FALSE), "") -> 20 | C68: 1 | D68: =C68 -> 1 | E68: 0 | F68: =E68 -> 0 | G68: C
A69: Southwest Engineers Inc | B69: =IFERROR(VLOOKUP(A69, 'Current Decisions'!A:G, 7, FALSE), "") -> 20 | C69: 1 | D69: =C69 -> 1 | E69: 0 | F69: =E69 -> 0 | G69: C
A70: Spiars Engineering & Surveying | B70: =IFERROR(VLOOKUP(A70, 'Current Decisions'!A:G, 7, FALSE), "") -> 20 | C70: 1 | D70: 1 | E70: 0 | F70: 0 | G70: C
A71: Webber LLC | B71: =IFERROR(VLOOKUP(A71, 'Current Decisions'!A:G, 7, FALSE), "") -> 20 | C71: 2 | D71: =C71 -> 2 | E71: 2 | F71: =E71 -> 2 | G71: C
A72: Steger & Bizzell Engineering | B72: =IFERROR(VLOOKUP(A72, 'Current Decisions'!A:G, 7, FALSE), "") -> 20 | C72: 1 | D72: =C72 -> 1 | E72: 1 | F72: =E72 -> 1 | G72: C
A73: Bauer Foundation Corporation | B73: =IFERROR(VLOOKUP(A73, 'Current Decisions'!A:G, 7, FALSE), "") -> 17.2 | C73: 0 | D73: 0 | E73: 1 | F73: 1 | G73: C
A74: Walker Partners | B74: =IFERROR(VLOOKUP(A74, 'Current Decisions'!A:G, 7, FALSE), "") -> 17 | C74: 1 | D74: 1 | E74: 1 | F74: 1 | G74: C
A75: Building Crafts, Inc. | B75: =IFERROR(VLOOKUP(A75, 'Current Decisions'!A:G, 7, FALSE), "") -> 16.5 | C75: 1 | D75: 0 | E75: 0 | F75: 1 | G75: C
A76: CB&I | B76: =IFERROR(VLOOKUP(A76, 'Current Decisions'!A:G, 7, FALSE), "") -> 15.6 | C76: 1 | D76: =C76 -> 1 | E76: 0 | F76: =E76 -> 0 | G76: C
A77: WGA | B77: =IFERROR(VLOOKUP(A77, 'Current Decisions'!A:G, 7, FALSE), "") -> 15.5 | C77: 2 | D77: =C77 -> 2 | E77: 2 | F77: =E77 -> 2 | G77: C
A78: Datum Engineers + Datum Rios | B78: =IFERROR(VLOOKUP(A78, 'Current Decisions'!A:G, 7, FALSE), "") -> 15 | C78: 1 | D78: =C78 -> 1 | E78: 1 | F78: =E78 -> 1 | G78: C
A79: JMT - Round Rock | B79: =IFERROR(VLOOKUP(A79, 'Current Decisions'!A:G, 7, FALSE), "") -> 15 | C79: 0 | D79: 0 | E79: 1 | F79: 1 | G79: C
A80: Mortenson Construction | B80: =IFERROR(VLOOKUP(A80, 'Current Decisions'!A:G, 7, FALSE), "") -> 14.7 | C80: 1 | D80: 1 | E80: 1 | F80: 1 | G80: C
A81: TNP | B81: =IFERROR(VLOOKUP(A81, 'Current Decisions'!A:G, 7, FALSE), "") -> 14.3 | C81: 2 | D81: =C81 -> 2 | E81: 0 | F81: =E81 -> 0 | G81: C
A82: Dynamic Engineering Consultants, PC | B82: =IFERROR(VLOOKUP(A82, 'Current Decisions'!A:G, 7, FALSE), "") -> 13.2 | C82: 1 | D82: 0 | E82: 0 | F82: 1 | G82: C - BTT
A83: Hanson Professional Services, Inc. | B83: =IFERROR(VLOOKUP(A83, 'Current Decisions'!A:G, 7, FALSE), "") -> 13.2 | C83: 2 | D83: 2 | E83: 0 | F83: 0 | G83: C | H83: accepted for WS
A84: Kirkman Engineering | B84: =IFERROR(VLOOKUP(A84, 'Current Decisions'!A:G, 7, FALSE), "") -> 13.2 | C84: 0 | D84: 0 | E84: 1 | F84: 1 | G84: C - BTT
A85: MMA Texas | B85: =IFERROR(VLOOKUP(A85, 'Current Decisions'!A:G, 7, FALSE), "") -> 13.2 | C85: 0 | D85: 0 | E85: 1 | F85: 1 | G85: C
A86: Cushing Terrell | B86: =IFERROR(VLOOKUP(A86, 'Current Decisions'!A:G, 7, FALSE), "") -> 13.2 | C86: 0 | D86: 0 | E86: 1 | F86: 1 | G86: C - BTT
A87: Cude Engineers | B87: =IFERROR(VLOOKUP(A87, 'Current Decisions'!A:G, 7, FALSE), "") -> 12.5 | C87: 1 | D87: 1 | E87: 0 | F87: 0 | G87: C
A88: Texas Department of Transportation (TXDOT) | B88: =IFERROR(VLOOKUP(A88, 'Current Decisions'!A:G, 7, FALSE), "") -> 12.5 | C88: 2 | D88: 2 | E88: 2 | F88: 2 | G88: C
A89: HMT Engineering & Surveying | B89: =IFERROR(VLOOKUP(A89, 'Current Decisions'!A:G, 7, FALSE), "") -> 11.8 | C89: 0 | D89: 0 | E89: 1 | F89: 1 | G89: C
A90: F.H. Paschen | B90: =IFERROR(VLOOKUP(A90, 'Current Decisions'!A:G, 7, FALSE), "") -> 11.7 | C90: 0 | D90: 0 | E90: 1 | F90: 1 | G90: C - BTT
A91: Olsson | B91: =IFERROR(VLOOKUP(A91, 'Current Decisions'!A:G, 7, FALSE), "") -> 11.7 | C91: 1 | D91: 0 | E91: 0 | F91: 1 | G91: C - BTT
A92: Trihydro Corporation | B92: =IFERROR(VLOOKUP(A92, 'Current Decisions'!A:G, 7, FALSE), "") -> 11.7 | C92: 1 | D92: 0 | E92: 0 | F92: 0 | G92: r
A93: Zachry Construction Corporation | B93: =IFERROR(VLOOKUP(A93, 'Current Decisions'!A:G, 7, FALSE), "") -> 11 | C93: 1 | D93: 0 | E93: 1 | F93: 0 | G93: r
A94: Huitt-Zollars, Inc. | B94: =IFERROR(VLOOKUP(A94, 'Current Decisions'!A:G, 7, FALSE), "") -> 10.3 | C94: 0 | D94: 0 | E94: 1 | F94: 1 | G94: C
A95: Rimkus | B95: =IFERROR(VLOOKUP(A95, 'Current Decisions'!A:G, 7, FALSE), "") -> 10.3 | C95: 0 | D95: 0 | E95: 1 | F95: 1 | G95: C - BTT
... A116: Gate Precast | B116: =IFERROR(VLOOKUP(A116, 'Current Decisions'!A:G, 7, FALSE), "") -> 22.5 | C116: 0 | D116: 0 | E116: 1 | F116: 1 | G116: C - BTT
A117: Consor Engineers | B117: =IFERROR(VLOOKUP(A117, 'Current Decisions'!A:G, 7, FALSE), "") -> 23.8 | C117: 1 | E117: 0 | G117: BTT - emailed
A118: Texas A&M University - Department of Construction Science | B118: =IFERROR(VLOOKUP(A118, 'Current Decisions'!A:G, 7, FALSE), "") -> 20 | C118: 0 | D118: 0 | E118: 1 | F118: 1 | G118: C
A119: Boardwalk Pipelines, LP | B119: =IFERROR(VLOOKUP(A119, 'Current Decisions'!A:G, 7, FALSE), "") -> 32.9 | C119: 0 | D119: 0 | E119: 1 | F119: 1 | G119: C - BTT
A120: Neel-Schaffer, Inc. | B120: =IFERROR(VLOOKUP(A120, 'Current Decisions'!A:G, 7, FALSE), "") -> 25.42 | C120: 1 | D120: 1 | E120: 0 | F120: 0 | G120: C
...

Sheet CECNCEEN
A1: CECN/CEEN 38 | B1: Score | C1: Requested Wednesday Booths | D1: Final Wednesday Booths | E1: Requested Thursday Booths | F1: Final Thursday Booths | G1: Decision
A2: Dell Technologies | B2: =IFERROR(VLOOKUP(A2, 'Current Decisions'!A:G, 7, FALSE), "") -> 60.8 | C2: 1 | D2: =C2 -> 1 | E2: 0 | F2: 0 | G2: C
A3: Hewlett Packard Enterprise (HPE) | B3: =IFERROR(VLOOKUP(A3, 'Current Decisions'!A:G, 7, FALSE), "") -> 48.7 | C3: 3 | D3: =C3 -> 3 | E3: 0 | F3: =E3 -> 0 | G3: C
A4: Garmin International, Inc. | B4: =IFERROR(VLOOKUP(A4, 'Current Decisions'!A:G, 7, FALSE), "") -> 39.6 | C4: 2 | D4: 2 | E4: 0 | F4: 0 | G4: C
A5: General Motors | B5: =IFERROR(VLOOKUP(A5, 'Current Decisions'!A:G, 7, FALSE), "") -> 39.5 | C5: 1 | D5: 1 | E5: 0 | F5: 0 | G5: C
A6: Tanium | B6: =IFERROR(VLOOKUP(A6, 'Current Decisions'!A:G, 7, FALSE), "") -> 29.7 | C6: 1 | D6: 1 | E6: 0 | F6: 0 | G6: C
A7: Southwest Research Institute | B7: =IFERROR(VLOOKUP(A7, 'Current Decisions'!A:G, 7, FALSE), "") -> 28.2 | C7: 1 | D7: =C7 -> 1 | E7: 0 | F7: =E7 -> 0 | G7: C
A8: Texas Instruments (TI) | B8: =IFERROR(VLOOKUP(A8, 'Current Decisions'!A:G, 7, FALSE), "") -> 27 | C8: 3 | D8: =C8 -> 3 | E8: 3 | F8: =E8 -> 3 | G8: C
A9: Hexagon PPM | B9: =IFERROR(VLOOKUP(A9, 'Current Decisions'!A:G, 7, FALSE), "") -> 25.4 | C9: 1 | D9: 1 | E9: 1 | F9: 1 | G9: C
A10: VEX Robotics | B10: =IFERROR(VLOOKUP(A10, 'Current Decisions'!A:G, 7, FALSE), "") -> 20 | C10: 1 | D10: =C10 -> 1 | E10: 0 | F10: =E10 -> 0 | G10: C
A11: Nabors Industries | B11: =IFERROR(VLOOKUP(A11, 'Current Decisions'!A:G, 7, FALSE), "") -> 19.1 | C11: 2 | D11: =C11 -> 2 | E11: 0 | F11: =E11 -> 0 | G11: C
A12: Tenstorrent.com | B12: =IFERROR(VLOOKUP(A12, 'Current Decisions'!A:G, 7, FALSE), "") -> 24.7 | C12: 0 | D12: 0 | E12: 1 | F12: 1 | G12: C
A13: RAMBUS INC. | B13: =IFERROR(VLOOKUP(A13, 'Current Decisions'!A:G, 7, FALSE), "") -> 28.3 | C13: 1 | E13: 0
A14: RAMBUS INC. | B14: =IFERROR(VLOOKUP(A14, 'Current Decisions'!A:G, 7, FALSE), "") -> 28.3 | C14: 1 | E14: 0
A15: RAMBUS INC. | B15: =IFERROR(VLOOKUP(A15, 'Current Decisions'!A:G, 7, FALSE), "") -> 28.3 | C15: 1 | E15: 0
A16: RAMBUS INC. | B16: =IFERROR(VLOOKUP(A16, 'Current Decisions'!A:G, 7, FALSE), "") -> 28.3 | C16: 1 | E16: 0

Sheet DATA
A1: DATA | B1: Score | C1: Requested Wednesday Booths | D1: Final Wednesday Booths | E1: Requested Thursday Booths | F1: Final Thursday Booths | G1: Decision
A2: National Security Agency | B2: =IFERROR(VLOOKUP(A2, 'Current Decisions'!A:G, 7, FALSE), "") -> 26 | C2: 1 | D2: 1 | E2: 1 | F2: 1 | G2: c | H2: emailed
A3: USAA | B3: =IFERROR(VLOOKUP(A3, 'Current Decisions'!A:G, 7, FALSE), "") -> 63 | C3: 1 | D3: 1 | E3: 1 | F3: 1 | G3: C

Sheet ELEN
A1: ELEN | B1: Score | C1: Requested Wednesday Booths | D1: Final Wednesday Booths | E1: Requested Thursday Booths | F1: Final Thursday Booths
A2: NXP Semiconductors | B2: =IFERROR(VLOOKUP(A2, 'Current Decisions'!A:G, 7, FALSE), "") -> 42.6 | C2: 2 | D2: =C2 -> 2 | E2: 0 | F2: =E2 -> 0 | G2: C
A3: ONCOR Electric Delivery | B3: =IFERROR(VLOOKUP(A3, 'Current Decisions'!A:G, 7, FALSE), "") -> 40.5 | C3: 2 | D3: =C3 -> 2 | E3: 2 | F3: =E3 -> 2 | G3: C
A4: M&S Engineering, LLC | B4: =IFERROR(VLOOKUP(A4, 'Current Decisions'!A:G, 7, FALSE), "") -> 40.3 | C4: 1 | D4: =C4 -> 1 | E4: 1 | F4: =E4 -> 1 | G4: C
A5: Rockwell Automation | B5: =IFERROR(VLOOKUP(A5, 'Current Decisions'!A:G, 7, FALSE), "") -> 39.2 | C5: 1 | D5: =C5 -> 1 | E5: 0 | F5: =E5 -> 0 | G5: C
A6: Powell Industries | B6: =IFERROR(VLOOKUP(A6, 'Current Decisions'!A:G, 7, FALSE), "") -> 37.5 | C6: 1 | D6: =C6 -> 1 | E6: 0 | F6: =E6 -> 0 | G6: C
A7: NRG/Reliant | B7: =IFERROR(VLOOKUP(A7, 'Current Decisions'!A:G, 7, FALSE), "") -> 37.2 | C7: 1 | D7: 1 | E7: 1 | F7: 0 | G7: C
A8: Solar Turbines Inc. | B8: =IFERROR(VLOOKUP(A8, 'Current Decisions'!A:G, 7, FALSE), "") -> 36.7 | C8: 1 | D8: 1 | E8: 1 | F8: 1 | G8: C
A9: Skyworks Solutions | B9: =IFERROR(VLOOKUP(A9, 'Current Decisions'!A:G, 7, FALSE), "") -> 35.4 | C9: 1 | D9: 1 | E9: 1 | F9: 1 | G9: C
A10: Samsung Austin Semiconductor | B10: =IFERROR(VLOOKUP(A10, 'Current Decisions'!A:G, 7, FALSE), "") -> 33.8 | C10: 4 | D10: 4 | E10: 4 | F10: 4 | G10: C
A11: Toshiba | B11: =IFERROR(VLOOKUP(A11, 'Current Decisions'!A:G, 7, FALSE), "") -> 33.2 | C11: 2 | D11: =C11 -> 2 | E11: 0 | F11: =E11 -> 0 | G11: C
A12: Kimberly-Clark | B12: =IFERROR(VLOOKUP(A12, 'Current Decisions'!A:G, 7, FALSE), "") -> 32.5 | C12: 2 | D12: 2 | E12: 2 | F12: 2 | G12: C
A13: Burns Engineering | B13: =IFERROR(VLOOKUP(A13, 'Current Decisions'!A:G, 7, FALSE), "") -> 30.5 | C13: 1 | D13: 1 | E13: 0 | F13: 0 | G13: C
A14: Targa Resources | B14: =IFERROR(VLOOKUP(A14, 'Current Decisions'!A:G, 7, FALSE), "") -> 30.1 | C14: 2 | D14: 2 | E14: 0 | F14: 0 | G14: C
A15: SynchroGrid | B15: =IFERROR(VLOOKUP(A15, 'Current Decisions'!A:G, 7, FALSE), "") -> 29.7 | C15: 1 | D15: =C15 -> 1 | E15: 1 | F15: =E15 -> 1 | G15: C
A16: The Boeing Company | B16: =IFERROR(VLOOKUP(A16, 'Current Decisions'!A:G, 7, FALSE), "") -> 28.6 | C16: 2 | D16: 2 | E16: 0 | F16: 0 | G16: C
A17: HDR Engineering | B17: =IFERROR(VLOOKUP(A17, 'Current Decisions'!A:G, 7, FALSE), "") -> 28.2 | C17: 2 | D17: =C17 -> 2 | E17: 2 | F17: =E17 -> 2 | G17: C
A18: Viridien | B18: =IFERROR(VLOOKUP(A18, 'Current Decisions'!A:G, 7, FALSE), "") -> 28.1 | C18: 1 | D18: 1 | E18: 0 | F18: 0 | G18: C
A19: Infineon Technologies | B19: =IFERROR(VLOOKUP(A19, 'Current Decisions'!A:G, 7, FALSE), "") -> 27.8 | C19: 0 | D19: 0 | E19: 1 | F19: 1 | G19: C
A20: Electric Reliability Council of Texas (ERCOT) | B20: =IFERROR(VLOOKUP(A20, 'Current Decisions'!A:G, 7, FALSE), "") -> 26.8 | C20: 1 | D20: 1 | E20: 0 | F20: 0 | G20: C
A21: Shermco Industries | B21: =IFERROR(VLOOKUP(A21, 'Current Decisions'!A:G, 7, FALSE), "") -> 26 | C21: 1 | D21: =C21 -> 1 | E21: 0 | F21: =E21 -> 0 | G21: C
A22: Integrated Power Services | B22: =IFERROR(VLOOKUP(A22, 'Current Decisions'!A:G, 7, FALSE), "") -> 26 | C22: 0 | D22: 0 | E22: 1 | F22: 1 | G22: C
A23: Ulteig Engineers | B23: =IFERROR(VLOOKUP(A23, 'Current Decisions'!A:G, 7, FALSE), "") -> 24.7 | C23: 1 | D23: =C23 -> 1 | E23: 0 | F23: =E23 -> 0 | G23: C
A24: Global Prior Art Inc. | B24: =IFERROR(VLOOKUP(A24, 'Current Decisions'!A:G, 7, FALSE), "") -> 24.1 | C24: 0 | D24: 0 | E24: 1 | F24: 1 | G24: C
A25: Entergy | B25: =IFERROR(VLOOKUP(A25, 'Current Decisions'!A:G, 7, FALSE), "") -> 22.3 | C25: 4 | D25: 4 | E25: 0 | F25: 0 | G25: C
A26: Rosendin Electric | B26: =IFERROR(VLOOKUP(A26, 'Current Decisions'!A:G, 7, FALSE), "") -> 21.7 | C26: 1 | D26: =C26 -> 1 | E26: 0 | F26: =E26 -> 0 | G26: C
A27: Qorvo | B27: =IFERROR(VLOOKUP(A27, 'Current Decisions'!A:G, 7, FALSE), "") -> 21 | C27: 1 | D27: 1 | E27: 0 | F27: 0 | G27: C
A28: Hays Electrical Services | B28: =IFERROR(VLOOKUP(A28, 'Current Decisions'!A:G, 7, FALSE), "") -> 20.6 | C28: 0 | D28: 0 | E28: 1 | F28: 1 | G28: C
A29: HDL Research Lab, Inc. | B29: =IFERROR(VLOOKUP(A29, 'Current Decisions'!A:G, 7, FALSE), "") -> 20 | C29: 1 | D29: =C29 -> 1 | E29: 0 | F29: =E29 -> 0 | G29: C
A30: Mays Engineering MBA | B30: =IFERROR(VLOOKUP(A30, 'Current Decisions'!A:G, 7, FALSE), "") -> 20 | C30: 0 | D30: 0 | E30: 1 | F30: 1 | G30: C
A31: Patti Engineering | B31: =IFERROR(VLOOKUP(A31, 'Current Decisions'!A:G, 7, FALSE), "") -> 20 | C31: 1 | D31: =C31 -> 1 | E31: 0 | F31: =E31 -> 0 | G31: C
A32: Wind Energy Transmission Texas | B32: =IFERROR(VLOOKUP(A32, 'Current Decisions'!A:G, 7, FALSE), "") -> 20 | C32: 1 | D32: =C32 -> 1 | E32: 0 | F32: =E32 -> 0 | G32: C
A33: Applied Research Laboratories | B33: =IFERROR(VLOOKUP(A33, 'Current Decisions'!A:G, 7, FALSE), "") -> 19.6 | C33: 2 | D33: =C33 -> 2 | E33: 2 | F33: =E33 -> 2 | G33: C
A34: Pike Engineering | B34: =IFERROR(VLOOKUP(A34, 'Current Decisions'!A:G, 7, FALSE), "") -> 19.5 | C34: 1 | D34: 1 | E34: 1 | F34: 1 | G34: C
A35: American Electric Power (AEP) | B35: =IFERROR(VLOOKUP(A35, 'Current Decisions'!A:G, 7, FALSE), "") -> 18.5 | C35: 1 | D35: 1 | E35: 0 | F35: 0 | G35: C
A36: BW Design Group | B36: =IFERROR(VLOOKUP(A36, 'Current Decisions'!A:G, 7, FALSE), "") -> 18 | C36: 0 | D36: 0 | E36: 1 | F36: 1 | G36: C
A37: Loram Maintenance of Way | B37: =IFERROR(VLOOKUP(A37, 'Current Decisions'!A:G, 7, FALSE), "") -> 17.2 | C37: 0 | D37: =C37 -> 0 | E37: 1 | F37: =E37 -> 1 | G37: C
A38: TMEIC Corporation Americas | B38: =IFERROR(VLOOKUP(A38, 'Current Decisions'!A:G, 7, FALSE), "") -> 17 | C38: 2 | D38: 2 | E38: 0 | F38: 0 | G38: C
A39: Champion Technology Services | B39: =IFERROR(VLOOKUP(A39, 'Current Decisions'!A:G, 7, FALSE), "") -> 16.2 | C39: 1 | D39: =C39 -> 1 | E39: 1 | F39: =E39 -> 1 | G39: C
A40: CMTA | B40: =IFERROR(VLOOKUP(A40, 'Current Decisions'!A:G, 7, FALSE), "") -> 15.5 | C40: 1 | D40: 1 | E40: 0 | F40: 0 | G40: C | H40: said no
A41: Kinectrics AES, Inc. | B41: =IFERROR(VLOOKUP(A41, 'Current Decisions'!A:G, 7, FALSE), "") -> 15 | C41: 1 | D41: =C41 -> 1 | E41: 0 | F41: =E41 -> 0 | G41: C
A42: Savannah River Mission Completion | B42: =IFERROR(VLOOKUP(A42, 'Current Decisions'!A:G, 7, FALSE), "") -> 14 | C42: 1 | D42: 1 | E42: 0 | F42: 0 | G42: C
A43: Sandia National Laboratories | B43: =IFERROR(VLOOKUP(A43, 'Current Decisions'!A:G, 7, FALSE), "") -> 13.2 | C43: 1 | D43: =C43 -> 1 | E43: 0 | F43: =E43 -> 0 | G43: C
A44: Keystone Engineering | B44: =IFERROR(VLOOKUP(A44, 'Current Decisions'!A:G, 7, FALSE), "") -> 12.5 | C44: 1 | D44: 1 | E44: 0 | F44: 0 | G44: C
A45: Enercon Services, Inc. | B45: =IFERROR(VLOOKUP(A45, 'Current Decisions'!A:G, 7, FALSE), "") -> 11.8 | C45: 1 | D45: 1 | E45: 0 | F45: 0 | G45: C
A46: Brownsville Public Utilities Board | B46: =IFERROR(VLOOKUP(A46, 'Current Decisions'!A:G, 7, FALSE), "") -> 11.7 | C46: 1 | D46: =C46 -> 1 | E46: 1 | F46: =E46 -> 1 | G46: C
A47: MISO (Midcontinent Independent System Operator, Inc) | B47: =IFERROR(VLOOKUP(A47, 'Current Decisions'!A:G, 7, FALSE), "") -> 11.7 | C47: 2 | D47: =C47 -> 2 | E47: 2 | F47: =E47 -> 2 | G47: C
A48: Dashiell Corp. | B48: =IFERROR(VLOOKUP(A48, 'Current Decisions'!A:G, 7, FALSE), "") -> 11 | C48: 2 | D48: =C48 -> 2 | E48: 2 | F48: =E48 -> 2 | G48: C
A49: Sparx Engineering | B49: =IFERROR(VLOOKUP(A49, 'Current Decisions'!A:G, 7, FALSE), "") -> 11 | C49: 1 | D49: =C49 -> 1 | E49: 0 | F49: =E49 -> 0 | G49: C
A50: Saber Power Services | B50: =IFERROR(VLOOKUP(A50, 'Current Decisions'!A:G, 7, FALSE), "") -> 11 | C50: 1 | D50: 1 | E50: 0 | F50: 0 | G50: C
A51: Komatsu Mining Corporation | B51: =IFERROR(VLOOKUP(A51, 'Current Decisions'!A:G, 7, FALSE), "") -> 10.3 | C51: 1 | D51: 0 | E51: 0 | F51: 1 | G51: C
A52: GBA Companies | B52: =IFERROR(VLOOKUP(A52, 'Current Decisions'!A:G, 7, FALSE), "") -> 7.2 | C52: 0 | D52: 0 | E52: 1 | F52: 1 | G52: C | H52: Follow up
A53: Micro Systems Engineering, Inc. (MSEI) | B53: =IFERROR(VLOOKUP(A53, 'Current Decisions'!A:G, 7, FALSE), "") -> 5 | C53: 0 | D53: 0 | E53: 1 | F53: 1 | G53: C
A54: RPT Alliance LLC | B54: =IFERROR(VLOOKUP(A54, 'Current Decisions'!A:G, 7, FALSE), "") -> 5 | C54: 0 | D54: 0 | E54: 1 | F54: 1 | G54: BTT - C
A55: IBM | B55: =IFERROR(VLOOKUP(A55, 'Current Decisions'!A:G, 7, FALSE), "") -> 69.7 | C55: 1 | D55: 1 | E55: 1 | F55: 1 | G55: C
A56: Quanta Services | B56: =IFERROR(VLOOKUP(A56, 'Current Decisions'!A:G, 7, FALSE), "") -> 39 | C56: 0 | D56: 0 | E56: 1 | F56: 1 | G56: C - BTT
A57: GlobalFoundries | B57: =IFERROR(VLOOKUP(A57, 'Current Decisions'!A:G, 7, FALSE), "") -> 33.5 | C57: 1 | D57: 1 | E57: 1 | F57: 1 | G57: C
A58: Farmers Electric Cooperative | B58: =IFERROR(VLOOKUP(A58, 'Current Decisions'!A:G, 7, FALSE), "") -> 10.3 | C58: 1 | D58: 0 | E58: 1 | F58: 1 | G58: C - BTT
A59: ELM Microgrid | B59: =IFERROR(VLOOKUP(A59, 'Current Decisions'!A:G, 7, FALSE), "") -> 21.7 | C59: 0 | D59: 0 | E59: 1 | F59: 1 | G59: C - BTT
A60: Jelec USA Inc | B60: =IFERROR(VLOOKUP(A60, 'Current Decisions'!A:G, 7, FALSE), "") -> 15.3 | C60: 0 | D60: 0 | E60: 1 | F60: 1 | G60: C
A61: Coffman Engineers, Inc. | B61: =IFERROR(VLOOKUP(A61, 'Current Decisions'!A:G, 7, FALSE), "") -> 28.5 | C61: 0 | D61: 0 | E61: 1 | F61: 1 | G61: C
A62: Wood County Electric Cooperative | B62: =IFERROR(VLOOKUP(A62, 'Current Decisions'!A:G, 7, FALSE), "") -> 4.7 | C62: 0 | D62: 0 | E62: 1 | F62: 1 | G62: C - BTT
A63: NextEra Energy, Inc. | B63: =IFERROR(VLOOKUP(A63, 'Current Decisions'!A:G, 7, FALSE), "") -> 41.9 | C63: 1 | D63: 1 | E63: 0 | F63: 0 | G63: C
A64: HENDERSON ENGINEERS | B64: =IFERROR(VLOOKUP(A64, 'Current Decisions'!A:G, 7, FALSE), "") -> 24.1 | C64: 1 | D64: 1 | E64: 1 | F64: 1 | G64: C
... A66: HFA (Harrison French and Associates) | B66: =IFERROR(VLOOKUP(A66, 'Current Decisions'!A:G, 7, FALSE), "") -> 21 | C66: 0 | D66: 0 | E66: 1 | F66: 1 | G66: C - BTT
A67: RoviSys | B67: =IFERROR(VLOOKUP(A67, 'Current Decisions'!A:G, 7, FALSE), "") -> needs update | C67: 1 | E67: 1
A68: Stress Engineering Services | B68: =IFERROR(VLOOKUP(A68, 'Current Decisions'!A:G, 7, FALSE), "") -> needs update | C68: 1 | E68: 1
A69: TotalEnergies | B69: =IFERROR(VLOOKUP(A69, 'Current Decisions'!A:G, 7, FALSE), "") -> 26 | C69: 0 | E69: 1 | F69: 1 | G69: C
A70: RoviSys | B70: =IFERROR(VLOOKUP(A70, 'Current Decisions'!A:G, 7, FALSE), "") -> needs update | C70: 1 | E70: 1
A71: RoviSys | B71: =IFERROR(VLOOKUP(A71, 'Current Decisions'!A:G, 7, FALSE), "") -> needs update | C71: 1 | E71: 1
A72: Stress Engineering Services | B72: =IFERROR(VLOOKUP(A72, 'Current Decisions'!A:G, 7, FALSE), "") -> needs update | C72: 1 | E72: 1
A73: TotalEnergies | B73: =IFERROR(VLOOKUP(A73, 'Current Decisions'!A:G, 7, FALSE), "") -> 26 | C73: 0 | E73: 1
A74: RoviSys | B74: =IFERROR(VLOOKUP(A74, 'Current Decisions'!A:G, 7, FALSE), "") -> needs update | C74: 1 | E74: 1
A75: Stress Engineering Services | B75: =IFERROR(VLOOKUP(A75, 'Current Decisions'!A:G, 7, FALSE), "") -> needs update | C75: 1 | E75: 1

Sheet ESET
A1: ESET | B1: Score | C1: Requested Wednesday Booths | D1: Final Wednesday Booths | E1: Requested Thursday Booths | F1: Final Thursday Booths
A2: Emerson | B2: =IFERROR(VLOOKUP(A2, 'Current Decisions'!A:G, 7, FALSE), "") -> 42.1 | C2: 1 | D2: 1 | E2: 0 | F2: 0 | G2: C
A3: Haynes and Boone, LLP | B3: =IFERROR(VLOOKUP(A3, 'Current Decisions'!A:G, 7, FALSE), "") -> 26.3 | C3: 0 | D3: 0 | E3: 1 | F3: 1 | G3: C

Sheet EVEN
A1: EVEN | B1: Score | C1: Requested Wednesday Booths | D1: Final Wednesday Booths | E1: Requested Thursday Booths | F1: Final Thursday Booths | G1: Decision
A2: Ramboll | B2: =IFERROR(VLOOKUP(A2, 'Current Decisions'!A:G, 7, FALSE), "") -> 26 | C2: 1 | D2: 1 | E2: 0 | F2: 0 | G2: C

Sheet IDIS
A1: IDIS 55 | B1: Score | C1: Requested Wednesday Booths | D1: Final Wednesday Booths | E1: Requested Thursday Booths | F1: Final Thursday Booths | G1: Decision
A2: SLB | B2: =IFERROR(VLOOKUP(A2, 'Current Decisions'!A:G, 7, FALSE), "") -> 58.1 | C2: 1 | D2: =C2 -> 1 | E2: 0 | F2: =E2 -> 0 | G2: C
A3: Mays Business School - Department of Information & Operations Management | B3: =IFERROR(VLOOKUP(A3, 'Current Decisions'!A:G, 7, FALSE), "") -> 5 | C3: 0 | D3: 0 | E3: 1 | F3: 1 | G3: C
A4: Opportune LLP | B4: =IFERROR(VLOOKUP(A4, 'Current Decisions'!A:G, 7, FALSE), "") -> 9 | C4: 1 | D4: 1 | E4: 1 | F4: 1 | G4: C
A5: H-E-B | B5: =IFERROR(VLOOKUP(A5, 'Current Decisions'!A:G, 7, FALSE), "") -> 14 | C5: 1 | D5: 1 | E5: 0 | F5: 0 | G5: C

Sheet ISEN
A1: ISEN 78 | B1: Score | C1: Requested Wednesday Booths | D1: Final Wednesday Booths | E1: Requested Thursday Booths | F1: Final Thursday Booths | G1: Decision
A2: ABB Inc. | B2: =IFERROR(VLOOKUP(A2, 'Current Decisions'!A:G, 7, FALSE), "") -> 50.1 | C2: 2 | D2: =C2 -> 2 | E2: 0 | F2: =E2 -> 0 | G2: C
A3: Manhattan Associates | B3: =IFERROR(VLOOKUP(A3, 'Current Decisions'!A:G, 7, FALSE), "") -> 35.3 | C3: 1 | D3: 1 | E3: 0 | F3: 0 | G3: C
A4: capSpire | B4: =IFERROR(VLOOKUP(A4, 'Current Decisions'!A:G, 7, FALSE), "") -> 32.8 | C4: 1 | D4: =C4 -> 1 | E4: 0 | F4: =E4 -> 0 | G4: C
A5: Atlas Energy Solutions | B5: =IFERROR(VLOOKUP(A5, 'Current Decisions'!A:G, 7, FALSE), "") -> 15.1 | C5: 0 | D5: 0 | E5: 1 | F5: 1 | G5: C
A6: ProAutomated | B6: =IFERROR(VLOOKUP(A6, 'Current Decisions'!A:G, 7, FALSE), "") -> 6.7 | C6: 0 | D6: 0 | E6: 1 | F6: 1 | G6: C - BTT
A7: Cornerstone Building Brands | B7: =IFERROR(VLOOKUP(A7, 'Current Decisions'!A:G, 7, FALSE), "") -> 17.39 | C7: 0 | D7: 0 | E7: 1 | F7: 1 | G7: C - BTT
A8: Epiroc | B8: =IFERROR(VLOOKUP(A8, 'Current Decisions'!A:G, 7, FALSE), "") -> 31.2 | C8: 1 | D8: 1 | E8: 0 | F8: 0 | G8: C | H8: emailed
A9: Bimbo Bakeries USA | B9: =IFERROR(VLOOKUP(A9, 'Current Decisions'!A:G, 7, FALSE), "") -> needs update | C9: 1 | E9: 1
A10: Bimbo Bakeries USA | B10: =IFERROR(VLOOKUP(A10, 'Current Decisions'!A:G, 7, FALSE), "") -> needs update | C10: 1 | E10: 1
A11: Bimbo Bakeries USA | B11: =IFERROR(VLOOKUP(A11, 'Current Decisions'!A:G, 7, FALSE), "") -> needs update | C11: 1 | E11: 1
A12: Bimbo Bakeries USA | B12: =IFERROR(VLOOKUP(A12, 'Current Decisions'!A:G, 7, FALSE), "") -> needs update | C12: 1 | E12: 1

Sheet MEEN
A1: MEEN 114 | B1: Score | C1: Requested Wednesday Booths | D1: Final Wednesday Booths | E1: Requested Thursday Booths | F1: Final Thursday Booths | G1: Decision
A2: Halliburton (Silver Partner) | B2: =IFERROR(VLOOKUP(A2, 'Current Decisions'!A:G, 7, FALSE), "") -> 66 | C2: 2 | D2: =C2 -> 2 | E2: 2 | F2: =E2 -> 2 | G2: C
A3: PepsiCo | B3: =IFERROR(VLOOKUP(A3, 'Current Decisions'!A:G, 7, FALSE), "") -> 61.2 | C3: 4 | D3: =C3 -> 4 | E3: 4 | F3: =E3 -> 4 | G3: C
A4: TechnipFMC | B4: =IFERROR(VLOOKUP(A4, 'Current Decisions'!A:G, 7, FALSE), "") -> 54.3 | C4: 1 | D4: =C4 -> 1 | E4: 1 | F4: =E4 -> 1 | G4: C
A5: TC Energy | B5: =IFERROR(VLOOKUP(A5, 'Current Decisions'!A:G, 7, FALSE), "") -> 54.2 | C5: 1 | D5: =C5 -> 1 | E5: 0 | F5: =E5 -> 0 | G5: C
A6: Honeywell | B6: =IFERROR(VLOOKUP(A6, 'Current Decisions'!A:G, 7, FALSE), "") -> 54.1 | C6: 2 | D6: 2 | E6: 2 | F6: 2 | G6: C
A7: Applied Materials Inc | B7: =IFERROR(VLOOKUP(A7, 'Current Decisions'!A:G, 7, FALSE), "") -> 53.5 | C7: 4 | D7: 4 | E7: 4 | F7: 4 | G7: C
A8: Tenaris | B8: =IFERROR(VLOOKUP(A8, 'Current Decisions'!A:G, 7, FALSE), "") -> 52.6 | C8: 1 | D8: 1 | E8: 1 | F8: 1 | G8: C
A9: Micron Technology, Inc. | B9: =IFERROR(VLOOKUP(A9, 'Current Decisions'!A:G, 7, FALSE), "") -> 52.2 | C9: 1 | D9: =C9 -> 1 | E9: 0 | F9: =E9 -> 0 | G9: C
A10: Wood | B10: =IFERROR(VLOOKUP(A10, 'Current Decisions'!A:G, 7, FALSE), "") -> 50.4 | C10: 2 | D10: =C10 -> 2 | E10: 2 | F10: =E10 -> 2 | G10: C
A11: P&G (Procter & Gamble) | B11: =IFERROR(VLOOKUP(A11, 'Current Decisions'!A:G, 7, FALSE), "") -> 48.2 | C11: 2 | D11: 2 | E11: 2 | F11: 2 | G11: C
A12: TSMC | B12: =IFERROR(VLOOKUP(A12, 'Current Decisions'!A:G, 7, FALSE), "") -> 46.5 | C12: 1 | D12: 1 | E12: 1 | F12: 1 | G12: C
A13: Caterpillar Inc. | B13: =IFERROR(VLOOKUP(A13, 'Current Decisions'!A:G, 7, FALSE), "") -> 46.2 | C13: 2 | D13: =C13 -> 2 | E13: 2 | F13: =E13 -> 2 | G13: C
A14: Calpine Corporation | B14: =IFERROR(VLOOKUP(A14, 'Current Decisions'!A:G, 7, FALSE), "") -> 46.2 | C14: 0 | D14: 0 | E14: 1 | F14: 1 | G14: C
A15: Nucor | B15: =IFERROR(VLOOKUP(A15, 'Current Decisions'!A:G, 7, FALSE), "") -> 45.9 | C15: 1 | D15: =C15 -> 1 | E15: 1 | F15: =E15 -> 1 | G15: C
A16: Trane Technologies | B16: =IFERROR(VLOOKUP(A16, 'Current Decisions'!A:G, 7, FALSE), "") -> 43.8 | C16: 0 | D16: 0 | E16: 1 | F16: 1 | G16: C
A17: Technip Energies | B17: =IFERROR(VLOOKUP(A17, 'Current Decisions'!A:G, 7, FALSE), "") -> 42.4 | C17: 1 | D17: 1 | E17: 1 | F17: 1 | G17: C
A18: GE Vernova | B18: =IFERROR(VLOOKUP(A18, 'Current Decisions'!A:G, 7, FALSE), "") -> 42.4 | C18: 0 | D18: 0 | E18: 1 | F18: 1 | G18: C
A19: Linde Engineering | B19: =IFERROR(VLOOKUP(A19, 'Current Decisions'!A:G, 7, FALSE), "") -> 40.8 | C19: 0 | D19: =C19 -> 0 | E19: 1 | F19: =E19 -> 1 | G19: C
A20: Goodyear Tire & Rubber Company | B20: =IFERROR(VLOOKUP(A20, 'Current Decisions'!A:G, 7, FALSE), "") -> 40 | C20: 1 | D20: 1 | E20: 0 | F20: 0 | G20: C | H20: IF they respond, they can do two day
A21: Sulzer Turbo Services | B21: =IFERROR(VLOOKUP(A21, 'Current Decisions'!A:G, 7, FALSE), "") -> 39.6 | C21: 2 | D21: =C21 -> 2 | E21: 2 | F21: =E21 -> 2 | G21: C
A22: Atmos Energy | B22: =IFERROR(VLOOKUP(A22, 'Current Decisions'!A:G, 7, FALSE), "") -> 39.4 | C22: 1 | D22: =C22 -> 1 | E22: 1 | F22: =E22 -> 1 | G22: C
A23: DMC Inc. | B23: =IFERROR(VLOOKUP(A23, 'Current Decisions'!A:G, 7, FALSE), "") -> 38.5 | C23: 1 | D23: =C23 -> 1 | E23: 0 | F23: =E23 -> 0 | G23: C
A24: FieldCore, A GE Vernova company | B24: =IFERROR(VLOOKUP(A24, 'Current Decisions'!A:G, 7, FALSE), "") -> 37.4 | C24: 1 | D24: =C24 -> 1 | E24: 0 | F24: =E24 -> 0 | G24: C
A25: Nikkiso Clean Energy & Industrial Gases | B25: =IFERROR(VLOOKUP(A25, 'Current Decisions'!A:G, 7, FALSE), "") -> 36.5 | C25: 1 | D25: 2 | E25: 1 | F25: 2 | G25: C
A26: The Timken Company | B26: =IFERROR(VLOOKUP(A26, 'Current Decisions'!A:G, 7, FALSE), "") -> 36.5 | C26: 1 | D26: 1 | E26: 0 | F26: 0 | G26: C
A27: ROSEN Group | B27: =IFERROR(VLOOKUP(A27, 'Current Decisions'!A:G, 7, FALSE), "") -> 36.2 | C27: 1 | D27: 1 | E27: 1 | F27: 1 | G27: C
A28: NOV National Oilwell Varco | B28: =IFERROR(VLOOKUP(A28, 'Current Decisions'!A:G, 7, FALSE), "") -> 33.8 | C28: 2 | D28: =C28 -> 2 | E28: 2 | F28: =E28 -> 2 | G28: C
A29: GAF | B29: =IFERROR(VLOOKUP(A29, 'Current Decisions'!A:G, 7, FALSE), "") -> 33 | C29: 1 | D29: =C29 -> 1 | E29: 1 | F29: =E29 -> 1 | G29: C
A30: Pinnacle | B30: =IFERROR(VLOOKUP(A30, 'Current Decisions'!A:G, 7, FALSE), "") -> 32.3 | C30: 1 | D30: =C30 -> 1 | E30: 1 | F30: =E30 -> 1 | G30: C
A31: Dynamic Systems, Inc. | B31: =IFERROR(VLOOKUP(A31, 'Current Decisions'!A:G, 7, FALSE), "") -> 31.2 | C31: 1 | D31: =C31 -> 1 | E31: 1 | F31: =E31 -> 1 | G31: C
A32: Cerris | B32: =IFERROR(VLOOKUP(A32, 'Current Decisions'!A:G, 7, FALSE), "") -> 31 | C32: 1 | D32: 0 | E32: 1 | F32: 0 | G32: r
A33: De Nora Water Technologies | B33: =IFERROR(VLOOKUP(A33, 'Current Decisions'!A:G, 7, FALSE), "") -> 30.6 | C33: 1 | D33: 1 | E33: 0 | F33: 0 | G33: C
A34: H+M Industrial EPC | B34: =IFERROR(VLOOKUP(A34, 'Current Decisions'!A:G, 7, FALSE), "") -> 30.5 | C34: 1 | D34: =C34 -> 1 | E34: 1 | F34: =E34 -> 1 | G34: C
A35: JE Dunn Construction | B35: =IFERROR(VLOOKUP(A35, 'Current Decisions'!A:G, 7, FALSE), "") -> 30.5 | C35: 1 | D35: =C35 -> 1 | E35: 0 | F35: =E35 -> 0 | G35: C
A36: LCRA - Austin | B36: =IFERROR(VLOOKUP(A36, 'Current Decisions'!A:G, 7, FALSE), "") -> 30.5 | C36: 1 | D36: =C36 -> 1 | E36: 0 | F36: =E36 -> 0 | G36: C
A37: Baird, Hampton & Brown | B37: =IFERROR(VLOOKUP(A37, 'Current Decisions'!A:G, 7, FALSE), "") -> 29 | C37: 1 | D37: =C37 -> 1 | E37: 0 | F37: =E37 -> 0 | G37: C
A38: Secretariat | B38: =IFERROR(VLOOKUP(A38, 'Current Decisions'!A:G, 7, FALSE), "") -> 29 | C38: 1 | D38: =C38 -> 1 | E38: 0 | F38: =E38 -> 0 | G38: C
A39: Shah Smith & Associates, Inc. | B39: =IFERROR(VLOOKUP(A39, 'Current Decisions'!A:G, 7, FALSE), "") -> 29 | C39: 1 | D39: =C39 -> 1 | E39: 1 | F39: =E39 -> 1 | G39: C
A40: Great Lakes Dredge & Dock Company | B40: =IFERROR(VLOOKUP(A40, 'Current Decisions'!A:G, 7, FALSE), "") -> 28.9 | C40: 0 | D40: 0 | E40: 1 | F40: 0 | G40: r | H40: already registered
A41: Samson Controls, Inc | B41: =IFERROR(VLOOKUP(A41, 'Current Decisions'!A:G, 7, FALSE), "") -> 28.2 | C41: 0 | D41: 1 | E41: 1 | F41: 0 | G41: C
A42: The Brandt Companies, LLC | B42: =IFERROR(VLOOKUP(A42, 'Current Decisions'!A:G, 7, FALSE), "") -> 28.2 | C42: 1 | D42: =C42 -> 1 | E42: 1 | F42: =E42 -> 1 | G42: C
A43: Daily Thermetrics | B43: =IFERROR(VLOOKUP(A43, 'Current Decisions'!A:G, 7, FALSE), "") -> 28.2 | C43: 0 | D43: 0 | E43: 1 | F43: 1 | G43: C
A44: Kairos Power | B44: =IFERROR(VLOOKUP(A44, 'Current Decisions'!A:G, 7, FALSE), "") -> 28.2 | C44: 1 | D44: 1 | E44: 0 | F44: 0 | G44: C | H44: Rejected btt
A45: Andersen Corporation | B45: =IFERROR(VLOOKUP(A45, 'Current Decisions'!A:G, 7, FALSE), "") -> 27.5 | C45: 1 | D45: =C45 -> 1 | E45: 1 | F45: =E45 -> 1 | G45: C
A46: HTS Texas | B46: =IFERROR(VLOOKUP(A46, 'Current Decisions'!A:G, 7, FALSE), "") -> 27.5 | C46: 2 | D46: =C46 -> 2 | E46: 2 | F46: =E46 -> 2 | G46: C
A47: Tallgrass | B47: =IFERROR(VLOOKUP(A47, 'Current Decisions'!A:G, 7, FALSE), "") -> 27.5 | C47: 0 | D47: 0 | E47: 1 | F47: 1 | G47: C
A48: McKinstry | B48: =IFERROR(VLOOKUP(A48, 'Current Decisions'!A:G, 7, FALSE), "") -> 26.7 | C48: 1 | D48: =C48 -> 1 | E48: 0 | F48: =E48 -> 0 | G48: C
A49: Gulf Companies | B49: =IFERROR(VLOOKUP(A49, 'Current Decisions'!A:G, 7, FALSE), "") -> 26.7 | C49: 1 | D49: 1 | E49: 0 | F49: 0 | G49: C
A50: Sonoco Products Company | B50: =IFERROR(VLOOKUP(A50, 'Current Decisions'!A:G, 7, FALSE), "") -> 26.7 | C50: 0 | D50: 0 | E50: 1 | F50: 1 | G50: C
A51: Kinder Morgan | B51: =IFERROR(VLOOKUP(A51, 'Current Decisions'!A:G, 7, FALSE), "") -> 26.3 | C51: 2 | D51: 2 | E51: 0 | F51: 0 | G51: C
A52: Bray International, Inc | B52: =IFERROR(VLOOKUP(A52, 'Current Decisions'!A:G, 7, FALSE), "") -> 26 | C52: 2 | D52: =C52 -> 2 | E52: 2 | F52: =E52 -> 2 | G52: C
A53: General Dynamics Electric Boat | B53: =IFERROR(VLOOKUP(A53, 'Current Decisions'!A:G, 7, FALSE), "") -> 26 | C53: 1 | D53: =C53 -> 1 | E53: 0 | F53: =E53 -> 0 | G53: C
A54: Textron | B54: =IFERROR(VLOOKUP(A54, 'Current Decisions'!A:G, 7, FALSE), "") -> 25.5 | C54: 2 | D54: 2 | E54: 0 | F54: 0 | G54: C
A55: ARCO/Murray National Construction Company | B55: =IFERROR(VLOOKUP(A55, 'Current Decisions'!A:G, 7, FALSE), "") -> 25.3 | C55: 1 | D55: =C55 -> 1 | E55: 1 | F55: =E55 -> 1 | G55: C
A56: FM | B56: =IFERROR(VLOOKUP(A56, 'Current Decisions'!A:G, 7, FALSE), "") -> 25.3 | C56: 1 | D56: =C56 -> 1 | E56: 0 | F56: =E56 -> 0 | G56: C
A57: Lhoist North America, Inc. | B57: =IFERROR(VLOOKUP(A57, 'Current Decisions'!A:G, 7, FALSE), "") -> 25.3 | C57: 1 | D57: =C57 -> 1 | E57: 0 | F57: =E57 -> 0 | G57: C
A58: MiTek USA, Inc. | B58: =IFERROR(VLOOKUP(A58, 'Current Decisions'!A:G, 7, FALSE), "") -> 25.3 | C58: 1 | D58: =C58 -> 1 | E58: 0 | F58: =E58 -> 0 | G58: C
A59: Parker Hannifin | B59: =IFERROR(VLOOKUP(A59, 'Current Decisions'!A:G, 7, FALSE), "") -> 25 | C59: 2 | D59: 2 | E59: 0 | F59: 0 | G59: C
A60: CRB | B60: =IFERROR(VLOOKUP(A60, 'Current Decisions'!A:G, 7, FALSE), "") -> 24.8 | C60: 1 | D60: 1 | E60: 0 | F60: 0 | G60: C
A61: Affiliated Engineers Inc | B61: =IFERROR(VLOOKUP(A61, 'Current Decisions'!A:G, 7, FALSE), "") -> 24.7 | C61: 1 | D61: =C61 -> 1 | E61: 0 | F61: =E61 -> 0 | G61: C
A62: Centerpoint Energy | B62: =IFERROR(VLOOKUP(A62, 'Current Decisions'!A:G, 7, FALSE), "") -> 24.7 | C62: 1 | D62: =C62 -> 1 | E62: 0 | F62: 0 | G62: C
A63: Atwell, LLC | B63: =IFERROR(VLOOKUP(A63, 'Current Decisions'!A:G, 7, FALSE), "") -> 24.5 | C63: 1 | D63: 0 | E63: 0 | F63: =E63 -> 0 | G63: r
A64: Great Plains Manufacturing | B64: =IFERROR(VLOOKUP(A64, 'Current Decisions'!A:G, 7, FALSE), "") -> 24.5 | C64: 1 | D64: =C64 -> 1 | E64: 1 | F64: =E64 -> 1 | G64: C
A65: Lone Star Turbo | B65: =IFERROR(VLOOKUP(A65, 'Current Decisions'!A:G, 7, FALSE), "") -> 24.5 | C65: 1 | D65: 1 | E65: 0 | F65: 0 | G65: C
A66: alliantgroup | B66: =IFERROR(VLOOKUP(A66, 'Current Decisions'!A:G, 7, FALSE), "") -> 23.8 | C66: 1 | D66: 0 | E66: 1 | F66: 0 | G66: R
A67: LTY Engineers, PLLC | B67: =IFERROR(VLOOKUP(A67, 'Current Decisions'!A:G, 7, FALSE), "") -> 23.8 | C67: 1 | D67: =C67 -> 1 | E67: 1 | F67: =E67 -> 1 | G67: C
A68: SICK, Inc. | B68: =IFERROR(VLOOKUP(A68, 'Current Decisions'!A:G, 7, FALSE), "") -> 23.2 | C68: 0 | D68: 0 | E68: 1 | F68: 1 | G68: C
A69: Brock Solutions | B69: =IFERROR(VLOOKUP(A69, 'Current Decisions'!A:G, 7, FALSE), "") -> 22.2 | C69: 0 | D69: =C69 -> 0 | E69: 1 | F69: =E69 -> 1 | G69: C
A70: HMH | B70: =IFERROR(VLOOKUP(A70, 'Current Decisions'!A:G, 7, FALSE), "") -> 21.5 | C70: 1 | D70: =C70 -> 1 | E70: 0 | F70: =E70 -> 0 | G70: C
A71: Klein Tools, Inc. | B71: =IFERROR(VLOOKUP(A71, 'Current Decisions'!A:G, 7, FALSE), "") -> 21.3 | C71: 1 | D71: 1 | E71: 1 | F71: 1 | G71: C
A72: S&B Engineers and Constructors, Ltd. | B72: =IFERROR(VLOOKUP(A72, 'Current Decisions'!A:G, 7, FALSE), "") -> 20.5 | C72: 2 | D72: 2 | E72: 0 | F72: 0 | G72: C
A73: Hoffman Construction | B73: =IFERROR(VLOOKUP(A73, 'Current Decisions'!A:G, 7, FALSE), "") -> 20.3 | C73: 1 | D73: =C73 -> 1 | E73: 0 | F73: =E73 -> 0 | G73: C
A74: Heidelberg Materials | B74: =IFERROR(VLOOKUP(A74, 'Current Decisions'!A:G, 7, FALSE), "") -> 20.1 | C74: 1 | D74: =C74 -> 1 | E74: 0 | F74: =E74 -> 0 | G74: C
A75: Axis Pipe and Tube | B75: =IFERROR(VLOOKUP(A75, 'Current Decisions'!A:G, 7, FALSE), "") -> 20 | C75: 1 | D75: =C75 -> 1 | E75: 1 | F75: =E75 -> 1 | G75: C
A76: Broken Arrow Economic Development Corporation | B76: =IFERROR(VLOOKUP(A76, 'Current Decisions'!A:G, 7, FALSE), "") -> 20 | C76: 1 | D76: =C76 -> 1 | E76: 1 | F76: =E76 -> 1 | G76: C
A77: US Conec Ltd. | B77: =IFERROR(VLOOKUP(A77, 'Current Decisions'!A:G, 7, FALSE), "") -> 20 | C77: 1 | D77: =C77 -> 1 | E77: 1 | F77: =E77 -> 1 | G77: C
A78: Daikin Comfort Technologies | B78: =IFERROR(VLOOKUP(A78, 'Current Decisions'!A:G, 7, FALSE), "") -> 19.5 | C78: 1 | D78: 1 | E78: 1 | F78: 1 | G78: C
A79: Cargill (Maroon Partner) | B79: =IFERROR(VLOOKUP(A79, 'Current Decisions'!A:G, 7, FALSE), "") -> 18.9 | C79: 2 | D79: =C79 -> 2 | E79: 0 | F79: =E79 -> 0 | G79: C
A80: Weatherford International (Houston, TX) | B80: =IFERROR(VLOOKUP(A80, 'Current Decisions'!A:G, 7, FALSE), "") -> 18.4 | C80: 1 | D80: 1 | E80: 0 | F80: 0 | G80: C
A81: Det Norske Veritas (DNV) | B81: =IFERROR(VLOOKUP(A81, 'Current Decisions'!A:G, 7, FALSE), "") -> 17.4 | C81: 0 | D81: 0 | E81: 1 | F81: 1 | G81: C - BTT
A82: SESCO Cement Corp. | B82: =IFERROR(VLOOKUP(A82, 'Current Decisions'!A:G, 7, FALSE), "") -> 17.2 | C82: 1 | D82: 1 | E82: 0 | F82: 0 | G82: C
A83: Patterson-UTI Energy | B83: =IFERROR(VLOOKUP(A83, 'Current Decisions'!A:G, 7, FALSE), "") -> 16.8 | C83: 3 | D83: =C83 -> 3 | E83: 3 | F83: =E83 -> 3 | G83: C
A84: Barnhart Crane and Rigging | B84: =IFERROR(VLOOKUP(A84, 'Current Decisions'!A:G, 7, FALSE), "") -> 16.45 | C84: 0 | D84: 0 | E84: 1 | F84: 1 | G84: C
A85: Percheron Holdings LLC | B85: =IFERROR(VLOOKUP(A85, 'Current Decisions'!A:G, 7, FALSE), "") -> 15 | C85: 0 | D85: 0 | E85: 1 | F85: 1 | G85: C
A86: Heat Transfer Specialists, Inc. | B86: =IFERROR(VLOOKUP(A86, 'Current Decisions'!A:G, 7, FALSE), "") -> 15 | C86: 0 | D86: 0 | E86: 1 | F86: 1 | G86: C
A87: Signal Energy | B87: =IFERROR(VLOOKUP(A87, 'Current Decisions'!A:G, 7, FALSE), "") -> 15 | C87: 0 | D87: 0 | E87: 1 | F87: 1 | G87: C
A88: Vinson Process Controls Company | B88: =IFERROR(VLOOKUP(A88, 'Current Decisions'!A:G, 7, FALSE), "") -> 14.8 | C88: 1 | D88: 1 | E88: 0 | F88: 0 | G88: C
A89: SkyWater Technology | B89: =IFERROR(VLOOKUP(A89, 'Current Decisions'!A:G, 7, FALSE), "") -> 12.2 | C89: 0 | D89: 0 | E89: 1 | F89: 1 | G89: C
A90: Hatch Engineering and Consulting Associates | B90: =IFERROR(VLOOKUP(A90, 'Current Decisions'!A:G, 7, FALSE), "") -> 11 | C90: 1 | D90: 0 | E90: 1 | F90: 1 | G90: C | H90: BTT, two day to one day
A91: Pantex | B91: =IFERROR(VLOOKUP(A91, 'Current Decisions'!A:G, 7, FALSE), "") -> 11 | C91: 3 | D91: 3 | E91: 3 | F91: 3 | G91: C
A92: FBD Partnership, LP | B92: =IFERROR(VLOOKUP(A92, 'Current Decisions'!A:G, 7, FALSE), "") -> 10.5 | C92: 0 | D92: 0 | E92: 1 | F92: 1 | G92: C
A93: Baker Engineering and Risk Consultants, Inc. | B93: =IFERROR(VLOOKUP(A93, 'Current Decisions'!A:G, 7, FALSE), "") -> 9.5 | C93: 1 | D93: 1 | E93: 1 | F93: 1 | G93: C
A94: Mammoet USA | B94: =IFERROR(VLOOKUP(A94, 'Current Decisions'!A:G, 7, FALSE), "") -> 9.5 | C94: 1 | D94: 0 | E94: 0 | F94: 1 | G94: C - BTT
A95: Bernhard | B95: =IFERROR(VLOOKUP(A95, 'Current Decisions'!A:G, 7, FALSE), "") -> 8.8 | C95: 0 | D95: 0 | E95: 1 | F95: 1 | G95: C
A96: Draper | B96: =IFERROR(VLOOKUP(A96, 'Current Decisions'!A:G, 7, FALSE), "") -> 8.2 | C96: 0 | D96: 0 | E96: 1 | F96: 1 | G96: C - BTT
A97: EControls | Ethium | B97: =IFERROR(VLOOKUP(A97, 'Current Decisions'!A:G, 7, FALSE), "") -> 8 | C97: 1 | E97: 0 | G97: r
A98: NORFOLK NAVAL SHIPYARD | B98: =IFERROR(VLOOKUP(A98, 'Current Decisions'!A:G, 7, FALSE), "") -> 7.2 | C98: 1 | D98: 1 | E98: 1 | F98: 1 | G98: C
A99: Encotech Engineering | B99: =IFERROR(VLOOKUP(A99, 'Current Decisions'!A:G, 7, FALSE), "") -> 5 | C99: 0 | D99: 0 | E99: 1 | F99: 1 | G99: C
A100: Rheem Manufacturing | B100: =IFERROR(VLOOKUP(A100, 'Current Decisions'!A:G, 7, FALSE), "") -> 4.5 | C100: 0 | D100: 0 | E100: 1 | F100: 0 | G100: r
...

Sheet MSEN
A1: MSEN 24 | B1: Score | C1: Requested Wednesday Booths | D1: Final Wednesday Booths | E1: Requested Thursday Booths | F1: Final Thursday Booths | G1: Decision
A2: Los Alamos National Laboratory | B2: =IFERROR(VLOOKUP(A2, 'Current Decisions'!A:G, 7, FALSE), "") -> 38.2 | C2: 1 | D2: =C2 -> 1 | E2: 1 | F2: =E2 -> 1 | G2: C
A3: MP Materials | B3: =IFERROR(VLOOKUP(A3, 'Current Decisions'!A:G, 7, FALSE), "") -> 25.6 | C3: 1 | D3: 1 | E3: 0 | F3: 0 | G3: C
A4: Bodycote | B4: =IFERROR(VLOOKUP(A4, 'Current Decisions'!A:G, 7, FALSE), "") -> 24.5 | C4: 1 | D4: 1 | E4: 0 | F4: 0 | G4: C | H4: emailed for discounted thursday
A5: Martin Marietta Materials | B5: =IFERROR(VLOOKUP(A5, 'Current Decisions'!A:G, 7, FALSE), "") -> 19.9 | C5: 1 | E5: 0
A6: Martin Marietta Materials | B6: =IFERROR(VLOOKUP(A6, 'Current Decisions'!A:G, 7, FALSE), "") -> 19.9 | C6: 1 | E6: 0
A7: Martin Marietta Materials | B7: =IFERROR(VLOOKUP(A7, 'Current Decisions'!A:G, 7, FALSE), "") -> 19.9 | C7: 1 | E7: 0
A8: Martin Marietta Materials | B8: =IFERROR(VLOOKUP(A8, 'Current Decisions'!A:G, 7, FALSE), "") -> 19.9 | C8: 1 | E8: 0

Sheet MMET
A1: MMET 26 | B1: Score | C1: Requested Wednesday Booths | D1: Final Wednesday Booths | E1: Requested Thursday Booths | F1: Final Thursday Booths | G1: Decision
A2: FGF Brands Inc. | B2: =IFERROR(VLOOKUP(A2, 'Current Decisions'!A:G, 7, FALSE), "") -> 32.9 | C2: 1 | D2: 1 | E2: 0 | F2: 0 | G2: C
A3: Flint Hills Resources | B3: =IFERROR(VLOOKUP(A3, 'Current Decisions'!A:G, 7, FALSE), "") -> 23.2 | C3: 1 | D3: 1 | E3: 1 | F3: 1 | G3: C
A4: Bachoco OK Foods | B4: =IFERROR(VLOOKUP(A4, 'Current Decisions'!A:G, 7, FALSE), "") -> 15.8 | C4: 1 | D4: 1 | E4: 0 | F4: 0 | G4: C
A5: Ace Thermal Systems | B5: =IFERROR(VLOOKUP(A5, 'Current Decisions'!A:G, 7, FALSE), "") -> 0 | C5: 1 | D5: =C5 -> 1 | E5: 1 | F5: =E5 -> 1 | G5: C
A6: Rocrich AGV Solutions LLC | B6: =IFERROR(VLOOKUP(A6, 'Current Decisions'!A:G, 7, FALSE), "") -> 20 | C6: 0 | D6: 0 | E6: 1 | F6: 1 | G6: C
A7: CNS/Y-12 National Security Complex | B7: =IFERROR(VLOOKUP(A7, 'Current Decisions'!A:G, 7, FALSE), "") -> 12.44 | C7: 0 | D7: 0 | E7: 1 | F7: 0 | G7: r
A8: Del Sol Food Company, Inc. | B8: =IFERROR(VLOOKUP(A8, 'Current Decisions'!A:G, 7, FALSE), "") -> 6 | C8: 1 | D8: 1 | E8: 0 | F8: 0 | G8: C
A9: Tokyo Electron (TEL) | B9: =IFERROR(VLOOKUP(A9, 'Current Decisions'!A:G, 7, FALSE), "") -> 30.3 | C9: 0 | D9: 0 | E9: 1 | F9: 1 | G9: C
A10: Kaspar Companies | B10: =IFERROR(VLOOKUP(A10, 'Current Decisions'!A:G, 7, FALSE), "") -> 8 | C10: 0 | D10: 0 | E10: 1 | F10: 1 | G10: C
A11: Gerdau | B11: =IFERROR(VLOOKUP(A11, 'Current Decisions'!A:G, 7, FALSE), "") -> 42.1 | C11: 1 | D11: 1 | E11: 1 | F11: 1 | G11: C
A12: Five Star Management | B12: =IFERROR(VLOOKUP(A12, 'Current Decisions'!A:G, 7, FALSE), "") -> needs update | C12: 0 | E12: 1
A13: Five Star Management | B13: =IFERROR(VLOOKUP(A13, 'Current Decisions'!A:G, 7, FALSE), "") -> needs update | C13: 0 | E13: 1
A14: Five Star Management | B14: =IFERROR(VLOOKUP(A14, 'Current Decisions'!A:G, 7, FALSE), "") -> needs update | C14: 0 | E14: 1

Sheet MXET
A1: MXET 26 | B1: Score | C1: Requested Wednesday Booths | D1: Final Wednesday Booths | E1: Requested Thursday Booths | F1: Final Thursday Booths | G1: Decision
A2: Beckhoff Automation | B2: =IFERROR(VLOOKUP(A2, 'Current Decisions'!A:G, 7, FALSE), "") -> 14.7 | C2: 1 | D2: =C2 -> 1 | E2: 1 | F2: =E2 -> 1 | G2: C
A3: CAM Integrated Solutions, LLC | B3: =IFERROR(VLOOKUP(A3, 'Current Decisions'!A:G, 7, FALSE), "") -> 21.7 | C3: 1 | D3: =C3 -> 1 | E3: 1 | F3: =E3 -> 1 | G3: C

Sheet NUEN
A1: NUEN 24 | B1: Score | C1: Requested Wednesday Booths | D1: Final Wednesday Booths | E1: Requested Thursday Booths | F1: Final Thursday Booths | G1: Decision
A2: X-Energy | B2: =IFERROR(VLOOKUP(A2, 'Current Decisions'!A:G, 7, FALSE), "") -> 35.2 | C2: 1 | D2: =C2 -> 1 | E2: 1 | F2: =E2 -> 1 | G2: C
A3: Idaho National Laboratory (INL) | B3: =IFERROR(VLOOKUP(A3, 'Current Decisions'!A:G, 7, FALSE), "") -> 29 | C3: 1 | D3: =C3 -> 1 | E3: 0 | F3: =E3 -> 0 | G3: C
A4: Westinghouse Electric Company | B4: =IFERROR(VLOOKUP(A4, 'Current Decisions'!A:G, 7, FALSE), "") -> 24.5 | C4: 1 | D4: 1 | E4: 0 | F4: 0 | G4: C
A5: Argonne National Laboratory Radiological Protection Division | B5: =IFERROR(VLOOKUP(A5, 'Current Decisions'!A:G, 7, FALSE), "") -> 21.8 | C5: 1 | D5: 1 | E5: 0 | F5: 0 | G5: C
A6: US Navy | B6: =IFERROR(VLOOKUP(A6, 'Current Decisions'!A:G, 7, FALSE), "") -> 11 | C6: 1 | D6: 1 | E6: 1 | F6: 1 | G6: C
A7: Naval Nuclear Laboratory | B7: =IFERROR(VLOOKUP(A7, 'Current Decisions'!A:G, 7, FALSE), "") -> 9.5 | C7: 1 | D7: =C7 -> 1 | E7: 1 | F7: =E7 -> 1 | G7: C
A8: STP Nuclear Operating Company | B8: =IFERROR(VLOOKUP(A8, 'Current Decisions'!A:G, 7, FALSE), "") -> 8.8 | C8: 0 | D8: 0 | E8: 1 | F8: 1 | G8: C
A9: Terrestrial Energy Inc. | B9: =IFERROR(VLOOKUP(A9, 'Current Decisions'!A:G, 7, FALSE), "") -> 0 | C9: 0 | D9: 0 | E9: 1 | F9: 1 | G9: C
A10: Framatome | B10: =IFERROR(VLOOKUP(A10, 'Current Decisions'!A:G, 7, FALSE), "") -> 40.5 | C10: 1 | D10: 1 | E10: 0 | F10: 0 | G10: C

Sheet OCEN
A1: OCEN 14 | B1: Score | C1: Requested Wednesday Booths | D1: Final Wednesday Booths | E1: Requested Thursday Booths | F1: Final Thursday Booths | G1: Decision
A2: ABS (American Bureau of Shipping) | B2: =IFERROR(VLOOKUP(A2, 'Current Decisions'!A:G, 7, FALSE), "") -> 18.8 | C2: 1 | D2: 1 | E2: 1 | F2: 1 | G2: C
A3: Jay Cashman, Inc. | B3: =IFERROR(VLOOKUP(A3, 'Current Decisions'!A:G, 7, FALSE), "") -> 12.5 | C3: 1 | D3: 1 | E3: 1 | F3: 1 | G3: C
A4: Jay Cashman Inc. | B4: =IFERROR(VLOOKUP(A4, 'Current Decisions'!A:G, 7, FALSE), "") -> 12.5 | C4: 1 | E4: 1 | G4: r | H4: Sorted
A5: Subsea 7 | B5: =IFERROR(VLOOKUP(A5, 'Current Decisions'!A:G, 7, FALSE), "") -> 26.5 | C5: 1 | D5: 1 | E5: 0 | F5: 0 | G5: C | H5: emailed 8/12/25
A6: Exmar Offshore Company | B6: =IFERROR(VLOOKUP(A6, 'Current Decisions'!A:G, 7, FALSE), "") -> 25.5 | C6: 1 | D6: 1 | E6: 0 | F6: 0 | G6: C

Sheet PETE
A1: PETE | B1: Score | C1: Requested Wednesday Booths | D1: Final Wednesday Booths | E1: Requested Thursday Booths | F1: Final Thursday Booths | G1: Decision
A2: Chevron Corporation (Platinum Partner) | B2: =IFERROR(VLOOKUP(A2, 'Current Decisions'!A:G, 7, FALSE), "") -> 67.5 | C2: 3 | D2: 3 | E2: 3 | F2: 3 | G2: C
A3: Oxy | B3: =IFERROR(VLOOKUP(A3, 'Current Decisions'!A:G, 7, FALSE), "") -> 53.5 | C3: 2 | D3: =C3 -> 2 | E3: 2 | F3: =E3 -> 2 | G3: C
A4: BP America Inc. (Gold Partner) | B4: =IFERROR(VLOOKUP(A4, 'Current Decisions'!A:G, 7, FALSE), "") -> 49.7 | C4: 4 | D4: =C4 -> 4 | E4: 0 | F4: =E4 -> 0 | G4: C
A5: Peloton Computer Enterprises | B5: =IFERROR(VLOOKUP(A5, 'Current Decisions'!A:G, 7, FALSE), "") -> 31 | C5: 1 | D5: =C5 -> 1 | E5: 0 | F5: =E5 -> 0 | G5: C
A6: Railroad Commission of Texas | B6: =IFERROR(VLOOKUP(A6, 'Current Decisions'!A:G, 7, FALSE), "") -> 25.3 | C6: 1 | D6: 1 | E6: 1 | F6: 1 | G6: C
A7: Ovintiv | B7: =IFERROR(VLOOKUP(A7, 'Current Decisions'!A:G, 7, FALSE), "") -> 22.5 | C7: 1 | D7: 0 | E7: 0 | F7: 1 | G7: C - BTT
A8: SM Energy | B8: =IFERROR(VLOOKUP(A8, 'Current Decisions'!A:G, 7, FALSE), "") -> 21.4 | C8: 1 | D8: =C8 -> 1 | E8: 1 | F8: =E8 -> 1 | G8: C
A9: Continental Resources, Inc. | B9: =IFERROR(VLOOKUP(A9, 'Current Decisions'!A:G, 7, FALSE), "") -> 20.3 | C9: 1 | D9: =C9 -> 1 | E9: 1 | F9: =E9 -> 1 | G9: C
A10: Matador Resources | B10: =IFERROR(VLOOKUP(A10, 'Current Decisions'!A:G, 7, FALSE), "") -> 16.5 | C10: 2 | D10: =C10 -> 2 | E10: 2 | F10: =E10 -> 2 | G10: C
A11: Fervo Energy | B11: =IFERROR(VLOOKUP(A11, 'Current Decisions'!A:G, 7, FALSE), "") -> 15 | C11: 1 | D11: 1 | E11: 0 | F11: 0 | G11: C
A12: Rystad Energy | B12: =IFERROR(VLOOKUP(A12, 'Current Decisions'!A:G, 7, FALSE), "") -> 6 | C12: 1 | D12: 1 | E12: 0 | F12: =E12 -> 0 | G12: C
A13: Aramco Services Company | B13: =IFERROR(VLOOKUP(A13, 'Current Decisions'!A:G, 7, FALSE), "") -> 22.42 | C13: 0 | D13: 0 | E13: 1 | F13: 1 | G13: C - BTT
A14: Talos Energy | B14: =IFERROR(VLOOKUP(A14, 'Current Decisions'!A:G, 7, FALSE), "") -> 33.8 | C14: 0 | D14: 0 | E14: 1 | F14: 1 | G14: C - BTT

Sheet EXTRA
A1: COMPANIES THAT WEREN'T SORTED
B2: Date | C2: Net Worth | D2: Work Authorization | E2: Glassdoor | F2: Relationship with A&M | G2: Score | H2: Weeks Pending | I2: Decision | J2: Requested Wednesday Booths | K2: Final Wednesday Booths | L2: Requested Thursday Booths | M2: Final Thursday Booths | N2: Primary Major

Sheet Sorted Companies OutDated
A1: Company Name | B1: Net Worth | C1: Work Authorization | D1: Glassdoor | E1: Relationship with A&M | F1: Score | G1: Decision | H1: Final Wednesday Booths | I1: Final Thursday Booths
A11: Micron Technology, Inc. | B11: 17.4 | C11: 15 | D11: 5.3 | E11: 15 | F11: =SUM(B11 + C11 + D11 + E11) -> 52.7
A40: HR Green | B40: 10 | C40: 15 | D40: 9.75 | E40: 5 | F40: =SUM(B40 + C40 + D40 + E40) -> 39.75 | G40: R - MJC | H40: 0 | I40: 0
A57: Southwest Engineers Inc | B57: 4 | C57: 15 | D57: 11.3 | E57: 5 | F57: =SUM(B57 + C57 + D57 + E57) -> 35.3 | G57: R | H57: 0 | I57: 0
A71: Ferrovial Construction | B71: 14.5 | C71: 15 | D71: 3.8 | E71: 0 | F71: =SUM(B71 + C71 + D71 + E71) -> 33.3
A83: Geosyntec Consultants | B83: 5 | C83: 15 | D83: 7.5 | E83: 5 | F83: =SUM(B83 + C83 + D83 + E83) -> 32.5 | G83: R | H83: 0 | I83: 0
A91: Perficient | B91: 4.2 | C91: 15 | D91: 7.5 | E91: 5 | F91: =SUM(B91 + C91 + D91 + E91) -> 31.7 | G91: R - SSN | H91: 0 | I91: 0
A99: Baker Concrete Construction | B99: 4.4 | C99: 15 | D99: 6.7 | E99: 5 | F99: =SUM(B99 + C99 + D99 + E99) -> 31.1 | G99: R | H99: 0 | I99: 0
A106: Foresite Group, LLC | B106: 0 | C106: 15 | D106: 10.5 | E106: 5 | F106: =SUM(B106 + C106 + D106 + E106) -> 30.5 | G106: R - MJC | H106: 0 | I106: 0
A108: AbbVie | B108: 18.8 | C108: 0 | D108: 6.7 | E108: 5 | F108: =SUM(B108 + C108 + D108 + E108) -> 30.5
A128: Bowman | B128: 0 | C128: 15 | D128: 9 | E128: 5 | F128: =SUM(B128 + C128 + D128 + E128) -> 29 | G128: R - MJC | H128: 0 | I128: 0
A143: Modjeski and Masters | B143: 0 | C143: 15 | D143: 12.8 | E143: 0 | F143: =SUM(B143 + C143 + D143 + E143) -> 27.8
A146: ClayMoore Engineering | B146: 0 | C146: 15 | D146: 7.5 | E146: 5 | F146: =SUM(B146 + C146 + D146 + E146) -> 27.5 | G146: R | H146: 0 | I146: 0
A147: Massman Construction Co. | B147: 0 | C147: 15 | D147: 7.5 | E147: 5 | F147: =SUM(B147 + C147 + D147 + E147) -> 27.5 | G147: R | H147: 0 | I147: 0
A157: Entergy Enterprises, Inc. | B157: 15.348895 | C157: 0 | D157: 6 | E157: 5 | F157: =SUM(B157 + C157 + D157 + E157) -> 26.348895 | G157: R | H157: 0 | I157: 0
A158: Huntsman Corporation | B158: 16.0206 | C158: 0 | D158: 5.3 | E158: 5 | F158: =SUM(B158 + C158 + D158 + E158) -> 26.3206 | G158: R | H158: 0 | I158: 0
A163: Arbin Instruments | B163: 1.6 | C163: 15 | D163: 4.5 | E163: 5 | F163: =SUM(B163 + C163 + D163 + E163) -> 26.1
A166: General Dynamics Electric Boat | B166: 18 | C166: 0 | D166: 3 | E166: 5 | F166: =SUM(B166 + C166 + D166 + E166) -> 26 | G166: R | H166: 0 | I166: 0
A174: Steel Dynamics Inc | B174: 14.911582 | C174: 0 | D174: 10.5 | E174: 0 | F174: =SUM(B174 + C174 + D174 + E174) -> 25.411582 | G174: R | H174: 0 | I174: 0
A176: Lhoist North America, Inc. | B176: 0 | C176: 15 | D176: 5.3 | E176: 5 | F176: =SUM(B176 + C176 + D176 + E176) -> 25.3
A186: Discover Financial Services | B186: 15.6 | C186: 0 | D186: 9 | E186: 0 | F186: =SUM(B186 + C186 + D186 + E186) -> 24.6
A189: Liberty Energy | B189: 13.3 | C189: 0 | D189: 6 | E189: 5 | F189: =SUM(B189 + C189 + D189 + E189) -> 24.3 | G189: R - SSN | H189: 0 | I189: 0
A193: Granite Construction | B193: 12.4 | C193: 0 | D193: 6.7 | E193: 5 | F193: =SUM(B193 + C193 + D193 + E193) -> 24.1
A195: FUTO | B195: 0 | C195: 15 | D195: 9 | E195: 0 | F195: =SUM(B195 + C195 + D195 + E195) -> 24 | G195: R | H195: 0 | I195: 0
A203: Keller North America, Inc. | B203: 12.3 | C203: 0 | D203: 6 | E203: 5 | F203: =SUM(B203 + C203 + D203 + E203) -> 23.3
A206: Weatherford | B206: 12.808488 | C206: 0 | D206: 5.3 | E206: 5 | F206: =SUM(B206 + C206 + D206 + E206) -> 23.108488 | G206: R | H206: 0 | I206: 0
A208: CDC Curtain Wall Design and Consulting, Inc. | B208: 2 | C208: 15 | D208: 6 | E208: 0 | F208: =SUM(B208 + C208 + D208 + E208) -> 23 | G208: R | H208: 0 | I208: 0
A209: Rystad Energy | B209: 2 | C209: 15 | D209: 6 | E209: 0 | F209: =SUM(B209 + C209 + D209 + E209) -> 23 | G209: R | H209: 0 | I209: 0
A211: CoreLogic | B211: 11.227563 | C211: 0 | D211: 6.7 | E211: 5 | F211: =SUM(B211 + C211 + D211 + E211) -> 22.927563 | G211: R | H211: 0 | I211: 0
A213: National Instruments (NI) | B213: 11.1 | C213: 0 | D213: 6.7 | E213: 5 | F213: =SUM(B213 + C213 + D213 + E213) -> 22.8
A231: BoMac Contractors LTD. | B231: 6.50515 | C231: 0 | D231: 10.5 | E231: 5 | F231: =SUM(B231 + C231 + D231 + E231) -> 22.00515 | G231: R | H231: 0 | I231: 0
A234: Elbit Systems of America | B234: 12.5 | C234: 0 | D234: 4.5 | E234: 5 | F234: =SUM(B234 + C234 + D234 + E234) -> 22 | G234: R | H234: 0 | I234: 0
A235: Ball Corporation | B235: 16 | C235: 0 | D235: 6 | E235: 0 | F235: =SUM(B235 + C235 + D235 + E235) -> 22 | G235: wait
A239: Lennox International | B239: 10.7 | C239: 0 | D239: 6 | E239: 5 | F239: =SUM(B239 + C239 + D239 + E239) -> 21.7
A242: Evonik Corporation | B242: 15.431799 | C242: 0 | D242: 6 | E242: 0 | F242: =SUM(B242 + C242 + D242 + E242) -> 21.431799 | G242: R | H242: 0 | I242: 0
A262: GE Vernova | B262: 13 | C262: 0 | D262: 7.5 | E262: 0 | F262: =SUM(B262 + C262 + D262 + E262) -> 20.5 | G262: wait
A283: Renewable Energy Systems Americas, Inc. | B283: 10 | C283: 0 | D283: 9.7 | E283: 0 | F283: =SUM(B283 + C283 + D283 + E283) -> 19.7 | G283: wait
A289: CRB | B289: 6.2 | C289: 0 | D289: 8.2 | E289: 5 | F289: =SUM(B289 + C289 + D289 + E289) -> 19.4 | G289: R | H289: 0 | I289: 0
A291: Solar Turbines Inc. | B291: 11.7 | C291: 0 | D291: 7.5 | E291: 0 | F291: =SUM(B291 + C291 + D291 + E291) -> 19.2 | G291: R | H291: 0 | I291: 0
A293: BD Energy Systems | B293: 4.1 | C293: 0 | D293: 15 | E293: 0 | F293: =SUM(B293 + C293 + D293 + E293) -> 19.1
A297: Primoris Services Corporation | B297: 9.4726326 | C297: 0 | D297: 4.5 | E297: 5 | F297: =SUM(B297 + C297 + D297 + E297) -> 18.972633 | G297: R | H297: 0 | I297: 0
A298: Hilti North America | B298: 10.73064 | C298: 0 | D298: 8.2 | E298: 0 | F298: =SUM(B298 + C298 + D298 + E298) -> 18.93064 | G298: R | H298: 0 | I298: 0
A301: Sambatek, LLC | B301: 1 | C301: 0 | D301: 12.8 | E301: 5 | F301: =SUM(B301 + C301 + D301 + E301) -> 18.8 | G301: R | H301: 0 | I301: 0
A304: Leprino Foods | B304: 15 | C304: 0 | D304: 3.8 | E304: 0 | F304: =SUM(B304 + C304 + D304 + E304) -> 18.8
A306: Hunt & Joiner, Inc. | B306: 2.5 | C306: 0 | D306: 11.25 | E306: 5 | F306: =SUM(B306 + C306 + D306 + E306) -> 18.75 | G306: R | H306: 0 | I306: 0
A309: Weaver | B309: 5.5 | C309: 0 | D309: 8.2 | E309: 5 | F309: =SUM(B309 + C309 + D309 + E309) -> 18.7
A310: David Evans and Associates | B310: 5.4 | C310: 0 | D310: 8.25 | E310: 5 | F310: =SUM(B310 + C310 + D310 + E310) -> 18.65 | G310: R | H310: 0 | I310: 0
A313: Dialexa | B313: 2.9 | C313: 0 | D313: 10.5 | E313: 5 | F313: =SUM(B313 + C313 + D313 + E313) -> 18.4
A314: Ventura Foods | B314: 8.9 | C314: 0 | D314: 4.5 | E314: 5 | F314: =SUM(B314 + C314 + D314 + E314) -> 18.4
A317: Crestwood Midstream Partners LP | B317: 13 | C317: 0 | D317: 5.3 | E317: 0 | F317: =SUM(B317 + C317 + D317 + E317) -> 18.3 | G317: R | H317: 0 | I317: 0
A318: KSA | B318: 5 | C318: 0 | D318: 8.25 | E318: 5 | F318: =SUM(B318 + C318 + D318 + E318) -> 18.25 | G318: R | H318: 0 | I318: 0
A319: Mammoet USA | B319: 6.5 | C319: 0 | D319: 6.75 | E319: 5 | F319: =SUM(B319 + C319 + D319 + E319) -> 18.25 | G319: R | H319: 0 | I319: 0
A321: GBA Companies | B321: 3.5 | C321: 0 | D321: 9.7 | E321: 5 | F321: =SUM(B321 + C321 + D321 + E321) -> 18.2 | G321: R | H321: 0 | I321: 0
A322: Klein Tools | B322: 5 | C322: 0 | D322: 8.2 | E322: 5 | F322: =SUM(B322 + C322 + D322 + E322) -> 18.2 | G322: R - MJC | H322: 0 | I322: 0
A323: Kubota Tractor Corporation | B323: 14.298693 | C323: 0 | D323: 3.8 | E323: 0 | F323: =SUM(B323 + C323 + D323 + E323) -> 18.098693 | G323: R | H323: 0 | I323: 0
A324: RGM DCCM | B324: 0 | C324: 15 | D324: 3 | E324: 0 | F324: =SUM(B324 + C324 + D324 + E324) -> 18 | G324: R | H324: 0 | I324: 0
A327: The Brandt Companies, LLC | B327: 8.5 | C327: 0 | D327: 4.5 | E327: 5 | F327: =SUM(B327 + C327 + D327 + E327) -> 18 | G327: R | H327: 0 | I327: 0
A331: Telios Corporation | B331: 5 | C331: 0 | D331: 12.8 | E331: 0 | F331: =SUM(B331 + C331 + D331 + E331) -> 17.8 | G331: R | H331: 0 | I331: 0
A332: Chart Industries | B332: 10.6 | C332: 0 | D332: 2.2 | E332: 5 | F332: =SUM(B332 + C332 + D332 + E332) -> 17.8
A333: Cross Engineering Consultants, Inc. | B333: 0 | C333: 0 | D333: 12.75 | E333: 5 | F333: =SUM(B333 + C333 + D333 + E333) -> 17.75 | G333: R | H333: 0 | I333: 0
A334: Hatch Engineering and Consulting Associates | B334: 5.9 | C334: 0 | D334: 6.7 | E334: 5 | F334: =SUM(B334 + C334 + D334 + E334) -> 17.6 | G334: R | H334: 0 | I334: 0
A337: X-energy | B337: 7.5 | C337: 0 | D337: 9.7 | E337: 0 | F337: =SUM(B337 + C337 + D337 + E337) -> 17.2
A340: Capco | B340: 3.9 | C340: 0 | D340: 8.2 | E340: 5 | F340: =SUM(B340 + C340 + D340 + E340) -> 17.1
A346: The Boldt Company | B346: 5.9 | C346: 0 | D346: 6 | E346: 5 | F346: =SUM(B346 + C346 + D346 + E346) -> 16.9 | G346: R | H346: 0 | I346: 0
A348: Kongsberg Digital | B348: 11.50515 | C348: 0 | D348: 5.3 | E348: 0 | F348: =SUM(B348 + C348 + D348 + E348) -> 16.80515 | G348: R | H348: 0 | I348: 0
A351: Dunaway | B351: 3.5 | C351: 0 | D351: 8.2 | E351: 5 | F351: =SUM(B351 + C351 + D351 + E351) -> 16.7 | G351: R | H351: 0 | I351: 0
A352: Lockwood, Andrews, and Newnam, Inc. | B352: 3.5 | C352: 0 | D352: 8.2 | E352: 5 | F352: =SUM(B352 + C352 + D352 + E352) -> 16.7 | G352: R | H352: 0 | I352: 0
A354: Railroad Infrastructure & Terminal Development, LLC | B354: 3.5 | C354: 0 | D354: 8.2 | E354: 5 | F354: =SUM(B354 + C354 + D354 + E354) -> 16.7 | G354: R | H354: 0 | I354: 0
A355: QTS Data Centers | B355: 5 | C355: 0 | D355: 6.7 | E355: 5 | F355: =SUM(B355 + C355 + D355 + E355) -> 16.7 | G355: R | H355: 0 | I355: 0
A356: U.S. Army Corps of Engineers | B356: 3.5 | C356: 0 | D356: 8.2 | E356: 5 | F356: =SUM(B356 + C356 + D356 + E356) -> 16.7
A357: CDM Smith | B357: 6.3 | C357: 0 | D357: 5.3 | E357: 5 | F357: =SUM(B357 + C357 + D357 + E357) -> 16.6 | G357: R | H357: 0 | I357: 0
A358: CB&I | B358: 10 | C358: 0 | D358: 1.5 | E358: 5 | F358: =SUM(B358 + C358 + D358 + E358) -> 16.5 | G358: R | H358: 0 | I358: 0
A360: F.H. Paschen | B360: 1 | C360: 0 | D360: 10.5 | E360: 5 | F360: =SUM(B360 + C360 + D360 + E360) -> 16.5 | G360: R | H360: 0 | I360: 0
A361: Shimmick Construction | B361: 6.9010562 | C361: 0 | D361: 4.5 | E361: 5 | F361: =SUM(B361 + C361 + D361 + E361) -> 16.401056 | G361: R | H361: 0 | I361: 0
A365: PND Engineers, Inc. | B365: 0 | C365: 0 | D365: 11.25 | E365: 5 | F365: =SUM(B365 + C365 + D365 + E365) -> 16.25 | G365: R | H365: 0 | I365: 0
A371: IEA Inc. | B371: 5 | C371: 0 | D371: 6 | E371: 5 | F371: =SUM(B371 + C371 + D371 + E371) -> 16 | G371: R | H371: 0 | I371: 0
A375: Tektronix | B375: 5 | C375: 0 | D375: 6 | E375: 5 | F375: =SUM(B375 + C375 + D375 + E375) -> 16 | G375: R | H375: 0 | I375: 0 | J375: 850
A378: MiTek USA, Inc. | B378: 6.5 | C378: 0 | D378: 4.5 | E378: 5 | F378: =SUM(B378 + C378 + D378 + E378) -> 16 | G378: R | H378: 0 | I378: 0
A379: LCRA - Austin | B379: 10 | C379: 0 | D379: 6 | E379: 0 | F379: =SUM(B379 + C379 + D379 + E379) -> 16 | G379: R | H379: 0 | I379: 0
A383: Intelligent Engineering Services | B383: 2.5 | C383: 0 | D383: 8.25 | E383: 5 | F383: =SUM(B383 + C383 + D383 + E383) -> 15.75 | G383: R | H383: 0 | I383: 0
A384: K Friese & Associates, Inc. | B384: 2.5 | C384: 0 | D384: 8.2 | E384: 5 | F384: =SUM(B384 + C384 + D384 + E384) -> 15.7 | G384: R - MJC | H384: 0 | I384: 0
A386: IMEG Corp. | B386: 4.7 | C386: 0 | D386: 6 | E386: 5 | F386: =SUM(B386 + C386 + D386 + E386) -> 15.7 | G386: R | H386: 0 | I386: 0
A389: PEA Group | B389: 1 | C389: 0 | D389: 9.7 | E389: 5 | F389: =SUM(B389 + C389 + D389 + E389) -> 15.7 | G389: R | H389: 0 | I389: 0
A393: Elevation Land Solutions | B393: 0 | C393: 0 | D393: 10.5 | E393: 5 | F393: =SUM(B393 + C393 + D393 + E393) -> 15.5 | G393: R | H393: 0 | I393: 0
A396: Texas A&M Master of Geoscience- Online | B396: 0 | C396: 0 | D396: 10.5 | E396: 5 | F396: =SUM(B396 + C396 + D396 + E396) -> 15.5 | G396: R | H396: 0 | I396: 0
A397: SPEA AMERICA | B397: 5.2 | C397: 0 | D397: 5.25 | E397: 5 | F397: =SUM(B397 + C397 + D397 + E397) -> 15.45 | G397: R - SSN | H397: 0 | I397: 0
A398: Huitt-Zollars, Inc. | B398: 5.9 | C398: 0 | D398: 4.5 | E398: 5 | F398: =SUM(B398 + C398 + D398 + E398) -> 15.4 | G398: R | H398: 0 | I398: 0
A403: The Estes Group | B403: 1 | C403: 0 | D403: 9 | E403: 5 | F403: =SUM(B403 + C403 + D403 + E403) -> 15 | G403: R | H403: 0 | I403: 0
A405: Falkenberg Construction | B405: 0 | C405: 0 | D405: 15 | E405: 0 | F405: =SUM(B405 + C405 + D405 + E405) -> 15 | G405: R | H405: 0 | I405: 0
... A436: Summit Design & Build | B436: 4 | C436: 0 | D436: 9.75 | E436: 0 | F436: =SUM(B436 + C436 + D436 + E436) -> 13.75 | G436: R | H436: 0 | I436: 0
A437: Weeks Marine Inc | B437: 8.4 | C437: 0 | D437: 5.3 | E437: 0 | F437: =SUM(B437 + C437 + D437 + E437) -> 13.7
A438: DEC Corp. | B438: 5.4 | C438: 0 | D438: 8.2 | E438: 0 | F438: =SUM(B438 + C438 + D438 + E438) -> 13.6 | G438: R | H438: 0 | I438: 0
A442: Cude Engineers | B442: 0 | C442: 0 | D442: 8.25 | E442: 5 | F442: =SUM(B442 + C442 + D442 + E442) -> 13.25 | G442: R | H442: 0 | I442: 0
A444: U.S. Nuclear Regulatory Commission (NRC) | B444: 5 | C444: 0 | D444: 8.25 | E444: 0 | F444: =SUM(B444 + C444 + D444 + E444) -> 13.25 | G444: R | H444: 0 | I444: 0
A445: HKA Global | B445: 5 | C445: 0 | D445: 8.2 | E445: 0 | F445: =SUM(B445 + C445 + D445 + E445) -> 13.2 | G445: R | H445: 0 | I445: 0
A446: SCA Consulting Engineers | B446: 0 | C446: 0 | D446: 8.2 | E446: 5 | F446: =SUM(B446 + C446 + D446 + E446) -> 13.2 | G446: R | H446: 0 | I446: 0
A447: Dynamic Engineering Consultants, PC | B447: 0 | C447: 0 | D447: 8.2 | E447: 5 | F447: =SUM(B447 + C447 + D447 + E447) -> 13.2 | G447: R | H447: 0 | I447: 0
A450: HMT Engineering & Surveying | B450: 0 | C450: 0 | D450: 8.2 | E450: 5 | F450: =SUM(B450 + C450 + D450 + E450) -> 13.2 | G450: R | H450: 0 | I450: 0
A451: RPT Alliance LLC | B451: 0 | C451: 0 | D451: 8.2 | E451: 5 | F451: =SUM(B451 + C451 + D451 + E451) -> 13.2 | G451: R | H451: 0 | I451: 0
A453: Delta Airport Consultants Inc. | B453: 1.7022206 | C453: 0 | D453: 11.2 | E453: 0 | F453: =SUM(B453 + C453 + D453 + E453) -> 12.902221 | G453: R | H453: 0 | I453: 0
...

Sheet Companies in Majors
A1: A&S Engineers, Inc.
A2: AG&E
A3: Aguirre & Fields LP
A4: Air Liquide
A5: Albers Aerospace
A6: ALL4 LLC
A7: alliant
A8: Andersen Corporation
A9: Applied Research Laboratories
A10: Arbin Instruments
A11: ARCO/Murray National Construction Company
A12: Ardurra Group
... A308: Entergy
A309: Organization Name | C309: Private or Not Found
C310: Apple Inc. | E310: 385.60 Billion
E311: Tesla, Inc. | G311: 97.20 Billion
G312: Amazon.com, Inc. | I312: 620.10 Billion
I313: Google | K313: 256.70 Billion
K314: Microsoft Corporation | M314: 254.00 Billion
M315: Facebook | O315: 58.00 Billion
O316: SpaceX | Q316: Private or Not Found
Q317: Stripe | S317: Private or Not Found
S318: Airbnb, Inc. | U318: 3.70 Billion
U319: Uber Technologies, Inc. | W319: 42.00 Billion
W320: Palantir Technologies | Y320: 2.30 Billion
Y321: Epic Games | AA321: Private or Not Found
AA322: Zoom Video Communications, Inc. | AC322: Private or Not Found
AC323: Salesforce, Inc. | AE323: 36.50 Billion
AE324: Snap Inc. | AG324: 5.20 Billion
AG325: ByteDance | AI325: Private or Not Found
AI326: Samsung Electronics | AK326: Private or Not Found
AK327: Netflix, Inc. | AM327: 37.60 Billion
AM328: DoorDash, Inc. | AO328: 10.20 Billion
AO329: Rivian Automotive, Inc. | AQ329: 4.50 Billion
AQ330: Siemens | AS330: Private or Not Found

Sheet Totals
B1: Registrations/Requested | C1: Confirmed Booths | D1: Percentage of total | F1: Total booths Available

Sheet majors
C1: AERO
C2: AREN
C3: BAEN
C4: BMEN
C5: CHEN
C6: CECN
C7: CPSC
C8: CVEN
C9: ELEN
C10: ESET
C11: EVEN
C12: IDIS
... C21: DATA
