Workbook

Sheet CompanyDashboard
B3: Company Name: | D3: A&S Engineers, Inc. | I3: RG Dashboard Proof-of-Concept
C6: Company Overview | G6: Willing to Sponsor? | J6: Hiring (since 2022)
C7: Type: | D7: {=INDEX(CompanyList!B:B, MATCH(D3, CompanyList!A:A, 0))} -> Private | G7: {=INDEX(CompanyList!R:R, MATCH($D$3, CompanyList!A:A, 0))} -> Yes | J7: Bachelors | K7: {=INDEX(CompanyList!O:O, MATCH($D$3, CompanyList!A:A, 0))} -> #VALUE!
C8: 2025 Rev | D8: {=INDEX(CompanyList!C:C, MATCH($D$3, CompanyList!A:A, 0))} | E8: M $USD | J8: Masters | K8: {=INDEX(CompanyList!P:P, MATCH($D$3, CompanyList!A:A, 0))} -> #VALUE!
C9: Market Cap | D9: {=INDEX(CompanyList!E:E, MATCH($D$3, CompanyList!A:A, 0))} | E9: B $USD | J9: Doctorate | K9: {=INDEX(CompanyList!Q:Q, MATCH($D$3, CompanyList!A:A, 0))} -> #VALUE!
C10: # Emp | D10: {=INDEX(CompanyList!D:D, MATCH($D$3, CompanyList!A:A, 0))}
J11: Target Majors
J12: WIP
C13: Yearly Overview
D14: S24 | E14: F24 | F14: S25 | G14: F25 | H14: S26
C15: Attended CF? | D15: {=INDEX(CompanyList!AA:AA, MATCH($D$3, CompanyList!A:A, 0))} -> Yes | E15: {=INDEX(CompanyList!Y:Y, MATCH($D$3, CompanyList!$A:$A, 0))} -> Yes | F15: {=INDEX(CompanyList!W:W, MATCH($D$3, CompanyList!$A:$A, 0))} -> Yes | G15: {=INDEX(CompanyList!U:U, MATCH($D$3, CompanyList!$A:$A, 0))} -> Yes | H15: {=INDEX(CompanyList!S:S, MATCH($D$3, CompanyList!$A:$A, 0))} -> Yes
C16: Package | D16: {=INDEX(CompanyList!AB:AB, MATCH($D$3, CompanyList!A:A, 0))} -> Basic Two-Day [$2000.00] | E16: {=INDEX(CompanyList!Z:Z, MATCH($D$3, CompanyList!$A:$A, 0))} -> Basic One-Day: Thursday, September 5th [$1000.00] | F16: {=INDEX(CompanyList!X:X, MATCH($D$3, CompanyList!$A:$A, 0))} -> Basic One-Day: Thursday, January 23rd [$1000.00] | G16: {=INDEX(CompanyList!V:V, MATCH($D$3, CompanyList!$A:$A, 0))} -> Basic One-Day: Thursday, September 11th [$1000.00] | H16: {=INDEX(CompanyList!T:T, MATCH($D$3, CompanyList!$A:$A, 0))} -> Basic Two-Day [$2000.00]
C17: # Hired | D17: {=INDEX(CompanyList!J:J, MATCH($D$3, CompanyList!A:A, 0))} -> 0 | E17: {=INDEX(CompanyList!I:I, MATCH($D$3, CompanyList!$A:$A, 0))} -> 0 | F17: {=INDEX(CompanyList!H:H, MATCH($D$3, CompanyList!$A:$A, 0))} -> 0 | G17: {=INDEX(CompanyList!G:G, MATCH($D$3, CompanyList!$A:$A, 0))} -> 0 | H17: {=INDEX(CompanyList!F:F, MATCH($D$3, CompanyList!$A:$A, 0))} -> 0

Sheet CompanyList
A1: Company Name | B1: Type | C1: 2025 Revenue (M USD) | D1: 2025 Employees | E1: Market Cap (Billion USD) | F1: S26 Hiring | G1: F25 Hiring | H1: S25 Hiring | I1: F24 Hiring | J1: S24 Hiring | K1: F23 Hiring | L1: S23 Hiring | M1: F22 Hiring | N1: S22 Hiring | O1: Bachelor | P1: Master | Q1: Doctorate | R1: Willing to Sponsor? | S1: Attended S26? | T1: Package, S26 | U1: Attended F25? | V1: Package, F25 | W1: Attended S25? | X1: Package, S25 | Y1: Attended F24? | Z1: Package, F24 | AA1: Attended S24? | AB1: Package, S24
A2: A&S Engineers, Inc. | B2: Private | F2: =COUNTIF(S26_Emp!$C:$C,"*" &A2 & "*") -> 0 | G2: =COUNTIF(F25_Emp!$C:$C,"*" &A2 & "*") -> 0 | H2: =COUNTIF(S25_Emp!$C:$C,"*" & A2 & "*") -> 0 | I2: =COUNTIF(F24_Emp!$C:$C,"*" & $A2 & "*") -> 0 | J2: =COUNTIF(S24_Emp!$C:$C,"*" & $A2 & "*") -> 0 | K2: =COUNTIF(F23_Emp!$C:$C,"*" & $A2 & "*") -> 0 | L2: =COUNTIF(S23_Emp!$C:$C,"*" & $A2 & "*") -> 0 | M2: =COUNTIF(F22_Emp!$C:$C,"*" & $A2 & "*") -> 0 | N2: =COUNTIF(S22_Emp!$C:$C,"*" & $A2 & "*") -> 0 | O2: =COUNTIFS(S22_Emp!$C:$C,"*" & $A2 & "*", S22_S25_Emp!$B:$B, "Bachelor") -> #VALUE! | P2: =COUNTIFS(S22_Emp!$C:$C,"*" & $A2 & "*", S22_S25_Emp!$B:$B, "Master") -> #VALUE! | Q2: =COUNTIFS(S22_Emp!$C:$C,"*" & $A2 & "*", S22_S25_Emp!$B:$B, "Doctorate") -> #VALUE! | R2: {=IF(OR(INDEX(S26_CF!X:X, MATCH("*" & $A2 & "*", CompanyList!A:A, 0))=TRUE, INDEX(F25_CF!P:P, MATCH("*" & $A2 & "*", CompanyList!A:A, 0))=TRUE, INDEX(S25_CF!T:T, MATCH("*" & $A2 & "*", CompanyList!A:A, 0))=TRUE, INDEX(S24_CF!W:W, MATCH("*" & $A2 & "*", CompanyList!A:A, 0))=TRUE), "Yes", "No")} -> Yes | S2: =IF(COUNTIF(S26_CF!$A:$A,"*" & $A2 & "*") <> 0, "Yes", "No") -> Yes | T2: {=INDEX(S26_CF!K:K, MATCH("*" & $A2 & "*", S26_CF!A:A, 0))} -> Basic Two-Day [$2000.00] | U2: =IF(COUNTIF(F25_CF!$A:$A,"*" & $A2 & "*") <> 0, "Yes", "No") -> Yes | V2: {=INDEX(F25_CF!I:I, MATCH("*" & $A2 & "*", F25_CF!$A:$A, 0))} -> Basic One-Day: Thursday, September 11th [$1000.00] | W2: =IF(COUNTIF(S25_CF!$A:$A,"*" & $A2 & "*") <> 0, "Yes", "No") -> Yes | X2: {=INDEX(S25_CF!J:J, MATCH("*" & $A2 & "*", S25_CF!$A:$A, 0))} -> Basic One-Day: Thursday, January 23rd [$1000.00] | Y2: =IF(COUNTIF(F24_CF!$A:$A,"*" & $A2 & "*") <> 0, "Yes", "No") -> Yes | Z2: {=INDEX(F24_CF!N:N, MATCH("*" & $A2 & "*", F24_CF!$A:$A, 0))} -> Basic One-Day: Thursday, September 5th [$1000.00] | AA2: =IF(COUNTIF(S24_CF!$A:$A,"*" & $A2 & "*") <> 0, "Yes", "No") -> Yes | AB2: {=INDEX(S24_CF!H:H, MATCH("*" & $A2 & "*", S24_CF!$A:$A, 0))} -> Basic Two-Day [$2000.00]
A3: ABB Inc. | B3: Public | C3: 32000 | D3: 105000 | E3: 100 | F3: =COUNTIF(S26_Emp!$C:$C,"*" &A3 & "*") -> 0 | G3: =COUNTIF(F25_Emp!$C:$C,"*" &#REF! & "*") -> 0 | H3: =COUNTIF(S25_Emp!$C:$C,"*" & A3 & "*") -> 0 | I3: =COUNTIF(F24_Emp!$C:$C,"*" & B3 & "*") -> 1 | J3: =COUNTIF(S24_Emp!$C:$C,"*" & $A3 & "*") -> 1 | K3: =COUNTIF(F23_Emp!$C:$C,"*" & $A3 & "*") -> 0 | L3: =COUNTIF(S23_Emp!$C:$C,"*" & $A3 & "*") -> 0 | M3: =COUNTIF(F22_Emp!$C:$C,"*" & $A3 & "*") -> 0 | N3: =COUNTIF(S22_Emp!$C:$C,"*" & $A3 & "*") -> 0 | O3: =COUNTIFS(S22_Emp!$C:$C,"*" & $A3 & "*", S22_S25_Emp!$B:$B, "Bachelor") -> #VALUE! | P3: =COUNTIFS(S22_Emp!$C:$C,"*" & $A3 & "*", S22_S25_Emp!$B:$B, "Master") -> #VALUE! | Q3: =COUNTIFS(S22_Emp!$C:$C,"*" & $A3 & "*", S22_S25_Emp!$B:$B, "Doctorate") -> #VALUE! | R3: {=IF(OR(INDEX(S26_CF!X:X, MATCH("*" & $A3 & "*", CompanyList!A:A, 0))=TRUE, INDEX(F25_CF!P:P, MATCH("*" & $A3 & "*", CompanyList!A:A, 0))=TRUE, INDEX(S25_CF!T:T, MATCH("*" & $A3 & "*", CompanyList!A:A, 0))=TRUE, INDEX(S24_CF!W:W, MATCH("*" & $A3 & "*", CompanyList!A:A, 0))=TRUE), "Yes", "No")} -> No | S3: =IF(COUNTIF(S26_CF!$A:$A,"*" & $A3 & "*") <> 0, "Yes", "No") -> Yes | T3: {=INDEX(S26_CF!K:K, MATCH("*" & $A3 & "*", S26_CF!A:A, 0))} -> Gold One-Day: Wednesday, January 28th [$2500.00] | U3: =IF(COUNTIF(F25_CF!$A:$A,"*" & $A3 & "*") <> 0, "Yes", "No") -> Yes | V3: {=INDEX(F25_CF!I:I, MATCH("*" & $A3 & "*", F25_CF!$A:$A, 0))} -> Gold One-Day: Wednesday, September 10th [$2500.00] | W3: =IF(COUNTIF(S25_CF!$A:$A,"*" & $A3 & "*") <> 0, "Yes", "No") -> No | X3: {=INDEX(S25_CF!J:J, MATCH("*" & $A3 & "*", S25_CF!$A:$A, 0))} -> #N/A | Y3: =IF(COUNTIF(F24_CF!$A:$A,"*" & $A3 & "*") <> 0, "Yes", "No") -> Yes | Z3: {=INDEX(F24_CF!N:N, MATCH("*" & $A3 & "*", F24_CF!$A:$A, 0))} -> Gold One-Day: Wednesday, September 4th [$2500.00] | AA3: =IF(COUNTIF(S24_CF!$A:$A,"*" & $A3 & "*") <> 0, "Yes", "No") -> Yes | AB3: {=INDEX(S24_CF!H:H, MATCH("*" & $A3 & "*", S24_CF!$A:$A, 0))} -> Basic One-Day [$1000.00]
A4: AG&E | B4: Private | F4: =COUNTIF(S26_Emp!$C:$C,"*" &A4 & "*") -> 0 | G4: =COUNTIF(F25_Emp!$C:$C,"*" &#REF! & "*") -> 0 | H4: =COUNTIF(S25_Emp!$C:$C,"*" & A4 & "*") -> 0 | I4: =COUNTIF(F24_Emp!$C:$C,"*" & B4 & "*") -> 0 | J4: =COUNTIF(S24_Emp!$C:$C,"*" & $A4 & "*") -> 0 | K4: =COUNTIF(F23_Emp!$C:$C,"*" & $A4 & "*") -> 1 | L4: =COUNTIF(S23_Emp!$C:$C,"*" & $A4 & "*") -> 1 | M4: =COUNTIF(F22_Emp!$C:$C,"*" & $A4 & "*") -> 0 | N4: =COUNTIF(S22_Emp!$C:$C,"*" & $A4 & "*") -> 0 | O4: =COUNTIFS(S22_Emp!$C:$C,"*" & $A4 & "*", S22_S25_Emp!$B:$B, "Bachelor") -> #VALUE! | P4: =COUNTIFS(S22_Emp!$C:$C,"*" & $A4 & "*", S22_S25_Emp!$B:$B, "Master") -> #VALUE! | Q4: =COUNTIFS(S22_Emp!$C:$C,"*" & $A4 & "*", S22_S25_Emp!$B:$B, "Doctorate") -> #VALUE! | R4: {=IF(OR(INDEX(S26_CF!X:X, MATCH("*" & $A4 & "*", CompanyList!A:A, 0))=TRUE, INDEX(F25_CF!P:P, MATCH("*" & $A4 & "*", CompanyList!A:A, 0))=TRUE, INDEX(S25_CF!T:T, MATCH("*" & $A4 & "*", CompanyList!A:A, 0))=TRUE, INDEX(S24_CF!W:W, MATCH("*" & $A4 & "*", CompanyList!A:A, 0))=TRUE), "Yes", "No")} -> Yes | S4: =IF(COUNTIF(S26_CF!$A:$A,"*" & $A4 & "*") <> 0, "Yes", "No") -> Yes | T4: {=INDEX(S26_CF!K:K, MATCH("*" & $A4 & "*", S26_CF!A:A, 0))} -> Basic One-Day: Wednesday, January 28th [$1000.00] | U4: =IF(COUNTIF(F25_CF!$A:$A,"*" & $A4 & "*") <> 0, "Yes", "No") -> No | V4: {=INDEX(F25_CF!I:I, MATCH("*" & $A4 & "*", F25_CF!$A:$A, 0))} -> #N/A | W4: =IF(COUNTIF(S25_CF!$A:$A,"*" & $A4 & "*") <> 0, "Yes", "No") -> Yes | X4: {=INDEX(S25_CF!J:J, MATCH("*" & $A4 & "*", S25_CF!$A:$A, 0))} -> Basic One-Day: Wednesday, January 22nd [$1000.00] | Y4: =IF(COUNTIF(F24_CF!$A:$A,"*" & $A4 & "*") <> 0, "Yes", "No") -> No | Z4: {=INDEX(F24_CF!N:N, MATCH("*" & $A4 & "*", F24_CF!$A:$A, 0))} -> #N/A | AA4: =IF(COUNTIF(S24_CF!$A:$A,"*" & $A4 & "*") <> 0, "Yes", "No") -> Yes | AB4: {=INDEX(S24_CF!H:H, MATCH("*" & $A4 & "*", S24_CF!$A:$A, 0))} -> Basic Two-Day [$2000.00]
A5: Aguirre & Fields LP | B5: Private | F5: =COUNTIF(S26_Emp!$C:$C,"*" &A5 & "*") -> 0 | G5: =COUNTIF(F25_Emp!$C:$C,"*" &#REF! & "*") -> 0 | H5: =COUNTIF(S25_Emp!$C:$C,"*" & A5 & "*") -> 0 | I5: =COUNTIF(F24_Emp!$C:$C,"*" & B5 & "*") -> 0 | J5: =COUNTIF(S24_Emp!$C:$C,"*" & $A5 & "*") -> 0 | K5: =COUNTIF(F23_Emp!$C:$C,"*" & $A5 & "*") -> 0 | L5: =COUNTIF(S23_Emp!$C:$C,"*" & $A5 & "*") -> 1 | M5: =COUNTIF(F22_Emp!$C:$C,"*" & $A5 & "*") -> 0 | N5: =COUNTIF(S22_Emp!$C:$C,"*" & $A5 & "*") -> 0 | O5: =COUNTIFS(S22_Emp!$C:$C,"*" & $A5 & "*", S22_S25_Emp!$B:$B, "Bachelor") -> #VALUE! | P5: =COUNTIFS(S22_Emp!$C:$C,"*" & $A5 & "*", S22_S25_Emp!$B:$B, "Master") -> #VALUE! | Q5: =COUNTIFS(S22_Emp!$C:$C,"*" & $A5 & "*", S22_S25_Emp!$B:$B, "Doctorate") -> #VALUE! | R5: {=IF(OR(INDEX(S26_CF!X:X, MATCH("*" & $A5 & "*", CompanyList!A:A, 0))=TRUE, INDEX(F25_CF!P:P, MATCH("*" & $A5 & "*", CompanyList!A:A, 0))=TRUE, INDEX(S25_CF!T:T, MATCH("*" & $A5 & "*", CompanyList!A:A, 0))=TRUE, INDEX(S24_CF!W:W, MATCH("*" & $A5 & "*", CompanyList!A:A, 0))=TRUE), "Yes", "No")} -> No | S5: =IF(COUNTIF(S26_CF!$A:$A,"*" & $A5 & "*") <> 0, "Yes", "No") -> Yes | T5: {=INDEX(S26_CF!K:K, MATCH("*" & $A5 & "*", S26_CF!A:A, 0))} -> Basic One-Day: Wednesday, January 28th [$1000.00] | U5: =IF(COUNTIF(F25_CF!$A:$A,"*" & $A5 & "*") <> 0, "Yes", "No") -> No | V5: {=INDEX(F25_CF!I:I, MATCH("*" & $A5 & "*", F25_CF!$A:$A, 0))} -> #N/A | W5: =IF(COUNTIF(S25_CF!$A:$A,"*" & $A5 & "*") <> 0, "Yes", "No") -> Yes | X5: {=INDEX(S25_CF!J:J, MATCH("*" & $A5 & "*", S25_CF!$A:$A, 0))} -> Basic One-Day: Thursday, January 23rd [$1000.00] | Y5: =IF(COUNTIF(F24_CF!$A:$A,"*" & $A5 & "*") <> 0, "Yes", "No") -> Yes | Z5: {=INDEX(F24_CF!N:N, MATCH("*" & $A5 & "*", F24_CF!$A:$A, 0))} -> Basic One-Day: Thursday, September 5th [$1000.00] | AA5: =IF(COUNTIF(S24_CF!$A:$A,"*" & $A5 & "*") <> 0, "Yes", "No") -> Yes | AB5: {=INDEX(S24_CF!H:H, MATCH("*" & $A5 & "*", S24_CF!$A:$A, 0))} -> Silver One-Day [$1800.00]
A6: Air Liquide | B6: Public | C6: 29500 | D6: 67000 | E6: 101 | F6: =COUNTIF(S26_Emp!$C:$C,"*" &A6 & "*") -> 0 | G6: =COUNTIF(F25_Emp!$C:$C,"*" &#REF! & "*") -> 0 | H6: =COUNTIF(S25_Emp!$C:$C,"*" & A6 & "*") -> 1 | I6: =COUNTIF(F24_Emp!$C:$C,"*" & B6 & "*") -> 1 | J6: =COUNTIF(S24_Emp!$C:$C,"*" & $A6 & "*") -> 2 | K6: =COUNTIF(F23_Emp!$C:$C,"*" & $A6 & "*") -> 1 | L6: =COUNTIF(S23_Emp!$C:$C,"*" & $A6 & "*") -> 1 | M6: =COUNTIF(F22_Emp!$C:$C,"*" & $A6 & "*") -> 1 | N6: =COUNTIF(S22_Emp!$C:$C,"*" & $A6 & "*") -> 1 | O6: =COUNTIFS(S22_Emp!$C:$C,"*" & $A6 & "*", S22_S25_Emp!$B:$B, "Bachelor") -> #VALUE! | P6: =COUNTIFS(S22_Emp!$C:$C,"*" & $A6 & "*", S22_S25_Emp!$B:$B, "Master") -> #VALUE! | Q6: =COUNTIFS(S22_Emp!$C:$C,"*" & $A6 & "*", S22_S25_Emp!$B:$B, "Doctorate") -> #VALUE! | R6: {=IF(OR(INDEX(S26_CF!X:X, MATCH("*" & $A6 & "*", CompanyList!A:A, 0))=TRUE, INDEX(F25_CF!P:P, MATCH("*" & $A6 & "*", CompanyList!A:A, 0))=TRUE, INDEX(S25_CF!T:T, MATCH("*" & $A6 & "*", CompanyList!A:A, 0))=TRUE, INDEX(S24_CF!W:W, MATCH("*" & $A6 & "*", CompanyList!A:A, 0))=TRUE), "Yes", "No")} -> No | S6: =IF(COUNTIF(S26_CF!$A:$A,"*" & $A6 & "*") <> 0, "Yes", "No") -> Yes | T6: {=INDEX(S26_CF!K:K, MATCH("*" & $A6 & "*", S26_CF!A:A, 0))} -> Basic One-Day: Wednesday, January 28th [$1000.00] | U6: =IF(COUNTIF(F25_CF!$A:$A,"*" & $A6 & "*") <> 0, "Yes", "No") -> Yes | V6: {=INDEX(F25_CF!I:I, MATCH("*" & $A6 & "*", F25_CF!$A:$A, 0))} -> Basic One-Day: Wednesday, September 10th [$1000.00] | W6: =IF(COUNTIF(S25_CF!$A:$A,"*" & $A6 & "*") <> 0, "Yes", "No") -> Yes | X6: {=INDEX(S25_CF!J:J, MATCH("*" & $A6 & "*", S25_CF!$A:$A, 0))} -> Basic One-Day: Thursday, January 23rd [$1000.00] | Y6: =IF(COUNTIF(F24_CF!$A:$A,"*" & $A6 & "*") <> 0, "Yes", "No") -> Yes | Z6: {=INDEX(F24_CF!N:N, MATCH("*" & $A6 & "*", F24_CF!$A:$A, 0))} -> Basic One-Day: Wednesday, September 4th [$1000.00] | AA6: =IF(COUNTIF(S24_CF!$A:$A,"*" & $A6 & "*") <> 0, "Yes", "No") -> Yes | AB6: {=INDEX(S24_CF!H:H, MATCH("*" & $A6 & "*", S24_CF!$A:$A, 0))} -> Basic One-Day [$1000.00]
A7: Albers Aerospace | B7: Private | F7: =COUNTIF(S26_Emp!$C:$C,"*" &A7 & "*") -> 0 | G7: =COUNTIF(F25_Emp!$C:$C,"*" &#REF! & "*") -> 0 | H7: =COUNTIF(S25_Emp!$C:$C,"*" & A7 & "*") -> 0 | I7: =COUNTIF(F24_Emp!$C:$C,"*" & B7 & "*") -> 0 | J7: =COUNTIF(S24_Emp!$C:$C,"*" & $A7 & "*") -> 0 | K7: =COUNTIF(F23_Emp!$C:$C,"*" & $A7 & "*") -> 0 | L7: =COUNTIF(S23_Emp!$C:$C,"*" & $A7 & "*") -> 2 | M7: =COUNTIF(F22_Emp!$C:$C,"*" & $A7 & "*") -> 0 | N7: =COUNTIF(S22_Emp!$C:$C,"*" & $A7 & "*") -> 2 | O7: =COUNTIFS(S22_Emp!$C:$C,"*" & $A7 & "*", S22_S25_Emp!$B:$B, "Bachelor") -> #VALUE! | P7: =COUNTIFS(S22_Emp!$C:$C,"*" & $A7 & "*", S22_S25_Emp!$B:$B, "Master") -> #VALUE! | Q7: =COUNTIFS(S22_Emp!$C:$C,"*" & $A7 & "*", S22_S25_Emp!$B:$B, "Doctorate") -> #VALUE! | R7: {=IF(OR(INDEX(S26_CF!X:X, MATCH("*" & $A7 & "*", CompanyList!A:A, 0))=TRUE, INDEX(F25_CF!P:P, MATCH("*" & $A7 & "*", CompanyList!A:A, 0))=TRUE, INDEX(S25_CF!T:T, MATCH("*" & $A7 & "*", CompanyList!A:A, 0))=TRUE, INDEX(S24_CF!W:W, MATCH("*" & $A7 & "*", CompanyList!A:A, 0))=TRUE), "Yes", "No")} -> No | S7: =IF(COUNTIF(S26_CF!$A:$A,"*" & $A7 & "*") <> 0, "Yes", "No") -> No | T7: {=INDEX(S26_CF!K:K, MATCH("*" & $A7 & "*", S26_CF!A:A, 0))} -> #N/A | U7: =IF(COUNTIF(F25_CF!$A:$A,"*" & $A7 & "*") <> 0, "Yes", "No") -> Yes | V7: {=INDEX(F25_CF!I:I, MATCH("*" & $A7 & "*", F25_CF!$A:$A, 0))} -> Basic Two-Day [$2000.00] | W7: =IF(COUNTIF(S25_CF!$A:$A,"*" & $A7 & "*") <> 0, "Yes", "No") -> Yes | X7: {=INDEX(S25_CF!J:J, MATCH("*" & $A7 & "*", S25_CF!$A:$A, 0))} -> Basic One-Day: Thursday, January 23rd [$1000.00] | Y7: =IF(COUNTIF(F24_CF!$A:$A,"*" & $A7 & "*") <> 0, "Yes", "No") -> Yes | Z7: {=INDEX(F24_CF!N:N, MATCH("*" & $A7 & "*", F24_CF!$A:$A, 0))} -> Basic Two-Day [$2000.00] | AA7: =IF(COUNTIF(S24_CF!$A:$A,"*" & $A7 & "*") <> 0, "Yes", "No") -> Yes | AB7: {=INDEX(S24_CF!H:H, MATCH("*" & $A7 & "*", S24_CF!$A:$A, 0))} -> Basic Two-Day [$2000.00]
A8: ALL4 LLC | B8: Private | F8: =COUNTIF(S26_Emp!$C:$C,"*" &A8 & "*") -> 0 | G8: =COUNTIF(F25_Emp!$C:$C,"*" &#REF! & "*") -> 0 | H8: =COUNTIF(S25_Emp!$C:$C,"*" & A8 & "*") -> 0 | I8: =COUNTIF(F24_Emp!$C:$C,"*" & B8 & "*") -> 0 | J8: =COUNTIF(S24_Emp!$C:$C,"*" & $A8 & "*") -> 0 | K8: =COUNTIF(F23_Emp!$C:$C,"*" & $A8 & "*") -> 0 | L8: =COUNTIF(S23_Emp!$C:$C,"*" & $A8 & "*") -> 0 | M8: =COUNTIF(F22_Emp!$C:$C,"*" & $A8 & "*") -> 0 | N8: =COUNTIF(S22_Emp!$C:$C,"*" & $A8 & "*") -> 0 | O8: =COUNTIFS(S22_Emp!$C:$C,"*" & $A8 & "*", S22_S25_Emp!$B:$B, "Bachelor") -> #VALUE! | P8: =COUNTIFS(S22_Emp!$C:$C,"*" & $A8 & "*", S22_S25_Emp!$B:$B, "Master") -> #VALUE! | Q8: =COUNTIFS(S22_Emp!$C:$C,"*" & $A8 & "*", S22_S25_Emp!$B:$B, "Doctorate") -> #VALUE! | R8: {=IF(OR(INDEX(S26_CF!X:X, MATCH("*" & $A8 & "*", CompanyList!A:A, 0))=TRUE, INDEX(F25_CF!P:P, MATCH("*" & $A8 & "*", CompanyList!A:A, 0))=TRUE, INDEX(S25_CF!T:T, MATCH("*" & $A8 & "*", CompanyList!A:A, 0))=TRUE, INDEX(S24_CF!W:W, MATCH("*" & $A8 & "*", CompanyList!A:A, 0))=TRUE), "Yes", "No")} -> No | S8: =IF(COUNTIF(S26_CF!$A:$A,"*" & $A8 & "*") <> 0, "Yes", "No") -> No | T8: {=INDEX(S26_CF!K:K, MATCH("*" & $A8 & "*", S26_CF!A:A, 0))} -> #N/A | U8: =IF(COUNTIF(F25_CF!$A:$A,"*" & $A8 & "*") <> 0, "Yes", "No") -> No | V8: {=INDEX(F25_CF!I:I, MATCH("*" & $A8 & "*", F25_CF!$A:$A, 0))} -> #N/A | W8: =IF(COUNTIF(S25_CF!$A:$A,"*" & $A8 & "*") <> 0, "Yes", "No") -> Yes | X8: {=INDEX(S25_CF!J:J, MATCH("*" & $A8 & "*", S25_CF!$A:$A, 0))} -> Basic One-Day: Wednesday, January 22nd [$1000.00] | Y8: =IF(COUNTIF(F24_CF!$A:$A,"*" & $A8 & "*") <> 0, "Yes", "No") -> Yes | Z8: {=INDEX(F24_CF!N:N, MATCH("*" & $A8 & "*", F24_CF!$A:$A, 0))} -> Basic One-Day: Thursday, September 5th [$1000.00] | AA8: =IF(COUNTIF(S24_CF!$A:$A,"*" & $A8 & "*") <> 0, "Yes", "No") -> Yes | AB8: {=INDEX(S24_CF!H:H, MATCH("*" & $A8 & "*", S24_CF!$A:$A, 0))} -> Basic One-Day [$1000.00]
A9: America's Navy | B9: Government | D9: 330000 | F9: =COUNTIF(S26_Emp!$C:$C,"*" &A9 & "*") -> 0 | G9: =COUNTIF(F25_Emp!$C:$C,"*" &#REF! & "*") -> 0 | H9: =COUNTIF(S25_Emp!$C:$C,"*" & A9 & "*") -> 0 | I9: =COUNTIF(F24_Emp!$C:$C,"*" & B9 & "*") -> 0 | J9: =COUNTIF(S24_Emp!$C:$C,"*" & $A9 & "*") -> 1 | K9: =COUNTIF(F23_Emp!$C:$C,"*" & $A9 & "*") -> 0 | L9: =COUNTIF(S23_Emp!$C:$C,"*" & $A9 & "*") -> 0 | M9: =COUNTIF(F22_Emp!$C:$C,"*" & $A9 & "*") -> 0 | N9: =COUNTIF(S22_Emp!$C:$C,"*" & $A9 & "*") -> 0 | O9: =COUNTIFS(S22_Emp!$C:$C,"*" & $A9 & "*", S22_S25_Emp!$B:$B, "Bachelor") -> #VALUE! | P9: =COUNTIFS(S22_Emp!$C:$C,"*" & $A9 & "*", S22_S25_Emp!$B:$B, "Master") -> #VALUE! | Q9: =COUNTIFS(S22_Emp!$C:$C,"*" & $A9 & "*", S22_S25_Emp!$B:$B, "Doctorate") -> #VALUE! | R9: {=IF(OR(INDEX(S26_CF!X:X, MATCH("*" & $A9 & "*", CompanyList!A:A, 0))=TRUE, INDEX(F25_CF!P:P, MATCH("*" & $A9 & "*", CompanyList!A:A, 0))=TRUE, INDEX(S25_CF!T:T, MATCH("*" & $A9 & "*", CompanyList!A:A, 0))=TRUE, INDEX(S24_CF!W:W, MATCH("*" & $A9 & "*", CompanyList!A:A, 0))=TRUE), "Yes", "No")} -> No | S9: =IF(COUNTIF(S26_CF!$A:$A,"*" & $A9 & "*") <> 0, "Yes", "No") -> No | T9: {=INDEX(S26_CF!K:K, MATCH("*" & $A9 & "*", S26_CF!A:A, 0))} -> #N/A | U9: =IF(COUNTIF(F25_CF!$A:$A,"*" & $A9 & "*") <> 0, "Yes", "No") -> No | V9: {=INDEX(F25_CF!I:I, MATCH("*" & $A9 & "*", F25_CF!$A:$A, 0))} -> #N/A | W9: =IF(COUNTIF(S25_CF!$A:$A,"*" & $A9 & "*") <> 0, "Yes", "No") -> No | X9: {=INDEX(S25_CF!J:J, MATCH("*" & $A9 & "*", S25_CF!$A:$A, 0))} -> #N/A | Y9: =IF(COUNTIF(F24_CF!$A:$A,"*" & $A9 & "*") <> 0, "Yes", "No") -> Yes | Z9: {=INDEX(F24_CF!N:N, MATCH("*" & $A9 & "*", F24_CF!$A:$A, 0))} -> Basic Two-Day [$2000.00] | AA9: =IF(COUNTIF(S24_CF!$A:$A,"*" & $A9 & "*") <> 0, "Yes", "No") -> Yes | AB9: {=INDEX(S24_CF!H:H, MATCH("*" & $A9 & "*", S24_CF!$A:$A, 0))} -> Basic Two-Day [$2000.00]
A10: Andersen Corporation | B10: Private | C10: 3500 | D10: 13000 | F10: =COUNTIF(S26_Emp!$C:$C,"*" &A10 & "*") -> 0 | G10: =COUNTIF(F25_Emp!$C:$C,"*" &#REF! & "*") -> 0 | H10: =COUNTIF(S25_Emp!$C:$C,"*" & A10 & "*") -> 0 | I10: =COUNTIF(F24_Emp!$C:$C,"*" & B10 & "*") -> 0 | J10: =COUNTIF(S24_Emp!$C:$C,"*" & $A10 & "*") -> 0 | K10: =COUNTIF(F23_Emp!$C:$C,"*" & $A10 & "*") -> 0 | L10: =COUNTIF(S23_Emp!$C:$C,"*" & $A10 & "*") -> 0 | M10: =COUNTIF(F22_Emp!$C:$C,"*" & $A10 & "*") -> 1 | N10: =COUNTIF(S22_Emp!$C:$C,"*" & $A10 & "*") -> 2 | O10: =COUNTIFS(S22_Emp!$C:$C,"*" & $A10 & "*", S22_S25_Emp!$B:$B, "Bachelor") -> #VALUE! | P10: =COUNTIFS(S22_Emp!$C:$C,"*" & $A10 & "*", S22_S25_Emp!$B:$B, "Master") -> #VALUE! | Q10: =COUNTIFS(S22_Emp!$C:$C,"*" & $A10 & "*", S22_S25_Emp!$B:$B, "Doctorate") -> #VALUE! | R10: {=IF(OR(INDEX(S26_CF!X:X, MATCH("*" & $A10 & "*", CompanyList!A:A, 0))=TRUE, INDEX(F25_CF!P:P, MATCH("*" & $A10 & "*", CompanyList!A:A, 0))=TRUE, INDEX(S25_CF!T:T, MATCH("*" & $A10 & "*", CompanyList!A:A, 0))=TRUE, INDEX(S24_CF!W:W, MATCH("*" & $A10 & "*", CompanyList!A:A, 0))=TRUE), "Yes", "No")} -> Yes | S10: =IF(COUNTIF(S26_CF!$A:$A,"*" & $A10 & "*") <> 0, "Yes", "No") -> Yes | T10: {=INDEX(S26_CF!K:K, MATCH("*" & $A10 & "*", S26_CF!A:A, 0))} -> Silver Two-Day [$3000.00] | U10: =IF(COUNTIF(F25_CF!$A:$A,"*" & $A10 & "*") <> 0, "Yes", "No") -> Yes | V10: {=INDEX(F25_CF!I:I, MATCH("*" & $A10 & "*", F25_CF!$A:$A, 0))} -> Silver Two-Day [$3000.00] | W10: =IF(COUNTIF(S25_CF!$A:$A,"*" & $A10 & "*") <> 0, "Yes", "No") -> Yes | X10: {=INDEX(S25_CF!J:J, MATCH("*" & $A10 & "*", S25_CF!$A:$A, 0))} -> Gold Two-Day [$5500.00] | Y10: =IF(COUNTIF(F24_CF!$A:$A,"*" & $A10 & "*") <> 0, "Yes", "No") -> Yes | Z10: {=INDEX(F24_CF!N:N, MATCH("*" & $A10 & "*", F24_CF!$A:$A, 0))} -> Gold Two-Day [$5500.00] | AA10: =IF(COUNTIF(S24_CF!$A:$A,"*" & $A10 & "*") <> 0, "Yes", "No") -> Yes | AB10: {=INDEX(S24_CF!H:H, MATCH("*" & $A10 & "*", S24_CF!$A:$A, 0))} -> Basic Two-Day [$2000.00]
A11: Applied Research Laboratories | B11: Government/Univ | D11: 1000 | F11: =COUNTIF(S26_Emp!$C:$C,"*" &A11 & "*") -> 0 | G11: =COUNTIF(F25_Emp!$C:$C,"*" &#REF! & "*") -> 0 | H11: =COUNTIF(S25_Emp!$C:$C,"*" & A11 & "*") -> 0 | I11: =COUNTIF(F24_Emp!$C:$C,"*" & B11 & "*") -> 0 | J11: =COUNTIF(S24_Emp!$C:$C,"*" & $A11 & "*") -> 0 | K11: =COUNTIF(F23_Emp!$C:$C,"*" & $A11 & "*") -> 0 | L11: =COUNTIF(S23_Emp!$C:$C,"*" & $A11 & "*") -> 1 | M11: =COUNTIF(F22_Emp!$C:$C,"*" & $A11 & "*") -> 0 | N11: =COUNTIF(S22_Emp!$C:$C,"*" & $A11 & "*") -> 0 | O11: =COUNTIFS(S22_Emp!$C:$C,"*" & $A11 & "*", S22_S25_Emp!$B:$B, "Bachelor") -> #VALUE! | P11: =COUNTIFS(S22_Emp!$C:$C,"*" & $A11 & "*", S22_S25_Emp!$B:$B, "Master") -> #VALUE! | Q11: =COUNTIFS(S22_Emp!$C:$C,"*" & $A11 & "*", S22_S25_Emp!$B:$B, "Doctorate") -> #VALUE! | R11: {=IF(OR(INDEX(S26_CF!X:X, MATCH("*" & $A11 & "*", CompanyList!A:A, 0))=TRUE, INDEX(F25_CF!P:P, MATCH("*" & $A11 & "*", CompanyList!A:A, 0))=TRUE, INDEX(S25_CF!T:T, MATCH("*" & $A11 & "*", CompanyList!A:A, 0))=TRUE, INDEX(S24_CF!W:W, MATCH("*" & $A11 & "*", CompanyList!A:A, 0))=TRUE), "Yes", "No")} -> No | S11: =IF(COUNTIF(S26_CF!$A:$A,"*" & $A11 & "*") <> 0, "Yes", "No") -> Yes | T11: {=INDEX(S26_CF!K:K, MATCH("*" & $A11 & "*", S26_CF!A:A, 0))} -> Gold Two-Day [$5500.00] | U11: =IF(COUNTIF(F25_CF!$A:$A,"*" & $A11 & "*") <> 0, "Yes", "No") -> Yes | V11: {=INDEX(F25_CF!I:I, MATCH("*" & $A11 & "*", F25_CF!$A:$A, 0))} -> Gold Two-Day [$5500.00] | W11: =IF(COUNTIF(S25_CF!$A:$A,"*" & $A11 & "*") <> 0, "Yes", "No") -> Yes | X11: {=INDEX(S25_CF!J:J, MATCH("*" & $A11 & "*", S25_CF!$A:$A, 0))} -> Gold Two-Day [$5500.00] | Y11: =IF(COUNTIF(F24_CF!$A:$A,"*" & $A11 & "*") <> 0, "Yes", "No") -> Yes | Z11: {=INDEX(F24_CF!N:N, MATCH("*" & $A11 & "*", F24_CF!$A:$A, 0))} -> Gold Two-Day [$5500.00] | AA11: =IF(COUNTIF(S24_CF!$A:$A,"*" & $A11 & "*") <> 0, "Yes", "No") -> Yes | AB11: {=INDEX(S24_CF!H:H, MATCH("*" & $A11 & "*", S24_CF!$A:$A, 0))} -> Gold Two-Day [$5000.00]
A12: Arbin Instruments | B12: Private | F12: =COUNTIF(S26_Emp!$C:$C,"*" &A12 & "*") -> 0 | G12: =COUNTIF(F25_Emp!$C:$C,"*" &#REF! & "*") -> 0 | H12: =COUNTIF(S25_Emp!$C:$C,"*" & A12 & "*") -> 0 | I12: =COUNTIF(F24_Emp!$C:$C,"*" & B12 & "*") -> 0 | J12: =COUNTIF(S24_Emp!$C:$C,"*" & $A12 & "*") -> 1 | K12: =COUNTIF(F23_Emp!$C:$C,"*" & $A12 & "*") -> 0 | L12: =COUNTIF(S23_Emp!$C:$C,"*" & $A12 & "*") -> 1 | M12: =COUNTIF(F22_Emp!$C:$C,"*" & $A12 & "*") -> 0 | N12: =COUNTIF(S22_Emp!$C:$C,"*" & $A12 & "*") -> 0 | O12: =COUNTIFS(S22_Emp!$C:$C,"*" & $A12 & "*", S22_S25_Emp!$B:$B, "Bachelor") -> #VALUE! | P12: =COUNTIFS(S22_Emp!$C:$C,"*" & $A12 & "*", S22_S25_Emp!$B:$B, "Master") -> #VALUE! | Q12: =COUNTIFS(S22_Emp!$C:$C,"*" & $A12 & "*", S22_S25_Emp!$B:$B, "Doctorate") -> #VALUE! | R12: {=IF(OR(INDEX(S26_CF!X:X, MATCH("*" & $A12 & "*", CompanyList!A:A, 0))=TRUE, INDEX(F25_CF!P:P, MATCH("*" & $A12 & "*", CompanyList!A:A, 0))=TRUE, INDEX(S25_CF!T:T, MATCH("*" & $A12 & "*", CompanyList!A:A, 0))=TRUE, INDEX(S24_CF!W:W, MATCH("*" & $A12 & "*", CompanyList!A:A, 0))=TRUE), "Yes", "No")} -> No | S12: =IF(COUNTIF(S26_CF!$A:$A,"*" & $A12 & "*") <> 0, "Yes", "No") -> No | T12: {=INDEX(S26_CF!K:K, MATCH("*" & $A12 & "*", S26_CF!A:A, 0))} -> #N/A | U12: =IF(COUNTIF(F25_CF!$A:$A,"*" & $A12 & "*") <> 0, "Yes", "No") -> No | V12: {=INDEX(F25_CF!I:I, MATCH("*" & $A12 & "*", F25_CF!$A:$A, 0))} -> #N/A | W12: =IF(COUNTIF(S25_CF!$A:$A,"*" & $A12 & "*") <> 0, "Yes", "No") -> Yes | X12: {=INDEX(S25_CF!J:J, MATCH("*" & $A12 & "*", S25_CF!$A:$A, 0))} -> Gold Two-Day [$5500.00] | Y12: =IF(COUNTIF(F24_CF!$A:$A,"*" & $A12 & "*") <> 0, "Yes", "No") -> Yes | Z12: {=INDEX(F24_CF!N:N, MATCH("*" & $A12 & "*", F24_CF!$A:$A, 0))} -> Gold Two-Day [$5500.00] | AA12: =IF(COUNTIF(S24_CF!$A:$A,"*" & $A12 & "*") <> 0, "Yes", "No") -> Yes | AB12: {=INDEX(S24_CF!H:H, MATCH("*" & $A12 & "*", S24_CF!$A:$A, 0))} -> Gold Two-Day [$5000.00]
A13: ARCO/Murray National Construction Company | B13: Private | F13: =COUNTIF(S26_Emp!$C:$C,"*" &A13 & "*") -> 0 | G13: =COUNTIF(F25_Emp!$C:$C,"*" &#REF! & "*") -> 0 | H13: =COUNTIF(S25_Emp!$C:$C,"*" & A13 & "*") -> 0 | I13: =COUNTIF(F24_Emp!$C:$C,"*" & B13 & "*") -> 0 | J13: =COUNTIF(S24_Emp!$C:$C,"*" & $A13 & "*") -> 1 | K13: =COUNTIF(F23_Emp!$C:$C,"*" & $A13 & "*") -> 0 | L13: =COUNTIF(S23_Emp!$C:$C,"*" & $A13 & "*") -> 0 | M13: =COUNTIF(F22_Emp!$C:$C,"*" & $A13 & "*") -> 0 | N13: =COUNTIF(S22_Emp!$C:$C,"*" & $A13 & "*") -> 0 | O13: =COUNTIFS(S22_Emp!$C:$C,"*" & $A13 & "*", S22_S25_Emp!$B:$B, "Bachelor") -> #VALUE! | P13: =COUNTIFS(S22_Emp!$C:$C,"*" & $A13 & "*", S22_S25_Emp!$B:$B, "Master") -> #VALUE! | Q13: =COUNTIFS(S22_Emp!$C:$C,"*" & $A13 & "*", S22_S25_Emp!$B:$B, "Doctorate") -> #VALUE! | R13: {=IF(OR(INDEX(S26_CF!X:X, MATCH("*" & $A13 & "*", CompanyList!A:A, 0))=TRUE, INDEX(F25_CF!P:P, MATCH("*" & $A13 & "*", CompanyList!A:A, 0))=TRUE, INDEX(S25_CF!T:T, MATCH("*" & $A13 & "*", CompanyList!A:A, 0))=TRUE, INDEX(S24_CF!W:W, MATCH("*" & $A13 & "*", CompanyList!A:A, 0))=TRUE), "Yes", "No")} -> No | S13: =IF(COUNTIF(S26_CF!$A:$A,"*" & $A13 & "*") <> 0, "Yes", "No") -> Yes | T13: {=INDEX(S26_CF!K:K, MATCH("*" & $A13 & "*", S26_CF!A:A, 0))} -> Basic Two-Day [$2000.00] | U13: =IF(COUNTIF(F25_CF!$A:$A,"*" & $A13 & "*") <> 0, "Yes", "No") -> Yes | V13: {=INDEX(F25_CF!I:I, MATCH("*" & $A13 & "*", F25_CF!$A:$A, 0))} -> Basic Two-Day [$2000.00] | W13: =IF(COUNTIF(S25_CF!$A:$A,"*" & $A13 & "*") <> 0, "Yes", "No") -> Yes | X13: {=INDEX(S25_CF!J:J, MATCH("*" & $A13 & "*", S25_CF!$A:$A, 0))} -> Basic Two-Day [$2000.00] | Y13: =IF(COUNTIF(F24_CF!$A:$A,"*" & $A13 & "*") <> 0, "Yes", "No") -> Yes | Z13: {=INDEX(F24_CF!N:N, MATCH("*" & $A13 & "*", F24_CF!$A:$A, 0))} -> Basic Two-Day [$2000.00] | AA13: =IF(COUNTIF(S24_CF!$A:$A,"*" & $A13 & "*") <> 0, "Yes", "No") -> Yes | AB13: {=INDEX(S24_CF!H:H, MATCH("*" & $A13 & "*", S24_CF!$A:$A, 0))} -> Basic Two-Day [$2000.00]
A14: Ardurra Group | B14: Private | F14: =COUNTIF(S26_Emp!$C:$C,"*" &A14 & "*") -> 0 | G14: =COUNTIF(F25_Emp!$C:$C,"*" &#REF! & "*") -> 0 | H14: =COUNTIF(S25_Emp!$C:$C,"*" & A14 & "*") -> 0 | I14: =COUNTIF(F24_Emp!$C:$C,"*" & B14 & "*") -> 0 | J14: =COUNTIF(S24_Emp!$C:$C,"*" & $A14 & "*") -> 0 | K14: =COUNTIF(F23_Emp!$C:$C,"*" & $A14 & "*") -> 0 | L14: =COUNTIF(S23_Emp!$C:$C,"*" & $A14 & "*") -> 0 | M14: =COUNTIF(F22_Emp!$C:$C,"*" & $A14 & "*") -> 0 | N14: =COUNTIF(S22_Emp!$C:$C,"*" & $A14 & "*") -> 0 | O14: =COUNTIFS(S22_Emp!$C:$C,"*" & $A14 & "*", S22_S25_Emp!$B:$B, "Bachelor") -> #VALUE! | P14: =COUNTIFS(S22_Emp!$C:$C,"*" & $A14 & "*", S22_S25_Emp!$B:$B, "Master") -> #VALUE! | Q14: =COUNTIFS(S22_Emp!$C:$C,"*" & $A14 & "*", S22_S25_Emp!$B:$B, "Doctorate") -> #VALUE! | R14: {=IF(OR(INDEX(S26_CF!X:X, MATCH("*" & $A14 & "*", CompanyList!A:A, 0))=TRUE, INDEX(F25_CF!P:P, MATCH("*" & $A14 & "*", CompanyList!A:A, 0))=TRUE, INDEX(S25_CF!T:T, MATCH("*" & $A14 & "*", CompanyList!A:A, 0))=TRUE, INDEX(S24_CF!W:W, MATCH("*" & $A14 & "*", CompanyList!A:A, 0))=TRUE), "Yes", "No")} -> Yes | S14: =IF(COUNTIF(S26_CF!$A:$A,"*" & $A14 & "*") <> 0, "Yes", "No") -> Yes | T14: {=INDEX(S26_CF!K:K, MATCH("*" & $A14 & "*", S26_CF!A:A, 0))} -> Basic One-Day: Wednesday, January 28th [$1000.00] | U14: =IF(COUNTIF(F25_CF!$A:$A,"*" & $A14 & "*") <> 0, "Yes", "No") -> No | V14: {=INDEX(F25_CF!I:I, MATCH("*" & $A14 & "*", F25_CF!$A:$A, 0))} -> #N/A | W14: =IF(COUNTIF(S25_CF!$A:$A,"*" & $A14 & "*") <> 0, "Yes", "No") -> Yes | X14: {=INDEX(S25_CF!J:J, MATCH("*" & $A14 & "*", S25_CF!$A:$A, 0))} -> Silver One-Day: Thursday, January 23rd [$1800.00] | Y14: =IF(COUNTIF(F24_CF!$A:$A,"*" & $A14 & "*") <> 0, "Yes", "No") -> Yes | Z14: {=INDEX(F24_CF!N:N, MATCH("*" & $A14 & "*", F24_CF!$A:$A, 0))} -> Gold One-Day: Thursday, September 5th [$2500.00] | AA14: =IF(COUNTIF(S24_CF!$A:$A,"*" & $A14 & "*") <> 0, "Yes", "No") -> Yes | AB14: {=INDEX(S24_CF!H:H, MATCH("*" & $A14 & "*", S24_CF!$A:$A, 0))} -> Basic Two-Day [$2000.00]
A15: Arion Blue, LLC | B15: Private | F15: =COUNTIF(S26_Emp!$C:$C,"*" &A15 & "*") -> 0 | G15: =COUNTIF(F25_Emp!$C:$C,"*" &#REF! & "*") -> 0 | H15: =COUNTIF(S25_Emp!$C:$C,"*" & A15 & "*") -> 0 | I15: =COUNTIF(F24_Emp!$C:$C,"*" & B15 & "*") -> 0 | J15: =COUNTIF(S24_Emp!$C:$C,"*" & $A15 & "*") -> 0 | K15: =COUNTIF(F23_Emp!$C:$C,"*" & $A15 & "*") -> 0 | L15: =COUNTIF(S23_Emp!$C:$C,"*" & $A15 & "*") -> 1 | M15: =COUNTIF(F22_Emp!$C:$C,"*" & $A15 & "*") -> 1 | N15: =COUNTIF(S22_Emp!$C:$C,"*" & $A15 & "*") -> 0 | O15: =COUNTIFS(S22_Emp!$C:$C,"*" & $A15 & "*", S22_S25_Emp!$B:$B, "Bachelor") -> #VALUE! | P15: =COUNTIFS(S22_Emp!$C:$C,"*" & $A15 & "*", S22_S25_Emp!$B:$B, "Master") -> #VALUE! | Q15: =COUNTIFS(S22_Emp!$C:$C,"*" & $A15 & "*", S22_S25_Emp!$B:$B, "Doctorate") -> #VALUE! | R15: {=IF(OR(INDEX(S26_CF!X:X, MATCH("*" & $A15 & "*", CompanyList!A:A, 0))=TRUE, INDEX(F25_CF!P:P, MATCH("*" & $A15 & "*", CompanyList!A:A, 0))=TRUE, INDEX(S25_CF!T:T, MATCH("*" & $A15 & "*", CompanyList!A:A, 0))=TRUE, INDEX(S24_CF!W:W, MATCH("*" & $A15 & "*", CompanyList!A:A, 0))=TRUE), "Yes", "No")} -> No | S15: =IF(COUNTIF(S26_CF!$A:$A,"*" & $A15 & "*") <> 0, "Yes", "No") -> Yes | T15: {=INDEX(S26_CF!K:K, MATCH("*" & $A15 & "*", S26_CF!A:A, 0))} -> Basic One-Day: Thursday, January 29th [$1000.00] | U15: =IF(COUNTIF(F25_CF!$A:$A,"*" & $A15 & "*") <> 0, "Yes", "No") -> Yes | V15: {=INDEX(F25_CF!I:I, MATCH("*" & $A15 & "*", F25_CF!$A:$A, 0))} -> Basic One-Day: Wednesday, September 10th [$1000.00] | W15: =IF(COUNTIF(S25_CF!$A:$A,"*" & $A15 & "*") <> 0, "Yes", "No") -> Yes | X15: {=INDEX(S25_CF!J:J, MATCH("*" & $A15 & "*", S25_CF!$A:$A, 0))} -> Basic One-Day: Wednesday, January 22nd [$1000.00] | Y15: =IF(COUNTIF(F24_CF!$A:$A,"*" & $A15 & "*") <> 0, "Yes", "No") -> No | Z15: {=INDEX(F24_CF!N:N, MATCH("*" & $A15 & "*", F24_CF!$A:$A, 0))} -> #N/A | AA15: =IF(COUNTIF(S24_CF!$A:$A,"*" & $A15 & "*") <> 0, "Yes", "No") -> Yes | AB15: {=INDEX(S24_CF!H:H, MATCH("*" & $A15 & "*", S24_CF!$A:$A, 0))} -> Basic One-Day [$1000.00]
A16: AtkinsRéalis | B16: Public | C16: 6500 | D16: 37000 | E16: 10 | F16: =COUNTIF(S26_Emp!$C:$C,"*" &A16 & "*") -> 0 | G16: =COUNTIF(F25_Emp!$C:$C,"*" &#REF! & "*") -> 0 | H16: =COUNTIF(S25_Emp!$C:$C,"*" & A16 & "*") -> 0 | I16: =COUNTIF(F24_Emp!$C:$C,"*" & B16 & "*") -> 1 | J16: =COUNTIF(S24_Emp!$C:$C,"*" & $A16 & "*") -> 2 | K16: =COUNTIF(F23_Emp!$C:$C,"*" & $A16 & "*") -> 1 | L16: =COUNTIF(S23_Emp!$C:$C,"*" & $A16 & "*") -> 0 | M16: =COUNTIF(F22_Emp!$C:$C,"*" & $A16 & "*") -> 0 | N16: =COUNTIF(S22_Emp!$C:$C,"*" & $A16 & "*") -> 0 | O16: =COUNTIFS(S22_Emp!$C:$C,"*" & $A16 & "*", S22_S25_Emp!$B:$B, "Bachelor") -> #VALUE! | P16: =COUNTIFS(S22_Emp!$C:$C,"*" & $A16 & "*", S22_S25_Emp!$B:$B, "Master") -> #VALUE! | Q16: =COUNTIFS(S22_Emp!$C:$C,"*" & $A16 & "*", S22_S25_Emp!$B:$B, "Doctorate") -> #VALUE! | R16: {=IF(OR(INDEX(S26_CF!X:X, MATCH("*" & $A16 & "*", CompanyList!A:A, 0))=TRUE, INDEX(F25_CF!P:P, MATCH("*" & $A16 & "*", CompanyList!A:A, 0))=TRUE, INDEX(S25_CF!T:T, MATCH("*" & $A16 & "*", CompanyList!A:A, 0))=TRUE, INDEX(S24_CF!W:W, MATCH("*" & $A16 & "*", CompanyList!A:A, 0))=TRUE), "Yes", "No")} -> Yes | S16: =IF(COUNTIF(S26_CF!$A:$A,"*" & $A16 & "*") <> 0, "Yes", "No") -> Yes | T16: {=INDEX(S26_CF!K:K, MATCH("*" & $A16 & "*", S26_CF!A:A, 0))} -> Basic One-Day: Wednesday, January 28th [$1000.00] | U16: =IF(COUNTIF(F25_CF!$A:$A,"*" & $A16 & "*") <> 0, "Yes", "No") -> Yes | V16: {=INDEX(F25_CF!I:I, MATCH("*" & $A16 & "*", F25_CF!$A:$A, 0))} -> Basic One-Day: Wednesday, September 10th [$1000.00] | W16: =IF(COUNTIF(S25_CF!$A:$A,"*" & $A16 & "*") <> 0, "Yes", "No") -> Yes | X16: {=INDEX(S25_CF!J:J, MATCH("*" & $A16 & "*", S25_CF!$A:$A, 0))} -> Basic One-Day: Wednesday, January 22nd [$1000.00] | Y16: =IF(COUNTIF(F24_CF!$A:$A,"*" & $A16 & "*") <> 0, "Yes", "No") -> Yes | Z16: {=INDEX(F24_CF!N:N, MATCH("*" & $A16 & "*", F24_CF!$A:$A, 0))} -> Basic One-Day: Wednesday, September 4th [$1000.00] | AA16: =IF(COUNTIF(S24_CF!$A:$A,"*" & $A16 & "*") <> 0, "Yes", "No") -> Yes | AB16: {=INDEX(S24_CF!H:H, MATCH("*" & $A16 & "*", S24_CF!$A:$A, 0))} -> Basic One-Day [$1000.00]
A17: Atlas Energy Solutions | B17: Private | F17: =COUNTIF(S26_Emp!$C:$C,"*" &A17 & "*") -> 0 | G17: =COUNTIF(F25_Emp!$C:$C,"*" &#REF! & "*") -> 0 | H17: =COUNTIF(S25_Emp!$C:$C,"*" & A17 & "*") -> 0 | I17: =COUNTIF(F24_Emp!$C:$C,"*" & B17 & "*") -> 0 | J17: =COUNTIF(S24_Emp!$C:$C,"*" & $A17 & "*") -> 0 | K17: =COUNTIF(F23_Emp!$C:$C,"*" & $A17 & "*") -> 0 | L17: =COUNTIF(S23_Emp!$C:$C,"*" & $A17 & "*") -> 0 | M17: =COUNTIF(F22_Emp!$C:$C,"*" & $A17 & "*") -> 0 | N17: =COUNTIF(S22_Emp!$C:$C,"*" & $A17 & "*") -> 0 | O17: =COUNTIFS(S22_Emp!$C:$C,"*" & $A17 & "*", S22_S25_Emp!$B:$B, "Bachelor") -> #VALUE! | P17: =COUNTIFS(S22_Emp!$C:$C,"*" & $A17 & "*", S22_S25_Emp!$B:$B, "Master") -> #VALUE! | Q17: =COUNTIFS(S22_Emp!$C:$C,"*" & $A17 & "*", S22_S25_Emp!$B:$B, "Doctorate") -> #VALUE! | R17: {=IF(OR(INDEX(S26_CF!X:X, MATCH("*" & $A17 & "*", CompanyList!A:A, 0))=TRUE, INDEX(F25_CF!P:P, MATCH("*" & $A17 & "*", CompanyList!A:A, 0))=TRUE, INDEX(S25_CF!T:T, MATCH("*" & $A17 & "*", CompanyList!A:A, 0))=TRUE, INDEX(S24_CF!W:W, MATCH("*" & $A17 & "*", CompanyList!A:A, 0))=TRUE), "Yes", "No")} -> No | S17: =IF(COUNTIF(S26_CF!$A:$A,"*" & $A17 & "*") <> 0, "Yes", "No") -> Yes | T17: {=INDEX(S26_CF!K:K, MATCH("*" & $A17 & "*", S26_CF!A:A, 0))} -> Basic One-Day: Thursday, January 29th [$1000.00] | U17: =IF(COUNTIF(F25_CF!$A:$A,"*" & $A17 & "*") <> 0, "Yes", "No") -> Yes | V17: {=INDEX(F25_CF!I:I, MATCH("*" & $A17 & "*", F25_CF!$A:$A, 0))} -> Basic One-Day: Thursday, September 11th [$1000.00] | W17: =IF(COUNTIF(S25_CF!$A:$A,"*" & $A17 & "*") <> 0, "Yes", "No") -> No | X17: {=INDEX(S25_CF!J:J, MATCH("*" & $A17 & "*", S25_CF!$A:$A, 0))} -> #N/A | Y17: =IF(COUNTIF(F24_CF!$A:$A,"*" & $A17 & "*") <> 0, "Yes", "No") -> Yes | Z17: {=INDEX(F24_CF!N:N, MATCH("*" & $A17 & "*", F24_CF!$A:$A, 0))} -> Basic One-Day: Wednesday, September 4th [$1000.00] | AA17: =IF(COUNTIF(S24_CF!$A:$A,"*" & $A17 & "*") <> 0, "Yes", "No") -> Yes | AB17: {=INDEX(S24_CF!H:H, MATCH("*" & $A17 & "*", S24_CF!$A:$A, 0))} -> Basic Two-Day [$2000.00]
A18: Atmos Energy | B18: Public | C18: 4200 | D18: 4800 | E18: 17 | F18: =COUNTIF(S26_Emp!$C:$C,"*" &A18 & "*") -> 0 | G18: =COUNTIF(F25_Emp!$C:$C,"*" &#REF! & "*") -> 0 | H18: =COUNTIF(S25_Emp!$C:$C,"*" & A18 & "*") -> 0 | I18: =COUNTIF(F24_Emp!$C:$C,"*" & B18 & "*") -> 1 | J18: =COUNTIF(S24_Emp!$C:$C,"*" & $A18 & "*") -> 2 | K18: =COUNTIF(F23_Emp!$C:$C,"*" & $A18 & "*") -> 0 | L18: =COUNTIF(S23_Emp!$C:$C,"*" & $A18 & "*") -> 0 | M18: =COUNTIF(F22_Emp!$C:$C,"*" & $A18 & "*") -> 0 | N18: =COUNTIF(S22_Emp!$C:$C,"*" & $A18 & "*") -> 0 | O18: =COUNTIFS(S22_Emp!$C:$C,"*" & $A18 & "*", S22_S25_Emp!$B:$B, "Bachelor") -> #VALUE! | P18: =COUNTIFS(S22_Emp!$C:$C,"*" & $A18 & "*", S22_S25_Emp!$B:$B, "Master") -> #VALUE! | Q18: =COUNTIFS(S22_Emp!$C:$C,"*" & $A18 & "*", S22_S25_Emp!$B:$B, "Doctorate") -> #VALUE! | R18: {=IF(OR(INDEX(S26_CF!X:X, MATCH("*" & $A18 & "*", CompanyList!A:A, 0))=TRUE, INDEX(F25_CF!P:P, MATCH("*" & $A18 & "*", CompanyList!A:A, 0))=TRUE, INDEX(S25_CF!T:T, MATCH("*" & $A18 & "*", CompanyList!A:A, 0))=TRUE, INDEX(S24_CF!W:W, MATCH("*" & $A18 & "*", CompanyList!A:A, 0))=TRUE), "Yes", "No")} -> Yes | S18: =IF(COUNTIF(S26_CF!$A:$A,"*" & $A18 & "*") <> 0, "Yes", "No") -> Yes | T18: {=INDEX(S26_CF!K:K, MATCH("*" & $A18 & "*", S26_CF!A:A, 0))} -> Basic One-Day: Wednesday, January 28th [$1000.00] | U18: =IF(COUNTIF(F25_CF!$A:$A,"*" & $A18 & "*") <> 0, "Yes", "No") -> Yes | V18: {=INDEX(F25_CF!I:I, MATCH("*" & $A18 & "*", F25_CF!$A:$A, 0))} -> Silver Two-Day [$3000.00] | W18: =IF(COUNTIF(S25_CF!$A:$A,"*" & $A18 & "*") <> 0, "Yes", "No") -> No | X18: {=INDEX(S25_CF!J:J, MATCH("*" & $A18 & "*", S25_CF!$A:$A, 0))} -> #N/A | Y18: =IF(COUNTIF(F24_CF!$A:$A,"*" & $A18 & "*") <> 0, "Yes", "No") -> Yes | Z18: {=INDEX(F24_CF!N:N, MATCH("*" & $A18 & "*", F24_CF!$A:$A, 0))} -> Silver Two-Day [$3000.00] | AA18: =IF(COUNTIF(S24_CF!$A:$A,"*" & $A18 & "*") <> 0, "Yes", "No") -> Yes | AB18: {=INDEX(S24_CF!H:H, MATCH("*" & $A18 & "*", S24_CF!$A:$A, 0))} -> Basic One-Day [$1000.00]
A19: Atwell, LLC | B19: Private | F19: =COUNTIF(S26_Emp!$C:$C,"*" &A19 & "*") -> 0 | G19: =COUNTIF(F25_Emp!$C:$C,"*" &#REF! & "*") -> 0 | H19: =COUNTIF(S25_Emp!$C:$C,"*" & A19 & "*") -> 0 | I19: =COUNTIF(F24_Emp!$C:$C,"*" & B19 & "*") -> 0 | J19: =COUNTIF(S24_Emp!$C:$C,"*" & $A19 & "*") -> 0 | K19: =COUNTIF(F23_Emp!$C:$C,"*" & $A19 & "*") -> 0 | L19: =COUNTIF(S23_Emp!$C:$C,"*" & $A19 & "*") -> 0 | M19: =COUNTIF(F22_Emp!$C:$C,"*" & $A19 & "*") -> 0 | N19: =COUNTIF(S22_Emp!$C:$C,"*" & $A19 & "*") -> 0 | O19: =COUNTIFS(S22_Emp!$C:$C,"*" & $A19 & "*", S22_S25_Emp!$B:$B, "Bachelor") -> #VALUE! | P19: =COUNTIFS(S22_Emp!$C:$C,"*" & $A19 & "*", S22_S25_Emp!$B:$B, "Master") -> #VALUE! | Q19: =COUNTIFS(S22_Emp!$C:$C,"*" & $A19 & "*", S22_S25_Emp!$B:$B, "Doctorate") -> #VALUE! | R19: {=IF(OR(INDEX(S26_CF!X:X, MATCH("*" & $A19 & "*", CompanyList!A:A, 0))=TRUE, INDEX(F25_CF!P:P, MATCH("*" & $A19 & "*", CompanyList!A:A, 0))=TRUE, INDEX(S25_CF!T:T, MATCH("*" & $A19 & "*", CompanyList!A:A, 0))=TRUE, INDEX(S24_CF!W:W, MATCH("*" & $A19 & "*", CompanyList!A:A, 0))=TRUE), "Yes", "No")} -> Yes | S19: =IF(COUNTIF(S26_CF!$A:$A,"*" & $A19 & "*") <> 0, "Yes", "No") -> Yes | T19: {=INDEX(S26_CF!K:K, MATCH("*" & $A19 & "*", S26_CF!A:A, 0))} -> Basic One-Day: Thursday, January 29th [$1000.00] | U19: =IF(COUNTIF(F25_CF!$A:$A,"*" & $A19 & "*") <> 0, "Yes", "No") -> Yes | V19: {=INDEX(F25_CF!I:I, MATCH("*" & $A19 & "*", F25_CF!$A:$A, 0))} -> Silver One-Day: Wednesday, September 10th [$1800.00] | W19: =IF(COUNTIF(S25_CF!$A:$A,"*" & $A19 & "*") <> 0, "Yes", "No") -> No | X19: {=INDEX(S25_CF!J:J, MATCH("*" & $A19 & "*", S25_CF!$A:$A, 0))} -> #N/A | Y19: =IF(COUNTIF(F24_CF!$A:$A,"*" & $A19 & "*") <> 0, "Yes", "No") -> Yes | Z19: {=INDEX(F24_CF!N:N, MATCH("*" & $A19 & "*", F24_CF!$A:$A, 0))} -> Basic One-Day: Wednesday, September 4th [$1000.00] | AA19: =IF(COUNTIF(S24_CF!$A:$A,"*" & $A19 & "*") <> 0, "Yes", "No") -> Yes | AB19: {=INDEX(S24_CF!H:H, MATCH("*" & $A19 & "*", S24_CF!$A:$A, 0))} -> Basic One-Day [$1000.00]
A20: Audubon Companies | B20: Private | F20: =COUNTIF(S26_Emp!$C:$C,"*" &A20 & "*") -> 0 | G20: =COUNTIF(F25_Emp!$C:$C,"*" &#REF! & "*") -> 0 | H20: =COUNTIF(S25_Emp!$C:$C,"*" & A20 & "*") -> 0 | I20: =COUNTIF(F24_Emp!$C:$C,"*" & B20 & "*") -> 0 | J20: =COUNTIF(S24_Emp!$C:$C,"*" & $A20 & "*") -> 0 | K20: =COUNTIF(F23_Emp!$C:$C,"*" & $A20 & "*") -> 0 | L20: =COUNTIF(S23_Emp!$C:$C,"*" & $A20 & "*") -> 1 | M20: =COUNTIF(F22_Emp!$C:$C,"*" & $A20 & "*") -> 0 | N20: =COUNTIF(S22_Emp!$C:$C,"*" & $A20 & "*") -> 0 | O20: =COUNTIFS(S22_Emp!$C:$C,"*" & $A20 & "*", S22_S25_Emp!$B:$B, "Bachelor") -> #VALUE! | P20: =COUNTIFS(S22_Emp!$C:$C,"*" & $A20 & "*", S22_S25_Emp!$B:$B, "Master") -> #VALUE! | Q20: =COUNTIFS(S22_Emp!$C:$C,"*" & $A20 & "*", S22_S25_Emp!$B:$B, "Doctorate") -> #VALUE! | R20: {=IF(OR(INDEX(S26_CF!X:X, MATCH("*" & $A20 & "*", CompanyList!A:A, 0))=TRUE, INDEX(F25_CF!P:P, MATCH("*" & $A20 & "*", CompanyList!A:A, 0))=TRUE, INDEX(S25_CF!T:T, MATCH("*" & $A20 & "*", CompanyList!A:A, 0))=TRUE, INDEX(S24_CF!W:W, MATCH("*" & $A20 & "*", CompanyList!A:A, 0))=TRUE), "Yes", "No")} -> Yes | S20: =IF(COUNTIF(S26_CF!$A:$A,"*" & $A20 & "*") <> 0, "Yes", "No") -> Yes | T20: {=INDEX(S26_CF!K:K, MATCH("*" & $A20 & "*", S26_CF!A:A, 0))} -> Basic One-Day: Wednesday, January 28th [$1000.00] | U20: =IF(COUNTIF(F25_CF!$A:$A,"*" & $A20 & "*") <> 0, "Yes", "No") -> Yes | V20: {=INDEX(F25_CF!I:I, MATCH("*" & $A20 & "*", F25_CF!$A:$A, 0))} -> Basic One-Day: Wednesday, September 10th [$1000.00] | W20: =IF(COUNTIF(S25_CF!$A:$A,"*" & $A20 & "*") <> 0, "Yes", "No") -> Yes | X20: {=INDEX(S25_CF!J:J, MATCH("*" & $A20 & "*", S25_CF!$A:$A, 0))} -> Basic One-Day: Thursday, January 23rd [$1000.00] | Y20: =IF(COUNTIF(F24_CF!$A:$A,"*" & $A20 & "*") <> 0, "Yes", "No") -> Yes | Z20: {=INDEX(F24_CF!N:N, MATCH("*" & $A20 & "*", F24_CF!$A:$A, 0))} -> Basic One-Day: Wednesday, September 4th [$1000.00] | AA20: =IF(COUNTIF(S24_CF!$A:$A,"*" & $A20 & "*") <> 0, "Yes", "No") -> Yes | AB20: {=INDEX(S24_CF!H:H, MATCH("*" & $A20 & "*", S24_CF!$A:$A, 0))} -> Basic One-Day [$1000.00]
A21: Austin Bridge & Road, L.P. | B21: Private | F21: =COUNTIF(S26_Emp!$C:$C,"*" &A21 & "*") -> 0 | G21: =COUNTIF(F25_Emp!$C:$C,"*" &#REF! & "*") -> 0 | H21: =COUNTIF(S25_Emp!$C:$C,"*" & A21 & "*") -> 0 | I21: =COUNTIF(F24_Emp!$C:$C,"*" & B21 & "*") -> 0 | J21: =COUNTIF(S24_Emp!$C:$C,"*" & $A21 & "*") -> 0 | K21: =COUNTIF(F23_Emp!$C:$C,"*" & $A21 & "*") -> 1 | L21: =COUNTIF(S23_Emp!$C:$C,"*" & $A21 & "*") -> 0 | M21: =COUNTIF(F22_Emp!$C:$C,"*" & $A21 & "*") -> 0 | N21: =COUNTIF(S22_Emp!$C:$C,"*" & $A21 & "*") -> 0 | O21: =COUNTIFS(S22_Emp!$C:$C,"*" & $A21 & "*", S22_S25_Emp!$B:$B, "Bachelor") -> #VALUE! | P21: =COUNTIFS(S22_Emp!$C:$C,"*" & $A21 & "*", S22_S25_Emp!$B:$B, "Master") -> #VALUE! | Q21: =COUNTIFS(S22_Emp!$C:$C,"*" & $A21 & "*", S22_S25_Emp!$B:$B, "Doctorate") -> #VALUE! | R21: {=IF(OR(INDEX(S26_CF!X:X, MATCH("*" & $A21 & "*", CompanyList!A:A, 0))=TRUE, INDEX(F25_CF!P:P, MATCH("*" & $A21 & "*", CompanyList!A:A, 0))=TRUE, INDEX(S25_CF!T:T, MATCH("*" & $A21 & "*", CompanyList!A:A, 0))=TRUE, INDEX(S24_CF!W:W, MATCH("*" & $A21 & "*", CompanyList!A:A, 0))=TRUE), "Yes", "No")} -> Yes | S21: =IF(COUNTIF(S26_CF!$A:$A,"*" & $A21 & "*") <> 0, "Yes", "No") -> Yes | T21: {=INDEX(S26_CF!K:K, MATCH("*" & $A21 & "*", S26_CF!A:A, 0))} -> Basic One-Day: Wednesday, January 28th [$1000.00] | U21: =IF(COUNTIF(F25_CF!$A:$A,"*" & $A21 & "*") <> 0, "Yes", "No") -> Yes | V21: {=INDEX(F25_CF!I:I, MATCH("*" & $A21 & "*", F25_CF!$A:$A, 0))} -> Basic One-Day: Thursday, September 11th [$1000.00] | W21: =IF(COUNTIF(S25_CF!$A:$A,"*" & $A21 & "*") <> 0, "Yes", "No") -> Yes | X21: {=INDEX(S25_CF!J:J, MATCH("*" & $A21 & "*", S25_CF!$A:$A, 0))} -> Basic One-Day: Wednesday, January 22nd [$1000.00] | Y21: =IF(COUNTIF(F24_CF!$A:$A,"*" & $A21 & "*") <> 0, "Yes", "No") -> Yes | Z21: {=INDEX(F24_CF!N:N, MATCH("*" & $A21 & "*", F24_CF!$A:$A, 0))} -> Silver One-Day: Thursday, September 5th [$1800.00] | AA21: =IF(COUNTIF(S24_CF!$A:$A,"*" & $A21 & "*") <> 0, "Yes", "No") -> Yes | AB21: {=INDEX(S24_CF!H:H, MATCH("*" & $A21 & "*", S24_CF!$A:$A, 0))} -> Silver One-Day [$1800.00]
A22: Baird, Hampton & Brown | B22: Private | F22: =COUNTIF(S26_Emp!$C:$C,"*" &A22 & "*") -> 0 | G22: =COUNTIF(F25_Emp!$C:$C,"*" &#REF! & "*") -> 0 | H22: =COUNTIF(S25_Emp!$C:$C,"*" & A22 & "*") -> 0 | I22: =COUNTIF(F24_Emp!$C:$C,"*" & B22 & "*") -> 0 | J22: =COUNTIF(S24_Emp!$C:$C,"*" & $A22 & "*") -> 3 | K22: =COUNTIF(F23_Emp!$C:$C,"*" & $A22 & "*") -> 0 | L22: =COUNTIF(S23_Emp!$C:$C,"*" & $A22 & "*") -> 0 | M22: =COUNTIF(F22_Emp!$C:$C,"*" & $A22 & "*") -> 1 | N22: =COUNTIF(S22_Emp!$C:$C,"*" & $A22 & "*") -> 0 | O22: =COUNTIFS(S22_Emp!$C:$C,"*" & $A22 & "*", S22_S25_Emp!$B:$B, "Bachelor") -> #VALUE! | P22: =COUNTIFS(S22_Emp!$C:$C,"*" & $A22 & "*", S22_S25_Emp!$B:$B, "Master") -> #VALUE! | Q22: =COUNTIFS(S22_Emp!$C:$C,"*" & $A22 & "*", S22_S25_Emp!$B:$B, "Doctorate") -> #VALUE! | R22: {=IF(OR(INDEX(S26_CF!X:X, MATCH("*" & $A22 & "*", CompanyList!A:A, 0))=TRUE, INDEX(F25_CF!P:P, MATCH("*" & $A22 & "*", CompanyList!A:A, 0))=TRUE, INDEX(S25_CF!T:T, MATCH("*" & $A22 & "*", CompanyList!A:A, 0))=TRUE, INDEX(S24_CF!W:W, MATCH("*" & $A22 & "*", CompanyList!A:A, 0))=TRUE), "Yes", "No")} -> Yes | S22: =IF(COUNTIF(S26_CF!$A:$A,"*" & $A22 & "*") <> 0, "Yes", "No") -> Yes | T22: {=INDEX(S26_CF!K:K, MATCH("*" & $A22 & "*", S26_CF!A:A, 0))} -> Basic One-Day: Wednesday, January 28th [$1000.00] | U22: =IF(COUNTIF(F25_CF!$A:$A,"*" & $A22 & "*") <> 0, "Yes", "No") -> Yes | V22: {=INDEX(F25_CF!I:I, MATCH("*" & $A22 & "*", F25_CF!$A:$A, 0))} -> Basic One-Day: Wednesday, September 10th [$1000.00] | W22: =IF(COUNTIF(S25_CF!$A:$A,"*" & $A22 & "*") <> 0, "Yes", "No") -> Yes | X22: {=INDEX(S25_CF!J:J, MATCH("*" & $A22 & "*", S25_CF!$A:$A, 0))} -> Basic One-Day: Thursday, January 23rd [$1000.00] | Y22: =IF(COUNTIF(F24_CF!$A:$A,"*" & $A22 & "*") <> 0, "Yes", "No") -> Yes | Z22: {=INDEX(F24_CF!N:N, MATCH("*" & $A22 & "*", F24_CF!$A:$A, 0))} -> Basic One-Day: Thursday, September 5th [$1000.00] | AA22: =IF(COUNTIF(S24_CF!$A:$A,"*" & $A22 & "*") <> 0, "Yes", "No") -> Yes | AB22: {=INDEX(S24_CF!H:H, MATCH("*" & $A22 & "*", S24_CF!$A:$A, 0))} -> Basic One-Day [$1000.00]
A23: Baker Concrete Construction | B23: Private | F23: =COUNTIF(S26_Emp!$C:$C,"*" &A23 & "*") -> 0 | G23: =COUNTIF(F25_Emp!$C:$C,"*" &#REF! & "*") -> 0 | H23: =COUNTIF(S25_Emp!$C:$C,"*" & A23 & "*") -> 0 | I23: =COUNTIF(F24_Emp!$C:$C,"*" & B23 & "*") -> 0 | J23: =COUNTIF(S24_Emp!$C:$C,"*" & $A23 & "*") -> 0 | K23: =COUNTIF(F23_Emp!$C:$C,"*" & $A23 & "*") -> 0 | L23: =COUNTIF(S23_Emp!$C:$C,"*" & $A23 & "*") -> 0 | M23: =COUNTIF(F22_Emp!$C:$C,"*" & $A23 & "*") -> 1 | N23: =COUNTIF(S22_Emp!$C:$C,"*" & $A23 & "*") -> 0 | O23: =COUNTIFS(S22_Emp!$C:$C,"*" & $A23 & "*", S22_S25_Emp!$B:$B, "Bachelor") -> #VALUE! | P23: =COUNTIFS(S22_Emp!$C:$C,"*" & $A23 & "*", S22_S25_Emp!$B:$B, "Master") -> #VALUE! | Q23: =COUNTIFS(S22_Emp!$C:$C,"*" & $A23 & "*", S22_S25_Emp!$B:$B, "Doctorate") -> #VALUE! | R23: {=IF(OR(INDEX(S26_CF!X:X, MATCH("*" & $A23 & "*", CompanyList!A:A, 0))=TRUE, INDEX(F25_CF!P:P, MATCH("*" & $A23 & "*", CompanyList!A:A, 0))=TRUE, INDEX(S25_CF!T:T, MATCH("*" & $A23 & "*", CompanyList!A:A, 0))=TRUE, INDEX(S24_CF!W:W, MATCH("*" & $A23 & "*", CompanyList!A:A, 0))=TRUE), "Yes", "No")} -> Yes | S23: =IF(COUNTIF(S26_CF!$A:$A,"*" & $A23 & "*") <> 0, "Yes", "No") -> Yes | T23: {=INDEX(S26_CF!K:K, MATCH("*" & $A23 & "*", S26_CF!A:A, 0))} -> Basic One-Day: Wednesday, January 28th [$1000.00] | U23: =IF(COUNTIF(F25_CF!$A:$A,"*" & $A23 & "*") <> 0, "Yes", "No") -> No | V23: {=INDEX(F25_CF!I:I, MATCH("*" & $A23 & "*", F25_CF!$A:$A, 0))} -> #N/A | W23: =IF(COUNTIF(S25_CF!$A:$A,"*" & $A23 & "*") <> 0, "Yes", "No") -> No | X23: {=INDEX(S25_CF!J:J, MATCH("*" & $A23 & "*", S25_CF!$A:$A, 0))} -> #N/A | Y23: =IF(COUNTIF(F24_CF!$A:$A,"*" & $A23 & "*") <> 0, "Yes", "No") -> Yes | Z23: {=INDEX(F24_CF!N:N, MATCH("*" & $A23 & "*", F24_CF!$A:$A, 0))} -> Basic Two-Day [$2000.00] | AA23: =IF(COUNTIF(S24_CF!$A:$A,"*" & $A23 & "*") <> 0, "Yes", "No") -> Yes | AB23: {=INDEX(S24_CF!H:H, MATCH("*" & $A23 & "*", S24_CF!$A:$A, 0))} -> Basic Two-Day [$2000.00]
A24: Baker Hughes | B24: Public | C24: 25500 | D24: 58000 | E24: 35 | F24: =COUNTIF(S26_Emp!$C:$C,"*" &A24 & "*") -> 0 | G24: =COUNTIF(F25_Emp!$C:$C,"*" &#REF! & "*") -> 0 | H24: =COUNTIF(S25_Emp!$C:$C,"*" & A24 & "*") -> 2 | I24: =COUNTIF(F24_Emp!$C:$C,"*" & B24 & "*") -> 1 | J24: =COUNTIF(S24_Emp!$C:$C,"*" & $A24 & "*") -> 2 | K24: =COUNTIF(F23_Emp!$C:$C,"*" & $A24 & "*") -> 0 | L24: =COUNTIF(S23_Emp!$C:$C,"*" & $A24 & "*") -> 1 | M24: =COUNTIF(F22_Emp!$C:$C,"*" & $A24 & "*") -> 0 | N24: =COUNTIF(S22_Emp!$C:$C,"*" & $A24 & "*") -> 6 | O24: =COUNTIFS(S22_Emp!$C:$C,"*" & $A24 & "*", S22_S25_Emp!$B:$B, "Bachelor") -> #VALUE! | P24: =COUNTIFS(S22_Emp!$C:$C,"*" & $A24 & "*", S22_S25_Emp!$B:$B, "Master") -> #VALUE! | Q24: =COUNTIFS(S22_Emp!$C:$C,"*" & $A24 & "*", S22_S25_Emp!$B:$B, "Doctorate") -> #VALUE! | R24: {=IF(OR(INDEX(S26_CF!X:X, MATCH("*" & $A24 & "*", CompanyList!A:A, 0))=TRUE, INDEX(F25_CF!P:P, MATCH("*" & $A24 & "*", CompanyList!A:A, 0))=TRUE, INDEX(S25_CF!T:T, MATCH("*" & $A24 & "*", CompanyList!A:A, 0))=TRUE, INDEX(S24_CF!W:W, MATCH("*" & $A24 & "*", CompanyList!A:A, 0))=TRUE), "Yes", "No")} -> Yes | S24: =IF(COUNTIF(S26_CF!$A:$A,"*" & $A24 & "*") <> 0, "Yes", "No") -> Yes | T24: {=INDEX(S26_CF!K:K, MATCH("*" & $A24 & "*", S26_CF!A:A, 0))} -> Gold One-Day: Wednesday, January 28th [$2500.00] | U24: =IF(COUNTIF(F25_CF!$A:$A,"*" & $A24 & "*") <> 0, "Yes", "No") -> Yes | V24: {=INDEX(F25_CF!I:I, MATCH("*" & $A24 & "*", F25_CF!$A:$A, 0))} -> Gold One-Day: Wednesday, September 10th [$2500.00] | W24: =IF(COUNTIF(S25_CF!$A:$A,"*" & $A24 & "*") <> 0, "Yes", "No") -> Yes | X24: {=INDEX(S25_CF!J:J, MATCH("*" & $A24 & "*", S25_CF!$A:$A, 0))} -> Gold Two-Day [$5500.00] | Y24: =IF(COUNTIF(F24_CF!$A:$A,"*" & $A24 & "*") <> 0, "Yes", "No") -> Yes | Z24: {=INDEX(F24_CF!N:N, MATCH("*" & $A24 & "*", F24_CF!$A:$A, 0))} -> Silver Two-Day [$3000.00] | AA24: =IF(COUNTIF(S24_CF!$A:$A,"*" & $A24 & "*") <> 0, "Yes", "No") -> Yes | AB24: {=INDEX(S24_CF!H:H, MATCH("*" & $A24 & "*", S24_CF!$A:$A, 0))} -> Basic One-Day [$1000.00]
A25: Beckhoff Automation | B25: Private | F25: =COUNTIF(S26_Emp!$C:$C,"*" &A25 & "*") -> 0 | G25: =COUNTIF(F25_Emp!$C:$C,"*" &#REF! & "*") -> 0 | H25: =COUNTIF(S25_Emp!$C:$C,"*" & A25 & "*") -> 0 | I25: =COUNTIF(F24_Emp!$C:$C,"*" & B25 & "*") -> 0 | J25: =COUNTIF(S24_Emp!$C:$C,"*" & $A25 & "*") -> 0 | K25: =COUNTIF(F23_Emp!$C:$C,"*" & $A25 & "*") -> 0 | L25: =COUNTIF(S23_Emp!$C:$C,"*" & $A25 & "*") -> 2 | M25: =COUNTIF(F22_Emp!$C:$C,"*" & $A25 & "*") -> 1 | N25: =COUNTIF(S22_Emp!$C:$C,"*" & $A25 & "*") -> 1 | O25: =COUNTIFS(S22_Emp!$C:$C,"*" & $A25 & "*", S22_S25_Emp!$B:$B, "Bachelor") -> #VALUE! | P25: =COUNTIFS(S22_Emp!$C:$C,"*" & $A25 & "*", S22_S25_Emp!$B:$B, "Master") -> #VALUE! | Q25: =COUNTIFS(S22_Emp!$C:$C,"*" & $A25 & "*", S22_S25_Emp!$B:$B, "Doctorate") -> #VALUE! | R25: {=IF(OR(INDEX(S26_CF!X:X, MATCH("*" & $A25 & "*", CompanyList!A:A, 0))=TRUE, INDEX(F25_CF!P:P, MATCH("*" & $A25 & "*", CompanyList!A:A, 0))=TRUE, INDEX(S25_CF!T:T, MATCH("*" & $A25 & "*", CompanyList!A:A, 0))=TRUE, INDEX(S24_CF!W:W, MATCH("*" & $A25 & "*", CompanyList!A:A, 0))=TRUE), "Yes", "No")} -> Yes | S25: =IF(COUNTIF(S26_CF!$A:$A,"*" & $A25 & "*") <> 0, "Yes", "No") -> No | T25: {=INDEX(S26_CF!K:K, MATCH("*" & $A25 & "*", S26_CF!A:A, 0))} -> #N/A | U25: =IF(COUNTIF(F25_CF!$A:$A,"*" & $A25 & "*") <> 0, "Yes", "No") -> Yes | V25: {=INDEX(F25_CF!I:I, MATCH("*" & $A25 & "*", F25_CF!$A:$A, 0))} -> Silver Two-Day [$3000.00] | W25: =IF(COUNTIF(S25_CF!$A:$A,"*" & $A25 & "*") <> 0, "Yes", "No") -> No | X25: {=INDEX(S25_CF!J:J, MATCH("*" & $A25 & "*", S25_CF!$A:$A, 0))} -> #N/A | Y25: =IF(COUNTIF(F24_CF!$A:$A,"*" & $A25 & "*") <> 0, "Yes", "No") -> Yes | Z25: {=INDEX(F24_CF!N:N, MATCH("*" & $A25 & "*", F24_CF!$A:$A, 0))} -> Silver Two-Day [$3000.00] | AA25: =IF(COUNTIF(S24_CF!$A:$A,"*" & $A25 & "*") <> 0, "Yes", "No") -> Yes | AB25: {=INDEX(S24_CF!H:H, MATCH("*" & $A25 & "*", S24_CF!$A:$A, 0))} -> Silver Two-Day [$3000.00]
A26: Bernhard | B26: Private | F26: =COUNTIF(S26_Emp!$C:$C,"*" &A26 & "*") -> 0 | G26: =COUNTIF(F25_Emp!$C:$C,"*" &#REF! & "*") -> 0 | H26: =COUNTIF(S25_Emp!$C:$C,"*" & A26 & "*") -> 0 | I26: =COUNTIF(F24_Emp!$C:$C,"*" & B26 & "*") -> 0 | J26: =COUNTIF(S24_Emp!$C:$C,"*" & $A26 & "*") -> 0 | K26: =COUNTIF(F23_Emp!$C:$C,"*" & $A26 & "*") -> 0 | L26: =COUNTIF(S23_Emp!$C:$C,"*" & $A26 & "*") -> 0 | M26: =COUNTIF(F22_Emp!$C:$C,"*" & $A26 & "*") -> 0 | N26: =COUNTIF(S22_Emp!$C:$C,"*" & $A26 & "*") -> 0 | O26: =COUNTIFS(S22_Emp!$C:$C,"*" & $A26 & "*", S22_S25_Emp!$B:$B, "Bachelor") -> #VALUE! | P26: =COUNTIFS(S22_Emp!$C:$C,"*" & $A26 & "*", S22_S25_Emp!$B:$B, "Master") -> #VALUE! | Q26: =COUNTIFS(S22_Emp!$C:$C,"*" & $A26 & "*", S22_S25_Emp!$B:$B, "Doctorate") -> #VALUE! | R26: {=IF(OR(INDEX(S26_CF!X:X, MATCH("*" & $A26 & "*", CompanyList!A:A, 0))=TRUE, INDEX(F25_CF!P:P, MATCH("*" & $A26 & "*", CompanyList!A:A, 0))=TRUE, INDEX(S25_CF!T:T, MATCH("*" & $A26 & "*", CompanyList!A:A, 0))=TRUE, INDEX(S24_CF!W:W, MATCH("*" & $A26 & "*", CompanyList!A:A, 0))=TRUE), "Yes", "No")} -> No | S26: =IF(COUNTIF(S26_CF!$A:$A,"*" & $A26 & "*") <> 0, "Yes", "No") -> No | T26: {=INDEX(S26_CF!K:K, MATCH("*" & $A26 & "*", S26_CF!A:A, 0))} -> #N/A | U26: =IF(COUNTIF(F25_CF!$A:$A,"*" & $A26 & "*") <> 0, "Yes", "No") -> Yes | V26: {=INDEX(F25_CF!I:I, MATCH("*" & $A26 & "*", F25_CF!$A:$A, 0))} -> Basic One-Day: Thursday, September 11th [$1000.00] | W26: =IF(COUNTIF(S25_CF!$A:$A,"*" & $A26 & "*") <> 0, "Yes", "No") -> No | X26: {=INDEX(S25_CF!J:J, MATCH("*" & $A26 & "*", S25_CF!$A:$A, 0))} -> #N/A | Y26: =IF(COUNTIF(F24_CF!$A:$A,"*" & $A26 & "*") <> 0, "Yes", "No") -> Yes | Z26: {=INDEX(F24_CF!N:N, MATCH("*" & $A26 & "*", F24_CF!$A:$A, 0))} -> Basic One-Day: Wednesday, September 4th [$1000.00] | AA26: =IF(COUNTIF(S24_CF!$A:$A,"*" & $A26 & "*") <> 0, "Yes", "No") -> Yes | AB26: {=INDEX(S24_CF!H:H, MATCH("*" & $A26 & "*", S24_CF!$A:$A, 0))} -> Basic One-Day [$1000.00]
A27: BGE, Inc | B27: Private | F27: =COUNTIF(S26_Emp!$C:$C,"*" &A27 & "*") -> 0 | G27: =COUNTIF(F25_Emp!$C:$C,"*" &#REF! & "*") -> 0 | H27: =COUNTIF(S25_Emp!$C:$C,"*" & A27 & "*") -> 0 | I27: =COUNTIF(F24_Emp!$C:$C,"*" & B27 & "*") -> 0 | J27: =COUNTIF(S24_Emp!$C:$C,"*" & $A27 & "*") -> 3 | K27: =COUNTIF(F23_Emp!$C:$C,"*" & $A27 & "*") -> 1 | L27: =COUNTIF(S23_Emp!$C:$C,"*" & $A27 & "*") -> 1 | M27: =COUNTIF(F22_Emp!$C:$C,"*" & $A27 & "*") -> 2 | N27: =COUNTIF(S22_Emp!$C:$C,"*" & $A27 & "*") -> 0 | O27: =COUNTIFS(S22_Emp!$C:$C,"*" & $A27 & "*", S22_S25_Emp!$B:$B, "Bachelor") -> #VALUE! | P27: =COUNTIFS(S22_Emp!$C:$C,"*" & $A27 & "*", S22_S25_Emp!$B:$B, "Master") -> #VALUE! | Q27: =COUNTIFS(S22_Emp!$C:$C,"*" & $A27 & "*", S22_S25_Emp!$B:$B, "Doctorate") -> #VALUE! | R27: {=IF(OR(INDEX(S26_CF!X:X, MATCH("*" & $A27 & "*", CompanyList!A:A, 0))=TRUE, INDEX(F25_CF!P:P, MATCH("*" & $A27 & "*", CompanyList!A:A, 0))=TRUE, INDEX(S25_CF!T:T, MATCH("*" & $A27 & "*", CompanyList!A:A, 0))=TRUE, INDEX(S24_CF!W:W, MATCH("*" & $A27 & "*", CompanyList!A:A, 0))=TRUE), "Yes", "No")} -> Yes | S27: =IF(COUNTIF(S26_CF!$A:$A,"*" & $A27 & "*") <> 0, "Yes", "No") -> Yes | T27: {=INDEX(S26_CF!K:K, MATCH("*" & $A27 & "*", S26_CF!A:A, 0))} -> Gold Two-Day [$5500.00] | U27: =IF(COUNTIF(F25_CF!$A:$A,"*" & $A27 & "*") <> 0, "Yes", "No") -> Yes | V27: {=INDEX(F25_CF!I:I, MATCH("*" & $A27 & "*", F25_CF!$A:$A, 0))} -> Gold Two-Day [$5500.00] | W27: =IF(COUNTIF(S25_CF!$A:$A,"*" & $A27 & "*") <> 0, "Yes", "No") -> Yes | X27: {=INDEX(S25_CF!J:J, MATCH("*" & $A27 & "*", S25_CF!$A:$A, 0))} -> Gold Two-Day [$5500.00] | Y27: =IF(COUNTIF(F24_CF!$A:$A,"*" & $A27 & "*") <> 0, "Yes", "No") -> Yes | Z27: {=INDEX(F24_CF!N:N, MATCH("*" & $A27 & "*", F24_CF!$A:$A, 0))} -> Gold Two-Day [$5500.00] | AA27: =IF(COUNTIF(S24_CF!$A:$A,"*" & $A27 & "*") <> 0, "Yes", "No") -> Yes | AB27: {=INDEX(S24_CF!H:H, MATCH("*" & $A27 & "*", S24_CF!$A:$A, 0))} -> Gold Two-Day [$5000.00]
A28: Black & Veatch | B28: Private | C28: 4200 | D28: 12000 | F28: =COUNTIF(S26_Emp!$C:$C,"*" &A28 & "*") -> 0 | G28: =COUNTIF(F25_Emp!$C:$C,"*" &#REF! & "*") -> 0 | H28: =COUNTIF(S25_Emp!$C:$C,"*" & A28 & "*") -> 3 | I28: =COUNTIF(F24_Emp!$C:$C,"*" & B28 & "*") -> 0 | J28: =COUNTIF(S24_Emp!$C:$C,"*" & $A28 & "*") -> 1 | K28: =COUNTIF(F23_Emp!$C:$C,"*" & $A28 & "*") -> 1 | L28: =COUNTIF(S23_Emp!$C:$C,"*" & $A28 & "*") -> 0 | M28: =COUNTIF(F22_Emp!$C:$C,"*" & $A28 & "*") -> 2 | N28: =COUNTIF(S22_Emp!$C:$C,"*" & $A28 & "*") -> 2 | O28: =COUNTIFS(S22_Emp!$C:$C,"*" & $A28 & "*", S22_S25_Emp!$B:$B, "Bachelor") -> #VALUE! | P28: =COUNTIFS(S22_Emp!$C:$C,"*" & $A28 & "*", S22_S25_Emp!$B:$B, "Master") -> #VALUE! | Q28: =COUNTIFS(S22_Emp!$C:$C,"*" & $A28 & "*", S22_S25_Emp!$B:$B, "Doctorate") -> #VALUE! | R28: {=IF(OR(INDEX(S26_CF!X:X, MATCH("*" & $A28 & "*", CompanyList!A:A, 0))=TRUE, INDEX(F25_CF!P:P, MATCH("*" & $A28 & "*", CompanyList!A:A, 0))=TRUE, INDEX(S25_CF!T:T, MATCH("*" & $A28 & "*", CompanyList!A:A, 0))=TRUE, INDEX(S24_CF!W:W, MATCH("*" & $A28 & "*", CompanyList!A:A, 0))=TRUE), "Yes", "No")} -> No | S28: =IF(COUNTIF(S26_CF!$A:$A,"*" & $A28 & "*") <> 0, "Yes", "No") -> Yes | T28: {=INDEX(S26_CF!K:K, MATCH("*" & $A28 & "*", S26_CF!A:A, 0))} -> Basic One-Day: Wednesday, January 28th [$1000.00] | U28: =IF(COUNTIF(F25_CF!$A:$A,"*" & $A28 & "*") <> 0, "Yes", "No") -> Yes | V28: {=INDEX(F25_CF!I:I, MATCH("*" & $A28 & "*", F25_CF!$A:$A, 0))} -> Basic One-Day: Wednesday, September 10th [$1000.00] | W28: =IF(COUNTIF(S25_CF!$A:$A,"*" & $A28 & "*") <> 0, "Yes", "No") -> Yes | X28: {=INDEX(S25_CF!J:J, MATCH("*" & $A28 & "*", S25_CF!$A:$A, 0))} -> Basic One-Day: Thursday, January 23rd [$1000.00] | Y28: =IF(COUNTIF(F24_CF!$A:$A,"*" & $A28 & "*") <> 0, "Yes", "No") -> Yes | Z28: {=INDEX(F24_CF!N:N, MATCH("*" & $A28 & "*", F24_CF!$A:$A, 0))} -> Basic One-Day: Wednesday, September 4th [$1000.00] | AA28: =IF(COUNTIF(S24_CF!$A:$A,"*" & $A28 & "*") <> 0, "Yes", "No") -> Yes | AB28: {=INDEX(S24_CF!H:H, MATCH("*" & $A28 & "*", S24_CF!$A:$A, 0))} -> Basic One-Day [$1000.00]
A29: BNSF Railway | B29: Private (Sub of Berkshire) | C29: 23000 | D29: 36000 | F29: =COUNTIF(S26_Emp!$C:$C,"*" &A29 & "*") -> 0 | G29: =COUNTIF(F25_Emp!$C:$C,"*" &#REF! & "*") -> 0 | H29: =COUNTIF(S25_Emp!$C:$C,"*" & A29 & "*") -> 0 | I29: =COUNTIF(F24_Emp!$C:$C,"*" & B29 & "*") -> 0 | J29: =COUNTIF(S24_Emp!$C:$C,"*" & $A29 & "*") -> 1 | K29: =COUNTIF(F23_Emp!$C:$C,"*" & $A29 & "*") -> 0 | L29: =COUNTIF(S23_Emp!$C:$C,"*" & $A29 & "*") -> 4 | M29: =COUNTIF(F22_Emp!$C:$C,"*" & $A29 & "*") -> 0 | N29: =COUNTIF(S22_Emp!$C:$C,"*" & $A29 & "*") -> 2 | O29: =COUNTIFS(S22_Emp!$C:$C,"*" & $A29 & "*", S22_S25_Emp!$B:$B, "Bachelor") -> #VALUE! | P29: =COUNTIFS(S22_Emp!$C:$C,"*" & $A29 & "*", S22_S25_Emp!$B:$B, "Master") -> #VALUE! | Q29: =COUNTIFS(S22_Emp!$C:$C,"*" & $A29 & "*", S22_S25_Emp!$B:$B, "Doctorate") -> #VALUE! | R29: {=IF(OR(INDEX(S26_CF!X:X, MATCH("*" & $A29 & "*", CompanyList!A:A, 0))=TRUE, INDEX(F25_CF!P:P, MATCH("*" & $A29 & "*", CompanyList!A:A, 0))=TRUE, INDEX(S25_CF!T:T, MATCH("*" & $A29 & "*", CompanyList!A:A, 0))=TRUE, INDEX(S24_CF!W:W, MATCH("*" & $A29 & "*", CompanyList!A:A, 0))=TRUE), "Yes", "No")} -> No | S29: =IF(COUNTIF(S26_CF!$A:$A,"*" & $A29 & "*") <> 0, "Yes", "No") -> Yes | T29: {=INDEX(S26_CF!K:K, MATCH("*" & $A29 & "*", S26_CF!A:A, 0))} -> Basic Two-Day [$2000.00] | U29: =IF(COUNTIF(F25_CF!$A:$A,"*" & $A29 & "*") <> 0, "Yes", "No") -> Yes | V29: {=INDEX(F25_CF!I:I, MATCH("*" & $A29 & "*", F25_CF!$A:$A, 0))} -> Basic Two-Day [$2000.00] | W29: =IF(COUNTIF(S25_CF!$A:$A,"*" & $A29 & "*") <> 0, "Yes", "No") -> No | X29: {=INDEX(S25_CF!J:J, MATCH("*" & $A29 & "*", S25_CF!$A:$A, 0))} -> #N/A | Y29: =IF(COUNTIF(F24_CF!$A:$A,"*" & $A29 & "*") <> 0, "Yes", "No") -> Yes | Z29: {=INDEX(F24_CF!N:N, MATCH("*" & $A29 & "*", F24_CF!$A:$A, 0))} -> Basic One-Day: Wednesday, September 4th [$1000.00] | AA29: =IF(COUNTIF(S24_CF!$A:$A,"*" & $A29 & "*") <> 0, "Yes", "No") -> Yes | AB29: {=INDEX(S24_CF!H:H, MATCH("*" & $A29 & "*", S24_CF!$A:$A, 0))} -> Basic Two-Day [$2000.00]
A30: Bowman | B30: Public | C30: 350 | D30: 1700 | E30: 0.6 | F30: =COUNTIF(S26_Emp!$C:$C,"*" &A30 & "*") -> 0 | G30: =COUNTIF(F25_Emp!$C:$C,"*" &#REF! & "*") -> 0 | H30: =COUNTIF(S25_Emp!$C:$C,"*" & A30 & "*") -> 0 | I30: =COUNTIF(F24_Emp!$C:$C,"*" & B30 & "*") -> 1 | J30: =COUNTIF(S24_Emp!$C:$C,"*" & $A30 & "*") -> 1 | K30: =COUNTIF(F23_Emp!$C:$C,"*" & $A30 & "*") -> 0 | L30: =COUNTIF(S23_Emp!$C:$C,"*" & $A30 & "*") -> 0 | M30: =COUNTIF(F22_Emp!$C:$C,"*" & $A30 & "*") -> 0 | N30: =COUNTIF(S22_Emp!$C:$C,"*" & $A30 & "*") -> 0 | O30: =COUNTIFS(S22_Emp!$C:$C,"*" & $A30 & "*", S22_S25_Emp!$B:$B, "Bachelor") -> #VALUE! | P30: =COUNTIFS(S22_Emp!$C:$C,"*" & $A30 & "*", S22_S25_Emp!$B:$B, "Master") -> #VALUE! | Q30: =COUNTIFS(S22_Emp!$C:$C,"*" & $A30 & "*", S22_S25_Emp!$B:$B, "Doctorate") -> #VALUE! | R30: {=IF(OR(INDEX(S26_CF!X:X, MATCH("*" & $A30 & "*", CompanyList!A:A, 0))=TRUE, INDEX(F25_CF!P:P, MATCH("*" & $A30 & "*", CompanyList!A:A, 0))=TRUE, INDEX(S25_CF!T:T, MATCH("*" & $A30 & "*", CompanyList!A:A, 0))=TRUE, INDEX(S24_CF!W:W, MATCH("*" & $A30 & "*", CompanyList!A:A, 0))=TRUE), "Yes", "No")} -> Yes | S30: =IF(COUNTIF(S26_CF!$A:$A,"*" & $A30 & "*") <> 0, "Yes", "No") -> No | T30: {=INDEX(S26_CF!K:K, MATCH("*" & $A30 & "*", S26_CF!A:A, 0))} -> #N/A | U30: =IF(COUNTIF(F25_CF!$A:$A,"*" & $A30 & "*") <> 0, "Yes", "No") -> Yes | V30: {=INDEX(F25_CF!I:I, MATCH("*" & $A30 & "*", F25_CF!$A:$A, 0))} -> Basic One-Day: Thursday, September 11th [$1000.00] | W30: =IF(COUNTIF(S25_CF!$A:$A,"*" & $A30 & "*") <> 0, "Yes", "No") -> Yes | X30: {=INDEX(S25_CF!J:J, MATCH("*" & $A30 & "*", S25_CF!$A:$A, 0))} -> Basic One-Day: Thursday, January 23rd [$1000.00] | Y30: =IF(COUNTIF(F24_CF!$A:$A,"*" & $A30 & "*") <> 0, "Yes", "No") -> Yes | Z30: {=INDEX(F24_CF!N:N, MATCH("*" & $A30 & "*", F24_CF!$A:$A, 0))} -> Basic Two-Day [$2000.00] | AA30: =IF(COUNTIF(S24_CF!$A:$A,"*" & $A30 & "*") <> 0, "Yes", "No") -> Yes | AB30: {=INDEX(S24_CF!H:H, MATCH("*" & $A30 & "*", S24_CF!$A:$A, 0))} -> Basic One-Day [$1000.00]
A31: Brasfield & Gorrie, LLC | B31: Private | C31: 5000 | D31: 3500 | F31: =COUNTIF(S26_Emp!$C:$C,"*" &A31 & "*") -> 0 | G31: =COUNTIF(F25_Emp!$C:$C,"*" &#REF! & "*") -> 0 | H31: =COUNTIF(S25_Emp!$C:$C,"*" & A31 & "*") -> 0 | I31: =COUNTIF(F24_Emp!$C:$C,"*" & B31 & "*") -> 0 | J31: =COUNTIF(S24_Emp!$C:$C,"*" & $A31 & "*") -> 1 | K31: =COUNTIF(F23_Emp!$C:$C,"*" & $A31 & "*") -> 1 | L31: =COUNTIF(S23_Emp!$C:$C,"*" & $A31 & "*") -> 0 | M31: =COUNTIF(F22_Emp!$C:$C,"*" & $A31 & "*") -> 0 | N31: =COUNTIF(S22_Emp!$C:$C,"*" & $A31 & "*") -> 0 | O31: =COUNTIFS(S22_Emp!$C:$C,"*" & $A31 & "*", S22_S25_Emp!$B:$B, "Bachelor") -> #VALUE! | P31: =COUNTIFS(S22_Emp!$C:$C,"*" & $A31 & "*", S22_S25_Emp!$B:$B, "Master") -> #VALUE! | Q31: =COUNTIFS(S22_Emp!$C:$C,"*" & $A31 & "*", S22_S25_Emp!$B:$B, "Doctorate") -> #VALUE! | R31: {=IF(OR(INDEX(S26_CF!X:X, MATCH("*" & $A31 & "*", CompanyList!A:A, 0))=TRUE, INDEX(F25_CF!P:P, MATCH("*" & $A31 & "*", CompanyList!A:A, 0))=TRUE, INDEX(S25_CF!T:T, MATCH("*" & $A31 & "*", CompanyList!A:A, 0))=TRUE, INDEX(S24_CF!W:W, MATCH("*" & $A31 & "*", CompanyList!A:A, 0))=TRUE), "Yes", "No")} -> No | S31: =IF(COUNTIF(S26_CF!$A:$A,"*" & $A31 & "*") <> 0, "Yes", "No") -> No | T31: {=INDEX(S26_CF!K:K, MATCH("*" & $A31 & "*", S26_CF!A:A, 0))} -> #N/A | U31: =IF(COUNTIF(F25_CF!$A:$A,"*" & $A31 & "*") <> 0, "Yes", "No") -> No | V31: {=INDEX(F25_CF!I:I, MATCH("*" & $A31 & "*", F25_CF!$A:$A, 0))} -> #N/A | W31: =IF(COUNTIF(S25_CF!$A:$A,"*" & $A31 & "*") <> 0, "Yes", "No") -> Yes | X31: {=INDEX(S25_CF!J:J, MATCH("*" & $A31 & "*", S25_CF!$A:$A, 0))} -> Basic One-Day: Wednesday, January 22nd [$1000.00] | Y31: =IF(COUNTIF(F24_CF!$A:$A,"*" & $A31 & "*") <> 0, "Yes", "No") -> Yes | Z31: {=INDEX(F24_CF!N:N, MATCH("*" & $A31 & "*", F24_CF!$A:$A, 0))} -> Silver One-Day: Wednesday, September 4th [$1800.00] | AA31: =IF(COUNTIF(S24_CF!$A:$A,"*" & $A31 & "*") <> 0, "Yes", "No") -> Yes | AB31: {=INDEX(S24_CF!H:H, MATCH("*" & $A31 & "*", S24_CF!$A:$A, 0))} -> Basic One-Day [$1000.00]
A32: Bray International, Inc | B32: Private | F32: =COUNTIF(S26_Emp!$C:$C,"*" &A32 & "*") -> 0 | G32: =COUNTIF(F25_Emp!$C:$C,"*" &#REF! & "*") -> 0 | H32: =COUNTIF(S25_Emp!$C:$C,"*" & A32 & "*") -> 0 | I32: =COUNTIF(F24_Emp!$C:$C,"*" & B32 & "*") -> 0 | J32: =COUNTIF(S24_Emp!$C:$C,"*" & $A32 & "*") -> 1 | K32: =COUNTIF(F23_Emp!$C:$C,"*" & $A32 & "*") -> 1 | L32: =COUNTIF(S23_Emp!$C:$C,"*" & $A32 & "*") -> 1 | M32: =COUNTIF(F22_Emp!$C:$C,"*" & $A32 & "*") -> 1 | N32: =COUNTIF(S22_Emp!$C:$C,"*" & $A32 & "*") -> 0 | O32: =COUNTIFS(S22_Emp!$C:$C,"*" & $A32 & "*", S22_S25_Emp!$B:$B, "Bachelor") -> #VALUE! | P32: =COUNTIFS(S22_Emp!$C:$C,"*" & $A32 & "*", S22_S25_Emp!$B:$B, "Master") -> #VALUE! | Q32: =COUNTIFS(S22_Emp!$C:$C,"*" & $A32 & "*", S22_S25_Emp!$B:$B, "Doctorate") -> #VALUE! | R32: {=IF(OR(INDEX(S26_CF!X:X, MATCH("*" & $A32 & "*", CompanyList!A:A, 0))=TRUE, INDEX(F25_CF!P:P, MATCH("*" & $A32 & "*", CompanyList!A:A, 0))=TRUE, INDEX(S25_CF!T:T, MATCH("*" & $A32 & "*", CompanyList!A:A, 0))=TRUE, INDEX(S24_CF!W:W, MATCH("*" & $A32 & "*", CompanyList!A:A, 0))=TRUE), "Yes", "No")} -> Yes | S32: =IF(COUNTIF(S26_CF!$A:$A,"*" & $A32 & "*") <> 0, "Yes", "No") -> Yes | T32: {=INDEX(S26_CF!K:K, MATCH("*" & $A32 & "*", S26_CF!A:A, 0))} -> Gold Two-Day [$5500.00] | U32: =IF(COUNTIF(F25_CF!$A:$A,"*" & $A32 & "*") <> 0, "Yes", "No") -> Yes | V32: {=INDEX(F25_CF!I:I, MATCH("*" & $A32 & "*", F25_CF!$A:$A, 0))} -> Gold Two-Day [$5500.00] | W32: =IF(COUNTIF(S25_CF!$A:$A,"*" & $A32 & "*") <> 0, "Yes", "No") -> Yes | X32: {=INDEX(S25_CF!J:J, MATCH("*" & $A32 & "*", S25_CF!$A:$A, 0))} -> Silver One-Day: Thursday, January 23rd [$1800.00] | Y32: =IF(COUNTIF(F24_CF!$A:$A,"*" & $A32 & "*") <> 0, "Yes", "No") -> Yes | Z32: {=INDEX(F24_CF!N:N, MATCH("*" & $A32 & "*", F24_CF!$A:$A, 0))} -> Silver Two-Day [$3000.00] | AA32: =IF(COUNTIF(S24_CF!$A:$A,"*" & $A32 & "*") <> 0, "Yes", "No") -> Yes | AB32: {=INDEX(S24_CF!H:H, MATCH("*" & $A32 & "*", S24_CF!$A:$A, 0))} -> Silver Two-Day [$3000.00]
A33: Brock Solutions | B33: Private | F33: =COUNTIF(S26_Emp!$C:$C,"*" &A33 & "*") -> 0 | G33: =COUNTIF(F25_Emp!$C:$C,"*" &#REF! & "*") -> 0 | H33: =COUNTIF(S25_Emp!$C:$C,"*" & A33 & "*") -> 0 | I33: =COUNTIF(F24_Emp!$C:$C,"*" & B33 & "*") -> 0 | J33: =COUNTIF(S24_Emp!$C:$C,"*" & $A33 & "*") -> 0 | K33: =COUNTIF(F23_Emp!$C:$C,"*" & $A33 & "*") -> 0 | L33: =COUNTIF(S23_Emp!$C:$C,"*" & $A33 & "*") -> 1 | M33: =COUNTIF(F22_Emp!$C:$C,"*" & $A33 & "*") -> 1 | N33: =COUNTIF(S22_Emp!$C:$C,"*" & $A33 & "*") -> 0 | O33: =COUNTIFS(S22_Emp!$C:$C,"*" & $A33 & "*", S22_S25_Emp!$B:$B, "Bachelor") -> #VALUE! | P33: =COUNTIFS(S22_Emp!$C:$C,"*" & $A33 & "*", S22_S25_Emp!$B:$B, "Master") -> #VALUE! | Q33: =COUNTIFS(S22_Emp!$C:$C,"*" & $A33 & "*", S22_S25_Emp!$B:$B, "Doctorate") -> #VALUE! | R33: {=IF(OR(INDEX(S26_CF!X:X, MATCH("*" & $A33 & "*", CompanyList!A:A, 0))=TRUE, INDEX(F25_CF!P:P, MATCH("*" & $A33 & "*", CompanyList!A:A, 0))=TRUE, INDEX(S25_CF!T:T, MATCH("*" & $A33 & "*", CompanyList!A:A, 0))=TRUE, INDEX(S24_CF!W:W, MATCH("*" & $A33 & "*", CompanyList!A:A, 0))=TRUE), "Yes", "No")} -> No | S33: =IF(COUNTIF(S26_CF!$A:$A,"*" & $A33 & "*") <> 0, "Yes", "No") -> No | T33: {=INDEX(S26_CF!K:K, MATCH("*" & $A33 & "*", S26_CF!A:A, 0))} -> #N/A | U33: =IF(COUNTIF(F25_CF!$A:$A,"*" & $A33 & "*") <> 0, "Yes", "No") -> Yes | V33: {=INDEX(F25_CF!I:I, MATCH("*" & $A33 & "*", F25_CF!$A:$A, 0))} -> Basic One-Day: Thursday, September 11th [$1000.00] | W33: =IF(COUNTIF(S25_CF!$A:$A,"*" & $A33 & "*") <> 0, "Yes", "No") -> Yes | X33: {=INDEX(S25_CF!J:J, MATCH("*" & $A33 & "*", S25_CF!$A:$A, 0))} -> Basic One-Day: Wednesday, January 22nd [$1000.00] | Y33: =IF(COUNTIF(F24_CF!$A:$A,"*" & $A33 & "*") <> 0, "Yes", "No") -> Yes | Z33: {=INDEX(F24_CF!N:N, MATCH("*" & $A33 & "*", F24_CF!$A:$A, 0))} -> Basic One-Day: Thursday, September 5th [$1000.00] | AA33: =IF(COUNTIF(S24_CF!$A:$A,"*" & $A33 & "*") <> 0, "Yes", "No") -> Yes | AB33: {=INDEX(S24_CF!H:H, MATCH("*" & $A33 & "*", S24_CF!$A:$A, 0))} -> Basic One-Day [$1000.00]
A34: Bryan Research & Engineering | B34: Private | F34: =COUNTIF(S26_Emp!$C:$C,"*" &A34 & "*") -> 0 | G34: =COUNTIF(F25_Emp!$C:$C,"*" &#REF! & "*") -> 0 | H34: =COUNTIF(S25_Emp!$C:$C,"*" & A34 & "*") -> 1 | I34: =COUNTIF(F24_Emp!$C:$C,"*" & B34 & "*") -> 0 | J34: =COUNTIF(S24_Emp!$C:$C,"*" & $A34 & "*") -> 1 | K34: =COUNTIF(F23_Emp!$C:$C,"*" & $A34 & "*") -> 2 | L34: =COUNTIF(S23_Emp!$C:$C,"*" & $A34 & "*") -> 0 | M34: =COUNTIF(F22_Emp!$C:$C,"*" & $A34 & "*") -> 1 | N34: =COUNTIF(S22_Emp!$C:$C,"*" & $A34 & "*") -> 1 | O34: =COUNTIFS(S22_Emp!$C:$C,"*" & $A34 & "*", S22_S25_Emp!$B:$B, "Bachelor") -> #VALUE! | P34: =COUNTIFS(S22_Emp!$C:$C,"*" & $A34 & "*", S22_S25_Emp!$B:$B, "Master") -> #VALUE! | Q34: =COUNTIFS(S22_Emp!$C:$C,"*" & $A34 & "*", S22_S25_Emp!$B:$B, "Doctorate") -> #VALUE! | R34: {=IF(OR(INDEX(S26_CF!X:X, MATCH("*" & $A34 & "*", CompanyList!A:A, 0))=TRUE, INDEX(F25_CF!P:P, MATCH("*" & $A34 & "*", CompanyList!A:A, 0))=TRUE, INDEX(S25_CF!T:T, MATCH("*" & $A34 & "*", CompanyList!A:A, 0))=TRUE, INDEX(S24_CF!W:W, MATCH("*" & $A34 & "*", CompanyList!A:A, 0))=TRUE), "Yes", "No")} -> Yes | S34: =IF(COUNTIF(S26_CF!$A:$A,"*" & $A34 & "*") <> 0, "Yes", "No") -> Yes | T34: {=INDEX(S26_CF!K:K, MATCH("*" & $A34 & "*", S26_CF!A:A, 0))} -> Basic One-Day: Wednesday, January 28th [$1000.00] | U34: =IF(COUNTIF(F25_CF!$A:$A,"*" & $A34 & "*") <> 0, "Yes", "No") -> Yes | V34: {=INDEX(F25_CF!I:I, MATCH("*" & $A34 & "*", F25_CF!$A:$A, 0))} -> Basic One-Day: Wednesday, September 10th [$1000.00] | W34: =IF(COUNTIF(S25_CF!$A:$A,"*" & $A34 & "*") <> 0, "Yes", "No") -> Yes | X34: {=INDEX(S25_CF!J:J, MATCH("*" & $A34 & "*", S25_CF!$A:$A, 0))} -> Basic One-Day: Thursday, January 23rd [$1000.00] | Y34: =IF(COUNTIF(F24_CF!$A:$A,"*" & $A34 & "*") <> 0, "Yes", "No") -> Yes | Z34: {=INDEX(F24_CF!N:N, MATCH("*" & $A34 & "*", F24_CF!$A:$A, 0))} -> Gold One-Day: Wednesday, September 4th [$2500.00] | AA34: =IF(COUNTIF(S24_CF!$A:$A,"*" & $A34 & "*") <> 0, "Yes", "No") -> Yes | AB34: {=INDEX(S24_CF!H:H, MATCH("*" & $A34 & "*", S24_CF!$A:$A, 0))} -> Basic One-Day [$1000.00]
A35: Burns & McDonnell | B35: Private | C35: 7000 | D35: 14000 | F35: =COUNTIF(S26_Emp!$C:$C,"*" &A35 & "*") -> 0 | G35: =COUNTIF(F25_Emp!$C:$C,"*" &#REF! & "*") -> 0 | H35: =COUNTIF(S25_Emp!$C:$C,"*" & A35 & "*") -> 6 | I35: =COUNTIF(F24_Emp!$C:$C,"*" & B35 & "*") -> 0 | J35: =COUNTIF(S24_Emp!$C:$C,"*" & $A35 & "*") -> 3 | K35: =COUNTIF(F23_Emp!$C:$C,"*" & $A35 & "*") -> 4 | L35: =COUNTIF(S23_Emp!$C:$C,"*" & $A35 & "*") -> 4 | M35: =COUNTIF(F22_Emp!$C:$C,"*" & $A35 & "*") -> 4 | N35: =COUNTIF(S22_Emp!$C:$C,"*" & $A35 & "*") -> 4 | O35: =COUNTIFS(S22_Emp!$C:$C,"*" & $A35 & "*", S22_S25_Emp!$B:$B, "Bachelor") -> #VALUE! | P35: =COUNTIFS(S22_Emp!$C:$C,"*" & $A35 & "*", S22_S25_Emp!$B:$B, "Master") -> #VALUE! | Q35: =COUNTIFS(S22_Emp!$C:$C,"*" & $A35 & "*", S22_S25_Emp!$B:$B, "Doctorate") -> #VALUE! | R35: {=IF(OR(INDEX(S26_CF!X:X, MATCH("*" & $A35 & "*", CompanyList!A:A, 0))=TRUE, INDEX(F25_CF!P:P, MATCH("*" & $A35 & "*", CompanyList!A:A, 0))=TRUE, INDEX(S25_CF!T:T, MATCH("*" & $A35 & "*", CompanyList!A:A, 0))=TRUE, INDEX(S24_CF!W:W, MATCH("*" & $A35 & "*", CompanyList!A:A, 0))=TRUE), "Yes", "No")} -> No | S35: =IF(COUNTIF(S26_CF!$A:$A,"*" & $A35 & "*") <> 0, "Yes", "No") -> Yes | T35: {=INDEX(S26_CF!K:K, MATCH("*" & $A35 & "*", S26_CF!A:A, 0))} -> Gold One-Day: Wednesday, January 28th [$2500.00] | U35: =IF(COUNTIF(F25_CF!$A:$A,"*" & $A35 & "*") <> 0, "Yes", "No") -> Yes | V35: {=INDEX(F25_CF!I:I, MATCH("*" & $A35 & "*", F25_CF!$A:$A, 0))} -> Gold Two-Day [$5500.00] | W35: =IF(COUNTIF(S25_CF!$A:$A,"*" & $A35 & "*") <> 0, "Yes", "No") -> Yes | X35: {=INDEX(S25_CF!J:J, MATCH("*" & $A35 & "*", S25_CF!$A:$A, 0))} -> Gold One-Day: Thursday, January 23rd [$2500.00] | Y35: =IF(COUNTIF(F24_CF!$A:$A,"*" & $A35 & "*") <> 0, "Yes", "No") -> Yes | Z35: {=INDEX(F24_CF!N:N, MATCH("*" & $A35 & "*", F24_CF!$A:$A, 0))} -> Gold Two-Day [$5500.00] | AA35: =IF(COUNTIF(S24_CF!$A:$A,"*" & $A35 & "*") <> 0, "Yes", "No") -> Yes | AB35: {=INDEX(S24_CF!H:H, MATCH("*" & $A35 & "*", S24_CF!$A:$A, 0))} -> Silver One-Day [$1800.00]
A36: Cadence | B36: Public | C36: 4100 | D36: 11000 | E36: 85 | F36: =COUNTIF(S26_Emp!$C:$C,"*" &A36 & "*") -> 0 | G36: =COUNTIF(F25_Emp!$C:$C,"*" &#REF! & "*") -> 0 | H36: =COUNTIF(S25_Emp!$C:$C,"*" & A36 & "*") -> 1 | I36: =COUNTIF(F24_Emp!$C:$C,"*" & B36 & "*") -> 1 | J36: =COUNTIF(S24_Emp!$C:$C,"*" & $A36 & "*") -> 1 | K36: =COUNTIF(F23_Emp!$C:$C,"*" & $A36 & "*") -> 0 | L36: =COUNTIF(S23_Emp!$C:$C,"*" & $A36 & "*") -> 0 | M36: =COUNTIF(F22_Emp!$C:$C,"*" & $A36 & "*") -> 2 | N36: =COUNTIF(S22_Emp!$C:$C,"*" & $A36 & "*") -> 4 | O36: =COUNTIFS(S22_Emp!$C:$C,"*" & $A36 & "*", S22_S25_Emp!$B:$B, "Bachelor") -> #VALUE! | P36: =COUNTIFS(S22_Emp!$C:$C,"*" & $A36 & "*", S22_S25_Emp!$B:$B, "Master") -> #VALUE! | Q36: =COUNTIFS(S22_Emp!$C:$C,"*" & $A36 & "*", S22_S25_Emp!$B:$B, "Doctorate") -> #VALUE! | R36: {=IF(OR(INDEX(S26_CF!X:X, MATCH("*" & $A36 & "*", CompanyList!A:A, 0))=TRUE, INDEX(F25_CF!P:P, MATCH("*" & $A36 & "*", CompanyList!A:A, 0))=TRUE, INDEX(S25_CF!T:T, MATCH("*" & $A36 & "*", CompanyList!A:A, 0))=TRUE, INDEX(S24_CF!W:W, MATCH("*" & $A36 & "*", CompanyList!A:A, 0))=TRUE), "Yes", "No")} -> No | S36: =IF(COUNTIF(S26_CF!$A:$A,"*" & $A36 & "*") <> 0, "Yes", "No") -> Yes | T36: {=INDEX(S26_CF!K:K, MATCH("*" & $A36 & "*", S26_CF!A:A, 0))} -> Silver One-Day: Wednesday, January 28th [$1800.00] | U36: =IF(COUNTIF(F25_CF!$A:$A,"*" & $A36 & "*") <> 0, "Yes", "No") -> No | V36: {=INDEX(F25_CF!I:I, MATCH("*" & $A36 & "*", F25_CF!$A:$A, 0))} -> #N/A | W36: =IF(COUNTIF(S25_CF!$A:$A,"*" & $A36 & "*") <> 0, "Yes", "No") -> Yes | X36: {=INDEX(S25_CF!J:J, MATCH("*" & $A36 & "*", S25_CF!$A:$A, 0))} -> Silver One-Day: Thursday, January 23rd [$1800.00] | Y36: =IF(COUNTIF(F24_CF!$A:$A,"*" & $A36 & "*") <> 0, "Yes", "No") -> No | Z36: {=INDEX(F24_CF!N:N, MATCH("*" & $A36 & "*", F24_CF!$A:$A, 0))} -> #N/A | AA36: =IF(COUNTIF(S24_CF!$A:$A,"*" & $A36 & "*") <> 0, "Yes", "No") -> Yes | AB36: {=INDEX(S24_CF!H:H, MATCH("*" & $A36 & "*", S24_CF!$A:$A, 0))} -> Silver One-Day [$1800.00]
A37: Calpine Corporation | B37: Private | D37: 2200 | F37: =COUNTIF(S26_Emp!$C:$C,"*" &A37 & "*") -> 0 | G37: =COUNTIF(F25_Emp!$C:$C,"*" &#REF! & "*") -> 0 | H37: =COUNTIF(S25_Emp!$C:$C,"*" & A37 & "*") -> 0 | I37: =COUNTIF(F24_Emp!$C:$C,"*" & B37 & "*") -> 0 | J37: =COUNTIF(S24_Emp!$C:$C,"*" & $A37 & "*") -> 0 | K37: =COUNTIF(F23_Emp!$C:$C,"*" & $A37 & "*") -> 0 | L37: =COUNTIF(S23_Emp!$C:$C,"*" & $A37 & "*") -> 1 | M37: =COUNTIF(F22_Emp!$C:$C,"*" & $A37 & "*") -> 0 | N37: =COUNTIF(S22_Emp!$C:$C,"*" & $A37 & "*") -> 0 | O37: =COUNTIFS(S22_Emp!$C:$C,"*" & $A37 & "*", S22_S25_Emp!$B:$B, "Bachelor") -> #VALUE! | P37: =COUNTIFS(S22_Emp!$C:$C,"*" & $A37 & "*", S22_S25_Emp!$B:$B, "Master") -> #VALUE! | Q37: =COUNTIFS(S22_Emp!$C:$C,"*" & $A37 & "*", S22_S25_Emp!$B:$B, "Doctorate") -> #VALUE! | R37: {=IF(OR(INDEX(S26_CF!X:X, MATCH("*" & $A37 & "*", CompanyList!A:A, 0))=TRUE, INDEX(F25_CF!P:P, MATCH("*" & $A37 & "*", CompanyList!A:A, 0))=TRUE, INDEX(S25_CF!T:T, MATCH("*" & $A37 & "*", CompanyList!A:A, 0))=TRUE, INDEX(S24_CF!W:W, MATCH("*" & $A37 & "*", CompanyList!A:A, 0))=TRUE), "Yes", "No")} -> Yes | S37: =IF(COUNTIF(S26_CF!$A:$A,"*" & $A37 & "*") <> 0, "Yes", "No") -> No | T37: {=INDEX(S26_CF!K:K, MATCH("*" & $A37 & "*", S26_CF!A:A, 0))} -> #N/A | U37: =IF(COUNTIF(F25_CF!$A:$A,"*" & $A37 & "*") <> 0, "Yes", "No") -> Yes | V37: {=INDEX(F25_CF!I:I, MATCH("*" & $A37 & "*", F25_CF!$A:$A, 0))} -> Silver One-Day: Thursday, September 11th [$1800.00] | W37: =IF(COUNTIF(S25_CF!$A:$A,"*" & $A37 & "*") <> 0, "Yes", "No") -> No | X37: {=INDEX(S25_CF!J:J, MATCH("*" & $A37 & "*", S25_CF!$A:$A, 0))} -> #N/A | Y37: =IF(COUNTIF(F24_CF!$A:$A,"*" & $A37 & "*") <> 0, "Yes", "No") -> Yes | Z37: {=INDEX(F24_CF!N:N, MATCH("*" & $A37 & "*", F24_CF!$A:$A, 0))} -> Silver One-Day: Wednesday, September 4th [$1800.00] | AA37: =IF(COUNTIF(S24_CF!$A:$A,"*" & $A37 & "*") <> 0, "Yes", "No") -> Yes | AB37: {=INDEX(S24_CF!H:H, MATCH("*" & $A37 & "*", S24_CF!$A:$A, 0))} -> Basic One-Day [$1000.00]
A38: Capco | B38: Private | F38: =COUNTIF(S26_Emp!$C:$C,"*" &A38 & "*") -> 0 | G38: =COUNTIF(F25_Emp!$C:$C,"*" &#REF! & "*") -> 0 | H38: =COUNTIF(S25_Emp!$C:$C,"*" & A38 & "*") -> 1 | I38: =COUNTIF(F24_Emp!$C:$C,"*" & B38 & "*") -> 0 | J38: =COUNTIF(S24_Emp!$C:$C,"*" & $A38 & "*") -> 0 | K38: =COUNTIF(F23_Emp!$C:$C,"*" & $A38 & "*") -> 0 | L38: =COUNTIF(S23_Emp!$C:$C,"*" & $A38 & "*") -> 0 | M38: =COUNTIF(F22_Emp!$C:$C,"*" & $A38 & "*") -> 1 | N38: =COUNTIF(S22_Emp!$C:$C,"*" & $A38 & "*") -> 1 | O38: =COUNTIFS(S22_Emp!$C:$C,"*" & $A38 & "*", S22_S25_Emp!$B:$B, "Bachelor") -> #VALUE! | P38: =COUNTIFS(S22_Emp!$C:$C,"*" & $A38 & "*", S22_S25_Emp!$B:$B, "Master") -> #VALUE! | Q38: =COUNTIFS(S22_Emp!$C:$C,"*" & $A38 & "*", S22_S25_Emp!$B:$B, "Doctorate") -> #VALUE! | R38: {=IF(OR(INDEX(S26_CF!X:X, MATCH("*" & $A38 & "*", CompanyList!A:A, 0))=TRUE, INDEX(F25_CF!P:P, MATCH("*" & $A38 & "*", CompanyList!A:A, 0))=TRUE, INDEX(S25_CF!T:T, MATCH("*" & $A38 & "*", CompanyList!A:A, 0))=TRUE, INDEX(S24_CF!W:W, MATCH("*" & $A38 & "*", CompanyList!A:A, 0))=TRUE), "Yes", "No")} -> No | S38: =IF(COUNTIF(S26_CF!$A:$A,"*" & $A38 & "*") <> 0, "Yes", "No") -> Yes | T38: {=INDEX(S26_CF!K:K, MATCH("*" & $A38 & "*", S26_CF!A:A, 0))} -> Silver One-Day: Wednesday, January 28th [$1800.00] | U38: =IF(COUNTIF(F25_CF!$A:$A,"*" & $A38 & "*") <> 0, "Yes", "No") -> Yes | V38: {=INDEX(F25_CF!I:I, MATCH("*" & $A38 & "*", F25_CF!$A:$A, 0))} -> Basic One-Day: Wednesday, September 10th [$1000.00] | W38: =IF(COUNTIF(S25_CF!$A:$A,"*" & $A38 & "*") <> 0, "Yes", "No") -> Yes | X38: {=INDEX(S25_CF!J:J, MATCH("*" & $A38 & "*", S25_CF!$A:$A, 0))} -> Basic One-Day: Thursday, January 23rd [$1000.00] | Y38: =IF(COUNTIF(F24_CF!$A:$A,"*" & $A38 & "*") <> 0, "Yes", "No") -> Yes | Z38: {=INDEX(F24_CF!N:N, MATCH("*" & $A38 & "*", F24_CF!$A:$A, 0))} -> Basic One-Day: Wednesday, September 4th [$1000.00] | AA38: =IF(COUNTIF(S24_CF!$A:$A,"*" & $A38 & "*") <> 0, "Yes", "No") -> Yes | AB38: {=INDEX(S24_CF!H:H, MATCH("*" & $A38 & "*", S24_CF!$A:$A, 0))} -> Basic One-Day [$1000.00]
A39: CAPSHER Technology | B39: Private | F39: =COUNTIF(S26_Emp!$C:$C,"*" &A39 & "*") -> 0 | G39: =COUNTIF(F25_Emp!$C:$C,"*" &#REF! & "*") -> 0 | H39: =COUNTIF(S25_Emp!$C:$C,"*" & A39 & "*") -> 0 | I39: =COUNTIF(F24_Emp!$C:$C,"*" & B39 & "*") -> 0 | J39: =COUNTIF(S24_Emp!$C:$C,"*" & $A39 & "*") -> 2 | K39: =COUNTIF(F23_Emp!$C:$C,"*" & $A39 & "*") -> 1 | L39: =COUNTIF(S23_Emp!$C:$C,"*" & $A39 & "*") -> 1 | M39: =COUNTIF(F22_Emp!$C:$C,"*" & $A39 & "*") -> 0 | N39: =COUNTIF(S22_Emp!$C:$C,"*" & $A39 & "*") -> 0 | O39: =COUNTIFS(S22_Emp!$C:$C,"*" & $A39 & "*", S22_S25_Emp!$B:$B, "Bachelor") -> #VALUE! | P39: =COUNTIFS(S22_Emp!$C:$C,"*" & $A39 & "*", S22_S25_Emp!$B:$B, "Master") -> #VALUE! | Q39: =COUNTIFS(S22_Emp!$C:$C,"*" & $A39 & "*", S22_S25_Emp!$B:$B, "Doctorate") -> #VALUE! | R39: {=IF(OR(INDEX(S26_CF!X:X, MATCH("*" & $A39 & "*", CompanyList!A:A, 0))=TRUE, INDEX(F25_CF!P:P, MATCH("*" & $A39 & "*", CompanyList!A:A, 0))=TRUE, INDEX(S25_CF!T:T, MATCH("*" & $A39 & "*", CompanyList!A:A, 0))=TRUE, INDEX(S24_CF!W:W, MATCH("*" & $A39 & "*", CompanyList!A:A, 0))=TRUE), "Yes", "No")} -> No | S39: =IF(COUNTIF(S26_CF!$A:$A,"*" & $A39 & "*") <> 0, "Yes", "No") -> Yes | T39: {=INDEX(S26_CF!K:K, MATCH("*" & $A39 & "*", S26_CF!A:A, 0))} -> Basic Two-Day [$2000.00] | U39: =IF(COUNTIF(F25_CF!$A:$A,"*" & $A39 & "*") <> 0, "Yes", "No") -> Yes | V39: {=INDEX(F25_CF!I:I, MATCH("*" & $A39 & "*", F25_CF!$A:$A, 0))} -> Basic Two-Day [$2000.00] | W39: =IF(COUNTIF(S25_CF!$A:$A,"*" & $A39 & "*") <> 0, "Yes", "No") -> Yes | X39: {=INDEX(S25_CF!J:J, MATCH("*" & $A39 & "*", S25_CF!$A:$A, 0))} -> Basic Two-Day [$2000.00] | Y39: =IF(COUNTIF(F24_CF!$A:$A,"*" & $A39 & "*") <> 0, "Yes", "No") -> Yes | Z39: {=INDEX(F24_CF!N:N, MATCH("*" & $A39 & "*", F24_CF!$A:$A, 0))} -> Basic Two-Day [$2000.00] | AA39: =IF(COUNTIF(S24_CF!$A:$A,"*" & $A39 & "*") <> 0, "Yes", "No") -> Yes | AB39: {=INDEX(S24_CF!H:H, MATCH("*" & $A39 & "*", S24_CF!$A:$A, 0))} -> Basic Two-Day [$2000.00]
A40: Cargill (Maroon Partner) | B40: Private | C40: 177000 | D40: 160000 | F40: =COUNTIF(S26_Emp!$C:$C,"*" &A40 & "*") -> 0 | G40: =COUNTIF(F25_Emp!$C:$C,"*" &#REF! & "*") -> 0 | H40: =COUNTIF(S25_Emp!$C:$C,"*" & A40 & "*") -> 0 | I40: =COUNTIF(F24_Emp!$C:$C,"*" & B40 & "*") -> 0 | J40: =COUNTIF(S24_Emp!$C:$C,"*" & $A40 & "*") -> 0 | K40: =COUNTIF(F23_Emp!$C:$C,"*" & $A40 & "*") -> 0 | L40: =COUNTIF(S23_Emp!$C:$C,"*" & $A40 & "*") -> 0 | M40: =COUNTIF(F22_Emp!$C:$C,"*" & $A40 & "*") -> 0 | N40: =COUNTIF(S22_Emp!$C:$C,"*" & $A40 & "*") -> 0 | O40: =COUNTIFS(S22_Emp!$C:$C,"*" & $A40 & "*", S22_S25_Emp!$B:$B, "Bachelor") -> #VALUE! | P40: =COUNTIFS(S22_Emp!$C:$C,"*" & $A40 & "*", S22_S25_Emp!$B:$B, "Master") -> #VALUE! | Q40: =COUNTIFS(S22_Emp!$C:$C,"*" & $A40 & "*", S22_S25_Emp!$B:$B, "Doctorate") -> #VALUE! | R40: {=IF(OR(INDEX(S26_CF!X:X, MATCH("*" & $A40 & "*", CompanyList!A:A, 0))=TRUE, INDEX(F25_CF!P:P, MATCH("*" & $A40 & "*", CompanyList!A:A, 0))=TRUE, INDEX(S25_CF!T:T, MATCH("*" & $A40 & "*", CompanyList!A:A, 0))=TRUE, INDEX(S24_CF!W:W, MATCH("*" & $A40 & "*", CompanyList!A:A, 0))=TRUE), "Yes", "No")} -> No | S40: =IF(COUNTIF(S26_CF!$A:$A,"*" & $A40 & "*") <> 0, "Yes", "No") -> No | T40: {=INDEX(S26_CF!K:K, MATCH("*" & $A40 & "*", S26_CF!A:A, 0))} -> #N/A | U40: =IF(COUNTIF(F25_CF!$A:$A,"*" & $A40 & "*") <> 0, "Yes", "No") -> Yes | V40: {=INDEX(F25_CF!I:I, MATCH("*" & $A40 & "*", F25_CF!$A:$A, 0))} -> Gold One-Day: Wednesday, September 10th [$2500.00] | W40: =IF(COUNTIF(S25_CF!$A:$A,"*" & $A40 & "*") <> 0, "Yes", "No") -> Yes | X40: {=INDEX(S25_CF!J:J, MATCH("*" & $A40 & "*", S25_CF!$A:$A, 0))} -> Gold One-Day: Thursday, January 23rd [$2500.00] | Y40: =IF(COUNTIF(F24_CF!$A:$A,"*" & $A40 & "*") <> 0, "Yes", "No") -> Yes | Z40: {=INDEX(F24_CF!N:N, MATCH("*" & $A40 & "*", F24_CF!$A:$A, 0))} -> Gold Two-Day [$5500.00] | AA40: =IF(COUNTIF(S24_CF!$A:$A,"*" & $A40 & "*") <> 0, "Yes", "No") -> Yes | AB40: {=INDEX(S24_CF!H:H, MATCH("*" & $A40 & "*", S24_CF!$A:$A, 0))} -> Gold Two-Day [$5000.00]
A41: CB&I | B41: Private | D41: 18000 | F41: =COUNTIF(S26_Emp!$C:$C,"*" &A41 & "*") -> 0 | G41: =COUNTIF(F25_Emp!$C:$C,"*" &#REF! & "*") -> 0 | H41: =COUNTIF(S25_Emp!$C:$C,"*" & A41 & "*") -> 0 | I41: =COUNTIF(F24_Emp!$C:$C,"*" & B41 & "*") -> 0 | J41: =COUNTIF(S24_Emp!$C:$C,"*" & $A41 & "*") -> 0 | K41: =COUNTIF(F23_Emp!$C:$C,"*" & $A41 & "*") -> 0 | L41: =COUNTIF(S23_Emp!$C:$C,"*" & $A41 & "*") -> 0 | M41: =COUNTIF(F22_Emp!$C:$C,"*" & $A41 & "*") -> 0 | N41: =COUNTIF(S22_Emp!$C:$C,"*" & $A41 & "*") -> 0 | O41: =COUNTIFS(S22_Emp!$C:$C,"*" & $A41 & "*", S22_S25_Emp!$B:$B, "Bachelor") -> #VALUE! | P41: =COUNTIFS(S22_Emp!$C:$C,"*" & $A41 & "*", S22_S25_Emp!$B:$B, "Master") -> #VALUE! | Q41: =COUNTIFS(S22_Emp!$C:$C,"*" & $A41 & "*", S22_S25_Emp!$B:$B, "Doctorate") -> #VALUE! | R41: {=IF(OR(INDEX(S26_CF!X:X, MATCH("*" & $A41 & "*", CompanyList!A:A, 0))=TRUE, INDEX(F25_CF!P:P, MATCH("*" & $A41 & "*", CompanyList!A:A, 0))=TRUE, INDEX(S25_CF!T:T, MATCH("*" & $A41 & "*", CompanyList!A:A, 0))=TRUE, INDEX(S24_CF!W:W, MATCH("*" & $A41 & "*", CompanyList!A:A, 0))=TRUE), "Yes", "No")} -> Yes | S41: =IF(COUNTIF(S26_CF!$A:$A,"*" & $A41 & "*") <> 0, "Yes", "No") -> Yes | T41: {=INDEX(S26_CF!K:K, MATCH("*" & $A41 & "*", S26_CF!A:A, 0))} -> Basic One-Day: Thursday, January 29th [$1000.00] | U41: =IF(COUNTIF(F25_CF!$A:$A,"*" & $A41 & "*") <> 0, "Yes", "No") -> Yes | V41: {=INDEX(F25_CF!I:I, MATCH("*" & $A41 & "*", F25_CF!$A:$A, 0))} -> Basic One-Day: Wednesday, September 10th [$1000.00] | W41: =IF(COUNTIF(S25_CF!$A:$A,"*" & $A41 & "*") <> 0, "Yes", "No") -> Yes | X41: {=INDEX(S25_CF!J:J, MATCH("*" & $A41 & "*", S25_CF!$A:$A, 0))} -> Basic One-Day: Thursday, January 23rd [$1000.00] | Y41: =IF(COUNTIF(F24_CF!$A:$A,"*" & $A41 & "*") <> 0, "Yes", "No") -> Yes | Z41: {=INDEX(F24_CF!N:N, MATCH("*" & $A41 & "*", F24_CF!$A:$A, 0))} -> Basic One-Day: Wednesday, September 4th [$1000.00] | AA41: =IF(COUNTIF(S24_CF!$A:$A,"*" & $A41 & "*") <> 0, "Yes", "No") -> Yes | AB41: {=INDEX(S24_CF!H:H, MATCH("*" & $A41 & "*", S24_CF!$A:$A, 0))} -> Basic One-Day [$1000.00]
A42: Centerpoint Energy | B42: Public | C42: 8500 | D42: 8900 | E42: 18 | F42: =COUNTIF(S26_Emp!$C:$C,"*" &A42 & "*") -> 0 | G42: =COUNTIF(F25_Emp!$C:$C,"*" &#REF! & "*") -> 0 | H42: =COUNTIF(S25_Emp!$C:$C,"*" & A42 & "*") -> 0 | I42: =COUNTIF(F24_Emp!$C:$C,"*" & B42 & "*") -> 1 | J42: =COUNTIF(S24_Emp!$C:$C,"*" & $A42 & "*") -> 2 | K42: =COUNTIF(F23_Emp!$C:$C,"*" & $A42 & "*") -> 1 | L42: =COUNTIF(S23_Emp!$C:$C,"*" & $A42 & "*") -> 1 | M42: =COUNTIF(F22_Emp!$C:$C,"*" & $A42 & "*") -> 1 | N42: =COUNTIF(S22_Emp!$C:$C,"*" & $A42 & "*") -> 1 | O42: =COUNTIFS(S22_Emp!$C:$C,"*" & $A42 & "*", S22_S25_Emp!$B:$B, "Bachelor") -> #VALUE! | P42: =COUNTIFS(S22_Emp!$C:$C,"*" & $A42 & "*", S22_S25_Emp!$B:$B, "Master") -> #VALUE! | Q42: =COUNTIFS(S22_Emp!$C:$C,"*" & $A42 & "*", S22_S25_Emp!$B:$B, "Doctorate") -> #VALUE! | R42: {=IF(OR(INDEX(S26_CF!X:X, MATCH("*" & $A42 & "*", CompanyList!A:A, 0))=TRUE, INDEX(F25_CF!P:P, MATCH("*" & $A42 & "*", CompanyList!A:A, 0))=TRUE, INDEX(S25_CF!T:T, MATCH("*" & $A42 & "*", CompanyList!A:A, 0))=TRUE, INDEX(S24_CF!W:W, MATCH("*" & $A42 & "*", CompanyList!A:A, 0))=TRUE), "Yes", "No")} -> Yes | S42: =IF(COUNTIF(S26_CF!$A:$A,"*" & $A42 & "*") <> 0, "Yes", "No") -> Yes | T42: {=INDEX(S26_CF!K:K, MATCH("*" & $A42 & "*", S26_CF!A:A, 0))} -> Silver One-Day: Thursday, January 29th [$1800.00] | U42: =IF(COUNTIF(F25_CF!$A:$A,"*" & $A42 & "*") <> 0, "Yes", "No") -> Yes | V42: {=INDEX(F25_CF!I:I, MATCH("*" & $A42 & "*", F25_CF!$A:$A, 0))} -> Silver One-Day: Wednesday, September 10th [$1800.00] | W42: =IF(COUNTIF(S25_CF!$A:$A,"*" & $A42 & "*") <> 0, "Yes", "No") -> Yes | X42: {=INDEX(S25_CF!J:J, MATCH("*" & $A42 & "*", S25_CF!$A:$A, 0))} -> Silver One-Day: Wednesday, January 22nd [$1800.00] | Y42: =IF(COUNTIF(F24_CF!$A:$A,"*" & $A42 & "*") <> 0, "Yes", "No") -> Yes | Z42: {=INDEX(F24_CF!N:N, MATCH("*" & $A42 & "*", F24_CF!$A:$A, 0))} -> Silver One-Day: Wednesday, September 4th [$1800.00] | AA42: =IF(COUNTIF(S24_CF!$A:$A,"*" & $A42 & "*") <> 0, "Yes", "No") -> Yes | AB42: {=INDEX(S24_CF!H:H, MATCH("*" & $A42 & "*", S24_CF!$A:$A, 0))} -> Basic One-Day [$1000.00]
A43: Champion Technology Services | B43: Private | F43: =COUNTIF(S26_Emp!$C:$C,"*" &A43 & "*") -> 0 | G43: =COUNTIF(F25_Emp!$C:$C,"*" &#REF! & "*") -> 0 | H43: =COUNTIF(S25_Emp!$C:$C,"*" & A43 & "*") -> 0 | I43: =COUNTIF(F24_Emp!$C:$C,"*" & B43 & "*") -> 0 | J43: =COUNTIF(S24_Emp!$C:$C,"*" & $A43 & "*") -> 1 | K43: =COUNTIF(F23_Emp!$C:$C,"*" & $A43 & "*") -> 1 | L43: =COUNTIF(S23_Emp!$C:$C,"*" & $A43 & "*") -> 0 | M43: =COUNTIF(F22_Emp!$C:$C,"*" & $A43 & "*") -> 0 | N43: =COUNTIF(S22_Emp!$C:$C,"*" & $A43 & "*") -> 1 | O43: =COUNTIFS(S22_Emp!$C:$C,"*" & $A43 & "*", S22_S25_Emp!$B:$B, "Bachelor") -> #VALUE! | P43: =COUNTIFS(S22_Emp!$C:$C,"*" & $A43 & "*", S22_S25_Emp!$B:$B, "Master") -> #VALUE! | Q43: =COUNTIFS(S22_Emp!$C:$C,"*" & $A43 & "*", S22_S25_Emp!$B:$B, "Doctorate") -> #VALUE! | R43: {=IF(OR(INDEX(S26_CF!X:X, MATCH("*" & $A43 & "*", CompanyList!A:A, 0))=TRUE, INDEX(F25_CF!P:P, MATCH("*" & $A43 & "*", CompanyList!A:A, 0))=TRUE, INDEX(S25_CF!T:T, MATCH("*" & $A43 & "*", CompanyList!A:A, 0))=TRUE, INDEX(S24_CF!W:W, MATCH("*" & $A43 & "*", CompanyList!A:A, 0))=TRUE), "Yes", "No")} -> No | S43: =IF(COUNTIF(S26_CF!$A:$A,"*" & $A43 & "*") <> 0, "Yes", "No") -> Yes | T43: {=INDEX(S26_CF!K:K, MATCH("*" & $A43 & "*", S26_CF!A:A, 0))} -> Basic Two-Day [$2000.00] | U43: =IF(COUNTIF(F25_CF!$A:$A,"*" & $A43 & "*") <> 0, "Yes", "No") -> Yes | V43: {=INDEX(F25_CF!I:I, MATCH("*" & $A43 & "*", F25_CF!$A:$A, 0))} -> Basic Two-Day [$2000.00] | W43: =IF(COUNTIF(S25_CF!$A:$A,"*" & $A43 & "*") <> 0, "Yes", "No") -> Yes | X43: {=INDEX(S25_CF!J:J, MATCH("*" & $A43 & "*", S25_CF!$A:$A, 0))} -> Basic Two-Day [$2000.00] | Y43: =IF(COUNTIF(F24_CF!$A:$A,"*" & $A43 & "*") <> 0, "Yes", "No") -> Yes | Z43: {=INDEX(F24_CF!N:N, MATCH("*" & $A43 & "*", F24_CF!$A:$A, 0))} -> Basic Two-Day [$2000.00] | AA43: =IF(COUNTIF(S24_CF!$A:$A,"*" & $A43 & "*") <> 0, "Yes", "No") -> Yes | AB43: {=INDEX(S24_CF!H:H, MATCH("*" & $A43 & "*", S24_CF!$A:$A, 0))} -> Basic Two-Day [$2000.00]
A44: Chart Industries | B44: Public | C44: 4000 | D44: 11000 | E44: 6 | F44: =COUNTIF(S26_Emp!$C:$C,"*" &A44 & "*") -> 0 | G44: =COUNTIF(F25_Emp!$C:$C,"*" &#REF! & "*") -> 0 | H44: =COUNTIF(S25_Emp!$C:$C,"*" & A44 & "*") -> 1 | I44: =COUNTIF(F24_Emp!$C:$C,"*" & B44 & "*") -> 1 | J44: =COUNTIF(S24_Emp!$C:$C,"*" & $A44 & "*") -> 1 | K44: =COUNTIF(F23_Emp!$C:$C,"*" & $A44 & "*") -> 0 | L44: =COUNTIF(S23_Emp!$C:$C,"*" & $A44 & "*") -> 1 | M44: =COUNTIF(F22_Emp!$C:$C,"*" & $A44 & "*") -> 0 | N44: =COUNTIF(S22_Emp!$C:$C,"*" & $A44 & "*") -> 1 | O44: =COUNTIFS(S22_Emp!$C:$C,"*" & $A44 & "*", S22_S25_Emp!$B:$B, "Bachelor") -> #VALUE! | P44: =COUNTIFS(S22_Emp!$C:$C,"*" & $A44 & "*", S22_S25_Emp!$B:$B, "Master") -> #VALUE! | Q44: =COUNTIFS(S22_Emp!$C:$C,"*" & $A44 & "*", S22_S25_Emp!$B:$B, "Doctorate") -> #VALUE! | R44: {=IF(OR(INDEX(S26_CF!X:X, MATCH("*" & $A44 & "*", CompanyList!A:A, 0))=TRUE, INDEX(F25_CF!P:P, MATCH("*" & $A44 & "*", CompanyList!A:A, 0))=TRUE, INDEX(S25_CF!T:T, MATCH("*" & $A44 & "*", CompanyList!A:A, 0))=TRUE, INDEX(S24_CF!W:W, MATCH("*" & $A44 & "*", CompanyList!A:A, 0))=TRUE), "Yes", "No")} -> No | S44: =IF(COUNTIF(S26_CF!$A:$A,"*" & $A44 & "*") <> 0, "Yes", "No") -> Yes | T44: {=INDEX(S26_CF!K:K, MATCH("*" & $A44 & "*", S26_CF!A:A, 0))} -> Basic Two-Day [$2000.00] | U44: =IF(COUNTIF(F25_CF!$A:$A,"*" & $A44 & "*") <> 0, "Yes", "No") -> Yes | V44: {=INDEX(F25_CF!I:I, MATCH("*" & $A44 & "*", F25_CF!$A:$A, 0))} -> Basic One-Day: Thursday, September 11th [$1000.00] | W44: =IF(COUNTIF(S25_CF!$A:$A,"*" & $A44 & "*") <> 0, "Yes", "No") -> Yes | X44: {=INDEX(S25_CF!J:J, MATCH("*" & $A44 & "*", S25_CF!$A:$A, 0))} -> Basic Two-Day [$2000.00] | Y44: =IF(COUNTIF(F24_CF!$A:$A,"*" & $A44 & "*") <> 0, "Yes", "No") -> Yes | Z44: {=INDEX(F24_CF!N:N, MATCH("*" & $A44 & "*", F24_CF!$A:$A, 0))} -> Basic Two-Day [$2000.00] | AA44: =IF(COUNTIF(S24_CF!$A:$A,"*" & $A44 & "*") <> 0, "Yes", "No") -> Yes | AB44: {=INDEX(S24_CF!H:H, MATCH("*" & $A44 & "*", S24_CF!$A:$A, 0))} -> Basic Two-Day [$2000.00]
A45: Civil & Environmental Consultants, Inc. | B45: Private | F45: =COUNTIF(S26_Emp!$C:$C,"*" &A45 & "*") -> 0 | G45: =COUNTIF(F25_Emp!$C:$C,"*" &#REF! & "*") -> 0 | H45: =COUNTIF(S25_Emp!$C:$C,"*" & A45 & "*") -> 0 | I45: =COUNTIF(F24_Emp!$C:$C,"*" & B45 & "*") -> 0 | J45: =COUNTIF(S24_Emp!$C:$C,"*" & $A45 & "*") -> 0 | K45: =COUNTIF(F23_Emp!$C:$C,"*" & $A45 & "*") -> 0 | L45: =COUNTIF(S23_Emp!$C:$C,"*" & $A45 & "*") -> 0 | M45: =COUNTIF(F22_Emp!$C:$C,"*" & $A45 & "*") -> 0 | N45: =COUNTIF(S22_Emp!$C:$C,"*" & $A45 & "*") -> 0 | O45: =COUNTIFS(S22_Emp!$C:$C,"*" & $A45 & "*", S22_S25_Emp!$B:$B, "Bachelor") -> #VALUE! | P45: =COUNTIFS(S22_Emp!$C:$C,"*" & $A45 & "*", S22_S25_Emp!$B:$B, "Master") -> #VALUE! | Q45: =COUNTIFS(S22_Emp!$C:$C,"*" & $A45 & "*", S22_S25_Emp!$B:$B, "Doctorate") -> #VALUE! | R45: {=IF(OR(INDEX(S26_CF!X:X, MATCH("*" & $A45 & "*", CompanyList!A:A, 0))=TRUE, INDEX(F25_CF!P:P, MATCH("*" & $A45 & "*", CompanyList!A:A, 0))=TRUE, INDEX(S25_CF!T:T, MATCH("*" & $A45 & "*", CompanyList!A:A, 0))=TRUE, INDEX(S24_CF!W:W, MATCH("*" & $A45 & "*", CompanyList!A:A, 0))=TRUE), "Yes", "No")} -> No | S45: =IF(COUNTIF(S26_CF!$A:$A,"*" & $A45 & "*") <> 0, "Yes", "No") -> Yes | T45: {=INDEX(S26_CF!K:K, MATCH("*" & $A45 & "*", S26_CF!A:A, 0))} -> Basic One-Day: Wednesday, January 28th [$1000.00] | U45: =IF(COUNTIF(F25_CF!$A:$A,"*" & $A45 & "*") <> 0, "Yes", "No") -> Yes | V45: {=INDEX(F25_CF!I:I, MATCH("*" & $A45 & "*", F25_CF!$A:$A, 0))} -> Basic One-Day: Thursday, September 11th [$1000.00] | W45: =IF(COUNTIF(S25_CF!$A:$A,"*" & $A45 & "*") <> 0, "Yes", "No") -> Yes | X45: {=INDEX(S25_CF!J:J, MATCH("*" & $A45 & "*", S25_CF!$A:$A, 0))} -> Basic One-Day: Thursday, January 23rd [$1000.00] | Y45: =IF(COUNTIF(F24_CF!$A:$A,"*" & $A45 & "*") <> 0, "Yes", "No") -> No | Z45: {=INDEX(F24_CF!N:N, MATCH("*" & $A45 & "*", F24_CF!$A:$A, 0))} -> #N/A | AA45: =IF(COUNTIF(S24_CF!$A:$A,"*" & $A45 & "*") <> 0, "Yes", "No") -> Yes | AB45: {=INDEX(S24_CF!H:H, MATCH("*" & $A45 & "*", S24_CF!$A:$A, 0))} -> Basic One-Day [$1000.00]
A46: CMC Steel Texas | B46: Private | F46: =COUNTIF(S26_Emp!$C:$C,"*" &A46 & "*") -> 0 | G46: =COUNTIF(F25_Emp!$C:$C,"*" &#REF! & "*") -> 0 | H46: =COUNTIF(S25_Emp!$C:$C,"*" & A46 & "*") -> 0 | I46: =COUNTIF(F24_Emp!$C:$C,"*" & B46 & "*") -> 0 | J46: =COUNTIF(S24_Emp!$C:$C,"*" & $A46 & "*") -> 0 | K46: =COUNTIF(F23_Emp!$C:$C,"*" & $A46 & "*") -> 0 | L46: =COUNTIF(S23_Emp!$C:$C,"*" & $A46 & "*") -> 0 | M46: =COUNTIF(F22_Emp!$C:$C,"*" & $A46 & "*") -> 0 | N46: =COUNTIF(S22_Emp!$C:$C,"*" & $A46 & "*") -> 0 | O46: =COUNTIFS(S22_Emp!$C:$C,"*" & $A46 & "*", S22_S25_Emp!$B:$B, "Bachelor") -> #VALUE! | P46: =COUNTIFS(S22_Emp!$C:$C,"*" & $A46 & "*", S22_S25_Emp!$B:$B, "Master") -> #VALUE! | Q46: =COUNTIFS(S22_Emp!$C:$C,"*" & $A46 & "*", S22_S25_Emp!$B:$B, "Doctorate") -> #VALUE! | R46: {=IF(OR(INDEX(S26_CF!X:X, MATCH("*" & $A46 & "*", CompanyList!A:A, 0))=TRUE, INDEX(F25_CF!P:P, MATCH("*" & $A46 & "*", CompanyList!A:A, 0))=TRUE, INDEX(S25_CF!T:T, MATCH("*" & $A46 & "*", CompanyList!A:A, 0))=TRUE, INDEX(S24_CF!W:W, MATCH("*" & $A46 & "*", CompanyList!A:A, 0))=TRUE), "Yes", "No")} -> Yes | S46: =IF(COUNTIF(S26_CF!$A:$A,"*" & $A46 & "*") <> 0, "Yes", "No") -> No | T46: {=INDEX(S26_CF!K:K, MATCH("*" & $A46 & "*", S26_CF!A:A, 0))} -> #N/A | U46: =IF(COUNTIF(F25_CF!$A:$A,"*" & $A46 & "*") <> 0, "Yes", "No") -> No | V46: {=INDEX(F25_CF!I:I, MATCH("*" & $A46 & "*", F25_CF!$A:$A, 0))} -> #N/A | W46: =IF(COUNTIF(S25_CF!$A:$A,"*" & $A46 & "*") <> 0, "Yes", "No") -> Yes | X46: {=INDEX(S25_CF!J:J, MATCH("*" & $A46 & "*", S25_CF!$A:$A, 0))} -> Basic One-Day: Wednesday, January 22nd [$1000.00] | Y46: =IF(COUNTIF(F24_CF!$A:$A,"*" & $A46 & "*") <> 0, "Yes", "No") -> Yes | Z46: {=INDEX(F24_CF!N:N, MATCH("*" & $A46 & "*", F24_CF!$A:$A, 0))} -> Basic One-Day: Wednesday, September 4th [$1000.00] | AA46: =IF(COUNTIF(S24_CF!$A:$A,"*" & $A46 & "*") <> 0, "Yes", "No") -> Yes | AB46: {=INDEX(S24_CF!H:H, MATCH("*" & $A46 & "*", S24_CF!$A:$A, 0))} -> Basic One-Day [$1000.00]
A47: Cobb, Fendley & Associates, Inc. | B47: Private | F47: =COUNTIF(S26_Emp!$C:$C,"*" &A47 & "*") -> 0 | G47: =COUNTIF(F25_Emp!$C:$C,"*" &#REF! & "*") -> 0 | H47: =COUNTIF(S25_Emp!$C:$C,"*" & A47 & "*") -> 0 | I47: =COUNTIF(F24_Emp!$C:$C,"*" & B47 & "*") -> 0 | J47: =COUNTIF(S24_Emp!$C:$C,"*" & $A47 & "*") -> 0 | K47: =COUNTIF(F23_Emp!$C:$C,"*" & $A47 & "*") -> 0 | L47: =COUNTIF(S23_Emp!$C:$C,"*" & $A47 & "*") -> 1 | M47: =COUNTIF(F22_Emp!$C:$C,"*" & $A47 & "*") -> 1 | N47: =COUNTIF(S22_Emp!$C:$C,"*" & $A47 & "*") -> 0 | O47: =COUNTIFS(S22_Emp!$C:$C,"*" & $A47 & "*", S22_S25_Emp!$B:$B, "Bachelor") -> #VALUE! | P47: =COUNTIFS(S22_Emp!$C:$C,"*" & $A47 & "*", S22_S25_Emp!$B:$B, "Master") -> #VALUE! | Q47: =COUNTIFS(S22_Emp!$C:$C,"*" & $A47 & "*", S22_S25_Emp!$B:$B, "Doctorate") -> #VALUE! | R47: {=IF(OR(INDEX(S26_CF!X:X, MATCH("*" & $A47 & "*", CompanyList!A:A, 0))=TRUE, INDEX(F25_CF!P:P, MATCH("*" & $A47 & "*", CompanyList!A:A, 0))=TRUE, INDEX(S25_CF!T:T, MATCH("*" & $A47 & "*", CompanyList!A:A, 0))=TRUE, INDEX(S24_CF!W:W, MATCH("*" & $A47 & "*", CompanyList!A:A, 0))=TRUE), "Yes", "No")} -> No | S47: =IF(COUNTIF(S26_CF!$A:$A,"*" & $A47 & "*") <> 0, "Yes", "No") -> Yes | T47: {=INDEX(S26_CF!K:K, MATCH("*" & $A47 & "*", S26_CF!A:A, 0))} -> Basic One-Day: Thursday, January 29th [$1000.00] | U47: =IF(COUNTIF(F25_CF!$A:$A,"*" & $A47 & "*") <> 0, "Yes", "No") -> Yes | V47: {=INDEX(F25_CF!I:I, MATCH("*" & $A47 & "*", F25_CF!$A:$A, 0))} -> Basic Two-Day [$2000.00] | W47: =IF(COUNTIF(S25_CF!$A:$A,"*" & $A47 & "*") <> 0, "Yes", "No") -> Yes | X47: {=INDEX(S25_CF!J:J, MATCH("*" & $A47 & "*", S25_CF!$A:$A, 0))} -> Basic One-Day: Thursday, January 23rd [$1000.00] | Y47: =IF(COUNTIF(F24_CF!$A:$A,"*" & $A47 & "*") <> 0, "Yes", "No") -> No | Z47: {=INDEX(F24_CF!N:N, MATCH("*" & $A47 & "*", F24_CF!$A:$A, 0))} -> #N/A | AA47: =IF(COUNTIF(S24_CF!$A:$A,"*" & $A47 & "*") <> 0, "Yes", "No") -> Yes | AB47: {=INDEX(S24_CF!H:H, MATCH("*" & $A47 & "*", S24_CF!$A:$A, 0))} -> Basic One-Day [$1000.00]
A48: Colliers Engineering & Design | B48: Private | F48: =COUNTIF(S26_Emp!$C:$C,"*" &A48 & "*") -> 0 | G48: =COUNTIF(F25_Emp!$C:$C,"*" &#REF! & "*") -> 0 | H48: =COUNTIF(S25_Emp!$C:$C,"*" & A48 & "*") -> 1 | I48: =COUNTIF(F24_Emp!$C:$C,"*" & B48 & "*") -> 0 | J48: =COUNTIF(S24_Emp!$C:$C,"*" & $A48 & "*") -> 1 | K48: =COUNTIF(F23_Emp!$C:$C,"*" & $A48 & "*") -> 0 | L48: =COUNTIF(S23_Emp!$C:$C,"*" & $A48 & "*") -> 0 | M48: =COUNTIF(F22_Emp!$C:$C,"*" & $A48 & "*") -> 0 | N48: =COUNTIF(S22_Emp!$C:$C,"*" & $A48 & "*") -> 0 | O48: =COUNTIFS(S22_Emp!$C:$C,"*" & $A48 & "*", S22_S25_Emp!$B:$B, "Bachelor") -> #VALUE! | P48: =COUNTIFS(S22_Emp!$C:$C,"*" & $A48 & "*", S22_S25_Emp!$B:$B, "Master") -> #VALUE! | Q48: =COUNTIFS(S22_Emp!$C:$C,"*" & $A48 & "*", S22_S25_Emp!$B:$B, "Doctorate") -> #VALUE! | R48: {=IF(OR(INDEX(S26_CF!X:X, MATCH("*" & $A48 & "*", CompanyList!A:A, 0))=TRUE, INDEX(F25_CF!P:P, MATCH("*" & $A48 & "*", CompanyList!A:A, 0))=TRUE, INDEX(S25_CF!T:T, MATCH("*" & $A48 & "*", CompanyList!A:A, 0))=TRUE, INDEX(S24_CF!W:W, MATCH("*" & $A48 & "*", CompanyList!A:A, 0))=TRUE), "Yes", "No")} -> No | S48: =IF(COUNTIF(S26_CF!$A:$A,"*" & $A48 & "*") <> 0, "Yes", "No") -> Yes | T48: {=INDEX(S26_CF!K:K, MATCH("*" & $A48 & "*", S26_CF!A:A, 0))} -> Basic One-Day: Thursday, January 29th [$1000.00] | U48: =IF(COUNTIF(F25_CF!$A:$A,"*" & $A48 & "*") <> 0, "Yes", "No") -> Yes | V48: {=INDEX(F25_CF!I:I, MATCH("*" & $A48 & "*", F25_CF!$A:$A, 0))} -> Basic One-Day: Wednesday, September 10th [$1000.00] | W48: =IF(COUNTIF(S25_CF!$A:$A,"*" & $A48 & "*") <> 0, "Yes", "No") -> Yes | X48: {=INDEX(S25_CF!J:J, MATCH("*" & $A48 & "*", S25_CF!$A:$A, 0))} -> Basic One-Day: Thursday, January 23rd [$1000.00] | Y48: =IF(COUNTIF(F24_CF!$A:$A,"*" & $A48 & "*") <> 0, "Yes", "No") -> Yes | Z48: {=INDEX(F24_CF!N:N, MATCH("*" & $A48 & "*", F24_CF!$A:$A, 0))} -> Basic One-Day: Wednesday, September 4th [$1000.00] | AA48: =IF(COUNTIF(S24_CF!$A:$A,"*" & $A48 & "*") <> 0, "Yes", "No") -> Yes | AB48: {=INDEX(S24_CF!H:H, MATCH("*" & $A48 & "*", S24_CF!$A:$A, 0))} -> Basic One-Day [$1000.00]
A49: Contech | B49: Private | F49: =COUNTIF(S26_Emp!$C:$C,"*" &A49 & "*") -> 0 | G49: =COUNTIF(F25_Emp!$C:$C,"*" &#REF! & "*") -> 0 | H49: =COUNTIF(S25_Emp!$C:$C,"*" & A49 & "*") -> 1 | I49: =COUNTIF(F24_Emp!$C:$C,"*" & B49 & "*") -> 0 | J49: =COUNTIF(S24_Emp!$C:$C,"*" & $A49 & "*") -> 2 | K49: =COUNTIF(F23_Emp!$C:$C,"*" & $A49 & "*") -> 1 | L49: =COUNTIF(S23_Emp!$C:$C,"*" & $A49 & "*") -> 0 | M49: =COUNTIF(F22_Emp!$C:$C,"*" & $A49 & "*") -> 1 | N49: =COUNTIF(S22_Emp!$C:$C,"*" & $A49 & "*") -> 2 | O49: =COUNTIFS(S22_Emp!$C:$C,"*" & $A49 & "*", S22_S25_Emp!$B:$B, "Bachelor") -> #VALUE! | P49: =COUNTIFS(S22_Emp!$C:$C,"*" & $A49 & "*", S22_S25_Emp!$B:$B, "Master") -> #VALUE! | Q49: =COUNTIFS(S22_Emp!$C:$C,"*" & $A49 & "*", S22_S25_Emp!$B:$B, "Doctorate") -> #VALUE! | R49: {=IF(OR(INDEX(S26_CF!X:X, MATCH("*" & $A49 & "*", CompanyList!A:A, 0))=TRUE, INDEX(F25_CF!P:P, MATCH("*" & $A49 & "*", CompanyList!A:A, 0))=TRUE, INDEX(S25_CF!T:T, MATCH("*" & $A49 & "*", CompanyList!A:A, 0))=TRUE, INDEX(S24_CF!W:W, MATCH("*" & $A49 & "*", CompanyList!A:A, 0))=TRUE), "Yes", "No")} -> No | S49: =IF(COUNTIF(S26_CF!$A:$A,"*" & $A49 & "*") <> 0, "Yes", "No") -> Yes | T49: {=INDEX(S26_CF!K:K, MATCH("*" & $A49 & "*", S26_CF!A:A, 0))} -> Basic One-Day: Thursday, January 29th [$1000.00] | U49: =IF(COUNTIF(F25_CF!$A:$A,"*" & $A49 & "*") <> 0, "Yes", "No") -> Yes | V49: {=INDEX(F25_CF!I:I, MATCH("*" & $A49 & "*", F25_CF!$A:$A, 0))} -> Basic One-Day: Thursday, September 11th [$1000.00] | W49: =IF(COUNTIF(S25_CF!$A:$A,"*" & $A49 & "*") <> 0, "Yes", "No") -> Yes | X49: {=INDEX(S25_CF!J:J, MATCH("*" & $A49 & "*", S25_CF!$A:$A, 0))} -> Basic One-Day: Thursday, January 23rd [$1000.00] | Y49: =IF(COUNTIF(F24_CF!$A:$A,"*" & $A49 & "*") <> 0, "Yes", "No") -> Yes | Z49: {=INDEX(F24_CF!N:N, MATCH("*" & $A49 & "*", F24_CF!$A:$A, 0))} -> Basic One-Day: Thursday, September 5th [$1000.00] | AA49: =IF(COUNTIF(S24_CF!$A:$A,"*" & $A49 & "*") <> 0, "Yes", "No") -> Yes | AB49: {=INDEX(S24_CF!H:H, MATCH("*" & $A49 & "*", S24_CF!$A:$A, 0))} -> Basic One-Day [$1000.00]
A50: Daily Thermetrics | B50: Private | F50: =COUNTIF(S26_Emp!$C:$C,"*" &A50 & "*") -> 0 | G50: =COUNTIF(F25_Emp!$C:$C,"*" &#REF! & "*") -> 0 | H50: =COUNTIF(S25_Emp!$C:$C,"*" & A50 & "*") -> 0 | I50: =COUNTIF(F24_Emp!$C:$C,"*" & B50 & "*") -> 0 | J50: =COUNTIF(S24_Emp!$C:$C,"*" & $A50 & "*") -> 0 | K50: =COUNTIF(F23_Emp!$C:$C,"*" & $A50 & "*") -> 0 | L50: =COUNTIF(S23_Emp!$C:$C,"*" & $A50 & "*") -> 0 | M50: =COUNTIF(F22_Emp!$C:$C,"*" & $A50 & "*") -> 0 | N50: =COUNTIF(S22_Emp!$C:$C,"*" & $A50 & "*") -> 0 | O50: =COUNTIFS(S22_Emp!$C:$C,"*" & $A50 & "*", S22_S25_Emp!$B:$B, "Bachelor") -> #VALUE! | P50: =COUNTIFS(S22_Emp!$C:$C,"*" & $A50 & "*", S22_S25_Emp!$B:$B, "Master") -> #VALUE! | Q50: =COUNTIFS(S22_Emp!$C:$C,"*" & $A50 & "*", S22_S25_Emp!$B:$B, "Doctorate") -> #VALUE! | R50: {=IF(OR(INDEX(S26_CF!X:X, MATCH("*" & $A50 & "*", CompanyList!A:A, 0))=TRUE, INDEX(F25_CF!P:P, MATCH("*" & $A50 & "*", CompanyList!A:A, 0))=TRUE, INDEX(S25_CF!T:T, MATCH("*" & $A50 & "*", CompanyList!A:A, 0))=TRUE, INDEX(S24_CF!W:W, MATCH("*" & $A50 & "*", CompanyList!A:A, 0))=TRUE), "Yes", "No")} -> No | S50: =IF(COUNTIF(S26_CF!$A:$A,"*" & $A50 & "*") <> 0, "Yes", "No") -> Yes | T50: {=INDEX(S26_CF!K:K, MATCH("*" & $A50 & "*", S26_CF!A:A, 0))} -> Basic One-Day: Thursday, January 29th [$1000.00] | U50: =IF(COUNTIF(F25_CF!$A:$A,"*" & $A50 & "*") <> 0, "Yes", "No") -> Yes | V50: {=INDEX(F25_CF!I:I, MATCH("*" & $A50 & "*", F25_CF!$A:$A, 0))} -> Basic One-Day: Thursday, September 11th [$1000.00] | W50: =IF(COUNTIF(S25_CF!$A:$A,"*" & $A50 & "*") <> 0, "Yes", "No") -> Yes | X50: {=INDEX(S25_CF!J:J, MATCH("*" & $A50 & "*", S25_CF!$A:$A, 0))} -> Basic One-Day: Wednesday, January 22nd [$1000.00] | Y50: =IF(COUNTIF(F24_CF!$A:$A,"*" & $A50 & "*") <> 0, "Yes", "No") -> No | Z50: {=INDEX(F24_CF!N:N, MATCH("*" & $A50 & "*", F24_CF!$A:$A, 0))} -> #N/A | AA50: =IF(COUNTIF(S24_CF!$A:$A,"*" & $A50 & "*") <> 0, "Yes", "No") -> Yes | AB50: {=INDEX(S24_CF!H:H, MATCH("*" & $A50 & "*", S24_CF!$A:$A, 0))} -> Basic Two-Day [$2000.00]
A51: Dally + Associates, Inc. | B51: Private | F51: =COUNTIF(S26_Emp!$C:$C,"*" &A51 & "*") -> 0 | G51: =COUNTIF(F25_Emp!$C:$C,"*" &#REF! & "*") -> 0 | H51: =COUNTIF(S25_Emp!$C:$C,"*" & A51 & "*") -> 0 | I51: =COUNTIF(F24_Emp!$C:$C,"*" & B51 & "*") -> 0 | J51: =COUNTIF(S24_Emp!$C:$C,"*" & $A51 & "*") -> 0 | K51: =COUNTIF(F23_Emp!$C:$C,"*" & $A51 & "*") -> 0 | L51: =COUNTIF(S23_Emp!$C:$C,"*" & $A51 & "*") -> 0 | M51: =COUNTIF(F22_Emp!$C:$C,"*" & $A51 & "*") -> 0 | N51: =COUNTIF(S22_Emp!$C:$C,"*" & $A51 & "*") -> 0 | O51: =COUNTIFS(S22_Emp!$C:$C,"*" & $A51 & "*", S22_S25_Emp!$B:$B, "Bachelor") -> #VALUE! | P51: =COUNTIFS(S22_Emp!$C:$C,"*" & $A51 & "*", S22_S25_Emp!$B:$B, "Master") -> #VALUE! | Q51: =COUNTIFS(S22_Emp!$C:$C,"*" & $A51 & "*", S22_S25_Emp!$B:$B, "Doctorate") -> #VALUE! | R51: {=IF(OR(INDEX(S26_CF!X:X, MATCH("*" & $A51 & "*", CompanyList!A:A, 0))=TRUE, INDEX(F25_CF!P:P, MATCH("*" & $A51 & "*", CompanyList!A:A, 0))=TRUE, INDEX(S25_CF!T:T, MATCH("*" & $A51 & "*", CompanyList!A:A, 0))=TRUE, INDEX(S24_CF!W:W, MATCH("*" & $A51 & "*", CompanyList!A:A, 0))=TRUE), "Yes", "No")} -> No | S51: =IF(COUNTIF(S26_CF!$A:$A,"*" & $A51 & "*") <> 0, "Yes", "No") -> No | T51: {=INDEX(S26_CF!K:K, MATCH("*" & $A51 & "*", S26_CF!A:A, 0))} -> #N/A | U51: =IF(COUNTIF(F25_CF!$A:$A,"*" & $A51 & "*") <> 0, "Yes", "No") -> Yes | V51: {=INDEX(F25_CF!I:I, MATCH("*" & $A51 & "*", F25_CF!$A:$A, 0))} -> Silver One-Day: Wednesday, September 10th [$1800.00] | W51: =IF(COUNTIF(S25_CF!$A:$A,"*" & $A51 & "*") <> 0, "Yes", "No") -> Yes | X51: {=INDEX(S25_CF!J:J, MATCH("*" & $A51 & "*", S25_CF!$A:$A, 0))} -> Silver One-Day: Wednesday, January 22nd [$1800.00] | Y51: =IF(COUNTIF(F24_CF!$A:$A,"*" & $A51 & "*") <> 0, "Yes", "No") -> No | Z51: {=INDEX(F24_CF!N:N, MATCH("*" & $A51 & "*", F24_CF!$A:$A, 0))} -> #N/A | AA51: =IF(COUNTIF(S24_CF!$A:$A,"*" & $A51 & "*") <> 0, "Yes", "No") -> Yes | AB51: {=INDEX(S24_CF!H:H, MATCH("*" & $A51 & "*", S24_CF!$A:$A, 0))} -> Basic One-Day [$1000.00]
A52: Dashiell Corp. | B52: Private | F52: =COUNTIF(S26_Emp!$C:$C,"*" &A52 & "*") -> 0 | G52: =COUNTIF(F25_Emp!$C:$C,"*" &#REF! & "*") -> 0 | H52: =COUNTIF(S25_Emp!$C:$C,"*" & A52 & "*") -> 0 | I52: =COUNTIF(F24_Emp!$C:$C,"*" & B52 & "*") -> 0 | J52: =COUNTIF(S24_Emp!$C:$C,"*" & $A52 & "*") -> 0 | K52: =COUNTIF(F23_Emp!$C:$C,"*" & $A52 & "*") -> 1 | L52: =COUNTIF(S23_Emp!$C:$C,"*" & $A52 & "*") -> 1 | M52: =COUNTIF(F22_Emp!$C:$C,"*" & $A52 & "*") -> 0 | N52: =COUNTIF(S22_Emp!$C:$C,"*" & $A52 & "*") -> 0 | O52: =COUNTIFS(S22_Emp!$C:$C,"*" & $A52 & "*", S22_S25_Emp!$B:$B, "Bachelor") -> #VALUE! | P52: =COUNTIFS(S22_Emp!$C:$C,"*" & $A52 & "*", S22_S25_Emp!$B:$B, "Master") -> #VALUE! | Q52: =COUNTIFS(S22_Emp!$C:$C,"*" & $A52 & "*", S22_S25_Emp!$B:$B, "Doctorate") -> #VALUE! | R52: {=IF(OR(INDEX(S26_CF!X:X, MATCH("*" & $A52 & "*", CompanyList!A:A, 0))=TRUE, INDEX(F25_CF!P:P, MATCH("*" & $A52 & "*", CompanyList!A:A, 0))=TRUE, INDEX(S25_CF!T:T, MATCH("*" & $A52 & "*", CompanyList!A:A, 0))=TRUE, INDEX(S24_CF!W:W, MATCH("*" & $A52 & "*", CompanyList!A:A, 0))=TRUE), "Yes", "No")} -> Yes | S52: =IF(COUNTIF(S26_CF!$A:$A,"*" & $A52 & "*") <> 0, "Yes", "No") -> Yes | T52: {=INDEX(S26_CF!K:K, MATCH("*" & $A52 & "*", S26_CF!A:A, 0))} -> Gold Two-Day [$5500.00] | U52: =IF(COUNTIF(F25_CF!$A:$A,"*" & $A52 & "*") <> 0, "Yes", "No") -> Yes | V52: {=INDEX(F25_CF!I:I, MATCH("*" & $A52 & "*", F25_CF!$A:$A, 0))} -> Gold Two-Day [$5500.00] | W52: =IF(COUNTIF(S25_CF!$A:$A,"*" & $A52 & "*") <> 0, "Yes", "No") -> Yes | X52: {=INDEX(S25_CF!J:J, MATCH("*" & $A52 & "*", S25_CF!$A:$A, 0))} -> Gold Two-Day [$5500.00] | Y52: =IF(COUNTIF(F24_CF!$A:$A,"*" & $A52 & "*") <> 0, "Yes", "No") -> Yes | Z52: {=INDEX(F24_CF!N:N, MATCH("*" & $A52 & "*", F24_CF!$A:$A, 0))} -> Gold Two-Day [$5500.00] | AA52: =IF(COUNTIF(S24_CF!$A:$A,"*" & $A52 & "*") <> 0, "Yes", "No") -> Yes | AB52: {=INDEX(S24_CF!H:H, MATCH("*" & $A52 & "*", S24_CF!$A:$A, 0))} -> Gold Two-Day [$5000.00]
A53: DBI Construction Consultants | B53: Private | F53: =COUNTIF(S26_Emp!$C:$C,"*" &A53 & "*") -> 0 | G53: =COUNTIF(F25_Emp!$C:$C,"*" &#REF! & "*") -> 0 | H53: =COUNTIF(S25_Emp!$C:$C,"*" & A53 & "*") -> 0 | I53: =COUNTIF(F24_Emp!$C:$C,"*" & B53 & "*") -> 0 | J53: =COUNTIF(S24_Emp!$C:$C,"*" & $A53 & "*") -> 0 | K53: =COUNTIF(F23_Emp!$C:$C,"*" & $A53 & "*") -> 0 | L53: =COUNTIF(S23_Emp!$C:$C,"*" & $A53 & "*") -> 0 | M53: =COUNTIF(F22_Emp!$C:$C,"*" & $A53 & "*") -> 0 | N53: =COUNTIF(S22_Emp!$C:$C,"*" & $A53 & "*") -> 0 | O53: =COUNTIFS(S22_Emp!$C:$C,"*" & $A53 & "*", S22_S25_Emp!$B:$B, "Bachelor") -> #VALUE! | P53: =COUNTIFS(S22_Emp!$C:$C,"*" & $A53 & "*", S22_S25_Emp!$B:$B, "Master") -> #VALUE! | Q53: =COUNTIFS(S22_Emp!$C:$C,"*" & $A53 & "*", S22_S25_Emp!$B:$B, "Doctorate") -> #VALUE! | R53: {=IF(OR(INDEX(S26_CF!X:X, MATCH("*" & $A53 & "*", CompanyList!A:A, 0))=TRUE, INDEX(F25_CF!P:P, MATCH("*" & $A53 & "*", CompanyList!A:A, 0))=TRUE, INDEX(S25_CF!T:T, MATCH("*" & $A53 & "*", CompanyList!A:A, 0))=TRUE, INDEX(S24_CF!W:W, MATCH("*" & $A53 & "*", CompanyList!A:A, 0))=TRUE), "Yes", "No")} -> No | S53: =IF(COUNTIF(S26_CF!$A:$A,"*" & $A53 & "*") <> 0, "Yes", "No") -> No | T53: {=INDEX(S26_CF!K:K, MATCH("*" & $A53 & "*", S26_CF!A:A, 0))} -> #N/A | U53: =IF(COUNTIF(F25_CF!$A:$A,"*" & $A53 & "*") <> 0, "Yes", "No") -> No | V53: {=INDEX(F25_CF!I:I, MATCH("*" & $A53 & "*", F25_CF!$A:$A, 0))} -> #N/A | W53: =IF(COUNTIF(S25_CF!$A:$A,"*" & $A53 & "*") <> 0, "Yes", "No") -> Yes | X53: {=INDEX(S25_CF!J:J, MATCH("*" & $A53 & "*", S25_CF!$A:$A, 0))} -> Basic One-Day: Wednesday, January 22nd [$1000.00] | Y53: =IF(COUNTIF(F24_CF!$A:$A,"*" & $A53 & "*") <> 0, "Yes", "No") -> Yes | Z53: {=INDEX(F24_CF!N:N, MATCH("*" & $A53 & "*", F24_CF!$A:$A, 0))} -> Basic One-Day: Thursday, September 5th [$1000.00] | AA53: =IF(COUNTIF(S24_CF!$A:$A,"*" & $A53 & "*") <> 0, "Yes", "No") -> Yes | AB53: {=INDEX(S24_CF!H:H, MATCH("*" & $A53 & "*", S24_CF!$A:$A, 0))} -> Basic One-Day [$1000.00]
A54: Defense Intelligence Agency (DIA) | B54: Government | D54: 16500 | F54: =COUNTIF(S26_Emp!$C:$C,"*" &A54 & "*") -> 0 | G54: =COUNTIF(F25_Emp!$C:$C,"*" &#REF! & "*") -> 0 | H54: =COUNTIF(S25_Emp!$C:$C,"*" & A54 & "*") -> 0 | I54: =COUNTIF(F24_Emp!$C:$C,"*" & B54 & "*") -> 0 | J54: =COUNTIF(S24_Emp!$C:$C,"*" & $A54 & "*") -> 1 | K54: =COUNTIF(F23_Emp!$C:$C,"*" & $A54 & "*") -> 0 | L54: =COUNTIF(S23_Emp!$C:$C,"*" & $A54 & "*") -> 0 | M54: =COUNTIF(F22_Emp!$C:$C,"*" & $A54 & "*") -> 0 | N54: =COUNTIF(S22_Emp!$C:$C,"*" & $A54 & "*") -> 0 | O54: =COUNTIFS(S22_Emp!$C:$C,"*" & $A54 & "*", S22_S25_Emp!$B:$B, "Bachelor") -> #VALUE! | P54: =COUNTIFS(S22_Emp!$C:$C,"*" & $A54 & "*", S22_S25_Emp!$B:$B, "Master") -> #VALUE! | Q54: =COUNTIFS(S22_Emp!$C:$C,"*" & $A54 & "*", S22_S25_Emp!$B:$B, "Doctorate") -> #VALUE! | R54: {=IF(OR(INDEX(S26_CF!X:X, MATCH("*" & $A54 & "*", CompanyList!A:A, 0))=TRUE, INDEX(F25_CF!P:P, MATCH("*" & $A54 & "*", CompanyList!A:A, 0))=TRUE, INDEX(S25_CF!T:T, MATCH("*" & $A54 & "*", CompanyList!A:A, 0))=TRUE, INDEX(S24_CF!W:W, MATCH("*" & $A54 & "*", CompanyList!A:A, 0))=TRUE), "Yes", "No")} -> No | S54: =IF(COUNTIF(S26_CF!$A:$A,"*" & $A54 & "*") <> 0, "Yes", "No") -> No | T54: {=INDEX(S26_CF!K:K, MATCH("*" & $A54 & "*", S26_CF!A:A, 0))} -> #N/A | U54: =IF(COUNTIF(F25_CF!$A:$A,"*" & $A54 & "*") <> 0, "Yes", "No") -> No | V54: {=INDEX(F25_CF!I:I, MATCH("*" & $A54 & "*", F25_CF!$A:$A, 0))} -> #N/A | W54: =IF(COUNTIF(S25_CF!$A:$A,"*" & $A54 & "*") <> 0, "Yes", "No") -> Yes | X54: {=INDEX(S25_CF!J:J, MATCH("*" & $A54 & "*", S25_CF!$A:$A, 0))} -> Basic One-Day: Thursday, January 23rd [$1000.00] | Y54: =IF(COUNTIF(F24_CF!$A:$A,"*" & $A54 & "*") <> 0, "Yes", "No") -> Yes | Z54: {=INDEX(F24_CF!N:N, MATCH("*" & $A54 & "*", F24_CF!$A:$A, 0))} -> Basic One-Day: Wednesday, September 4th [$1000.00] | AA54: =IF(COUNTIF(S24_CF!$A:$A,"*" & $A54 & "*") <> 0, "Yes", "No") -> Yes | AB54: {=INDEX(S24_CF!H:H, MATCH("*" & $A54 & "*", S24_CF!$A:$A, 0))} -> Basic One-Day [$1000.00]
A55: Det Norske Veritas (DNV) | B55: Private | F55: =COUNTIF(S26_Emp!$C:$C,"*" &A55 & "*") -> 0 | G55: =COUNTIF(F25_Emp!$C:$C,"*" &#REF! & "*") -> 0 | H55: =COUNTIF(S25_Emp!$C:$C,"*" & A55 & "*") -> 0 | I55: =COUNTIF(F24_Emp!$C:$C,"*" & B55 & "*") -> 0 | J55: =COUNTIF(S24_Emp!$C:$C,"*" & $A55 & "*") -> 0 | K55: =COUNTIF(F23_Emp!$C:$C,"*" & $A55 & "*") -> 0 | L55: =COUNTIF(S23_Emp!$C:$C,"*" & $A55 & "*") -> 0 | M55: =COUNTIF(F22_Emp!$C:$C,"*" & $A55 & "*") -> 0 | N55: =COUNTIF(S22_Emp!$C:$C,"*" & $A55 & "*") -> 0 | O55: =COUNTIFS(S22_Emp!$C:$C,"*" & $A55 & "*", S22_S25_Emp!$B:$B, "Bachelor") -> #VALUE! | P55: =COUNTIFS(S22_Emp!$C:$C,"*" & $A55 & "*", S22_S25_Emp!$B:$B, "Master") -> #VALUE! | Q55: =COUNTIFS(S22_Emp!$C:$C,"*" & $A55 & "*", S22_S25_Emp!$B:$B, "Doctorate") -> #VALUE! | R55: {=IF(OR(INDEX(S26_CF!X:X, MATCH("*" & $A55 & "*", CompanyList!A:A, 0))=TRUE, INDEX(F25_CF!P:P, MATCH("*" & $A55 & "*", CompanyList!A:A, 0))=TRUE, INDEX(S25_CF!T:T, MATCH("*" & $A55 & "*", CompanyList!A:A, 0))=TRUE, INDEX(S24_CF!W:W, MATCH("*" & $A55 & "*", CompanyList!A:A, 0))=TRUE), "Yes", "No")} -> Yes | S55: =IF(COUNTIF(S26_CF!$A:$A,"*" & $A55 & "*") <> 0, "Yes", "No") -> No | T55: {=INDEX(S26_CF!K:K, MATCH("*" & $A55 & "*", S26_CF!A:A, 0))} -> #N/A | U55: =IF(COUNTIF(F25_CF!$A:$A,"*" & $A55 & "*") <> 0, "Yes", "No") -> Yes | V55: {=INDEX(F25_CF!I:I, MATCH("*" & $A55 & "*", F25_CF!$A:$A, 0))} -> Basic One-Day: Thursday, September 11th [$1000.00] | W55: =IF(COUNTIF(S25_CF!$A:$A,"*" & $A55 & "*") <> 0, "Yes", "No") -> Yes | X55: {=INDEX(S25_CF!J:J, MATCH("*" & $A55 & "*", S25_CF!$A:$A, 0))} -> Basic One-Day: Wednesday, January 22nd [$1000.00] | Y55: =IF(COUNTIF(F24_CF!$A:$A,"*" & $A55 & "*") <> 0, "Yes", "No") -> No | Z55: {=INDEX(F24_CF!N:N, MATCH("*" & $A55 & "*", F24_CF!$A:$A, 0))} -> #N/A | AA55: =IF(COUNTIF(S24_CF!$A:$A,"*" & $A55 & "*") <> 0, "Yes", "No") -> Yes | AB55: {=INDEX(S24_CF!H:H, MATCH("*" & $A55 & "*", S24_CF!$A:$A, 0))} -> Basic One-Day [$1000.00]
A56: Dunaway | B56: Private | F56: =COUNTIF(S26_Emp!$C:$C,"*" &A56 & "*") -> 0 | G56: =COUNTIF(F25_Emp!$C:$C,"*" &#REF! & "*") -> 0 | H56: =COUNTIF(S25_Emp!$C:$C,"*" & A56 & "*") -> 0 | I56: =COUNTIF(F24_Emp!$C:$C,"*" & B56 & "*") -> 0 | J56: =COUNTIF(S24_Emp!$C:$C,"*" & $A56 & "*") -> 1 | K56: =COUNTIF(F23_Emp!$C:$C,"*" & $A56 & "*") -> 0 | L56: =COUNTIF(S23_Emp!$C:$C,"*" & $A56 & "*") -> 0 | M56: =COUNTIF(F22_Emp!$C:$C,"*" & $A56 & "*") -> 1 | N56: =COUNTIF(S22_Emp!$C:$C,"*" & $A56 & "*") -> 0 | O56: =COUNTIFS(S22_Emp!$C:$C,"*" & $A56 & "*", S22_S25_Emp!$B:$B, "Bachelor") -> #VALUE! | P56: =COUNTIFS(S22_Emp!$C:$C,"*" & $A56 & "*", S22_S25_Emp!$B:$B, "Master") -> #VALUE! | Q56: =COUNTIFS(S22_Emp!$C:$C,"*" & $A56 & "*", S22_S25_Emp!$B:$B, "Doctorate") -> #VALUE! | R56: {=IF(OR(INDEX(S26_CF!X:X, MATCH("*" & $A56 & "*", CompanyList!A:A, 0))=TRUE, INDEX(F25_CF!P:P, MATCH("*" & $A56 & "*", CompanyList!A:A, 0))=TRUE, INDEX(S25_CF!T:T, MATCH("*" & $A56 & "*", CompanyList!A:A, 0))=TRUE, INDEX(S24_CF!W:W, MATCH("*" & $A56 & "*", CompanyList!A:A, 0))=TRUE), "Yes", "No")} -> No | S56: =IF(COUNTIF(S26_CF!$A:$A,"*" & $A56 & "*") <> 0, "Yes", "No") -> Yes | T56: {=INDEX(S26_CF!K:K, MATCH("*" & $A56 & "*", S26_CF!A:A, 0))} -> Basic One-Day: Thursday, January 29th [$1000.00] | U56: =IF(COUNTIF(F25_CF!$A:$A,"*" & $A56 & "*") <> 0, "Yes", "No") -> Yes | V56: {=INDEX(F25_CF!I:I, MATCH("*" & $A56 & "*", F25_CF!$A:$A, 0))} -> Basic One-Day: Wednesday, September 10th [$1000.00] | W56: =IF(COUNTIF(S25_CF!$A:$A,"*" & $A56 & "*") <> 0, "Yes", "No") -> Yes | X56: {=INDEX(S25_CF!J:J, MATCH("*" & $A56 & "*", S25_CF!$A:$A, 0))} -> Basic One-Day: Thursday, January 23rd [$1000.00] | Y56: =IF(COUNTIF(F24_CF!$A:$A,"*" & $A56 & "*") <> 0, "Yes", "No") -> No | Z56: {=INDEX(F24_CF!N:N, MATCH("*" & $A56 & "*", F24_CF!$A:$A, 0))} -> #N/A | AA56: =IF(COUNTIF(S24_CF!$A:$A,"*" & $A56 & "*") <> 0, "Yes", "No") -> Yes | AB56: {=INDEX(S24_CF!H:H, MATCH("*" & $A56 & "*", S24_CF!$A:$A, 0))} -> Basic One-Day [$1000.00]
A57: Dynamic Engineering Consultants, PC | B57: Private | F57: =COUNTIF(S26_Emp!$C:$C,"*" &A57 & "*") -> 0 | G57: =COUNTIF(F25_Emp!$C:$C,"*" &#REF! & "*") -> 0 | H57: =COUNTIF(S25_Emp!$C:$C,"*" & A57 & "*") -> 0 | I57: =COUNTIF(F24_Emp!$C:$C,"*" & B57 & "*") -> 0 | J57: =COUNTIF(S24_Emp!$C:$C,"*" & $A57 & "*") -> 1 | K57: =COUNTIF(F23_Emp!$C:$C,"*" & $A57 & "*") -> 0 | L57: =COUNTIF(S23_Emp!$C:$C,"*" & $A57 & "*") -> 0 | M57: =COUNTIF(F22_Emp!$C:$C,"*" & $A57 & "*") -> 0 | N57: =COUNTIF(S22_Emp!$C:$C,"*" & $A57 & "*") -> 0 | O57: =COUNTIFS(S22_Emp!$C:$C,"*" & $A57 & "*", S22_S25_Emp!$B:$B, "Bachelor") -> #VALUE! | P57: =COUNTIFS(S22_Emp!$C:$C,"*" & $A57 & "*", S22_S25_Emp!$B:$B, "Master") -> #VALUE! | Q57: =COUNTIFS(S22_Emp!$C:$C,"*" & $A57 & "*", S22_S25_Emp!$B:$B, "Doctorate") -> #VALUE! | R57: {=IF(OR(INDEX(S26_CF!X:X, MATCH("*" & $A57 & "*", CompanyList!A:A, 0))=TRUE, INDEX(F25_CF!P:P, MATCH("*" & $A57 & "*", CompanyList!A:A, 0))=TRUE, INDEX(S25_CF!T:T, MATCH("*" & $A57 & "*", CompanyList!A:A, 0))=TRUE, INDEX(S24_CF!W:W, MATCH("*" & $A57 & "*", CompanyList!A:A, 0))=TRUE), "Yes", "No")} -> No | S57: =IF(COUNTIF(S26_CF!$A:$A,"*" & $A57 & "*") <> 0, "Yes", "No") -> No | T57: {=INDEX(S26_CF!K:K, MATCH("*" & $A57 & "*", S26_CF!A:A, 0))} -> #N/A | U57: =IF(COUNTIF(F25_CF!$A:$A,"*" & $A57 & "*") <> 0, "Yes", "No") -> Yes | V57: {=INDEX(F25_CF!I:I, MATCH("*" & $A57 & "*", F25_CF!$A:$A, 0))} -> Silver One-Day: Thursday, September 11th [$1800.00] | W57: =IF(COUNTIF(S25_CF!$A:$A,"*" & $A57 & "*") <> 0, "Yes", "No") -> Yes | X57: {=INDEX(S25_CF!J:J, MATCH("*" & $A57 & "*", S25_CF!$A:$A, 0))} -> Basic One-Day: Thursday, January 23rd [$1000.00] | Y57: =IF(COUNTIF(F24_CF!$A:$A,"*" & $A57 & "*") <> 0, "Yes", "No") -> Yes | Z57: {=INDEX(F24_CF!N:N, MATCH("*" & $A57 & "*", F24_CF!$A:$A, 0))} -> Basic One-Day: Wednesday, September 4th [$1000.00] | AA57: =IF(COUNTIF(S24_CF!$A:$A,"*" & $A57 & "*") <> 0, "Yes", "No") -> Yes | AB57: {=INDEX(S24_CF!H:H, MATCH("*" & $A57 & "*", S24_CF!$A:$A, 0))} -> Basic One-Day [$1000.00]
A58: Dynamic Systems, Inc. | B58: Private | F58: =COUNTIF(S26_Emp!$C:$C,"*" &A58 & "*") -> 0 | G58: =COUNTIF(F25_Emp!$C:$C,"*" &#REF! & "*") -> 0 | H58: =COUNTIF(S25_Emp!$C:$C,"*" & A58 & "*") -> 0 | I58: =COUNTIF(F24_Emp!$C:$C,"*" & B58 & "*") -> 0 | J58: =COUNTIF(S24_Emp!$C:$C,"*" & $A58 & "*") -> 1 | K58: =COUNTIF(F23_Emp!$C:$C,"*" & $A58 & "*") -> 0 | L58: =COUNTIF(S23_Emp!$C:$C,"*" & $A58 & "*") -> 1 | M58: =COUNTIF(F22_Emp!$C:$C,"*" & $A58 & "*") -> 1 | N58: =COUNTIF(S22_Emp!$C:$C,"*" & $A58 & "*") -> 0 | O58: =COUNTIFS(S22_Emp!$C:$C,"*" & $A58 & "*", S22_S25_Emp!$B:$B, "Bachelor") -> #VALUE! | P58: =COUNTIFS(S22_Emp!$C:$C,"*" & $A58 & "*", S22_S25_Emp!$B:$B, "Master") -> #VALUE! | Q58: =COUNTIFS(S22_Emp!$C:$C,"*" & $A58 & "*", S22_S25_Emp!$B:$B, "Doctorate") -> #VALUE! | R58: {=IF(OR(INDEX(S26_CF!X:X, MATCH("*" & $A58 & "*", CompanyList!A:A, 0))=TRUE, INDEX(F25_CF!P:P, MATCH("*" & $A58 & "*", CompanyList!A:A, 0))=TRUE, INDEX(S25_CF!T:T, MATCH("*" & $A58 & "*", CompanyList!A:A, 0))=TRUE, INDEX(S24_CF!W:W, MATCH("*" & $A58 & "*", CompanyList!A:A, 0))=TRUE), "Yes", "No")} -> Yes | S58: =IF(COUNTIF(S26_CF!$A:$A,"*" & $A58 & "*") <> 0, "Yes", "No") -> No | T58: {=INDEX(S26_CF!K:K, MATCH("*" & $A58 & "*", S26_CF!A:A, 0))} -> #N/A | U58: =IF(COUNTIF(F25_CF!$A:$A,"*" & $A58 & "*") <> 0, "Yes", "No") -> Yes | V58: {=INDEX(F25_CF!I:I, MATCH("*" & $A58 & "*", F25_CF!$A:$A, 0))} -> Silver Two-Day [$3000.00] | W58: =IF(COUNTIF(S25_CF!$A:$A,"*" & $A58 & "*") <> 0, "Yes", "No") -> Yes | X58: {=INDEX(S25_CF!J:J, MATCH("*" & $A58 & "*", S25_CF!$A:$A, 0))} -> Silver Two-Day [$3000.00] | Y58: =IF(COUNTIF(F24_CF!$A:$A,"*" & $A58 & "*") <> 0, "Yes", "No") -> Yes | Z58: {=INDEX(F24_CF!N:N, MATCH("*" & $A58 & "*", F24_CF!$A:$A, 0))} -> Silver Two-Day [$3000.00] | AA58: =IF(COUNTIF(S24_CF!$A:$A,"*" & $A58 & "*") <> 0, "Yes", "No") -> Yes | AB58: {=INDEX(S24_CF!H:H, MATCH("*" & $A58 & "*", S24_CF!$A:$A, 0))} -> Silver Two-Day [$3000.00]
A59: EDG | B59: Private | F59: =COUNTIF(S26_Emp!$C:$C,"*" &A59 & "*") -> 0 | G59: =COUNTIF(F25_Emp!$C:$C,"*" &#REF! & "*") -> 0 | H59: =COUNTIF(S25_Emp!$C:$C,"*" & A59 & "*") -> 3 | I59: =COUNTIF(F24_Emp!$C:$C,"*" & B59 & "*") -> 0 | J59: =COUNTIF(S24_Emp!$C:$C,"*" & $A59 & "*") -> 6 | K59: =COUNTIF(F23_Emp!$C:$C,"*" & $A59 & "*") -> 2 | L59: =COUNTIF(S23_Emp!$C:$C,"*" & $A59 & "*") -> 2 | M59: =COUNTIF(F22_Emp!$C:$C,"*" & $A59 & "*") -> 3 | N59: =COUNTIF(S22_Emp!$C:$C,"*" & $A59 & "*") -> 7 | O59: =COUNTIFS(S22_Emp!$C:$C,"*" & $A59 & "*", S22_S25_Emp!$B:$B, "Bachelor") -> #VALUE! | P59: =COUNTIFS(S22_Emp!$C:$C,"*" & $A59 & "*", S22_S25_Emp!$B:$B, "Master") -> #VALUE! | Q59: =COUNTIFS(S22_Emp!$C:$C,"*" & $A59 & "*", S22_S25_Emp!$B:$B, "Doctorate") -> #VALUE! | R59: {=IF(OR(INDEX(S26_CF!X:X, MATCH("*" & $A59 & "*", CompanyList!A:A, 0))=TRUE, INDEX(F25_CF!P:P, MATCH("*" & $A59 & "*", CompanyList!A:A, 0))=TRUE, INDEX(S25_CF!T:T, MATCH("*" & $A59 & "*", CompanyList!A:A, 0))=TRUE, INDEX(S24_CF!W:W, MATCH("*" & $A59 & "*", CompanyList!A:A, 0))=TRUE), "Yes", "No")} -> No | S59: =IF(COUNTIF(S26_CF!$A:$A,"*" & $A59 & "*") <> 0, "Yes", "No") -> Yes | T59: {=INDEX(S26_CF!K:K, MATCH("*" & $A59 & "*", S26_CF!A:A, 0))} -> Basic Two-Day [$2000.00] | U59: =IF(COUNTIF(F25_CF!$A:$A,"*" & $A59 & "*") <> 0, "Yes", "No") -> Yes | V59: {=INDEX(F25_CF!I:I, MATCH("*" & $A59 & "*", F25_CF!$A:$A, 0))} -> Basic Two-Day [$2000.00] | W59: =IF(COUNTIF(S25_CF!$A:$A,"*" & $A59 & "*") <> 0, "Yes", "No") -> Yes | X59: {=INDEX(S25_CF!J:J, MATCH("*" & $A59 & "*", S25_CF!$A:$A, 0))} -> Basic One-Day: Wednesday, January 22nd [$1000.00] | Y59: =IF(COUNTIF(F24_CF!$A:$A,"*" & $A59 & "*") <> 0, "Yes", "No") -> Yes | Z59: {=INDEX(F24_CF!N:N, MATCH("*" & $A59 & "*", F24_CF!$A:$A, 0))} -> Basic One-Day: Thursday, September 5th [$1000.00] | AA59: =IF(COUNTIF(S24_CF!$A:$A,"*" & $A59 & "*") <> 0, "Yes", "No") -> Yes | AB59: {=INDEX(S24_CF!H:H, MATCH("*" & $A59 & "*", S24_CF!$A:$A, 0))} -> Basic One-Day [$1000.00]
A60: Electric Reliability Council of Texas (ERCOT) | B60: Government/Non-profit | D60: 800 | F60: =COUNTIF(S26_Emp!$C:$C,"*" &A60 & "*") -> 0 | G60: =COUNTIF(F25_Emp!$C:$C,"*" &#REF! & "*") -> 0 | H60: =COUNTIF(S25_Emp!$C:$C,"*" & A60 & "*") -> 0 | I60: =COUNTIF(F24_Emp!$C:$C,"*" & B60 & "*") -> 0 | J60: =COUNTIF(S24_Emp!$C:$C,"*" & $A60 & "*") -> 1 | K60: =COUNTIF(F23_Emp!$C:$C,"*" & $A60 & "*") -> 2 | L60: =COUNTIF(S23_Emp!$C:$C,"*" & $A60 & "*") -> 1 | M60: =COUNTIF(F22_Emp!$C:$C,"*" & $A60 & "*") -> 0 | N60: =COUNTIF(S22_Emp!$C:$C,"*" & $A60 & "*") -> 0 | O60: =COUNTIFS(S22_Emp!$C:$C,"*" & $A60 & "*", S22_S25_Emp!$B:$B, "Bachelor") -> #VALUE! | P60: =COUNTIFS(S22_Emp!$C:$C,"*" & $A60 & "*", S22_S25_Emp!$B:$B, "Master") -> #VALUE! | Q60: =COUNTIFS(S22_Emp!$C:$C,"*" & $A60 & "*", S22_S25_Emp!$B:$B, "Doctorate") -> #VALUE! | R60: {=IF(OR(INDEX(S26_CF!X:X, MATCH("*" & $A60 & "*", CompanyList!A:A, 0))=TRUE, INDEX(F25_CF!P:P, MATCH("*" & $A60 & "*", CompanyList!A:A, 0))=TRUE, INDEX(S25_CF!T:T, MATCH("*" & $A60 & "*", CompanyList!A:A, 0))=TRUE, INDEX(S24_CF!W:W, MATCH("*" & $A60 & "*", CompanyList!A:A, 0))=TRUE), "Yes", "No")} -> Yes | S60: =IF(COUNTIF(S26_CF!$A:$A,"*" & $A60 & "*") <> 0, "Yes", "No") -> Yes | T60: {=INDEX(S26_CF!K:K, MATCH("*" & $A60 & "*", S26_CF!A:A, 0))} -> Basic One-Day: Thursday, January 29th [$1000.00] | U60: =IF(COUNTIF(F25_CF!$A:$A,"*" & $A60 & "*") <> 0, "Yes", "No") -> Yes | V60: {=INDEX(F25_CF!I:I, MATCH("*" & $A60 & "*", F25_CF!$A:$A, 0))} -> Basic One-Day: Wednesday, September 10th [$1000.00] | W60: =IF(COUNTIF(S25_CF!$A:$A,"*" & $A60 & "*") <> 0, "Yes", "No") -> Yes | X60: {=INDEX(S25_CF!J:J, MATCH("*" & $A60 & "*", S25_CF!$A:$A, 0))} -> Basic One-Day: Thursday, January 23rd [$1000.00] | Y60: =IF(COUNTIF(F24_CF!$A:$A,"*" & $A60 & "*") <> 0, "Yes", "No") -> Yes | Z60: {=INDEX(F24_CF!N:N, MATCH("*" & $A60 & "*", F24_CF!$A:$A, 0))} -> Basic One-Day: Wednesday, September 4th [$1000.00] | AA60: =IF(COUNTIF(S24_CF!$A:$A,"*" & $A60 & "*") <> 0, "Yes", "No") -> Yes | AB60: {=INDEX(S24_CF!H:H, MATCH("*" & $A60 & "*", S24_CF!$A:$A, 0))} -> Basic One-Day [$1000.00]
A61: Electronic Power Design (EPD) | B61: Private | F61: =COUNTIF(S26_Emp!$C:$C,"*" &A61 & "*") -> 0 | G61: =COUNTIF(F25_Emp!$C:$C,"*" &#REF! & "*") -> 0 | H61: =COUNTIF(S25_Emp!$C:$C,"*" & A61 & "*") -> 0 | I61: =COUNTIF(F24_Emp!$C:$C,"*" & B61 & "*") -> 0 | J61: =COUNTIF(S24_Emp!$C:$C,"*" & $A61 & "*") -> 0 | K61: =COUNTIF(F23_Emp!$C:$C,"*" & $A61 & "*") -> 0 | L61: =COUNTIF(S23_Emp!$C:$C,"*" & $A61 & "*") -> 0 | M61: =COUNTIF(F22_Emp!$C:$C,"*" & $A61 & "*") -> 0 | N61: =COUNTIF(S22_Emp!$C:$C,"*" & $A61 & "*") -> 0 | O61: =COUNTIFS(S22_Emp!$C:$C,"*" & $A61 & "*", S22_S25_Emp!$B:$B, "Bachelor") -> #VALUE! | P61: =COUNTIFS(S22_Emp!$C:$C,"*" & $A61 & "*", S22_S25_Emp!$B:$B, "Master") -> #VALUE! | Q61: =COUNTIFS(S22_Emp!$C:$C,"*" & $A61 & "*", S22_S25_Emp!$B:$B, "Doctorate") -> #VALUE! | R61: {=IF(OR(INDEX(S26_CF!X:X, MATCH("*" & $A61 & "*", CompanyList!A:A, 0))=TRUE, INDEX(F25_CF!P:P, MATCH("*" & $A61 & "*", CompanyList!A:A, 0))=TRUE, INDEX(S25_CF!T:T, MATCH("*" & $A61 & "*", CompanyList!A:A, 0))=TRUE, INDEX(S24_CF!W:W, MATCH("*" & $A61 & "*", CompanyList!A:A, 0))=TRUE), "Yes", "No")} -> No | S61: =IF(COUNTIF(S26_CF!$A:$A,"*" & $A61 & "*") <> 0, "Yes", "No") -> Yes | T61: {=INDEX(S26_CF!K:K, MATCH("*" & $A61 & "*", S26_CF!A:A, 0))} -> Silver Two-Day [$3000.00] | U61: =IF(COUNTIF(F25_CF!$A:$A,"*" & $A61 & "*") <> 0, "Yes", "No") -> No | V61: {=INDEX(F25_CF!I:I, MATCH("*" & $A61 & "*", F25_CF!$A:$A, 0))} -> #N/A | W61: =IF(COUNTIF(S25_CF!$A:$A,"*" & $A61 & "*") <> 0, "Yes", "No") -> Yes | X61: {=INDEX(S25_CF!J:J, MATCH("*" & $A61 & "*", S25_CF!$A:$A, 0))} -> Gold Two-Day [$5500.00] | Y61: =IF(COUNTIF(F24_CF!$A:$A,"*" & $A61 & "*") <> 0, "Yes", "No") -> No | Z61: {=INDEX(F24_CF!N:N, MATCH("*" & $A61 & "*", F24_CF!$A:$A, 0))} -> #N/A | AA61: =IF(COUNTIF(S24_CF!$A:$A,"*" & $A61 & "*") <> 0, "Yes", "No") -> Yes | AB61: {=INDEX(S24_CF!H:H, MATCH("*" & $A61 & "*", S24_CF!$A:$A, 0))} -> Silver Two-Day [$3000.00]
A62: Elevation Land Solutions | B62: Private | F62: =COUNTIF(S26_Emp!$C:$C,"*" &A62 & "*") -> 0 | G62: =COUNTIF(F25_Emp!$C:$C,"*" &#REF! & "*") -> 0 | H62: =COUNTIF(S25_Emp!$C:$C,"*" & A62 & "*") -> 1 | I62: =COUNTIF(F24_Emp!$C:$C,"*" & B62 & "*") -> 0 | J62: =COUNTIF(S24_Emp!$C:$C,"*" & $A62 & "*") -> 1 | K62: =COUNTIF(F23_Emp!$C:$C,"*" & $A62 & "*") -> 0 | L62: =COUNTIF(S23_Emp!$C:$C,"*" & $A62 & "*") -> 0 | M62: =COUNTIF(F22_Emp!$C:$C,"*" & $A62 & "*") -> 0 | N62: =COUNTIF(S22_Emp!$C:$C,"*" & $A62 & "*") -> 1 | O62: =COUNTIFS(S22_Emp!$C:$C,"*" & $A62 & "*", S22_S25_Emp!$B:$B, "Bachelor") -> #VALUE! | P62: =COUNTIFS(S22_Emp!$C:$C,"*" & $A62 & "*", S22_S25_Emp!$B:$B, "Master") -> #VALUE! | Q62: =COUNTIFS(S22_Emp!$C:$C,"*" & $A62 & "*", S22_S25_Emp!$B:$B, "Doctorate") -> #VALUE! | R62: {=IF(OR(INDEX(S26_CF!X:X, MATCH("*" & $A62 & "*", CompanyList!A:A, 0))=TRUE, INDEX(F25_CF!P:P, MATCH("*" & $A62 & "*", CompanyList!A:A, 0))=TRUE, INDEX(S25_CF!T:T, MATCH("*" & $A62 & "*", CompanyList!A:A, 0))=TRUE, INDEX(S24_CF!W:W, MATCH("*" & $A62 & "*", CompanyList!A:A, 0))=TRUE), "Yes", "No")} -> No | S62: =IF(COUNTIF(S26_CF!$A:$A,"*" & $A62 & "*") <> 0, "Yes", "No") -> Yes | T62: {=INDEX(S26_CF!K:K, MATCH("*" & $A62 & "*", S26_CF!A:A, 0))} -> Basic Two-Day [$2000.00] | U62: =IF(COUNTIF(F25_CF!$A:$A,"*" & $A62 & "*") <> 0, "Yes", "No") -> No | V62: {=INDEX(F25_CF!I:I, MATCH("*" & $A62 & "*", F25_CF!$A:$A, 0))} -> #N/A | W62: =IF(COUNTIF(S25_CF!$A:$A,"*" & $A62 & "*") <> 0, "Yes", "No") -> Yes | X62: {=INDEX(S25_CF!J:J, MATCH("*" & $A62 & "*", S25_CF!$A:$A, 0))} -> Basic One-Day: Thursday, January 23rd [$1000.00] | Y62: =IF(COUNTIF(F24_CF!$A:$A,"*" & $A62 & "*") <> 0, "Yes", "No") -> Yes | Z62: {=INDEX(F24_CF!N:N, MATCH("*" & $A62 & "*", F24_CF!$A:$A, 0))} -> Basic One-Day: Wednesday, September 4th [$1000.00] | AA62: =IF(COUNTIF(S24_CF!$A:$A,"*" & $A62 & "*") <> 0, "Yes", "No") -> Yes | AB62: {=INDEX(S24_CF!H:H, MATCH("*" & $A62 & "*", S24_CF!$A:$A, 0))} -> Basic One-Day [$1000.00]
A63: Enercon Services, Inc. | B63: Private | F63: =COUNTIF(S26_Emp!$C:$C,"*" &A63 & "*") -> 0 | G63: =COUNTIF(F25_Emp!$C:$C,"*" &#REF! & "*") -> 0 | H63: =COUNTIF(S25_Emp!$C:$C,"*" & A63 & "*") -> 0 | I63: =COUNTIF(F24_Emp!$C:$C,"*" & B63 & "*") -> 0 | J63: =COUNTIF(S24_Emp!$C:$C,"*" & $A63 & "*") -> 1 | K63: =COUNTIF(F23_Emp!$C:$C,"*" & $A63 & "*") -> 0 | L63: =COUNTIF(S23_Emp!$C:$C,"*" & $A63 & "*") -> 0 | M63: =COUNTIF(F22_Emp!$C:$C,"*" & $A63 & "*") -> 0 | N63: =COUNTIF(S22_Emp!$C:$C,"*" & $A63 & "*") -> 0 | O63: =COUNTIFS(S22_Emp!$C:$C,"*" & $A63 & "*", S22_S25_Emp!$B:$B, "Bachelor") -> #VALUE! | P63: =COUNTIFS(S22_Emp!$C:$C,"*" & $A63 & "*", S22_S25_Emp!$B:$B, "Master") -> #VALUE! | Q63: =COUNTIFS(S22_Emp!$C:$C,"*" & $A63 & "*", S22_S25_Emp!$B:$B, "Doctorate") -> #VALUE! | R63: {=IF(OR(INDEX(S26_CF!X:X, MATCH("*" & $A63 & "*", CompanyList!A:A, 0))=TRUE, INDEX(F25_CF!P:P, MATCH("*" & $A63 & "*", CompanyList!A:A, 0))=TRUE, INDEX(S25_CF!T:T, MATCH("*" & $A63 & "*", CompanyList!A:A, 0))=TRUE, INDEX(S24_CF!W:W, MATCH("*" & $A63 & "*", CompanyList!A:A, 0))=TRUE), "Yes", "No")} -> Yes | S63: =IF(COUNTIF(S26_CF!$A:$A,"*" & $A63 & "*") <> 0, "Yes", "No") -> Yes | T63: {=INDEX(S26_CF!K:K, MATCH("*" & $A63 & "*", S26_CF!A:A, 0))} -> Basic One-Day: Wednesday, January 28th [$1000.00] | U63: =IF(COUNTIF(F25_CF!$A:$A,"*" & $A63 & "*") <> 0, "Yes", "No") -> Yes | V63: {=INDEX(F25_CF!I:I, MATCH("*" & $A63 & "*", F25_CF!$A:$A, 0))} -> Basic One-Day: Wednesday, September 10th [$1000.00] | W63: =IF(COUNTIF(S25_CF!$A:$A,"*" & $A63 & "*") <> 0, "Yes", "No") -> Yes | X63: {=INDEX(S25_CF!J:J, MATCH("*" & $A63 & "*", S25_CF!$A:$A, 0))} -> Basic One-Day: Thursday, January 23rd [$1000.00] | Y63: =IF(COUNTIF(F24_CF!$A:$A,"*" & $A63 & "*") <> 0, "Yes", "No") -> Yes | Z63: {=INDEX(F24_CF!N:N, MATCH("*" & $A63 & "*", F24_CF!$A:$A, 0))} -> Basic One-Day: Thursday, September 5th [$1000.00] | AA63: =IF(COUNTIF(S24_CF!$A:$A,"*" & $A63 & "*") <> 0, "Yes", "No") -> Yes | AB63: {=INDEX(S24_CF!H:H, MATCH("*" & $A63 & "*", S24_CF!$A:$A, 0))} -> Basic One-Day [$1000.00]
A64: Engineering Consulting Services (ECS) | B64: Private | F64: =COUNTIF(S26_Emp!$C:$C,"*" &A64 & "*") -> 0 | G64: =COUNTIF(F25_Emp!$C:$C,"*" &#REF! & "*") -> 0 | H64: =COUNTIF(S25_Emp!$C:$C,"*" & A64 & "*") -> 0 | I64: =COUNTIF(F24_Emp!$C:$C,"*" & B64 & "*") -> 0 | J64: =COUNTIF(S24_Emp!$C:$C,"*" & $A64 & "*") -> 0 | K64: =COUNTIF(F23_Emp!$C:$C,"*" & $A64 & "*") -> 0 | L64: =COUNTIF(S23_Emp!$C:$C,"*" & $A64 & "*") -> 0 | M64: =COUNTIF(F22_Emp!$C:$C,"*" & $A64 & "*") -> 0 | N64: =COUNTIF(S22_Emp!$C:$C,"*" & $A64 & "*") -> 0 | O64: =COUNTIFS(S22_Emp!$C:$C,"*" & $A64 & "*", S22_S25_Emp!$B:$B, "Bachelor") -> #VALUE! | P64: =COUNTIFS(S22_Emp!$C:$C,"*" & $A64 & "*", S22_S25_Emp!$B:$B, "Master") -> #VALUE! | Q64: =COUNTIFS(S22_Emp!$C:$C,"*" & $A64 & "*", S22_S25_Emp!$B:$B, "Doctorate") -> #VALUE! | R64: {=IF(OR(INDEX(S26_CF!X:X, MATCH("*" & $A64 & "*", CompanyList!A:A, 0))=TRUE, INDEX(F25_CF!P:P, MATCH("*" & $A64 & "*", CompanyList!A:A, 0))=TRUE, INDEX(S25_CF!T:T, MATCH("*" & $A64 & "*", CompanyList!A:A, 0))=TRUE, INDEX(S24_CF!W:W, MATCH("*" & $A64 & "*", CompanyList!A:A, 0))=TRUE), "Yes", "No")} -> No | S64: =IF(COUNTIF(S26_CF!$A:$A,"*" & $A64 & "*") <> 0, "Yes", "No") -> Yes | T64: {=INDEX(S26_CF!K:K, MATCH("*" & $A64 & "*", S26_CF!A:A, 0))} -> Basic One-Day: Wednesday, January 28th [$1000.00] | U64: =IF(COUNTIF(F25_CF!$A:$A,"*" & $A64 & "*") <> 0, "Yes", "No") -> Yes | V64: {=INDEX(F25_CF!I:I, MATCH("*" & $A64 & "*", F25_CF!$A:$A, 0))} -> Basic One-Day: Wednesday, September 10th [$1000.00] | W64: =IF(COUNTIF(S25_CF!$A:$A,"*" & $A64 & "*") <> 0, "Yes", "No") -> Yes | X64: {=INDEX(S25_CF!J:J, MATCH("*" & $A64 & "*", S25_CF!$A:$A, 0))} -> Basic One-Day: Wednesday, January 22nd [$1000.00] | Y64: =IF(COUNTIF(F24_CF!$A:$A,"*" & $A64 & "*") <> 0, "Yes", "No") -> Yes | Z64: {=INDEX(F24_CF!N:N, MATCH("*" & $A64 & "*", F24_CF!$A:$A, 0))} -> Basic One-Day: Thursday, September 5th [$1000.00] | AA64: =IF(COUNTIF(S24_CF!$A:$A,"*" & $A64 & "*") <> 0, "Yes", "No") -> Yes | AB64: {=INDEX(S24_CF!H:H, MATCH("*" & $A64 & "*", S24_CF!$A:$A, 0))} -> Basic One-Day [$1000.00]
A65: Engineering Dynamics Inc. | B65: Private | F65: =COUNTIF(S26_Emp!$C:$C,"*" &A65 & "*") -> 0 | G65: =COUNTIF(F25_Emp!$C:$C,"*" &#REF! & "*") -> 0 | H65: =COUNTIF(S25_Emp!$C:$C,"*" & A65 & "*") -> 0 | I65: =COUNTIF(F24_Emp!$C:$C,"*" & B65 & "*") -> 0 | J65: =COUNTIF(S24_Emp!$C:$C,"*" & $A65 & "*") -> 0 | K65: =COUNTIF(F23_Emp!$C:$C,"*" & $A65 & "*") -> 0 | L65: =COUNTIF(S23_Emp!$C:$C,"*" & $A65 & "*") -> 0 | M65: =COUNTIF(F22_Emp!$C:$C,"*" & $A65 & "*") -> 0 | N65: =COUNTIF(S22_Emp!$C:$C,"*" & $A65 & "*") -> 0 | O65: =COUNTIFS(S22_Emp!$C:$C,"*" & $A65 & "*", S22_S25_Emp!$B:$B, "Bachelor") -> #VALUE! | P65: =COUNTIFS(S22_Emp!$C:$C,"*" & $A65 & "*", S22_S25_Emp!$B:$B, "Master") -> #VALUE! | Q65: =COUNTIFS(S22_Emp!$C:$C,"*" & $A65 & "*", S22_S25_Emp!$B:$B, "Doctorate") -> #VALUE! | R65: {=IF(OR(INDEX(S26_CF!X:X, MATCH("*" & $A65 & "*", CompanyList!A:A, 0))=TRUE, INDEX(F25_CF!P:P, MATCH("*" & $A65 & "*", CompanyList!A:A, 0))=TRUE, INDEX(S25_CF!T:T, MATCH("*" & $A65 & "*", CompanyList!A:A, 0))=TRUE, INDEX(S24_CF!W:W, MATCH("*" & $A65 & "*", CompanyList!A:A, 0))=TRUE), "Yes", "No")} -> Yes | S65: =IF(COUNTIF(S26_CF!$A:$A,"*" & $A65 & "*") <> 0, "Yes", "No") -> No | T65: {=INDEX(S26_CF!K:K, MATCH("*" & $A65 & "*", S26_CF!A:A, 0))} -> #N/A | U65: =IF(COUNTIF(F25_CF!$A:$A,"*" & $A65 & "*") <> 0, "Yes", "No") -> No | V65: {=INDEX(F25_CF!I:I, MATCH("*" & $A65 & "*", F25_CF!$A:$A, 0))} -> #N/A | W65: =IF(COUNTIF(S25_CF!$A:$A,"*" & $A65 & "*") <> 0, "Yes", "No") -> Yes | X65: {=INDEX(S25_CF!J:J, MATCH("*" & $A65 & "*", S25_CF!$A:$A, 0))} -> Basic One-Day: Thursday, January 23rd [$1000.00] | Y65: =IF(COUNTIF(F24_CF!$A:$A,"*" & $A65 & "*") <> 0, "Yes", "No") -> Yes | Z65: {=INDEX(F24_CF!N:N, MATCH("*" & $A65 & "*", F24_CF!$A:$A, 0))} -> Basic One-Day: Thursday, September 5th [$1000.00] | AA65: =IF(COUNTIF(S24_CF!$A:$A,"*" & $A65 & "*") <> 0, "Yes", "No") -> Yes | AB65: {=INDEX(S24_CF!H:H, MATCH("*" & $A65 & "*", S24_CF!$A:$A, 0))} -> Basic One-Day [$1000.00]
A66: ENTACT, LLC | B66: Private | F66: =COUNTIF(S26_Emp!$C:$C,"*" &A66 & "*") -> 0 | G66: =COUNTIF(F25_Emp!$C:$C,"*" &#REF! & "*") -> 0 | H66: =COUNTIF(S25_Emp!$C:$C,"*" & A66 & "*") -> 0 | I66: =COUNTIF(F24_Emp!$C:$C,"*" & B66 & "*") -> 0 | J66: =COUNTIF(S24_Emp!$C:$C,"*" & $A66 & "*") -> 0 | K66: =COUNTIF(F23_Emp!$C:$C,"*" & $A66 & "*") -> 0 | L66: =COUNTIF(S23_Emp!$C:$C,"*" & $A66 & "*") -> 0 | M66: =COUNTIF(F22_Emp!$C:$C,"*" & $A66 & "*") -> 0 | N66: =COUNTIF(S22_Emp!$C:$C,"*" & $A66 & "*") -> 0 | O66: =COUNTIFS(S22_Emp!$C:$C,"*" & $A66 & "*", S22_S25_Emp!$B:$B, "Bachelor") -> #VALUE! | P66: =COUNTIFS(S22_Emp!$C:$C,"*" & $A66 & "*", S22_S25_Emp!$B:$B, "Master") -> #VALUE! | Q66: =COUNTIFS(S22_Emp!$C:$C,"*" & $A66 & "*", S22_S25_Emp!$B:$B, "Doctorate") -> #VALUE! | R66: {=IF(OR(INDEX(S26_CF!X:X, MATCH("*" & $A66 & "*", CompanyList!A:A, 0))=TRUE, INDEX(F25_CF!P:P, MATCH("*" & $A66 & "*", CompanyList!A:A, 0))=TRUE, INDEX(S25_CF!T:T, MATCH("*" & $A66 & "*", CompanyList!A:A, 0))=TRUE, INDEX(S24_CF!W:W, MATCH("*" & $A66 & "*", CompanyList!A:A, 0))=TRUE), "Yes", "No")} -> No | S66: =IF(COUNTIF(S26_CF!$A:$A,"*" & $A66 & "*") <> 0, "Yes", "No") -> Yes | T66: {=INDEX(S26_CF!K:K, MATCH("*" & $A66 & "*", S26_CF!A:A, 0))} -> Basic Two-Day [$2000.00] | U66: =IF(COUNTIF(F25_CF!$A:$A,"*" & $A66 & "*") <> 0, "Yes", "No") -> Yes | V66: {=INDEX(F25_CF!I:I, MATCH("*" & $A66 & "*", F25_CF!$A:$A, 0))} -> Silver Two-Day [$3000.00] | W66: =IF(COUNTIF(S25_CF!$A:$A,"*" & $A66 & "*") <> 0, "Yes", "No") -> No | X66: {=INDEX(S25_CF!J:J, MATCH("*" & $A66 & "*", S25_CF!$A:$A, 0))} -> #N/A | Y66: =IF(COUNTIF(F24_CF!$A:$A,"*" & $A66 & "*") <> 0, "Yes", "No") -> Yes | Z66: {=INDEX(F24_CF!N:N, MATCH("*" & $A66 & "*", F24_CF!$A:$A, 0))} -> Gold One-Day: Thursday, September 5th [$2500.00] | AA66: =IF(COUNTIF(S24_CF!$A:$A,"*" & $A66 & "*") <> 0, "Yes", "No") -> Yes | AB66: {=INDEX(S24_CF!H:H, MATCH("*" & $A66 & "*", S24_CF!$A:$A, 0))} -> Gold Two-Day [$5000.00]
A67: Entergy Enterprises, Inc. | B67: Public | C67: 12000 | D67: 12000 | E67: 23 | F67: =COUNTIF(S26_Emp!$C:$C,"*" &A67 & "*") -> 0 | G67: =COUNTIF(F25_Emp!$C:$C,"*" &#REF! & "*") -> 0 | H67: =COUNTIF(S25_Emp!$C:$C,"*" & A67 & "*") -> 0 | I67: =COUNTIF(F24_Emp!$C:$C,"*" & B67 & "*") -> 1 | J67: =COUNTIF(S24_Emp!$C:$C,"*" & $A67 & "*") -> 0 | K67: =COUNTIF(F23_Emp!$C:$C,"*" & $A67 & "*") -> 0 | L67: =COUNTIF(S23_Emp!$C:$C,"*" & $A67 & "*") -> 0 | M67: =COUNTIF(F22_Emp!$C:$C,"*" & $A67 & "*") -> 0 | N67: =COUNTIF(S22_Emp!$C:$C,"*" & $A67 & "*") -> 0 | O67: =COUNTIFS(S22_Emp!$C:$C,"*" & $A67 & "*", S22_S25_Emp!$B:$B, "Bachelor") -> #VALUE! | P67: =COUNTIFS(S22_Emp!$C:$C,"*" & $A67 & "*", S22_S25_Emp!$B:$B, "Master") -> #VALUE! | Q67: =COUNTIFS(S22_Emp!$C:$C,"*" & $A67 & "*", S22_S25_Emp!$B:$B, "Doctorate") -> #VALUE! | R67: {=IF(OR(INDEX(S26_CF!X:X, MATCH("*" & $A67 & "*", CompanyList!A:A, 0))=TRUE, INDEX(F25_CF!P:P, MATCH("*" & $A67 & "*", CompanyList!A:A, 0))=TRUE, INDEX(S25_CF!T:T, MATCH("*" & $A67 & "*", CompanyList!A:A, 0))=TRUE, INDEX(S24_CF!W:W, MATCH("*" & $A67 & "*", CompanyList!A:A, 0))=TRUE), "Yes", "No")} -> Yes | S67: =IF(COUNTIF(S26_CF!$A:$A,"*" & $A67 & "*") <> 0, "Yes", "No") -> No | T67: {=INDEX(S26_CF!K:K, MATCH("*" & $A67 & "*", S26_CF!A:A, 0))} -> #N/A | U67: =IF(COUNTIF(F25_CF!$A:$A,"*" & $A67 & "*") <> 0, "Yes", "No") -> No | V67: {=INDEX(F25_CF!I:I, MATCH("*" & $A67 & "*", F25_CF!$A:$A, 0))} -> #N/A | W67: =IF(COUNTIF(S25_CF!$A:$A,"*" & $A67 & "*") <> 0, "Yes", "No") -> No | X67: {=INDEX(S25_CF!J:J, MATCH("*" & $A67 & "*", S25_CF!$A:$A, 0))} -> #N/A | Y67: =IF(COUNTIF(F24_CF!$A:$A,"*" & $A67 & "*") <> 0, "Yes", "No") -> No | Z67: {=INDEX(F24_CF!N:N, MATCH("*" & $A67 & "*", F24_CF!$A:$A, 0))} -> #N/A | AA67: =IF(COUNTIF(S24_CF!$A:$A,"*" & $A67 & "*") <> 0, "Yes", "No") -> Yes | AB67: {=INDEX(S24_CF!H:H, MATCH("*" & $A67 & "*", S24_CF!$A:$A, 0))} -> Gold One-Day [$2500.00]
A68: Enterprise Products Company | B68: Public | C68: 49000 | D68: 7300 | E68: 63 | F68: =COUNTIF(S26_Emp!$C:$C,"*" &A68 & "*") -> 0 | G68: =COUNTIF(F25_Emp!$C:$C,"*" &#REF! & "*") -> 0 | H68: =COUNTIF(S25_Emp!$C:$C,"*" & A68 & "*") -> 0 | I68: =COUNTIF(F24_Emp!$C:$C,"*" & B68 & "*") -> 1 | J68: =COUNTIF(S24_Emp!$C:$C,"*" & $A68 & "*") -> 0 | K68: =COUNTIF(F23_Emp!$C:$C,"*" & $A68 & "*") -> 2 | L68: =COUNTIF(S23_Emp!$C:$C,"*" & $A68 & "*") -> 1 | M68: =COUNTIF(F22_Emp!$C:$C,"*" & $A68 & "*") -> 0 | N68: =COUNTIF(S22_Emp!$C:$C,"*" & $A68 & "*") -> 0 | O68: =COUNTIFS(S22_Emp!$C:$C,"*" & $A68 & "*", S22_S25_Emp!$B:$B, "Bachelor") -> #VALUE! | P68: =COUNTIFS(S22_Emp!$C:$C,"*" & $A68 & "*", S22_S25_Emp!$B:$B, "Master") -> #VALUE! | Q68: =COUNTIFS(S22_Emp!$C:$C,"*" & $A68 & "*", S22_S25_Emp!$B:$B, "Doctorate") -> #VALUE! | R68: {=IF(OR(INDEX(S26_CF!X:X, MATCH("*" & $A68 & "*", CompanyList!A:A, 0))=TRUE, INDEX(F25_CF!P:P, MATCH("*" & $A68 & "*", CompanyList!A:A, 0))=TRUE, INDEX(S25_CF!T:T, MATCH("*" & $A68 & "*", CompanyList!A:A, 0))=TRUE, INDEX(S24_CF!W:W, MATCH("*" & $A68 & "*", CompanyList!A:A, 0))=TRUE), "Yes", "No")} -> No | S68: =IF(COUNTIF(S26_CF!$A:$A,"*" & $A68 & "*") <> 0, "Yes", "No") -> Yes | T68: {=INDEX(S26_CF!K:K, MATCH("*" & $A68 & "*", S26_CF!A:A, 0))} -> Basic One-Day: Wednesday, January 28th [$1000.00] | U68: =IF(COUNTIF(F25_CF!$A:$A,"*" & $A68 & "*") <> 0, "Yes", "No") -> Yes | V68: {=INDEX(F25_CF!I:I, MATCH("*" & $A68 & "*", F25_CF!$A:$A, 0))} -> Gold One-Day: Wednesday, September 10th [$2500.00] | W68: =IF(COUNTIF(S25_CF!$A:$A,"*" & $A68 & "*") <> 0, "Yes", "No") -> Yes | X68: {=INDEX(S25_CF!J:J, MATCH("*" & $A68 & "*", S25_CF!$A:$A, 0))} -> Basic Two-Day [$2000.00] | Y68: =IF(COUNTIF(F24_CF!$A:$A,"*" & $A68 & "*") <> 0, "Yes", "No") -> Yes | Z68: {=INDEX(F24_CF!N:N, MATCH("*" & $A68 & "*", F24_CF!$A:$A, 0))} -> Gold One-Day: Wednesday, September 4th [$2500.00] | AA68: =IF(COUNTIF(S24_CF!$A:$A,"*" & $A68 & "*") <> 0, "Yes", "No") -> Yes | AB68: {=INDEX(S24_CF!H:H, MATCH("*" & $A68 & "*", S24_CF!$A:$A, 0))} -> Basic Two-Day [$2000.00]
A69: Epic | B69: Private | F69: =COUNTIF(S26_Emp!$C:$C,"*" &A69 & "*") -> 0 | G69: =COUNTIF(F25_Emp!$C:$C,"*" &#REF! & "*") -> 0 | H69: =COUNTIF(S25_Emp!$C:$C,"*" & A69 & "*") -> 8 | I69: =COUNTIF(F24_Emp!$C:$C,"*" & B69 & "*") -> 0 | J69: =COUNTIF(S24_Emp!$C:$C,"*" & $A69 & "*") -> 3 | K69: =COUNTIF(F23_Emp!$C:$C,"*" & $A69 & "*") -> 1 | L69: =COUNTIF(S23_Emp!$C:$C,"*" & $A69 & "*") -> 10 | M69: =COUNTIF(F22_Emp!$C:$C,"*" & $A69 & "*") -> 4 | N69: =COUNTIF(S22_Emp!$C:$C,"*" & $A69 & "*") -> 8 | O69: =COUNTIFS(S22_Emp!$C:$C,"*" & $A69 & "*", S22_S25_Emp!$B:$B, "Bachelor") -> #VALUE! | P69: =COUNTIFS(S22_Emp!$C:$C,"*" & $A69 & "*", S22_S25_Emp!$B:$B, "Master") -> #VALUE! | Q69: =COUNTIFS(S22_Emp!$C:$C,"*" & $A69 & "*", S22_S25_Emp!$B:$B, "Doctorate") -> #VALUE! | R69: {=IF(OR(INDEX(S26_CF!X:X, MATCH("*" & $A69 & "*", CompanyList!A:A, 0))=TRUE, INDEX(F25_CF!P:P, MATCH("*" & $A69 & "*", CompanyList!A:A, 0))=TRUE, INDEX(S25_CF!T:T, MATCH("*" & $A69 & "*", CompanyList!A:A, 0))=TRUE, INDEX(S24_CF!W:W, MATCH("*" & $A69 & "*", CompanyList!A:A, 0))=TRUE), "Yes", "No")} -> Yes | S69: =IF(COUNTIF(S26_CF!$A:$A,"*" & $A69 & "*") <> 0, "Yes", "No") -> Yes | T69: {=INDEX(S26_CF!K:K, MATCH("*" & $A69 & "*", S26_CF!A:A, 0))} -> Basic Two-Day [$2000.00] | U69: =IF(COUNTIF(F25_CF!$A:$A,"*" & $A69 & "*") <> 0, "Yes", "No") -> Yes | V69: {=INDEX(F25_CF!I:I, MATCH("*" & $A69 & "*", F25_CF!$A:$A, 0))} -> Basic Two-Day [$2000.00] | W69: =IF(COUNTIF(S25_CF!$A:$A,"*" & $A69 & "*") <> 0, "Yes", "No") -> Yes | X69: {=INDEX(S25_CF!J:J, MATCH("*" & $A69 & "*", S25_CF!$A:$A, 0))} -> Basic Two-Day [$2000.00] | Y69: =IF(COUNTIF(F24_CF!$A:$A,"*" & $A69 & "*") <> 0, "Yes", "No") -> Yes | Z69: {=INDEX(F24_CF!N:N, MATCH("*" & $A69 & "*", F24_CF!$A:$A, 0))} -> Basic Two-Day [$2000.00] | AA69: =IF(COUNTIF(S24_CF!$A:$A,"*" & $A69 & "*") <> 0, "Yes", "No") -> Yes | AB69: {=INDEX(S24_CF!H:H, MATCH("*" & $A69 & "*", S24_CF!$A:$A, 0))} -> Basic One-Day [$1000.00]
A70: F.H. Paschen | B70: Private | F70: =COUNTIF(S26_Emp!$C:$C,"*" &A70 & "*") -> 0 | G70: =COUNTIF(F25_Emp!$C:$C,"*" &#REF! & "*") -> 0 | H70: =COUNTIF(S25_Emp!$C:$C,"*" & A70 & "*") -> 0 | I70: =COUNTIF(F24_Emp!$C:$C,"*" & B70 & "*") -> 0 | J70: =COUNTIF(S24_Emp!$C:$C,"*" & $A70 & "*") -> 0 | K70: =COUNTIF(F23_Emp!$C:$C,"*" & $A70 & "*") -> 0 | L70: =COUNTIF(S23_Emp!$C:$C,"*" & $A70 & "*") -> 0 | M70: =COUNTIF(F22_Emp!$C:$C,"*" & $A70 & "*") -> 0 | N70: =COUNTIF(S22_Emp!$C:$C,"*" & $A70 & "*") -> 0 | O70: =COUNTIFS(S22_Emp!$C:$C,"*" & $A70 & "*", S22_S25_Emp!$B:$B, "Bachelor") -> #VALUE! | P70: =COUNTIFS(S22_Emp!$C:$C,"*" & $A70 & "*", S22_S25_Emp!$B:$B, "Master") -> #VALUE! | Q70: =COUNTIFS(S22_Emp!$C:$C,"*" & $A70 & "*", S22_S25_Emp!$B:$B, "Doctorate") -> #VALUE! | R70: {=IF(OR(INDEX(S26_CF!X:X, MATCH("*" & $A70 & "*", CompanyList!A:A, 0))=TRUE, INDEX(F25_CF!P:P, MATCH("*" & $A70 & "*", CompanyList!A:A, 0))=TRUE, INDEX(S25_CF!T:T, MATCH("*" & $A70 & "*", CompanyList!A:A, 0))=TRUE, INDEX(S24_CF!W:W, MATCH("*" & $A70 & "*", CompanyList!A:A, 0))=TRUE), "Yes", "No")} -> No | S70: =IF(COUNTIF(S26_CF!$A:$A,"*" & $A70 & "*") <> 0, "Yes", "No") -> Yes | T70: {=INDEX(S26_CF!K:K, MATCH("*" & $A70 & "*", S26_CF!A:A, 0))} -> Basic One-Day: Thursday, January 29th [$1000.00] | U70: =IF(COUNTIF(F25_CF!$A:$A,"*" & $A70 & "*") <> 0, "Yes", "No") -> Yes | V70: {=INDEX(F25_CF!I:I, MATCH("*" & $A70 & "*", F25_CF!$A:$A, 0))} -> Basic One-Day: Thursday, September 11th [$1000.00] | W70: =IF(COUNTIF(S25_CF!$A:$A,"*" & $A70 & "*") <> 0, "Yes", "No") -> Yes | X70: {=INDEX(S25_CF!J:J, MATCH("*" & $A70 & "*", S25_CF!$A:$A, 0))} -> Basic One-Day: Wednesday, January 22nd [$1000.00] | Y70: =IF(COUNTIF(F24_CF!$A:$A,"*" & $A70 & "*") <> 0, "Yes", "No") -> Yes | Z70: {=INDEX(F24_CF!N:N, MATCH("*" & $A70 & "*", F24_CF!$A:$A, 0))} -> Basic One-Day: Thursday, September 5th [$1000.00] | AA70: =IF(COUNTIF(S24_CF!$A:$A,"*" & $A70 & "*") <> 0, "Yes", "No") -> Yes | AB70: {=INDEX(S24_CF!H:H, MATCH("*" & $A70 & "*", S24_CF!$A:$A, 0))} -> Basic One-Day [$1000.00]
A71: Federal Aviation Administration (FAA) | B71: Government | D71: 45000 | F71: =COUNTIF(S26_Emp!$C:$C,"*" &A71 & "*") -> 0 | G71: =COUNTIF(F25_Emp!$C:$C,"*" &#REF! & "*") -> 0 | H71: =COUNTIF(S25_Emp!$C:$C,"*" & A71 & "*") -> 0 | I71: =COUNTIF(F24_Emp!$C:$C,"*" & B71 & "*") -> 0 | J71: =COUNTIF(S24_Emp!$C:$C,"*" & $A71 & "*") -> 1 | K71: =COUNTIF(F23_Emp!$C:$C,"*" & $A71 & "*") -> 1 | L71: =COUNTIF(S23_Emp!$C:$C,"*" & $A71 & "*") -> 2 | M71: =COUNTIF(F22_Emp!$C:$C,"*" & $A71 & "*") -> 0 | N71: =COUNTIF(S22_Emp!$C:$C,"*" & $A71 & "*") -> 0 | O71: =COUNTIFS(S22_Emp!$C:$C,"*" & $A71 & "*", S22_S25_Emp!$B:$B, "Bachelor") -> #VALUE! | P71: =COUNTIFS(S22_Emp!$C:$C,"*" & $A71 & "*", S22_S25_Emp!$B:$B, "Master") -> #VALUE! | Q71: =COUNTIFS(S22_Emp!$C:$C,"*" & $A71 & "*", S22_S25_Emp!$B:$B, "Doctorate") -> #VALUE! | R71: {=IF(OR(INDEX(S26_CF!X:X, MATCH("*" & $A71 & "*", CompanyList!A:A, 0))=TRUE, INDEX(F25_CF!P:P, MATCH("*" & $A71 & "*", CompanyList!A:A, 0))=TRUE, INDEX(S25_CF!T:T, MATCH("*" & $A71 & "*", CompanyList!A:A, 0))=TRUE, INDEX(S24_CF!W:W, MATCH("*" & $A71 & "*", CompanyList!A:A, 0))=TRUE), "Yes", "No")} -> No | S71: =IF(COUNTIF(S26_CF!$A:$A,"*" & $A71 & "*") <> 0, "Yes", "No") -> No | T71: {=INDEX(S26_CF!K:K, MATCH("*" & $A71 & "*", S26_CF!A:A, 0))} -> #N/A | U71: =IF(COUNTIF(F25_CF!$A:$A,"*" & $A71 & "*") <> 0, "Yes", "No") -> Yes | V71: {=INDEX(F25_CF!I:I, MATCH("*" & $A71 & "*", F25_CF!$A:$A, 0))} -> Gold Two-Day [$5500.00] | W71: =IF(COUNTIF(S25_CF!$A:$A,"*" & $A71 & "*") <> 0, "Yes", "No") -> Yes | X71: {=INDEX(S25_CF!J:J, MATCH("*" & $A71 & "*", S25_CF!$A:$A, 0))} -> Gold Two-Day [$5500.00] | Y71: =IF(COUNTIF(F24_CF!$A:$A,"*" & $A71 & "*") <> 0, "Yes", "No") -> Yes | Z71: {=INDEX(F24_CF!N:N, MATCH("*" & $A71 & "*", F24_CF!$A:$A, 0))} -> Gold Two-Day [$5500.00] | AA71: =IF(COUNTIF(S24_CF!$A:$A,"*" & $A71 & "*") <> 0, "Yes", "No") -> Yes | AB71: {=INDEX(S24_CF!H:H, MATCH("*" & $A71 & "*", S24_CF!$A:$A, 0))} -> Gold Two-Day [$5000.00]
A72: Ferrovial Construction | B72: Private | F72: =COUNTIF(S26_Emp!$C:$C,"*" &A72 & "*") -> 0 | G72: =COUNTIF(F25_Emp!$C:$C,"*" &#REF! & "*") -> 0 | H72: =COUNTIF(S25_Emp!$C:$C,"*" & A72 & "*") -> 0 | I72: =COUNTIF(F24_Emp!$C:$C,"*" & B72 & "*") -> 0 | J72: =COUNTIF(S24_Emp!$C:$C,"*" & $A72 & "*") -> 0 | K72: =COUNTIF(F23_Emp!$C:$C,"*" & $A72 & "*") -> 0 | L72: =COUNTIF(S23_Emp!$C:$C,"*" & $A72 & "*") -> 0 | M72: =COUNTIF(F22_Emp!$C:$C,"*" & $A72 & "*") -> 0 | N72: =COUNTIF(S22_Emp!$C:$C,"*" & $A72 & "*") -> 0 | O72: =COUNTIFS(S22_Emp!$C:$C,"*" & $A72 & "*", S22_S25_Emp!$B:$B, "Bachelor") -> #VALUE! | P72: =COUNTIFS(S22_Emp!$C:$C,"*" & $A72 & "*", S22_S25_Emp!$B:$B, "Master") -> #VALUE! | Q72: =COUNTIFS(S22_Emp!$C:$C,"*" & $A72 & "*", S22_S25_Emp!$B:$B, "Doctorate") -> #VALUE! | R72: {=IF(OR(INDEX(S26_CF!X:X, MATCH("*" & $A72 & "*", CompanyList!A:A, 0))=TRUE, INDEX(F25_CF!P:P, MATCH("*" & $A72 & "*", CompanyList!A:A, 0))=TRUE, INDEX(S25_CF!T:T, MATCH("*" & $A72 & "*", CompanyList!A:A, 0))=TRUE, INDEX(S24_CF!W:W, MATCH("*" & $A72 & "*", CompanyList!A:A, 0))=TRUE), "Yes", "No")} -> No | S72: =IF(COUNTIF(S26_CF!$A:$A,"*" & $A72 & "*") <> 0, "Yes", "No") -> No | T72: {=INDEX(S26_CF!K:K, MATCH("*" & $A72 & "*", S26_CF!A:A, 0))} -> #N/A | U72: =IF(COUNTIF(F25_CF!$A:$A,"*" & $A72 & "*") <> 0, "Yes", "No") -> No | V72: {=INDEX(F25_CF!I:I, MATCH("*" & $A72 & "*", F25_CF!$A:$A, 0))} -> #N/A | W72: =IF(COUNTIF(S25_CF!$A:$A,"*" & $A72 & "*") <> 0, "Yes", "No") -> No | X72: {=INDEX(S25_CF!J:J, MATCH("*" & $A72 & "*", S25_CF!$A:$A, 0))} -> #N/A | Y72: =IF(COUNTIF(F24_CF!$A:$A,"*" & $A72 & "*") <> 0, "Yes", "No") -> Yes | Z72: {=INDEX(F24_CF!N:N, MATCH("*" & $A72 & "*", F24_CF!$A:$A, 0))} -> Basic Two-Day [$2000.00] | AA72: =IF(COUNTIF(S24_CF!$A:$A,"*" & $A72 & "*") <> 0, "Yes", "No") -> Yes | AB72: {=INDEX(S24_CF!H:H, MATCH("*" & $A72 & "*", S24_CF!$A:$A, 0))} -> Basic Two-Day [$2000.00]
A73: Flowserve Corporation | B73: Public | C73: 4300 | D73: 16000 | E73: 6 | F73: =COUNTIF(S26_Emp!$C:$C,"*" &A73 & "*") -> 0 | G73: =COUNTIF(F25_Emp!$C:$C,"*" &#REF! & "*") -> 0 | H73: =COUNTIF(S25_Emp!$C:$C,"*" & A73 & "*") -> 0 | I73: =COUNTIF(F24_Emp!$C:$C,"*" & B73 & "*") -> 1 | J73: =COUNTIF(S24_Emp!$C:$C,"*" & $A73 & "*") -> 3 | K73: =COUNTIF(F23_Emp!$C:$C,"*" & $A73 & "*") -> 0 | L73: =COUNTIF(S23_Emp!$C:$C,"*" & $A73 & "*") -> 2 | M73: =COUNTIF(F22_Emp!$C:$C,"*" & $A73 & "*") -> 1 | N73: =COUNTIF(S22_Emp!$C:$C,"*" & $A73 & "*") -> 0 | O73: =COUNTIFS(S22_Emp!$C:$C,"*" & $A73 & "*", S22_S25_Emp!$B:$B, "Bachelor") -> #VALUE! | P73: =COUNTIFS(S22_Emp!$C:$C,"*" & $A73 & "*", S22_S25_Emp!$B:$B, "Master") -> #VALUE! | Q73: =COUNTIFS(S22_Emp!$C:$C,"*" & $A73 & "*", S22_S25_Emp!$B:$B, "Doctorate") -> #VALUE! | R73: {=IF(OR(INDEX(S26_CF!X:X, MATCH("*" & $A73 & "*", CompanyList!A:A, 0))=TRUE, INDEX(F25_CF!P:P, MATCH("*" & $A73 & "*", CompanyList!A:A, 0))=TRUE, INDEX(S25_CF!T:T, MATCH("*" & $A73 & "*", CompanyList!A:A, 0))=TRUE, INDEX(S24_CF!W:W, MATCH("*" & $A73 & "*", CompanyList!A:A, 0))=TRUE), "Yes", "No")} -> Yes | S73: =IF(COUNTIF(S26_CF!$A:$A,"*" & $A73 & "*") <> 0, "Yes", "No") -> No | T73: {=INDEX(S26_CF!K:K, MATCH("*" & $A73 & "*", S26_CF!A:A, 0))} -> #N/A | U73: =IF(COUNTIF(F25_CF!$A:$A,"*" & $A73 & "*") <> 0, "Yes", "No") -> Yes | V73: {=INDEX(F25_CF!I:I, MATCH("*" & $A73 & "*", F25_CF!$A:$A, 0))} -> Gold One-Day: Thursday, September 11th [$2500.00] | W73: =IF(COUNTIF(S25_CF!$A:$A,"*" & $A73 & "*") <> 0, "Yes", "No") -> No | X73: {=INDEX(S25_CF!J:J, MATCH("*" & $A73 & "*", S25_CF!$A:$A, 0))} -> #N/A | Y73: =IF(COUNTIF(F24_CF!$A:$A,"*" & $A73 & "*") <> 0, "Yes", "No") -> Yes | Z73: {=INDEX(F24_CF!N:N, MATCH("*" & $A73 & "*", F24_CF!$A:$A, 0))} -> Gold Two-Day [$5500.00] | AA73: =IF(COUNTIF(S24_CF!$A:$A,"*" & $A73 & "*") <> 0, "Yes", "No") -> Yes | AB73: {=INDEX(S24_CF!H:H, MATCH("*" & $A73 & "*", S24_CF!$A:$A, 0))} -> Gold Two-Day [$5000.00]
A74: Fluor Corporation | B74: Public | C74: 15500 | D74: 30000 | E74: 6.5 | F74: =COUNTIF(S26_Emp!$C:$C,"*" &A74 & "*") -> 0 | G74: =COUNTIF(F25_Emp!$C:$C,"*" &#REF! & "*") -> 0 | H74: =COUNTIF(S25_Emp!$C:$C,"*" & A74 & "*") -> 0 | I74: =COUNTIF(F24_Emp!$C:$C,"*" & B74 & "*") -> 1 | J74: =COUNTIF(S24_Emp!$C:$C,"*" & $A74 & "*") -> 5 | K74: =COUNTIF(F23_Emp!$C:$C,"*" & $A74 & "*") -> 2 | L74: =COUNTIF(S23_Emp!$C:$C,"*" & $A74 & "*") -> 2 | M74: =COUNTIF(F22_Emp!$C:$C,"*" & $A74 & "*") -> 2 | N74: =COUNTIF(S22_Emp!$C:$C,"*" & $A74 & "*") -> 0 | O74: =COUNTIFS(S22_Emp!$C:$C,"*" & $A74 & "*", S22_S25_Emp!$B:$B, "Bachelor") -> #VALUE! | P74: =COUNTIFS(S22_Emp!$C:$C,"*" & $A74 & "*", S22_S25_Emp!$B:$B, "Master") -> #VALUE! | Q74: =COUNTIFS(S22_Emp!$C:$C,"*" & $A74 & "*", S22_S25_Emp!$B:$B, "Doctorate") -> #VALUE! | R74: {=IF(OR(INDEX(S26_CF!X:X, MATCH("*" & $A74 & "*", CompanyList!A:A, 0))=TRUE, INDEX(F25_CF!P:P, MATCH("*" & $A74 & "*", CompanyList!A:A, 0))=TRUE, INDEX(S25_CF!T:T, MATCH("*" & $A74 & "*", CompanyList!A:A, 0))=TRUE, INDEX(S24_CF!W:W, MATCH("*" & $A74 & "*", CompanyList!A:A, 0))=TRUE), "Yes", "No")} -> Yes | S74: =IF(COUNTIF(S26_CF!$A:$A,"*" & $A74 & "*") <> 0, "Yes", "No") -> Yes | T74: {=INDEX(S26_CF!K:K, MATCH("*" & $A74 & "*", S26_CF!A:A, 0))} -> Silver Two-Day [$3000.00] | U74: =IF(COUNTIF(F25_CF!$A:$A,"*" & $A74 & "*") <> 0, "Yes", "No") -> Yes | V74: {=INDEX(F25_CF!I:I, MATCH("*" & $A74 & "*", F25_CF!$A:$A, 0))} -> Silver Two-Day [$3000.00] | W74: =IF(COUNTIF(S25_CF!$A:$A,"*" & $A74 & "*") <> 0, "Yes", "No") -> Yes | X74: {=INDEX(S25_CF!J:J, MATCH("*" & $A74 & "*", S25_CF!$A:$A, 0))} -> Silver One-Day: Thursday, January 23rd [$1800.00] | Y74: =IF(COUNTIF(F24_CF!$A:$A,"*" & $A74 & "*") <> 0, "Yes", "No") -> Yes | Z74: {=INDEX(F24_CF!N:N, MATCH("*" & $A74 & "*", F24_CF!$A:$A, 0))} -> Silver Two-Day [$3000.00] | AA74: =IF(COUNTIF(S24_CF!$A:$A,"*" & $A74 & "*") <> 0, "Yes", "No") -> Yes | AB74: {=INDEX(S24_CF!H:H, MATCH("*" & $A74 & "*", S24_CF!$A:$A, 0))} -> Silver Two-Day [$3000.00]
A75: Formosa Plastics Corporation | B75: Public | C75: 6000 | D75: 11000 | E75: 14 | F75: =COUNTIF(S26_Emp!$C:$C,"*" &A75 & "*") -> 0 | G75: =COUNTIF(F25_Emp!$C:$C,"*" &#REF! & "*") -> 0 | H75: =COUNTIF(S25_Emp!$C:$C,"*" & A75 & "*") -> 0 | I75: =COUNTIF(F24_Emp!$C:$C,"*" & B75 & "*") -> 1 | J75: =COUNTIF(S24_Emp!$C:$C,"*" & $A75 & "*") -> 1 | K75: =COUNTIF(F23_Emp!$C:$C,"*" & $A75 & "*") -> 1 | L75: =COUNTIF(S23_Emp!$C:$C,"*" & $A75 & "*") -> 0 | M75: =COUNTIF(F22_Emp!$C:$C,"*" & $A75 & "*") -> 0 | N75: =COUNTIF(S22_Emp!$C:$C,"*" & $A75 & "*") -> 0 | O75: =COUNTIFS(S22_Emp!$C:$C,"*" & $A75 & "*", S22_S25_Emp!$B:$B, "Bachelor") -> #VALUE! | P75: =COUNTIFS(S22_Emp!$C:$C,"*" & $A75 & "*", S22_S25_Emp!$B:$B, "Master") -> #VALUE! | Q75: =COUNTIFS(S22_Emp!$C:$C,"*" & $A75 & "*", S22_S25_Emp!$B:$B, "Doctorate") -> #VALUE! | R75: {=IF(OR(INDEX(S26_CF!X:X, MATCH("*" & $A75 & "*", CompanyList!A:A, 0))=TRUE, INDEX(F25_CF!P:P, MATCH("*" & $A75 & "*", CompanyList!A:A, 0))=TRUE, INDEX(S25_CF!T:T, MATCH("*" & $A75 & "*", CompanyList!A:A, 0))=TRUE, INDEX(S24_CF!W:W, MATCH("*" & $A75 & "*", CompanyList!A:A, 0))=TRUE), "Yes", "No")} -> No | S75: =IF(COUNTIF(S26_CF!$A:$A,"*" & $A75 & "*") <> 0, "Yes", "No") -> Yes | T75: {=INDEX(S26_CF!K:K, MATCH("*" & $A75 & "*", S26_CF!A:A, 0))} -> Basic One-Day: Thursday, January 29th [$1000.00] | U75: =IF(COUNTIF(F25_CF!$A:$A,"*" & $A75 & "*") <> 0, "Yes", "No") -> Yes | V75: {=INDEX(F25_CF!I:I, MATCH("*" & $A75 & "*", F25_CF!$A:$A, 0))} -> Basic One-Day: Thursday, September 11th [$1000.00] | W75: =IF(COUNTIF(S25_CF!$A:$A,"*" & $A75 & "*") <> 0, "Yes", "No") -> No | X75: {=INDEX(S25_CF!J:J, MATCH("*" & $A75 & "*", S25_CF!$A:$A, 0))} -> #N/A | Y75: =IF(COUNTIF(F24_CF!$A:$A,"*" & $A75 & "*") <> 0, "Yes", "No") -> No | Z75: {=INDEX(F24_CF!N:N, MATCH("*" & $A75 & "*", F24_CF!$A:$A, 0))} -> #N/A | AA75: =IF(COUNTIF(S24_CF!$A:$A,"*" & $A75 & "*") <> 0, "Yes", "No") -> Yes | AB75: {=INDEX(S24_CF!H:H, MATCH("*" & $A75 & "*", S24_CF!$A:$A, 0))} -> Basic Two-Day [$2000.00]
A76: Freese and Nichols | B76: Private | F76: =COUNTIF(S26_Emp!$C:$C,"*" &A76 & "*") -> 0 | G76: =COUNTIF(F25_Emp!$C:$C,"*" &#REF! & "*") -> 0 | H76: =COUNTIF(S25_Emp!$C:$C,"*" & A76 & "*") -> 1 | I76: =COUNTIF(F24_Emp!$C:$C,"*" & B76 & "*") -> 0 | J76: =COUNTIF(S24_Emp!$C:$C,"*" & $A76 & "*") -> 3 | K76: =COUNTIF(F23_Emp!$C:$C,"*" & $A76 & "*") -> 2 | L76: =COUNTIF(S23_Emp!$C:$C,"*" & $A76 & "*") -> 2 | M76: =COUNTIF(F22_Emp!$C:$C,"*" & $A76 & "*") -> 1 | N76: =COUNTIF(S22_Emp!$C:$C,"*" & $A76 & "*") -> 3 | O76: =COUNTIFS(S22_Emp!$C:$C,"*" & $A76 & "*", S22_S25_Emp!$B:$B, "Bachelor") -> #VALUE! | P76: =COUNTIFS(S22_Emp!$C:$C,"*" & $A76 & "*", S22_S25_Emp!$B:$B, "Master") -> #VALUE! | Q76: =COUNTIFS(S22_Emp!$C:$C,"*" & $A76 & "*", S22_S25_Emp!$B:$B, "Doctorate") -> #VALUE! | R76: {=IF(OR(INDEX(S26_CF!X:X, MATCH("*" & $A76 & "*", CompanyList!A:A, 0))=TRUE, INDEX(F25_CF!P:P, MATCH("*" & $A76 & "*", CompanyList!A:A, 0))=TRUE, INDEX(S25_CF!T:T, MATCH("*" & $A76 & "*", CompanyList!A:A, 0))=TRUE, INDEX(S24_CF!W:W, MATCH("*" & $A76 & "*", CompanyList!A:A, 0))=TRUE), "Yes", "No")} -> Yes | S76: =IF(COUNTIF(S26_CF!$A:$A,"*" & $A76 & "*") <> 0, "Yes", "No") -> Yes | T76: {=INDEX(S26_CF!K:K, MATCH("*" & $A76 & "*", S26_CF!A:A, 0))} -> Gold Two-Day [$5500.00] | U76: =IF(COUNTIF(F25_CF!$A:$A,"*" & $A76 & "*") <> 0, "Yes", "No") -> Yes | V76: {=INDEX(F25_CF!I:I, MATCH("*" & $A76 & "*", F25_CF!$A:$A, 0))} -> Gold Two-Day [$5500.00] | W76: =IF(COUNTIF(S25_CF!$A:$A,"*" & $A76 & "*") <> 0, "Yes", "No") -> Yes | X76: {=INDEX(S25_CF!J:J, MATCH("*" & $A76 & "*", S25_CF!$A:$A, 0))} -> Gold Two-Day [$5500.00] | Y76: =IF(COUNTIF(F24_CF!$A:$A,"*" & $A76 & "*") <> 0, "Yes", "No") -> Yes | Z76: {=INDEX(F24_CF!N:N, MATCH("*" & $A76 & "*", F24_CF!$A:$A, 0))} -> Gold Two-Day [$5500.00] | AA76: =IF(COUNTIF(S24_CF!$A:$A,"*" & $A76 & "*") <> 0, "Yes", "No") -> Yes | AB76: {=INDEX(S24_CF!H:H, MATCH("*" & $A76 & "*", S24_CF!$A:$A, 0))} -> Gold Two-Day [$5000.00]
A77: FTI Consulting | B77: Public | C77: 3500 | D77: 7800 | E77: 8 | F77: =COUNTIF(S26_Emp!$C:$C,"*" &A77 & "*") -> 0 | G77: =COUNTIF(F25_Emp!$C:$C,"*" &#REF! & "*") -> 0 | H77: =COUNTIF(S25_Emp!$C:$C,"*" & A77 & "*") -> 1 | I77: =COUNTIF(F24_Emp!$C:$C,"*" & B77 & "*") -> 1 | J77: =COUNTIF(S24_Emp!$C:$C,"*" & $A77 & "*") -> 0 | K77: =COUNTIF(F23_Emp!$C:$C,"*" & $A77 & "*") -> 0 | L77: =COUNTIF(S23_Emp!$C:$C,"*" & $A77 & "*") -> 0 | M77: =COUNTIF(F22_Emp!$C:$C,"*" & $A77 & "*") -> 0 | N77: =COUNTIF(S22_Emp!$C:$C,"*" & $A77 & "*") -> 0 | O77: =COUNTIFS(S22_Emp!$C:$C,"*" & $A77 & "*", S22_S25_Emp!$B:$B, "Bachelor") -> #VALUE! | P77: =COUNTIFS(S22_Emp!$C:$C,"*" & $A77 & "*", S22_S25_Emp!$B:$B, "Master") -> #VALUE! | Q77: =COUNTIFS(S22_Emp!$C:$C,"*" & $A77 & "*", S22_S25_Emp!$B:$B, "Doctorate") -> #VALUE! | R77: {=IF(OR(INDEX(S26_CF!X:X, MATCH("*" & $A77 & "*", CompanyList!A:A, 0))=TRUE, INDEX(F25_CF!P:P, MATCH("*" & $A77 & "*", CompanyList!A:A, 0))=TRUE, INDEX(S25_CF!T:T, MATCH("*" & $A77 & "*", CompanyList!A:A, 0))=TRUE, INDEX(S24_CF!W:W, MATCH("*" & $A77 & "*", CompanyList!A:A, 0))=TRUE), "Yes", "No")} -> Yes | S77: =IF(COUNTIF(S26_CF!$A:$A,"*" & $A77 & "*") <> 0, "Yes", "No") -> No | T77: {=INDEX(S26_CF!K:K, MATCH("*" & $A77 & "*", S26_CF!A:A, 0))} -> #N/A | U77: =IF(COUNTIF(F25_CF!$A:$A,"*" & $A77 & "*") <> 0, "Yes", "No") -> Yes | V77: {=INDEX(F25_CF!I:I, MATCH("*" & $A77 & "*", F25_CF!$A:$A, 0))} -> Basic One-Day: Thursday, September 11th [$1000.00] | W77: =IF(COUNTIF(S25_CF!$A:$A,"*" & $A77 & "*") <> 0, "Yes", "No") -> Yes | X77: {=INDEX(S25_CF!J:J, MATCH("*" & $A77 & "*", S25_CF!$A:$A, 0))} -> Basic One-Day: Thursday, January 23rd [$1000.00] | Y77: =IF(COUNTIF(F24_CF!$A:$A,"*" & $A77 & "*") <> 0, "Yes", "No") -> Yes | Z77: {=INDEX(F24_CF!N:N, MATCH("*" & $A77 & "*", F24_CF!$A:$A, 0))} -> Basic One-Day: Thursday, September 5th [$1000.00] | AA77: =IF(COUNTIF(S24_CF!$A:$A,"*" & $A77 & "*") <> 0, "Yes", "No") -> Yes | AB77: {=INDEX(S24_CF!H:H, MATCH("*" & $A77 & "*", S24_CF!$A:$A, 0))} -> Silver One-Day [$1800.00]
A78: GAF | B78: Private | F78: =COUNTIF(S26_Emp!$C:$C,"*" &A78 & "*") -> 0 | G78: =COUNTIF(F25_Emp!$C:$C,"*" &#REF! & "*") -> 0 | H78: =COUNTIF(S25_Emp!$C:$C,"*" & A78 & "*") -> 1 | I78: =COUNTIF(F24_Emp!$C:$C,"*" & B78 & "*") -> 0 | J78: =COUNTIF(S24_Emp!$C:$C,"*" & $A78 & "*") -> 2 | K78: =COUNTIF(F23_Emp!$C:$C,"*" & $A78 & "*") -> 1 | L78: =COUNTIF(S23_Emp!$C:$C,"*" & $A78 & "*") -> 0 | M78: =COUNTIF(F22_Emp!$C:$C,"*" & $A78 & "*") -> 0 | N78: =COUNTIF(S22_Emp!$C:$C,"*" & $A78 & "*") -> 1 | O78: =COUNTIFS(S22_Emp!$C:$C,"*" & $A78 & "*", S22_S25_Emp!$B:$B, "Bachelor") -> #VALUE! | P78: =COUNTIFS(S22_Emp!$C:$C,"*" & $A78 & "*", S22_S25_Emp!$B:$B, "Master") -> #VALUE! | Q78: =COUNTIFS(S22_Emp!$C:$C,"*" & $A78 & "*", S22_S25_Emp!$B:$B, "Doctorate") -> #VALUE! | R78: {=IF(OR(INDEX(S26_CF!X:X, MATCH("*" & $A78 & "*", CompanyList!A:A, 0))=TRUE, INDEX(F25_CF!P:P, MATCH("*" & $A78 & "*", CompanyList!A:A, 0))=TRUE, INDEX(S25_CF!T:T, MATCH("*" & $A78 & "*", CompanyList!A:A, 0))=TRUE, INDEX(S24_CF!W:W, MATCH("*" & $A78 & "*", CompanyList!A:A, 0))=TRUE), "Yes", "No")} -> No | S78: =IF(COUNTIF(S26_CF!$A:$A,"*" & $A78 & "*") <> 0, "Yes", "No") -> Yes | T78: {=INDEX(S26_CF!K:K, MATCH("*" & $A78 & "*", S26_CF!A:A, 0))} -> Basic One-Day: Wednesday, January 28th [$1000.00] | U78: =IF(COUNTIF(F25_CF!$A:$A,"*" & $A78 & "*") <> 0, "Yes", "No") -> Yes | V78: {=INDEX(F25_CF!I:I, MATCH("*" & $A78 & "*", F25_CF!$A:$A, 0))} -> Basic Two-Day [$2000.00] | W78: =IF(COUNTIF(S25_CF!$A:$A,"*" & $A78 & "*") <> 0, "Yes", "No") -> Yes | X78: {=INDEX(S25_CF!J:J, MATCH("*" & $A78 & "*", S25_CF!$A:$A, 0))} -> Basic Two-Day [$2000.00] | Y78: =IF(COUNTIF(F24_CF!$A:$A,"*" & $A78 & "*") <> 0, "Yes", "No") -> Yes | Z78: {=INDEX(F24_CF!N:N, MATCH("*" & $A78 & "*", F24_CF!$A:$A, 0))} -> Basic Two-Day [$2000.00] | AA78: =IF(COUNTIF(S24_CF!$A:$A,"*" & $A78 & "*") <> 0, "Yes", "No") -> Yes | AB78: {=INDEX(S24_CF!H:H, MATCH("*" & $A78 & "*", S24_CF!$A:$A, 0))} -> Basic Two-Day [$2000.00]
A79: GBA Companies | B79: Private | F79: =COUNTIF(S26_Emp!$C:$C,"*" &A79 & "*") -> 0 | G79: =COUNTIF(F25_Emp!$C:$C,"*" &#REF! & "*") -> 0 | H79: =COUNTIF(S25_Emp!$C:$C,"*" & A79 & "*") -> 0 | I79: =COUNTIF(F24_Emp!$C:$C,"*" & B79 & "*") -> 0 | J79: =COUNTIF(S24_Emp!$C:$C,"*" & $A79 & "*") -> 0 | K79: =COUNTIF(F23_Emp!$C:$C,"*" & $A79 & "*") -> 1 | L79: =COUNTIF(S23_Emp!$C:$C,"*" & $A79 & "*") -> 1 | M79: =COUNTIF(F22_Emp!$C:$C,"*" & $A79 & "*") -> 0 | N79: =COUNTIF(S22_Emp!$C:$C,"*" & $A79 & "*") -> 0 | O79: =COUNTIFS(S22_Emp!$C:$C,"*" & $A79 & "*", S22_S25_Emp!$B:$B, "Bachelor") -> #VALUE! | P79: =COUNTIFS(S22_Emp!$C:$C,"*" & $A79 & "*", S22_S25_Emp!$B:$B, "Master") -> #VALUE! | Q79: =COUNTIFS(S22_Emp!$C:$C,"*" & $A79 & "*", S22_S25_Emp!$B:$B, "Doctorate") -> #VALUE! | R79: {=IF(OR(INDEX(S26_CF!X:X, MATCH("*" & $A79 & "*", CompanyList!A:A, 0))=TRUE, INDEX(F25_CF!P:P, MATCH("*" & $A79 & "*", CompanyList!A:A, 0))=TRUE, INDEX(S25_CF!T:T, MATCH("*" & $A79 & "*", CompanyList!A:A, 0))=TRUE, INDEX(S24_CF!W:W, MATCH("*" & $A79 & "*", CompanyList!A:A, 0))=TRUE), "Yes", "No")} -> Yes | S79: =IF(COUNTIF(S26_CF!$A:$A,"*" & $A79 & "*") <> 0, "Yes", "No") -> No | T79: {=INDEX(S26_CF!K:K, MATCH("*" & $A79 & "*", S26_CF!A:A, 0))} -> #N/A | U79: =IF(COUNTIF(F25_CF!$A:$A,"*" & $A79 & "*") <> 0, "Yes", "No") -> Yes | V79: {=INDEX(F25_CF!I:I, MATCH("*" & $A79 & "*", F25_CF!$A:$A, 0))} -> Basic One-Day: Thursday, September 11th [$1000.00] | W79: =IF(COUNTIF(S25_CF!$A:$A,"*" & $A79 & "*") <> 0, "Yes", "No") -> No | X79: {=INDEX(S25_CF!J:J, MATCH("*" & $A79 & "*", S25_CF!$A:$A, 0))} -> #N/A | Y79: =IF(COUNTIF(F24_CF!$A:$A,"*" & $A79 & "*") <> 0, "Yes", "No") -> Yes | Z79: {=INDEX(F24_CF!N:N, MATCH("*" & $A79 & "*", F24_CF!$A:$A, 0))} -> Basic One-Day: Wednesday, September 4th [$1000.00] | AA79: =IF(COUNTIF(S24_CF!$A:$A,"*" & $A79 & "*") <> 0, "Yes", "No") -> Yes | AB79: {=INDEX(S24_CF!H:H, MATCH("*" & $A79 & "*", S24_CF!$A:$A, 0))} -> Basic One-Day [$1000.00]
A80: General Dynamics Electric Boat | B80: Public | C80: 42000 | D80: 130000 | E80: 80 | F80: =COUNTIF(S26_Emp!$C:$C,"*" &A80 & "*") -> 0 | G80: =COUNTIF(F25_Emp!$C:$C,"*" &#REF! & "*") -> 0 | H80: =COUNTIF(S25_Emp!$C:$C,"*" & A80 & "*") -> 1 | I80: =COUNTIF(F24_Emp!$C:$C,"*" & B80 & "*") -> 1 | J80: =COUNTIF(S24_Emp!$C:$C,"*" & $A80 & "*") -> 1 | K80: =COUNTIF(F23_Emp!$C:$C,"*" & $A80 & "*") -> 2 | L80: =COUNTIF(S23_Emp!$C:$C,"*" & $A80 & "*") -> 0 | M80: =COUNTIF(F22_Emp!$C:$C,"*" & $A80 & "*") -> 0 | N80: =COUNTIF(S22_Emp!$C:$C,"*" & $A80 & "*") -> 0 | O80: =COUNTIFS(S22_Emp!$C:$C,"*" & $A80 & "*", S22_S25_Emp!$B:$B, "Bachelor") -> #VALUE! | P80: =COUNTIFS(S22_Emp!$C:$C,"*" & $A80 & "*", S22_S25_Emp!$B:$B, "Master") -> #VALUE! | Q80: =COUNTIFS(S22_Emp!$C:$C,"*" & $A80 & "*", S22_S25_Emp!$B:$B, "Doctorate") -> #VALUE! | R80: {=IF(OR(INDEX(S26_CF!X:X, MATCH("*" & $A80 & "*", CompanyList!A:A, 0))=TRUE, INDEX(F25_CF!P:P, MATCH("*" & $A80 & "*", CompanyList!A:A, 0))=TRUE, INDEX(S25_CF!T:T, MATCH("*" & $A80 & "*", CompanyList!A:A, 0))=TRUE, INDEX(S24_CF!W:W, MATCH("*" & $A80 & "*", CompanyList!A:A, 0))=TRUE), "Yes", "No")} -> No | S80: =IF(COUNTIF(S26_CF!$A:$A,"*" & $A80 & "*") <> 0, "Yes", "No") -> Yes | T80: {=INDEX(S26_CF!K:K, MATCH("*" & $A80 & "*", S26_CF!A:A, 0))} -> Basic One-Day: Wednesday, January 28th [$1000.00] | U80: =IF(COUNTIF(F25_CF!$A:$A,"*" & $A80 & "*") <> 0, "Yes", "No") -> Yes | V80: {=INDEX(F25_CF!I:I, MATCH("*" & $A80 & "*", F25_CF!$A:$A, 0))} -> Basic One-Day: Wednesday, September 10th [$1000.00] | W80: =IF(COUNTIF(S25_CF!$A:$A,"*" & $A80 & "*") <> 0, "Yes", "No") -> Yes | X80: {=INDEX(S25_CF!J:J, MATCH("*" & $A80 & "*", S25_CF!$A:$A, 0))} -> Basic One-Day: Thursday, January 23rd [$1000.00] | Y80: =IF(COUNTIF(F24_CF!$A:$A,"*" & $A80 & "*") <> 0, "Yes", "No") -> Yes | Z80: {=INDEX(F24_CF!N:N, MATCH("*" & $A80 & "*", F24_CF!$A:$A, 0))} -> Basic One-Day: Wednesday, September 4th [$1000.00] | AA80: =IF(COUNTIF(S24_CF!$A:$A,"*" & $A80 & "*") <> 0, "Yes", "No") -> Yes | AB80: {=INDEX(S24_CF!H:H, MATCH("*" & $A80 & "*", S24_CF!$A:$A, 0))} -> Basic One-Day [$1000.00]
A81: GMcivil | B81: Private | F81: =COUNTIF(S26_Emp!$C:$C,"*" &A81 & "*") -> 0 | G81: =COUNTIF(F25_Emp!$C:$C,"*" &#REF! & "*") -> 0 | H81: =COUNTIF(S25_Emp!$C:$C,"*" & A81 & "*") -> 0 | I81: =COUNTIF(F24_Emp!$C:$C,"*" & B81 & "*") -> 0 | J81: =COUNTIF(S24_Emp!$C:$C,"*" & $A81 & "*") -> 0 | K81: =COUNTIF(F23_Emp!$C:$C,"*" & $A81 & "*") -> 0 | L81: =COUNTIF(S23_Emp!$C:$C,"*" & $A81 & "*") -> 0 | M81: =COUNTIF(F22_Emp!$C:$C,"*" & $A81 & "*") -> 0 | N81: =COUNTIF(S22_Emp!$C:$C,"*" & $A81 & "*") -> 0 | O81: =COUNTIFS(S22_Emp!$C:$C,"*" & $A81 & "*", S22_S25_Emp!$B:$B, "Bachelor") -> #VALUE! | P81: =COUNTIFS(S22_Emp!$C:$C,"*" & $A81 & "*", S22_S25_Emp!$B:$B, "Master") -> #VALUE! | Q81: =COUNTIFS(S22_Emp!$C:$C,"*" & $A81 & "*", S22_S25_Emp!$B:$B, "Doctorate") -> #VALUE! | R81: {=IF(OR(INDEX(S26_CF!X:X, MATCH("*" & $A81 & "*", CompanyList!A:A, 0))=TRUE, INDEX(F25_CF!P:P, MATCH("*" & $A81 & "*", CompanyList!A:A, 0))=TRUE, INDEX(S25_CF!T:T, MATCH("*" & $A81 & "*", CompanyList!A:A, 0))=TRUE, INDEX(S24_CF!W:W, MATCH("*" & $A81 & "*", CompanyList!A:A, 0))=TRUE), "Yes", "No")} -> No | S81: =IF(COUNTIF(S26_CF!$A:$A,"*" & $A81 & "*") <> 0, "Yes", "No") -> Yes | T81: {=INDEX(S26_CF!K:K, MATCH("*" & $A81 & "*", S26_CF!A:A, 0))} -> Silver Two-Day [$3000.00] | U81: =IF(COUNTIF(F25_CF!$A:$A,"*" & $A81 & "*") <> 0, "Yes", "No") -> Yes | V81: {=INDEX(F25_CF!I:I, MATCH("*" & $A81 & "*", F25_CF!$A:$A, 0))} -> Silver One-Day: Thursday, September 11th [$1800.00] | W81: =IF(COUNTIF(S25_CF!$A:$A,"*" & $A81 & "*") <> 0, "Yes", "No") -> Yes | X81: {=INDEX(S25_CF!J:J, MATCH("*" & $A81 & "*", S25_CF!$A:$A, 0))} -> Silver One-Day: Thursday, January 23rd [$1800.00] | Y81: =IF(COUNTIF(F24_CF!$A:$A,"*" & $A81 & "*") <> 0, "Yes", "No") -> Yes | Z81: {=INDEX(F24_CF!N:N, MATCH("*" & $A81 & "*", F24_CF!$A:$A, 0))} -> Silver Two-Day [$3000.00] | AA81: =IF(COUNTIF(S24_CF!$A:$A,"*" & $A81 & "*") <> 0, "Yes", "No") -> Yes | AB81: {=INDEX(S24_CF!H:H, MATCH("*" & $A81 & "*", S24_CF!$A:$A, 0))} -> Silver One-Day [$1800.00]
A82: Great Lakes Dredge & Dock Company | B82: Private | F82: =COUNTIF(S26_Emp!$C:$C,"*" &A82 & "*") -> 0 | G82: =COUNTIF(F25_Emp!$C:$C,"*" &#REF! & "*") -> 0 | H82: =COUNTIF(S25_Emp!$C:$C,"*" & A82 & "*") -> 0 | I82: =COUNTIF(F24_Emp!$C:$C,"*" & B82 & "*") -> 0 | J82: =COUNTIF(S24_Emp!$C:$C,"*" & $A82 & "*") -> 1 | K82: =COUNTIF(F23_Emp!$C:$C,"*" & $A82 & "*") -> 0 | L82: =COUNTIF(S23_Emp!$C:$C,"*" & $A82 & "*") -> 0 | M82: =COUNTIF(F22_Emp!$C:$C,"*" & $A82 & "*") -> 0 | N82: =COUNTIF(S22_Emp!$C:$C,"*" & $A82 & "*") -> 0 | O82: =COUNTIFS(S22_Emp!$C:$C,"*" & $A82 & "*", S22_S25_Emp!$B:$B, "Bachelor") -> #VALUE! | P82: =COUNTIFS(S22_Emp!$C:$C,"*" & $A82 & "*", S22_S25_Emp!$B:$B, "Master") -> #VALUE! | Q82: =COUNTIFS(S22_Emp!$C:$C,"*" & $A82 & "*", S22_S25_Emp!$B:$B, "Doctorate") -> #VALUE! | R82: {=IF(OR(INDEX(S26_CF!X:X, MATCH("*" & $A82 & "*", CompanyList!A:A, 0))=TRUE, INDEX(F25_CF!P:P, MATCH("*" & $A82 & "*", CompanyList!A:A, 0))=TRUE, INDEX(S25_CF!T:T, MATCH("*" & $A82 & "*", CompanyList!A:A, 0))=TRUE, INDEX(S24_CF!W:W, MATCH("*" & $A82 & "*", CompanyList!A:A, 0))=TRUE), "Yes", "No")} -> No | S82: =IF(COUNTIF(S26_CF!$A:$A,"*" & $A82 & "*") <> 0, "Yes", "No") -> Yes | T82: {=INDEX(S26_CF!K:K, MATCH("*" & $A82 & "*", S26_CF!A:A, 0))} -> Basic Two-Day [$2000.00] | U82: =IF(COUNTIF(F25_CF!$A:$A,"*" & $A82 & "*") <> 0, "Yes", "No") -> Yes | V82: {=INDEX(F25_CF!I:I, MATCH("*" & $A82 & "*", F25_CF!$A:$A, 0))} -> Basic Two-Day [$2000.00] | W82: =IF(COUNTIF(S25_CF!$A:$A,"*" & $A82 & "*") <> 0, "Yes", "No") -> Yes | X82: {=INDEX(S25_CF!J:J, MATCH("*" & $A82 & "*", S25_CF!$A:$A, 0))} -> Basic Two-Day [$2000.00] | Y82: =IF(COUNTIF(F24_CF!$A:$A,"*" & $A82 & "*") <> 0, "Yes", "No") -> Yes | Z82: {=INDEX(F24_CF!N:N, MATCH("*" & $A82 & "*", F24_CF!$A:$A, 0))} -> Basic One-Day: Thursday, September 5th [$1000.00] | AA82: =IF(COUNTIF(S24_CF!$A:$A,"*" & $A82 & "*") <> 0, "Yes", "No") -> Yes | AB82: {=INDEX(S24_CF!H:H, MATCH("*" & $A82 & "*", S24_CF!$A:$A, 0))} -> Silver One-Day [$1800.00]
A83: Gulf Companies | B83: Private | F83: =COUNTIF(S26_Emp!$C:$C,"*" &A83 & "*") -> 0 | G83: =COUNTIF(F25_Emp!$C:$C,"*" &#REF! & "*") -> 0 | H83: =COUNTIF(S25_Emp!$C:$C,"*" & A83 & "*") -> 0 | I83: =COUNTIF(F24_Emp!$C:$C,"*" & B83 & "*") -> 0 | J83: =COUNTIF(S24_Emp!$C:$C,"*" & $A83 & "*") -> 0 | K83: =COUNTIF(F23_Emp!$C:$C,"*" & $A83 & "*") -> 0 | L83: =COUNTIF(S23_Emp!$C:$C,"*" & $A83 & "*") -> 0 | M83: =COUNTIF(F22_Emp!$C:$C,"*" & $A83 & "*") -> 0 | N83: =COUNTIF(S22_Emp!$C:$C,"*" & $A83 & "*") -> 0 | O83: =COUNTIFS(S22_Emp!$C:$C,"*" & $A83 & "*", S22_S25_Emp!$B:$B, "Bachelor") -> #VALUE! | P83: =COUNTIFS(S22_Emp!$C:$C,"*" & $A83 & "*", S22_S25_Emp!$B:$B, "Master") -> #VALUE! | Q83: =COUNTIFS(S22_Emp!$C:$C,"*" & $A83 & "*", S22_S25_Emp!$B:$B, "Doctorate") -> #VALUE! | R83: {=IF(OR(INDEX(S26_CF!X:X, MATCH("*" & $A83 & "*", CompanyList!A:A, 0))=TRUE, INDEX(F25_CF!P:P, MATCH("*" & $A83 & "*", CompanyList!A:A, 0))=TRUE, INDEX(S25_CF!T:T, MATCH("*" & $A83 & "*", CompanyList!A:A, 0))=TRUE, INDEX(S24_CF!W:W, MATCH("*" & $A83 & "*", CompanyList!A:A, 0))=TRUE), "Yes", "No")} -> No | S83: =IF(COUNTIF(S26_CF!$A:$A,"*" & $A83 & "*") <> 0, "Yes", "No") -> Yes | T83: {=INDEX(S26_CF!K:K, MATCH("*" & $A83 & "*", S26_CF!A:A, 0))} -> Basic One-Day: Wednesday, January 28th [$1000.00] | U83: =IF(COUNTIF(F25_CF!$A:$A,"*" & $A83 & "*") <> 0, "Yes", "No") -> Yes | V83: {=INDEX(F25_CF!I:I, MATCH("*" & $A83 & "*", F25_CF!$A:$A, 0))} -> Basic One-Day: Wednesday, September 10th [$1000.00] | W83: =IF(COUNTIF(S25_CF!$A:$A,"*" & $A83 & "*") <> 0, "Yes", "No") -> Yes | X83: {=INDEX(S25_CF!J:J, MATCH("*" & $A83 & "*", S25_CF!$A:$A, 0))} -> Basic One-Day: Wednesday, January 22nd [$1000.00] | Y83: =IF(COUNTIF(F24_CF!$A:$A,"*" & $A83 & "*") <> 0, "Yes", "No") -> Yes | Z83: {=INDEX(F24_CF!N:N, MATCH("*" & $A83 & "*", F24_CF!$A:$A, 0))} -> Basic One-Day: Thursday, September 5th [$1000.00] | AA83: =IF(COUNTIF(S24_CF!$A:$A,"*" & $A83 & "*") <> 0, "Yes", "No") -> Yes | AB83: {=INDEX(S24_CF!H:H, MATCH("*" & $A83 & "*", S24_CF!$A:$A, 0))} -> Basic One-Day [$1000.00]
A84: H2B, Inc. | B84: Private | F84: =COUNTIF(S26_Emp!$C:$C,"*" &A84 & "*") -> 0 | G84: =COUNTIF(F25_Emp!$C:$C,"*" &#REF! & "*") -> 0 | H84: =COUNTIF(S25_Emp!$C:$C,"*" & A84 & "*") -> 0 | I84: =COUNTIF(F24_Emp!$C:$C,"*" & B84 & "*") -> 0 | J84: =COUNTIF(S24_Emp!$C:$C,"*" & $A84 & "*") -> 2 | K84: =COUNTIF(F23_Emp!$C:$C,"*" & $A84 & "*") -> 1 | L84: =COUNTIF(S23_Emp!$C:$C,"*" & $A84 & "*") -> 0 | M84: =COUNTIF(F22_Emp!$C:$C,"*" & $A84 & "*") -> 0 | N84: =COUNTIF(S22_Emp!$C:$C,"*" & $A84 & "*") -> 0 | O84: =COUNTIFS(S22_Emp!$C:$C,"*" & $A84 & "*", S22_S25_Emp!$B:$B, "Bachelor") -> #VALUE! | P84: =COUNTIFS(S22_Emp!$C:$C,"*" & $A84 & "*", S22_S25_Emp!$B:$B, "Master") -> #VALUE! | Q84: =COUNTIFS(S22_Emp!$C:$C,"*" & $A84 & "*", S22_S25_Emp!$B:$B, "Doctorate") -> #VALUE! | R84: {=IF(OR(INDEX(S26_CF!X:X, MATCH("*" & $A84 & "*", CompanyList!A:A, 0))=TRUE, INDEX(F25_CF!P:P, MATCH("*" & $A84 & "*", CompanyList!A:A, 0))=TRUE, INDEX(S25_CF!T:T, MATCH("*" & $A84 & "*", CompanyList!A:A, 0))=TRUE, INDEX(S24_CF!W:W, MATCH("*" & $A84 & "*", CompanyList!A:A, 0))=TRUE), "Yes", "No")} -> Yes | S84: =IF(COUNTIF(S26_CF!$A:$A,"*" & $A84 & "*") <> 0, "Yes", "No") -> Yes | T84: {=INDEX(S26_CF!K:K, MATCH("*" & $A84 & "*", S26_CF!A:A, 0))} -> Basic One-Day: Thursday, January 29th [$1000.00] | U84: =IF(COUNTIF(F25_CF!$A:$A,"*" & $A84 & "*") <> 0, "Yes", "No") -> No | V84: {=INDEX(F25_CF!I:I, MATCH("*" & $A84 & "*", F25_CF!$A:$A, 0))} -> #N/A | W84: =IF(COUNTIF(S25_CF!$A:$A,"*" & $A84 & "*") <> 0, "Yes", "No") -> Yes | X84: {=INDEX(S25_CF!J:J, MATCH("*" & $A84 & "*", S25_CF!$A:$A, 0))} -> Basic One-Day: Thursday, January 23rd [$1000.00] | Y84: =IF(COUNTIF(F24_CF!$A:$A,"*" & $A84 & "*") <> 0, "Yes", "No") -> No | Z84: {=INDEX(F24_CF!N:N, MATCH("*" & $A84 & "*", F24_CF!$A:$A, 0))} -> #N/A | AA84: =IF(COUNTIF(S24_CF!$A:$A,"*" & $A84 & "*") <> 0, "Yes", "No") -> Yes | AB84: {=INDEX(S24_CF!H:H, MATCH("*" & $A84 & "*", S24_CF!$A:$A, 0))} -> Basic One-Day [$1000.00]
A85: Halff | B85: Private | F85: =COUNTIF(S26_Emp!$C:$C,"*" &A85 & "*") -> 0 | G85: =COUNTIF(F25_Emp!$C:$C,"*" &#REF! & "*") -> 0 | H85: =COUNTIF(S25_Emp!$C:$C,"*" & A85 & "*") -> 1 | I85: =COUNTIF(F24_Emp!$C:$C,"*" & B85 & "*") -> 0 | J85: =COUNTIF(S24_Emp!$C:$C,"*" & $A85 & "*") -> 3 | K85: =COUNTIF(F23_Emp!$C:$C,"*" & $A85 & "*") -> 2 | L85: =COUNTIF(S23_Emp!$C:$C,"*" & $A85 & "*") -> 2 | M85: =COUNTIF(F22_Emp!$C:$C,"*" & $A85 & "*") -> 2 | N85: =COUNTIF(S22_Emp!$C:$C,"*" & $A85 & "*") -> 1 | O85: =COUNTIFS(S22_Emp!$C:$C,"*" & $A85 & "*", S22_S25_Emp!$B:$B, "Bachelor") -> #VALUE! | P85: =COUNTIFS(S22_Emp!$C:$C,"*" & $A85 & "*", S22_S25_Emp!$B:$B, "Master") -> #VALUE! | Q85: =COUNTIFS(S22_Emp!$C:$C,"*" & $A85 & "*", S22_S25_Emp!$B:$B, "Doctorate") -> #VALUE! | R85: {=IF(OR(INDEX(S26_CF!X:X, MATCH("*" & $A85 & "*", CompanyList!A:A, 0))=TRUE, INDEX(F25_CF!P:P, MATCH("*" & $A85 & "*", CompanyList!A:A, 0))=TRUE, INDEX(S25_CF!T:T, MATCH("*" & $A85 & "*", CompanyList!A:A, 0))=TRUE, INDEX(S24_CF!W:W, MATCH("*" & $A85 & "*", CompanyList!A:A, 0))=TRUE), "Yes", "No")} -> No | S85: =IF(COUNTIF(S26_CF!$A:$A,"*" & $A85 & "*") <> 0, "Yes", "No") -> Yes | T85: {=INDEX(S26_CF!K:K, MATCH("*" & $A85 & "*", S26_CF!A:A, 0))} -> Silver Two-Day [$3000.00] | U85: =IF(COUNTIF(F25_CF!$A:$A,"*" & $A85 & "*") <> 0, "Yes", "No") -> Yes | V85: {=INDEX(F25_CF!I:I, MATCH("*" & $A85 & "*", F25_CF!$A:$A, 0))} -> Silver Two-Day [$3000.00] | W85: =IF(COUNTIF(S25_CF!$A:$A,"*" & $A85 & "*") <> 0, "Yes", "No") -> Yes | X85: {=INDEX(S25_CF!J:J, MATCH("*" & $A85 & "*", S25_CF!$A:$A, 0))} -> Silver Two-Day [$3000.00] | Y85: =IF(COUNTIF(F24_CF!$A:$A,"*" & $A85 & "*") <> 0, "Yes", "No") -> Yes | Z85: {=INDEX(F24_CF!N:N, MATCH("*" & $A85 & "*", F24_CF!$A:$A, 0))} -> Silver One-Day: Thursday, September 5th [$1800.00] | AA85: =IF(COUNTIF(S24_CF!$A:$A,"*" & $A85 & "*") <> 0, "Yes", "No") -> Yes | AB85: {=INDEX(S24_CF!H:H, MATCH("*" & $A85 & "*", S24_CF!$A:$A, 0))} -> Gold Two-Day [$5000.00]
A86: Halliburton | B86: Public | C86: 23000 | D86: 48000 | E86: 35 | F86: =COUNTIF(S26_Emp!$C:$C,"*" &A86 & "*") -> 0 | G86: =COUNTIF(F25_Emp!$C:$C,"*" &#REF! & "*") -> 0 | H86: =COUNTIF(S25_Emp!$C:$C,"*" & A86 & "*") -> 4 | I86: =COUNTIF(F24_Emp!$C:$C,"*" & B86 & "*") -> 1 | J86: =COUNTIF(S24_Emp!$C:$C,"*" & $A86 & "*") -> 7 | K86: =COUNTIF(F23_Emp!$C:$C,"*" & $A86 & "*") -> 4 | L86: =COUNTIF(S23_Emp!$C:$C,"*" & $A86 & "*") -> 5 | M86: =COUNTIF(F22_Emp!$C:$C,"*" & $A86 & "*") -> 5 | N86: =COUNTIF(S22_Emp!$C:$C,"*" & $A86 & "*") -> 6 | O86: =COUNTIFS(S22_Emp!$C:$C,"*" & $A86 & "*", S22_S25_Emp!$B:$B, "Bachelor") -> #VALUE! | P86: =COUNTIFS(S22_Emp!$C:$C,"*" & $A86 & "*", S22_S25_Emp!$B:$B, "Master") -> #VALUE! | Q86: =COUNTIFS(S22_Emp!$C:$C,"*" & $A86 & "*", S22_S25_Emp!$B:$B, "Doctorate") -> #VALUE! | R86: {=IF(OR(INDEX(S26_CF!X:X, MATCH("*" & $A86 & "*", CompanyList!A:A, 0))=TRUE, INDEX(F25_CF!P:P, MATCH("*" & $A86 & "*", CompanyList!A:A, 0))=TRUE, INDEX(S25_CF!T:T, MATCH("*" & $A86 & "*", CompanyList!A:A, 0))=TRUE, INDEX(S24_CF!W:W, MATCH("*" & $A86 & "*", CompanyList!A:A, 0))=TRUE), "Yes", "No")} -> No | S86: =IF(COUNTIF(S26_CF!$A:$A,"*" & $A86 & "*") <> 0, "Yes", "No") -> Yes | T86: {=INDEX(S26_CF!K:K, MATCH("*" & $A86 & "*", S26_CF!A:A, 0))} -> Gold Two-Day [$5500.00] | U86: =IF(COUNTIF(F25_CF!$A:$A,"*" & $A86 & "*") <> 0, "Yes", "No") -> Yes | V86: {=INDEX(F25_CF!I:I, MATCH("*" & $A86 & "*", F25_CF!$A:$A, 0))} -> Gold Two-Day [$5500.00] | W86: =IF(COUNTIF(S25_CF!$A:$A,"*" & $A86 & "*") <> 0, "Yes", "No") -> Yes | X86: {=INDEX(S25_CF!J:J, MATCH("*" & $A86 & "*", S25_CF!$A:$A, 0))} -> Gold Two-Day [$5500.00] | Y86: =IF(COUNTIF(F24_CF!$A:$A,"*" & $A86 & "*") <> 0, "Yes", "No") -> Yes | Z86: {=INDEX(F24_CF!N:N, MATCH("*" & $A86 & "*", F24_CF!$A:$A, 0))} -> Gold Two-Day [$5500.00] | AA86: =IF(COUNTIF(S24_CF!$A:$A,"*" & $A86 & "*") <> 0, "Yes", "No") -> Yes | AB86: {=INDEX(S24_CF!H:H, MATCH("*" & $A86 & "*", S24_CF!$A:$A, 0))} -> Gold Two-Day [$5000.00]
A87: Hargrove Engineers + Constructors | B87: Private | F87: =COUNTIF(S26_Emp!$C:$C,"*" &A87 & "*") -> 0 | G87: =COUNTIF(F25_Emp!$C:$C,"*" &#REF! & "*") -> 0 | H87: =COUNTIF(S25_Emp!$C:$C,"*" & A87 & "*") -> 0 | I87: =COUNTIF(F24_Emp!$C:$C,"*" & B87 & "*") -> 0 | J87: =COUNTIF(S24_Emp!$C:$C,"*" & $A87 & "*") -> 0 | K87: =COUNTIF(F23_Emp!$C:$C,"*" & $A87 & "*") -> 0 | L87: =COUNTIF(S23_Emp!$C:$C,"*" & $A87 & "*") -> 0 | M87: =COUNTIF(F22_Emp!$C:$C,"*" & $A87 & "*") -> 0 | N87: =COUNTIF(S22_Emp!$C:$C,"*" & $A87 & "*") -> 0 | O87: =COUNTIFS(S22_Emp!$C:$C,"*" & $A87 & "*", S22_S25_Emp!$B:$B, "Bachelor") -> #VALUE! | P87: =COUNTIFS(S22_Emp!$C:$C,"*" & $A87 & "*", S22_S25_Emp!$B:$B, "Master") -> #VALUE! | Q87: =COUNTIFS(S22_Emp!$C:$C,"*" & $A87 & "*", S22_S25_Emp!$B:$B, "Doctorate") -> #VALUE! | R87: {=IF(OR(INDEX(S26_CF!X:X, MATCH("*" & $A87 & "*", CompanyList!A:A, 0))=TRUE, INDEX(F25_CF!P:P, MATCH("*" & $A87 & "*", CompanyList!A:A, 0))=TRUE, INDEX(S25_CF!T:T, MATCH("*" & $A87 & "*", CompanyList!A:A, 0))=TRUE, INDEX(S24_CF!W:W, MATCH("*" & $A87 & "*", CompanyList!A:A, 0))=TRUE), "Yes", "No")} -> Yes | S87: =IF(COUNTIF(S26_CF!$A:$A,"*" & $A87 & "*") <> 0, "Yes", "No") -> No | T87: {=INDEX(S26_CF!K:K, MATCH("*" & $A87 & "*", S26_CF!A:A, 0))} -> #N/A | U87: =IF(COUNTIF(F25_CF!$A:$A,"*" & $A87 & "*") <> 0, "Yes", "No") -> No | V87: {=INDEX(F25_CF!I:I, MATCH("*" & $A87 & "*", F25_CF!$A:$A, 0))} -> #N/A | W87: =IF(COUNTIF(S25_CF!$A:$A,"*" & $A87 & "*") <> 0, "Yes", "No") -> Yes | X87: {=INDEX(S25_CF!J:J, MATCH("*" & $A87 & "*", S25_CF!$A:$A, 0))} -> Basic One-Day: Wednesday, January 22nd [$1000.00] | Y87: =IF(COUNTIF(F24_CF!$A:$A,"*" & $A87 & "*") <> 0, "Yes", "No") -> No | Z87: {=INDEX(F24_CF!N:N, MATCH("*" & $A87 & "*", F24_CF!$A:$A, 0))} -> #N/A | AA87: =IF(COUNTIF(S24_CF!$A:$A,"*" & $A87 & "*") <> 0, "Yes", "No") -> Yes | AB87: {=INDEX(S24_CF!H:H, MATCH("*" & $A87 & "*", S24_CF!$A:$A, 0))} -> Basic One-Day [$1000.00]
A88: Hart Gaugler + Associates | B88: Private | F88: =COUNTIF(S26_Emp!$C:$C,"*" &A88 & "*") -> 0 | G88: =COUNTIF(F25_Emp!$C:$C,"*" &#REF! & "*") -> 0 | H88: =COUNTIF(S25_Emp!$C:$C,"*" & A88 & "*") -> 0 | I88: =COUNTIF(F24_Emp!$C:$C,"*" & B88 & "*") -> 0 | J88: =COUNTIF(S24_Emp!$C:$C,"*" & $A88 & "*") -> 0 | K88: =COUNTIF(F23_Emp!$C:$C,"*" & $A88 & "*") -> 0 | L88: =COUNTIF(S23_Emp!$C:$C,"*" & $A88 & "*") -> 1 | M88: =COUNTIF(F22_Emp!$C:$C,"*" & $A88 & "*") -> 0 | N88: =COUNTIF(S22_Emp!$C:$C,"*" & $A88 & "*") -> 0 | O88: =COUNTIFS(S22_Emp!$C:$C,"*" & $A88 & "*", S22_S25_Emp!$B:$B, "Bachelor") -> #VALUE! | P88: =COUNTIFS(S22_Emp!$C:$C,"*" & $A88 & "*", S22_S25_Emp!$B:$B, "Master") -> #VALUE! | Q88: =COUNTIFS(S22_Emp!$C:$C,"*" & $A88 & "*", S22_S25_Emp!$B:$B, "Doctorate") -> #VALUE! | R88: {=IF(OR(INDEX(S26_CF!X:X, MATCH("*" & $A88 & "*", CompanyList!A:A, 0))=TRUE, INDEX(F25_CF!P:P, MATCH("*" & $A88 & "*", CompanyList!A:A, 0))=TRUE, INDEX(S25_CF!T:T, MATCH("*" & $A88 & "*", CompanyList!A:A, 0))=TRUE, INDEX(S24_CF!W:W, MATCH("*" & $A88 & "*", CompanyList!A:A, 0))=TRUE), "Yes", "No")} -> No | S88: =IF(COUNTIF(S26_CF!$A:$A,"*" & $A88 & "*") <> 0, "Yes", "No") -> Yes | T88: {=INDEX(S26_CF!K:K, MATCH("*" & $A88 & "*", S26_CF!A:A, 0))} -> Basic One-Day: Wednesday, January 28th [$1000.00] | U88: =IF(COUNTIF(F25_CF!$A:$A,"*" & $A88 & "*") <> 0, "Yes", "No") -> No | V88: {=INDEX(F25_CF!I:I, MATCH("*" & $A88 & "*", F25_CF!$A:$A, 0))} -> #N/A | W88: =IF(COUNTIF(S25_CF!$A:$A,"*" & $A88 & "*") <> 0, "Yes", "No") -> Yes | X88: {=INDEX(S25_CF!J:J, MATCH("*" & $A88 & "*", S25_CF!$A:$A, 0))} -> Silver One-Day: Thursday, January 23rd [$1800.00] | Y88: =IF(COUNTIF(F24_CF!$A:$A,"*" & $A88 & "*") <> 0, "Yes", "No") -> No | Z88: {=INDEX(F24_CF!N:N, MATCH("*" & $A88 & "*", F24_CF!$A:$A, 0))} -> #N/A | AA88: =IF(COUNTIF(S24_CF!$A:$A,"*" & $A88 & "*") <> 0, "Yes", "No") -> Yes | AB88: {=INDEX(S24_CF!H:H, MATCH("*" & $A88 & "*", S24_CF!$A:$A, 0))} -> Silver One-Day [$1800.00]
A89: Hatch Engineering and Consulting Associates | B89: Private | F89: =COUNTIF(S26_Emp!$C:$C,"*" &A89 & "*") -> 0 | G89: =COUNTIF(F25_Emp!$C:$C,"*" &#REF! & "*") -> 0 | H89: =COUNTIF(S25_Emp!$C:$C,"*" & A89 & "*") -> 0 | I89: =COUNTIF(F24_Emp!$C:$C,"*" & B89 & "*") -> 0 | J89: =COUNTIF(S24_Emp!$C:$C,"*" & $A89 & "*") -> 1 | K89: =COUNTIF(F23_Emp!$C:$C,"*" & $A89 & "*") -> 0 | L89: =COUNTIF(S23_Emp!$C:$C,"*" & $A89 & "*") -> 0 | M89: =COUNTIF(F22_Emp!$C:$C,"*" & $A89 & "*") -> 0 | N89: =COUNTIF(S22_Emp!$C:$C,"*" & $A89 & "*") -> 0 | O89: =COUNTIFS(S22_Emp!$C:$C,"*" & $A89 & "*", S22_S25_Emp!$B:$B, "Bachelor") -> #VALUE! | P89: =COUNTIFS(S22_Emp!$C:$C,"*" & $A89 & "*", S22_S25_Emp!$B:$B, "Master") -> #VALUE! | Q89: =COUNTIFS(S22_Emp!$C:$C,"*" & $A89 & "*", S22_S25_Emp!$B:$B, "Doctorate") -> #VALUE! | R89: {=IF(OR(INDEX(S26_CF!X:X, MATCH("*" & $A89 & "*", CompanyList!A:A, 0))=TRUE, INDEX(F25_CF!P:P, MATCH("*" & $A89 & "*", CompanyList!A:A, 0))=TRUE, INDEX(S25_CF!T:T, MATCH("*" & $A89 & "*", CompanyList!A:A, 0))=TRUE, INDEX(S24_CF!W:W, MATCH("*" & $A89 & "*", CompanyList!A:A, 0))=TRUE), "Yes", "No")} -> Yes | S89: =IF(COUNTIF(S26_CF!$A:$A,"*" & $A89 & "*") <> 0, "Yes", "No") -> Yes | T89: {=INDEX(S26_CF!K:K, MATCH("*" & $A89 & "*", S26_CF!A:A, 0))} -> Basic One-Day: Wednesday, January 28th [$1000.00] | U89: =IF(COUNTIF(F25_CF!$A:$A,"*" & $A89 & "*") <> 0, "Yes", "No") -> Yes | V89: {=INDEX(F25_CF!I:I, MATCH("*" & $A89 & "*", F25_CF!$A:$A, 0))} -> Basic One-Day: Thursday, September 11th [$1000.00] | W89: =IF(COUNTIF(S25_CF!$A:$A,"*" & $A89 & "*") <> 0, "Yes", "No") -> Yes | X89: {=INDEX(S25_CF!J:J, MATCH("*" & $A89 & "*", S25_CF!$A:$A, 0))} -> Basic Two-Day [$2000.00] | Y89: =IF(COUNTIF(F24_CF!$A:$A,"*" & $A89 & "*") <> 0, "Yes", "No") -> Yes | Z89: {=INDEX(F24_CF!N:N, MATCH("*" & $A89 & "*", F24_CF!$A:$A, 0))} -> Basic Two-Day [$2000.00] | AA89: =IF(COUNTIF(S24_CF!$A:$A,"*" & $A89 & "*") <> 0, "Yes", "No") -> Yes | AB89: {=INDEX(S24_CF!H:H, MATCH("*" & $A89 & "*", S24_CF!$A:$A, 0))} -> Basic Two-Day [$2000.00]
A90: HDR Engineering | B90: Private | F90: =COUNTIF(S26_Emp!$C:$C,"*" &A90 & "*") -> 0 | G90: =COUNTIF(F25_Emp!$C:$C,"*" &#REF! & "*") -> 0 | H90: =COUNTIF(S25_Emp!$C:$C,"*" & A90 & "*") -> 2 | I90: =COUNTIF(F24_Emp!$C:$C,"*" & B90 & "*") -> 0 | J90: =COUNTIF(S24_Emp!$C:$C,"*" & $A90 & "*") -> 0 | K90: =COUNTIF(F23_Emp!$C:$C,"*" & $A90 & "*") -> 1 | L90: =COUNTIF(S23_Emp!$C:$C,"*" & $A90 & "*") -> 0 | M90: =COUNTIF(F22_Emp!$C:$C,"*" & $A90 & "*") -> 0 | N90: =COUNTIF(S22_Emp!$C:$C,"*" & $A90 & "*") -> 3 | O90: =COUNTIFS(S22_Emp!$C:$C,"*" & $A90 & "*", S22_S25_Emp!$B:$B, "Bachelor") -> #VALUE! | P90: =COUNTIFS(S22_Emp!$C:$C,"*" & $A90 & "*", S22_S25_Emp!$B:$B, "Master") -> #VALUE! | Q90: =COUNTIFS(S22_Emp!$C:$C,"*" & $A90 & "*", S22_S25_Emp!$B:$B, "Doctorate") -> #VALUE! | R90: {=IF(OR(INDEX(S26_CF!X:X, MATCH("*" & $A90 & "*", CompanyList!A:A, 0))=TRUE, INDEX(F25_CF!P:P, MATCH("*" & $A90 & "*", CompanyList!A:A, 0))=TRUE, INDEX(S25_CF!T:T, MATCH("*" & $A90 & "*", CompanyList!A:A, 0))=TRUE, INDEX(S24_CF!W:W, MATCH("*" & $A90 & "*", CompanyList!A:A, 0))=TRUE), "Yes", "No")} -> No | S90: =IF(COUNTIF(S26_CF!$A:$A,"*" & $A90 & "*") <> 0, "Yes", "No") -> Yes | T90: {=INDEX(S26_CF!K:K, MATCH("*" & $A90 & "*", S26_CF!A:A, 0))} -> Gold Two-Day [$5500.00] | U90: =IF(COUNTIF(F25_CF!$A:$A,"*" & $A90 & "*") <> 0, "Yes", "No") -> Yes | V90: {=INDEX(F25_CF!I:I, MATCH("*" & $A90 & "*", F25_CF!$A:$A, 0))} -> Gold Two-Day [$5500.00] | W90: =IF(COUNTIF(S25_CF!$A:$A,"*" & $A90 & "*") <> 0, "Yes", "No") -> Yes | X90: {=INDEX(S25_CF!J:J, MATCH("*" & $A90 & "*", S25_CF!$A:$A, 0))} -> Gold Two-Day [$5500.00] | Y90: =IF(COUNTIF(F24_CF!$A:$A,"*" & $A90 & "*") <> 0, "Yes", "No") -> Yes | Z90: {=INDEX(F24_CF!N:N, MATCH("*" & $A90 & "*", F24_CF!$A:$A, 0))} -> Gold Two-Day [$5500.00] | AA90: =IF(COUNTIF(S24_CF!$A:$A,"*" & $A90 & "*") <> 0, "Yes", "No") -> Yes | AB90: {=INDEX(S24_CF!H:H, MATCH("*" & $A90 & "*", S24_CF!$A:$A, 0))} -> Gold Two-Day [$5000.00]
A91: Henderson Rogers Structural Engineers, LLC | B91: Private | F91: =COUNTIF(S26_Emp!$C:$C,"*" &A91 & "*") -> 0 | G91: =COUNTIF(F25_Emp!$C:$C,"*" &#REF! & "*") -> 0 | H91: =COUNTIF(S25_Emp!$C:$C,"*" & A91 & "*") -> 0 | I91: =COUNTIF(F24_Emp!$C:$C,"*" & B91 & "*") -> 0 | J91: =COUNTIF(S24_Emp!$C:$C,"*" & $A91 & "*") -> 0 | K91: =COUNTIF(F23_Emp!$C:$C,"*" & $A91 & "*") -> 0 | L91: =COUNTIF(S23_Emp!$C:$C,"*" & $A91 & "*") -> 1 | M91: =COUNTIF(F22_Emp!$C:$C,"*" & $A91 & "*") -> 0 | N91: =COUNTIF(S22_Emp!$C:$C,"*" & $A91 & "*") -> 0 | O91: =COUNTIFS(S22_Emp!$C:$C,"*" & $A91 & "*", S22_S25_Emp!$B:$B, "Bachelor") -> #VALUE! | P91: =COUNTIFS(S22_Emp!$C:$C,"*" & $A91 & "*", S22_S25_Emp!$B:$B, "Master") -> #VALUE! | Q91: =COUNTIFS(S22_Emp!$C:$C,"*" & $A91 & "*", S22_S25_Emp!$B:$B, "Doctorate") -> #VALUE! | R91: {=IF(OR(INDEX(S26_CF!X:X, MATCH("*" & $A91 & "*", CompanyList!A:A, 0))=TRUE, INDEX(F25_CF!P:P, MATCH("*" & $A91 & "*", CompanyList!A:A, 0))=TRUE, INDEX(S25_CF!T:T, MATCH("*" & $A91 & "*", CompanyList!A:A, 0))=TRUE, INDEX(S24_CF!W:W, MATCH("*" & $A91 & "*", CompanyList!A:A, 0))=TRUE), "Yes", "No")} -> No | S91: =IF(COUNTIF(S26_CF!$A:$A,"*" & $A91 & "*") <> 0, "Yes", "No") -> No | T91: {=INDEX(S26_CF!K:K, MATCH("*" & $A91 & "*", S26_CF!A:A, 0))} -> #N/A | U91: =IF(COUNTIF(F25_CF!$A:$A,"*" & $A91 & "*") <> 0, "Yes", "No") -> No | V91: {=INDEX(F25_CF!I:I, MATCH("*" & $A91 & "*", F25_CF!$A:$A, 0))} -> #N/A | W91: =IF(COUNTIF(S25_CF!$A:$A,"*" & $A91 & "*") <> 0, "Yes", "No") -> Yes | X91: {=INDEX(S25_CF!J:J, MATCH("*" & $A91 & "*", S25_CF!$A:$A, 0))} -> Silver One-Day: Thursday, January 23rd [$1800.00] | Y91: =IF(COUNTIF(F24_CF!$A:$A,"*" & $A91 & "*") <> 0, "Yes", "No") -> Yes | Z91: {=INDEX(F24_CF!N:N, MATCH("*" & $A91 & "*", F24_CF!$A:$A, 0))} -> Silver One-Day: Thursday, September 5th [$1800.00] | AA91: =IF(COUNTIF(S24_CF!$A:$A,"*" & $A91 & "*") <> 0, "Yes", "No") -> Yes | AB91: {=INDEX(S24_CF!H:H, MATCH("*" & $A91 & "*", S24_CF!$A:$A, 0))} -> Basic Two-Day [$2000.00]
A92: HMT Engineering & Surveying | B92: Private | F92: =COUNTIF(S26_Emp!$C:$C,"*" &A92 & "*") -> 0 | G92: =COUNTIF(F25_Emp!$C:$C,"*" &#REF! & "*") -> 0 | H92: =COUNTIF(S25_Emp!$C:$C,"*" & A92 & "*") -> 0 | I92: =COUNTIF(F24_Emp!$C:$C,"*" & B92 & "*") -> 0 | J92: =COUNTIF(S24_Emp!$C:$C,"*" & $A92 & "*") -> 2 | K92: =COUNTIF(F23_Emp!$C:$C,"*" & $A92 & "*") -> 0 | L92: =COUNTIF(S23_Emp!$C:$C,"*" & $A92 & "*") -> 0 | M92: =COUNTIF(F22_Emp!$C:$C,"*" & $A92 & "*") -> 0 | N92: =COUNTIF(S22_Emp!$C:$C,"*" & $A92 & "*") -> 0 | O92: =COUNTIFS(S22_Emp!$C:$C,"*" & $A92 & "*", S22_S25_Emp!$B:$B, "Bachelor") -> #VALUE! | P92: =COUNTIFS(S22_Emp!$C:$C,"*" & $A92 & "*", S22_S25_Emp!$B:$B, "Master") -> #VALUE! | Q92: =COUNTIFS(S22_Emp!$C:$C,"*" & $A92 & "*", S22_S25_Emp!$B:$B, "Doctorate") -> #VALUE! | R92: {=IF(OR(INDEX(S26_CF!X:X, MATCH("*" & $A92 & "*", CompanyList!A:A, 0))=TRUE, INDEX(F25_CF!P:P, MATCH("*" & $A92 & "*", CompanyList!A:A, 0))=TRUE, INDEX(S25_CF!T:T, MATCH("*" & $A92 & "*", CompanyList!A:A, 0))=TRUE, INDEX(S24_CF!W:W, MATCH("*" & $A92 & "*", CompanyList!A:A, 0))=TRUE), "Yes", "No")} -> No | S92: =IF(COUNTIF(S26_CF!$A:$A,"*" & $A92 & "*") <> 0, "Yes", "No") -> Yes | T92: {=INDEX(S26_CF!K:K, MATCH("*" & $A92 & "*", S26_CF!A:A, 0))} -> Silver One-Day: Thursday, January 29th [$1800.00] | U92: =IF(COUNTIF(F25_CF!$A:$A,"*" & $A92 & "*") <> 0, "Yes", "No") -> Yes | V92: {=INDEX(F25_CF!I:I, MATCH("*" & $A92 & "*", F25_CF!$A:$A, 0))} -> Basic One-Day: Thursday, September 11th [$1000.00] | W92: =IF(COUNTIF(S25_CF!$A:$A,"*" & $A92 & "*") <> 0, "Yes", "No") -> Yes | X92: {=INDEX(S25_CF!J:J, MATCH("*" & $A92 & "*", S25_CF!$A:$A, 0))} -> Basic One-Day: Thursday, January 23rd [$1000.00] | Y92: =IF(COUNTIF(F24_CF!$A:$A,"*" & $A92 & "*") <> 0, "Yes", "No") -> No | Z92: {=INDEX(F24_CF!N:N, MATCH("*" & $A92 & "*", F24_CF!$A:$A, 0))} -> #N/A | AA92: =IF(COUNTIF(S24_CF!$A:$A,"*" & $A92 & "*") <> 0, "Yes", "No") -> Yes | AB92: {=INDEX(S24_CF!H:H, MATCH("*" & $A92 & "*", S24_CF!$A:$A, 0))} -> Silver Two-Day [$3000.00]
A93: HNTB Corporation | B93: Private | F93: =COUNTIF(S26_Emp!$C:$C,"*" &A93 & "*") -> 0 | G93: =COUNTIF(F25_Emp!$C:$C,"*" &#REF! & "*") -> 0 | H93: =COUNTIF(S25_Emp!$C:$C,"*" & A93 & "*") -> 1 | I93: =COUNTIF(F24_Emp!$C:$C,"*" & B93 & "*") -> 0 | J93: =COUNTIF(S24_Emp!$C:$C,"*" & $A93 & "*") -> 1 | K93: =COUNTIF(F23_Emp!$C:$C,"*" & $A93 & "*") -> 1 | L93: =COUNTIF(S23_Emp!$C:$C,"*" & $A93 & "*") -> 0 | M93: =COUNTIF(F22_Emp!$C:$C,"*" & $A93 & "*") -> 1 | N93: =COUNTIF(S22_Emp!$C:$C,"*" & $A93 & "*") -> 0 | O93: =COUNTIFS(S22_Emp!$C:$C,"*" & $A93 & "*", S22_S25_Emp!$B:$B, "Bachelor") -> #VALUE! | P93: =COUNTIFS(S22_Emp!$C:$C,"*" & $A93 & "*", S22_S25_Emp!$B:$B, "Master") -> #VALUE! | Q93: =COUNTIFS(S22_Emp!$C:$C,"*" & $A93 & "*", S22_S25_Emp!$B:$B, "Doctorate") -> #VALUE! | R93: {=IF(OR(INDEX(S26_CF!X:X, MATCH("*" & $A93 & "*", CompanyList!A:A, 0))=TRUE, INDEX(F25_CF!P:P, MATCH("*" & $A93 & "*", CompanyList!A:A, 0))=TRUE, INDEX(S25_CF!T:T, MATCH("*" & $A93 & "*", CompanyList!A:A, 0))=TRUE, INDEX(S24_CF!W:W, MATCH("*" & $A93 & "*", CompanyList!A:A, 0))=TRUE), "Yes", "No")} -> No | S93: =IF(COUNTIF(S26_CF!$A:$A,"*" & $A93 & "*") <> 0, "Yes", "No") -> No | T93: {=INDEX(S26_CF!K:K, MATCH("*" & $A93 & "*", S26_CF!A:A, 0))} -> #N/A | U93: =IF(COUNTIF(F25_CF!$A:$A,"*" & $A93 & "*") <> 0, "Yes", "No") -> No | V93: {=INDEX(F25_CF!I:I, MATCH("*" & $A93 & "*", F25_CF!$A:$A, 0))} -> #N/A | W93: =IF(COUNTIF(S25_CF!$A:$A,"*" & $A93 & "*") <> 0, "Yes", "No") -> Yes | X93: {=INDEX(S25_CF!J:J, MATCH("*" & $A93 & "*", S25_CF!$A:$A, 0))} -> Basic One-Day: Thursday, January 23rd [$1000.00] | Y93: =IF(COUNTIF(F24_CF!$A:$A,"*" & $A93 & "*") <> 0, "Yes", "No") -> No | Z93: {=INDEX(F24_CF!N:N, MATCH("*" & $A93 & "*", F24_CF!$A:$A, 0))} -> #N/A | AA93: =IF(COUNTIF(S24_CF!$A:$A,"*" & $A93 & "*") <> 0, "Yes", "No") -> Yes | AB93: {=INDEX(S24_CF!H:H, MATCH("*" & $A93 & "*", S24_CF!$A:$A, 0))} -> Basic One-Day [$1000.00]
A94: Patterson UTI | B94: Public | C94: 3000 | D94: 8000 | E94: 5 | F94: =COUNTIF(S26_Emp!$C:$C,"*" &A94 & "*") -> 0 | G94: =COUNTIF(F25_Emp!$C:$C,"*" &#REF! & "*") -> 0 | H94: =COUNTIF(S25_Emp!$C:$C,"*" & A94 & "*") -> 0 | I94: =COUNTIF(F24_Emp!$C:$C,"*" & B94 & "*") -> 1 | J94: =COUNTIF(S24_Emp!$C:$C,"*" & $A94 & "*") -> 0 | K94: =COUNTIF(F23_Emp!$C:$C,"*" & $A94 & "*") -> 0 | L94: =COUNTIF(S23_Emp!$C:$C,"*" & $A94 & "*") -> 0 | M94: =COUNTIF(F22_Emp!$C:$C,"*" & $A94 & "*") -> 0 | N94: =COUNTIF(S22_Emp!$C:$C,"*" & $A94 & "*") -> 2 | O94: =COUNTIFS(S22_Emp!$C:$C,"*" & $A94 & "*", S22_S25_Emp!$B:$B, "Bachelor") -> #VALUE! | P94: =COUNTIFS(S22_Emp!$C:$C,"*" & $A94 & "*", S22_S25_Emp!$B:$B, "Master") -> #VALUE! | Q94: =COUNTIFS(S22_Emp!$C:$C,"*" & $A94 & "*", S22_S25_Emp!$B:$B, "Doctorate") -> #VALUE! | R94: {=IF(OR(INDEX(S26_CF!X:X, MATCH("*" & $A94 & "*", CompanyList!A:A, 0))=TRUE, INDEX(F25_CF!P:P, MATCH("*" & $A94 & "*", CompanyList!A:A, 0))=TRUE, INDEX(S25_CF!T:T, MATCH("*" & $A94 & "*", CompanyList!A:A, 0))=TRUE, INDEX(S24_CF!W:W, MATCH("*" & $A94 & "*", CompanyList!A:A, 0))=TRUE), "Yes", "No")} -> No | S94: =IF(COUNTIF(S26_CF!$A:$A,"*" & $A94 & "*") <> 0, "Yes", "No") -> No | T94: {=INDEX(S26_CF!K:K, MATCH("*" & $A94 & "*", S26_CF!A:A, 0))} -> #N/A | U94: =IF(COUNTIF(F25_CF!$A:$A,"*" & $A94 & "*") <> 0, "Yes", "No") -> No | V94: {=INDEX(F25_CF!I:I, MATCH("*" & $A94 & "*", F25_CF!$A:$A, 0))} -> #N/A | W94: =IF(COUNTIF(S25_CF!$A:$A,"*" & $A94 & "*") <> 0, "Yes", "No") -> No | X94: {=INDEX(S25_CF!J:J, MATCH("*" & $A94 & "*", S25_CF!$A:$A, 0))} -> #N/A | Y94: =IF(COUNTIF(F24_CF!$A:$A,"*" & $A94 & "*") <> 0, "Yes", "No") -> No | Z94: {=INDEX(F24_CF!N:N, MATCH("*" & $A94 & "*", F24_CF!$A:$A, 0))} -> #N/A | AA94: =IF(COUNTIF(S24_CF!$A:$A,"*" & $A94 & "*") <> 0, "Yes", "No") -> No | AB94: {=INDEX(S24_CF!H:H, MATCH("*" & $A94 & "*", S24_CF!$A:$A, 0))} -> #N/A
A95: HR Green | B95: Private | F95: =COUNTIF(S26_Emp!$C:$C,"*" &A95 & "*") -> 0 | G95: =COUNTIF(F25_Emp!$C:$C,"*" &#REF! & "*") -> 0 | H95: =COUNTIF(S25_Emp!$C:$C,"*" & A95 & "*") -> 0 | I95: =COUNTIF(F24_Emp!$C:$C,"*" & B95 & "*") -> 0 | J95: =COUNTIF(S24_Emp!$C:$C,"*" & $A95 & "*") -> 0 | K95: =COUNTIF(F23_Emp!$C:$C,"*" & $A95 & "*") -> 1 | L95: =COUNTIF(S23_Emp!$C:$C,"*" & $A95 & "*") -> 0 | M95: =COUNTIF(F22_Emp!$C:$C,"*" & $A95 & "*") -> 0 | N95: =COUNTIF(S22_Emp!$C:$C,"*" & $A95 & "*") -> 0 | O95: =COUNTIFS(S22_Emp!$C:$C,"*" & $A95 & "*", S22_S25_Emp!$B:$B, "Bachelor") -> #VALUE! | P95: =COUNTIFS(S22_Emp!$C:$C,"*" & $A95 & "*", S22_S25_Emp!$B:$B, "Master") -> #VALUE! | Q95: =COUNTIFS(S22_Emp!$C:$C,"*" & $A95 & "*", S22_S25_Emp!$B:$B, "Doctorate") -> #VALUE! | R95: {=IF(OR(INDEX(S26_CF!X:X, MATCH("*" & $A95 & "*", CompanyList!A:A, 0))=TRUE, INDEX(F25_CF!P:P, MATCH("*" & $A95 & "*", CompanyList!A:A, 0))=TRUE, INDEX(S25_CF!T:T, MATCH("*" & $A95 & "*", CompanyList!A:A, 0))=TRUE, INDEX(S24_CF!W:W, MATCH("*" & $A95 & "*", CompanyList!A:A, 0))=TRUE), "Yes", "No")} -> No | S95: =IF(COUNTIF(S26_CF!$A:$A,"*" & $A95 & "*") <> 0, "Yes", "No") -> Yes | T95: {=INDEX(S26_CF!K:K, MATCH("*" & $A95 & "*", S26_CF!A:A, 0))} -> Basic One-Day: Wednesday, January 28th [$1000.00] | U95: =IF(COUNTIF(F25_CF!$A:$A,"*" & $A95 & "*") <> 0, "Yes", "No") -> Yes | V95: {=INDEX(F25_CF!I:I, MATCH("*" & $A95 & "*", F25_CF!$A:$A, 0))} -> Basic One-Day: Wednesday, September 10th [$1000.00] | W95: =IF(COUNTIF(S25_CF!$A:$A,"*" & $A95 & "*") <> 0, "Yes", "No") -> Yes | X95: {=INDEX(S25_CF!J:J, MATCH("*" & $A95 & "*", S25_CF!$A:$A, 0))} -> Basic One-Day: Wednesday, January 22nd [$1000.00] | Y95: =IF(COUNTIF(F24_CF!$A:$A,"*" & $A95 & "*") <> 0, "Yes", "No") -> No | Z95: {=INDEX(F24_CF!N:N, MATCH("*" & $A95 & "*", F24_CF!$A:$A, 0))} -> #N/A | AA95: =IF(COUNTIF(S24_CF!$A:$A,"*" & $A95 & "*") <> 0, "Yes", "No") -> Yes | AB95: {=INDEX(S24_CF!H:H, MATCH("*" & $A95 & "*", S24_CF!$A:$A, 0))} -> Basic One-Day [$1000.00]
A96: HTS Texas | B96: Private | F96: =COUNTIF(S26_Emp!$C:$C,"*" &A96 & "*") -> 0 | G96: =COUNTIF(F25_Emp!$C:$C,"*" &#REF! & "*") -> 0 | H96: =COUNTIF(S25_Emp!$C:$C,"*" & A96 & "*") -> 0 | I96: =COUNTIF(F24_Emp!$C:$C,"*" & B96 & "*") -> 0 | J96: =COUNTIF(S24_Emp!$C:$C,"*" & $A96 & "*") -> 0 | K96: =COUNTIF(F23_Emp!$C:$C,"*" & $A96 & "*") -> 0 | L96: =COUNTIF(S23_Emp!$C:$C,"*" & $A96 & "*") -> 0 | M96: =COUNTIF(F22_Emp!$C:$C,"*" & $A96 & "*") -> 0 | N96: =COUNTIF(S22_Emp!$C:$C,"*" & $A96 & "*") -> 0 | O96: =COUNTIFS(S22_Emp!$C:$C,"*" & $A96 & "*", S22_S25_Emp!$B:$B, "Bachelor") -> #VALUE! | P96: =COUNTIFS(S22_Emp!$C:$C,"*" & $A96 & "*", S22_S25_Emp!$B:$B, "Master") -> #VALUE! | Q96: =COUNTIFS(S22_Emp!$C:$C,"*" & $A96 & "*", S22_S25_Emp!$B:$B, "Doctorate") -> #VALUE! | R96: {=IF(OR(INDEX(S26_CF!X:X, MATCH("*" & $A96 & "*", CompanyList!A:A, 0))=TRUE, INDEX(F25_CF!P:P, MATCH("*" & $A96 & "*", CompanyList!A:A, 0))=TRUE, INDEX(S25_CF!T:T, MATCH("*" & $A96 & "*", CompanyList!A:A, 0))=TRUE, INDEX(S24_CF!W:W, MATCH("*" & $A96 & "*", CompanyList!A:A, 0))=TRUE), "Yes", "No")} -> No | S96: =IF(COUNTIF(S26_CF!$A:$A,"*" & $A96 & "*") <> 0, "Yes", "No") -> Yes | T96: {=INDEX(S26_CF!K:K, MATCH("*" & $A96 & "*", S26_CF!A:A, 0))} -> Gold Two-Day [$5500.00] | U96: =IF(COUNTIF(F25_CF!$A:$A,"*" & $A96 & "*") <> 0, "Yes", "No") -> Yes | V96: {=INDEX(F25_CF!I:I, MATCH("*" & $A96 & "*", F25_CF!$A:$A, 0))} -> Gold Two-Day [$5500.00] | W96: =IF(COUNTIF(S25_CF!$A:$A,"*" & $A96 & "*") <> 0, "Yes", "No") -> Yes | X96: {=INDEX(S25_CF!J:J, MATCH("*" & $A96 & "*", S25_CF!$A:$A, 0))} -> Gold Two-Day [$5500.00] | Y96: =IF(COUNTIF(F24_CF!$A:$A,"*" & $A96 & "*") <> 0, "Yes", "No") -> Yes | Z96: {=INDEX(F24_CF!N:N, MATCH("*" & $A96 & "*", F24_CF!$A:$A, 0))} -> Gold Two-Day [$5500.00] | AA96: =IF(COUNTIF(S24_CF!$A:$A,"*" & $A96 & "*") <> 0, "Yes", "No") -> Yes | AB96: {=INDEX(S24_CF!H:H, MATCH("*" & $A96 & "*", S24_CF!$A:$A, 0))} -> Gold Two-Day [$5000.00]
A97: Huitt-Zollars, Inc. | B97: Private | F97: =COUNTIF(S26_Emp!$C:$C,"*" &A97 & "*") -> 0 | G97: =COUNTIF(F25_Emp!$C:$C,"*" &#REF! & "*") -> 0 | H97: =COUNTIF(S25_Emp!$C:$C,"*" & A97 & "*") -> 0 | I97: =COUNTIF(F24_Emp!$C:$C,"*" & B97 & "*") -> 0 | J97: =COUNTIF(S24_Emp!$C:$C,"*" & $A97 & "*") -> 1 | K97: =COUNTIF(F23_Emp!$C:$C,"*" & $A97 & "*") -> 0 | L97: =COUNTIF(S23_Emp!$C:$C,"*" & $A97 & "*") -> 0 | M97: =COUNTIF(F22_Emp!$C:$C,"*" & $A97 & "*") -> 1 | N97: =COUNTIF(S22_Emp!$C:$C,"*" & $A97 & "*") -> 0 | O97: =COUNTIFS(S22_Emp!$C:$C,"*" & $A97 & "*", S22_S25_Emp!$B:$B, "Bachelor") -> #VALUE! | P97: =COUNTIFS(S22_Emp!$C:$C,"*" & $A97 & "*", S22_S25_Emp!$B:$B, "Master") -> #VALUE! | Q97: =COUNTIFS(S22_Emp!$C:$C,"*" & $A97 & "*", S22_S25_Emp!$B:$B, "Doctorate") -> #VALUE! | R97: {=IF(OR(INDEX(S26_CF!X:X, MATCH("*" & $A97 & "*", CompanyList!A:A, 0))=TRUE, INDEX(F25_CF!P:P, MATCH("*" & $A97 & "*", CompanyList!A:A, 0))=TRUE, INDEX(S25_CF!T:T, MATCH("*" & $A97 & "*", CompanyList!A:A, 0))=TRUE, INDEX(S24_CF!W:W, MATCH("*" & $A97 & "*", CompanyList!A:A, 0))=TRUE), "Yes", "No")} -> No | S97: =IF(COUNTIF(S26_CF!$A:$A,"*" & $A97 & "*") <> 0, "Yes", "No") -> Yes | T97: {=INDEX(S26_CF!K:K, MATCH("*" & $A97 & "*", S26_CF!A:A, 0))} -> Basic One-Day: Wednesday, January 28th [$1000.00] | U97: =IF(COUNTIF(F25_CF!$A:$A,"*" & $A97 & "*") <> 0, "Yes", "No") -> Yes | V97: {=INDEX(F25_CF!I:I, MATCH("*" & $A97 & "*", F25_CF!$A:$A, 0))} -> Basic One-Day: Thursday, September 11th [$1000.00] | W97: =IF(COUNTIF(S25_CF!$A:$A,"*" & $A97 & "*") <> 0, "Yes", "No") -> Yes | X97: {=INDEX(S25_CF!J:J, MATCH("*" & $A97 & "*", S25_CF!$A:$A, 0))} -> Basic One-Day: Thursday, January 23rd [$1000.00] | Y97: =IF(COUNTIF(F24_CF!$A:$A,"*" & $A97 & "*") <> 0, "Yes", "No") -> Yes | Z97: {=INDEX(F24_CF!N:N, MATCH("*" & $A97 & "*", F24_CF!$A:$A, 0))} -> Basic One-Day: Thursday, September 5th [$1000.00] | AA97: =IF(COUNTIF(S24_CF!$A:$A,"*" & $A97 & "*") <> 0, "Yes", "No") -> Yes | AB97: {=INDEX(S24_CF!H:H, MATCH("*" & $A97 & "*", S24_CF!$A:$A, 0))} -> Basic One-Day [$1000.00]
A98: IBM | B98: Public | C98: 62000 | D98: 282000 | E98: 170 | F98: =COUNTIF(S26_Emp!$C:$C,"*" &A98 & "*") -> 0 | G98: =COUNTIF(F25_Emp!$C:$C,"*" &#REF! & "*") -> 0 | H98: =COUNTIF(S25_Emp!$C:$C,"*" & A98 & "*") -> 6 | I98: =COUNTIF(F24_Emp!$C:$C,"*" & B98 & "*") -> 1 | J98: =COUNTIF(S24_Emp!$C:$C,"*" & $A98 & "*") -> 1 | K98: =COUNTIF(F23_Emp!$C:$C,"*" & $A98 & "*") -> 1 | L98: =COUNTIF(S23_Emp!$C:$C,"*" & $A98 & "*") -> 6 | M98: =COUNTIF(F22_Emp!$C:$C,"*" & $A98 & "*") -> 3 | N98: =COUNTIF(S22_Emp!$C:$C,"*" & $A98 & "*") -> 6 | O98: =COUNTIFS(S22_Emp!$C:$C,"*" & $A98 & "*", S22_S25_Emp!$B:$B, "Bachelor") -> #VALUE! | P98: =COUNTIFS(S22_Emp!$C:$C,"*" & $A98 & "*", S22_S25_Emp!$B:$B, "Master") -> #VALUE! | Q98: =COUNTIFS(S22_Emp!$C:$C,"*" & $A98 & "*", S22_S25_Emp!$B:$B, "Doctorate") -> #VALUE! | R98: {=IF(OR(INDEX(S26_CF!X:X, MATCH("*" & $A98 & "*", CompanyList!A:A, 0))=TRUE, INDEX(F25_CF!P:P, MATCH("*" & $A98 & "*", CompanyList!A:A, 0))=TRUE, INDEX(S25_CF!T:T, MATCH("*" & $A98 & "*", CompanyList!A:A, 0))=TRUE, INDEX(S24_CF!W:W, MATCH("*" & $A98 & "*", CompanyList!A:A, 0))=TRUE), "Yes", "No")} -> No | S98: =IF(COUNTIF(S26_CF!$A:$A,"*" & $A98 & "*") <> 0, "Yes", "No") -> No | T98: {=INDEX(S26_CF!K:K, MATCH("*" & $A98 & "*", S26_CF!A:A, 0))} -> #N/A | U98: =IF(COUNTIF(F25_CF!$A:$A,"*" & $A98 & "*") <> 0, "Yes", "No") -> Yes | V98: {=INDEX(F25_CF!I:I, MATCH("*" & $A98 & "*", F25_CF!$A:$A, 0))} -> Silver Two-Day [$3000.00] | W98: =IF(COUNTIF(S25_CF!$A:$A,"*" & $A98 & "*") <> 0, "Yes", "No") -> No | X98: {=INDEX(S25_CF!J:J, MATCH("*" & $A98 & "*", S25_CF!$A:$A, 0))} -> #N/A | Y98: =IF(COUNTIF(F24_CF!$A:$A,"*" & $A98 & "*") <> 0, "Yes", "No") -> Yes | Z98: {=INDEX(F24_CF!N:N, MATCH("*" & $A98 & "*", F24_CF!$A:$A, 0))} -> Basic Two-Day [$2000.00] | AA98: =IF(COUNTIF(S24_CF!$A:$A,"*" & $A98 & "*") <> 0, "Yes", "No") -> Yes | AB98: {=INDEX(S24_CF!H:H, MATCH("*" & $A98 & "*", S24_CF!$A:$A, 0))} -> Gold Two-Day [$5000.00]
A99: iD Tech Camps | B99: Private | F99: =COUNTIF(S26_Emp!$C:$C,"*" &A99 & "*") -> 0 | G99: =COUNTIF(F25_Emp!$C:$C,"*" &#REF! & "*") -> 0 | H99: =COUNTIF(S25_Emp!$C:$C,"*" & A99 & "*") -> 0 | I99: =COUNTIF(F24_Emp!$C:$C,"*" & B99 & "*") -> 0 | J99: =COUNTIF(S24_Emp!$C:$C,"*" & $A99 & "*") -> 0 | K99: =COUNTIF(F23_Emp!$C:$C,"*" & $A99 & "*") -> 0 | L99: =COUNTIF(S23_Emp!$C:$C,"*" & $A99 & "*") -> 0 | M99: =COUNTIF(F22_Emp!$C:$C,"*" & $A99 & "*") -> 0 | N99: =COUNTIF(S22_Emp!$C:$C,"*" & $A99 & "*") -> 0 | O99: =COUNTIFS(S22_Emp!$C:$C,"*" & $A99 & "*", S22_S25_Emp!$B:$B, "Bachelor") -> #VALUE! | P99: =COUNTIFS(S22_Emp!$C:$C,"*" & $A99 & "*", S22_S25_Emp!$B:$B, "Master") -> #VALUE! | Q99: =COUNTIFS(S22_Emp!$C:$C,"*" & $A99 & "*", S22_S25_Emp!$B:$B, "Doctorate") -> #VALUE! | R99: {=IF(OR(INDEX(S26_CF!X:X, MATCH("*" & $A99 & "*", CompanyList!A:A, 0))=TRUE, INDEX(F25_CF!P:P, MATCH("*" & $A99 & "*", CompanyList!A:A, 0))=TRUE, INDEX(S25_CF!T:T, MATCH("*" & $A99 & "*", CompanyList!A:A, 0))=TRUE, INDEX(S24_CF!W:W, MATCH("*" & $A99 & "*", CompanyList!A:A, 0))=TRUE), "Yes", "No")} -> No | S99: =IF(COUNTIF(S26_CF!$A:$A,"*" & $A99 & "*") <> 0, "Yes", "No") -> Yes | T99: {=INDEX(S26_CF!K:K, MATCH("*" & $A99 & "*", S26_CF!A:A, 0))} -> Basic One-Day: Thursday, January 29th [$1000.00] | U99: =IF(COUNTIF(F25_CF!$A:$A,"*" & $A99 & "*") <> 0, "Yes", "No") -> No | V99: {=INDEX(F25_CF!I:I, MATCH("*" & $A99 & "*", F25_CF!$A:$A, 0))} -> #N/A | W99: =IF(COUNTIF(S25_CF!$A:$A,"*" & $A99 & "*") <> 0, "Yes", "No") -> Yes | X99: {=INDEX(S25_CF!J:J, MATCH("*" & $A99 & "*", S25_CF!$A:$A, 0))} -> Basic One-Day: Wednesday, January 22nd [$1000.00] | Y99: =IF(COUNTIF(F24_CF!$A:$A,"*" & $A99 & "*") <> 0, "Yes", "No") -> No | Z99: {=INDEX(F24_CF!N:N, MATCH("*" & $A99 & "*", F24_CF!$A:$A, 0))} -> #N/A | AA99: =IF(COUNTIF(S24_CF!$A:$A,"*" & $A99 & "*") <> 0, "Yes", "No") -> Yes | AB99: {=INDEX(S24_CF!H:H, MATCH("*" & $A99 & "*", S24_CF!$A:$A, 0))} -> Basic One-Day [$1000.00]
